Workbook

Sheet Sheet4
A1: 事项类型 | B1: (多项)
A2: 所属的ADPM需求 | B2: (多项)
A4: 用人科室 | B4: 求和项:工时（小时） | F4: 用人科室 | G4: 总人天数 | H4: 总人天数 | I4: 应关联ADPM人天数 | J4: 关联ADPM需求工时数量 | K4: 关联ADPM需求人天数量 | L4: 比例
A5: 数据开发部 | B5: 300.75 | F5: 数据测试部 | G5: 278.4499 | H5: 39.87 | I5: =G5/8.5 -> 32.758812 | K5: =J5/8.5 -> 0 | L5: =K5/I5 -> 0
A6: 数据平台部 | B6: 349.1333 | F6: 数据开发部 | G6: 1878.2662 | H6: 410.24 | I6: =G6/8.5 -> 220.97249 | J6: 300.75 | K6: =J6/8.5 -> 35.382353 | L6: =K6/I6 -> 0.16012107
A7: 信息管理部 | B7: 280.5 | F7: 数据平台部 | G7: 1225.3331 | H7: 241.66 | I7: =G7/8.5 -> 144.15684 | J7: 349.1333 | K7: =J7/8.5 -> 41.074506 | L7: =K7/I7 -> 0.2849293
A8: 智能应用二部 | B8: 76.5 | F8: 智能平台部 | G8: 160.6835 | H8: 37 | I8: =G8/8.5 -> 18.903941 | K8: =J8/8.5 -> 0 | L8: =K8/I8 -> 0
A9: 智能应用一部 | B9: 76.5 | F9: 智能应用二部 | G9: 919.4165 | H9: 201.5 | I9: =G9/8.5 -> 108.16665 | J9: 76.5 | K9: =J9/8.5 -> 9 | L9: =K9/I9 -> 0.083204946
A10: 总计 | B10: 1083.3833 | F10: 智能应用一部 | G10: 860.6997 | H10: 141.41 | I10: =G10/8.5 -> 101.25879 | J10: 76.5 | K10: =J10/8.5 -> 9 | L10: =K10/I10 -> 0.088881174

Sheet 数管部工时明细
A1: 工作日期 | B1: 记录名称 | C1: 工时（分钟） | D1: 姓名 | E1: 工号 | F1: 所属科室 | G1: 所属分组 | H1: 是否行员 | I1: 任务描述 | J1: 所属公司 | K1: 开发领域 | L1: 驻场模式 | M1: 所属部落 | N1: 所属小队 | O1: 应用系统 | P1: 批次 | Q1: 所属的ADPM需求 | R1: 工作类型 | S1: 人员等级 | T1: 用户名 | U1: 工号 | V1: 卡片类型 | W1: 人员角色 | X1: ADPM需求类型 | Y1: ADPM需求编号 | Z1: 应用标识 | AA1: 需求牵头部门（三级） | AB1: ADPM需求状态 | AC1: 工作卡状态 | AD1: 描述 | AE1: 工时（小时） | AF1: 需求牵头部门（二级） | AG1: 事项类型 | AH1: 工作大类
A2: 46107 | B2: 指标-工时 | C2: 510 | D2: 邢逸云 | E2: CS9316 | F2: 数据开发部 | H2: 否 | I2: udas_e_gs_corp_dpst_bal_hd开发 | J2: 深圳市长亮科技股份有限公司 | K2: 数据开发 | L2: B模式 | M2: 数据开发部落 | N2: 大数据应用三队 | O2: Hadoop大数据集群 | P2: ADPM需求-X20231222000020[第6批] | Q2: UDAS业务数据模型迁移 | S2: 中级 | T2: cs9316@bosc.cn | U2: cs9316 | V2: 系统功能 | W2: 开发 | X2: 项目 | Y2: X20231222000020 | Z2: BDPHADP | AB2: 进行中 | AC2: 已完成 | AD2: udas_e_gs_corp_dpst_bal_hd新增字段，银联标识、土保标识、源系统期限、源系统期限代码 仓内上下游联调测试（回归部分）按照3轮测试评估 | AE2: 8.5 | AF2: 数据平台部
A3: 46107 | B3: 指标-工时 | C3: 510 | D3: 高源 | E3: 307438 | F3: 智能应用二部 | G3: =VLOOKUP(D3,'人员清单-202603'!D:J,7,FALSE) -> 基础模型组 | H3: 是 | I3: 反诈个人账户风险分模型数据探查 | M3: 智能研发部落 | N3: 基础模型小队 | T3: 307438@bosc.cn | U3: 307438 | V3: 事项任务 | AC3: 进行中 | AE3: 8.5 | AG3: 开发（含模型、应用、数仓等）
A4: 46107 | B4: 指标-工时 | C4: 510 | D4: 包惠 | E4: CS5698 | F4: 数据开发部 | H4: 否 | I4: MRP迁移 | J4: 深圳市长亮科技股份有限公司 | K4: 数据开发 | L4: B模式 | M4: 数据开发部落 | N4: 基础数据小队 | O4: Hadoop大数据集群 | Q4: 基于整合模型金融市场领域的MRP迁移改造需求 | S4: 中级 | T4: cs5698@bosc.cn | U4: cs5698 | V4: 系统功能 | W4: 开发 | X4: 维护需求 | Y4: X20260224000012 | Z4: BDPHADP | AB4: 进行中 | AC4: 详细设计 | AE4: 8.5 | AF4: 数据开发部
A5: 46107 | B5: 指标-工时 | C5: 660 | D5: 张典兵 | E5: CS2303 | F5: 数据平台部 | H5: 否 | I5: 公司客户关系管理开发-CCRM-X20250409000030 | J5: 高伟达软件股份有限公司 | K5: CRM | L5: B模式 | M5: 信息管理部落 | N5: 同业CRM小队 | O5: 公司客户关系管理 | P5: ADPM需求-X20250409000030[第1批] | Q5: 投行业务管理平台优化需求 | S5: 资深 | T5: cs2303@bosc.cn | U5: cs2303 | V5: 系统功能 | W5: 管理人员（小队级） | X5: 项目 | Y5: X20250409000030 | Z5: CCRM | AA5: 开发一部 | AB5: 进行中 | AC5: 已完成 | AD5: 1. 代码开发 2. 配合联调 | AE5: 11 | AF5: 上海开发测试中心
A6: 46107 | B6: 指标-工时 | C6: 510 | D6: 陈烨 | E6: CS6318 | F6: 数据平台部 | H6: 否 | I6: 对公CRM移动端-新增周报管理功能-需求和系统分析 | J6: 北京东方国信科技股份有限公司 | K6: CRM | L6: B模式 | M6: 信息管理部落 | N6: 零售对公CRM APP小队 | O6: 公司客户关系管理 | Q6: 关于在对公CRM新增周报管理功能的需求 | S6: 中级 | T6: cs6318@bosc.cn | U6: cs6318 | V6: 系统功能 | W6: 开发 | X6: 维护需求 | Y6: X20260228000040 | Z6: CCRM | AB6: 进行中 | AC6: 详细设计 | AE6: 8.5 | AF6: 数据平台部
A7: 46107 | B7: 指标-工时 | C7: 510 | D7: 雷露 | E7: CS7825 | F7: 数据开发部 | H7: 否 | I7: X20250612000039_模型新增互联网标签 | J7: 深圳市长亮科技股份有限公司 | K7: 数据开发 | L7: B模式 | M7: 数据开发部落 | N7: 大数据应用三队 | O7: Hadoop大数据集群 | P7: ADPM需求-X20250612000039[第6批] | Q7: 2025年经营指标体系建设 | S7: 中级 | T7: cs7825@bosc.cn | U7: cs7825 | V7: 系统功能 | W7: 开发 | X7: 项目 | Y7: X20250612000039 | Z7: BDPHADP | AB7: 进行中 | AC7: 已完成 | AD7: UDAS_F_GS_IND_FIN_LOAN_DTL_N新增互联网标签 脚本开发 UDAS_F_GS_IND_FIN_LOAN_DTL_N新增互联网标签 单元测试 | AE7: 8.5 | AF7: 综合管理部
A8: 46107 | B8: 指标-工时 | C8: 510 | D8: 吕恩元 | E8: CS0966 | F8: 数据开发部 | H8: 否 | I8: KPI项目-KPI页面配置调整及数据验证 | J8: 北京宇信科技集团股份有限公司 | K8: 数据开发 | L8: B模式 | M8: 信息管理部落 | N8: UDAS风险数据小队 | O8: 掌上行 | P8: ADPM需求-X20250612000039[第6批] | Q8: 2025年经营指标体系建设 | S8: 高级 | T8: cs0966@bosc.cn | U8: cs0966 | V8: 系统功能 | W8: 需求分析BA | X8: 项目 | Y8: X20250612000039 | Z8: AMBI | AB8: 进行中 | AC8: 已完成 | AD8: 机构KPI页面配置及数据测试验证 | AE8: 8.5 | AF8: 综合管理部
A9: 46107 | B9: 指标-工时 | C9: 510 | D9: 陈旭东 | E9: CS1663 | F9: 数据开发部 | H9: 否 | I9: 视图底表构建-天正 | J9: 上海天正智能数据服务有限公司 | K9: 数据开发 | L9: B模式 | M9: 信息管理部落 | N9: NRP集市小队 | O9: Hadoop大数据集群 | P9: ADPM需求-X20240926000006[第3批] | Q9: 2024年度经营单位数字化管理建设项目 | S9: 高级 | T9: cs1663@bosc.cn | U9: cs1663 | V9: 系统功能 | W9: 开发 | X9: 项目 | Y9: X20240926000006 | Z9: BDPHADP | AB9: 进行中 | AC9: 已完成 | AD9: RDI_F_IND_AGNFUND_TX_BW作业迁移分析，S层缺失字段登记、脚本开发 | AE9: 8.5 | AF9: 信息管理部
A10: 46107 | B10: 指标-工时 | C10: 600 | D10: 胡丽 | E10: CS7763 | F10: 数据测试部 | H10: 否 | I10: X20240108000018__慧信工程-监管报送集市建设_第8批次 | J10: 中电金信软件有限公司 | L10: A模式 | M10: 核心系统重构项目组 | N10: 数据小队 | P10: ADPM需求-X20240108000018[第8批] | Q10: 慧信工程-监管报送集市建设 | S10: 高级 | T10: cs7763@bosc.cn | U10: cs7763 | V10: 条目需求 | W10: 测试 | X10: 项目 | Y10: X20240108000018 | AB10: 进行中 | AC10: 可行性分析 | AE10: 10 | AF10: 数据开发部
A11: 46107 | B11: 指标-工时 | C11: 510 | D11: 秦连奥 | E11: CS101076 | F11: 数据平台部 | H11: 否 | I11: MMM日常维护4 | J11: 深圳市长亮科技股份有限公司 | K11: 数据开发 | L11: B模式 | O11: 信用风险监测预警 | S11: 中级 | T11: cs101076@bosc.cn | U11: cs101076 | V11: 系统功能 | W11: 开发 | Z11: RAD | AC11: 详细设计 | AD11: 1.查看调试客户视图，集团视图代码逻辑。 | AE11: 8.5
A12: 46107 | B12: 指标-工时 | C12: 510 | D12: 胡文彬 | E12: CS100924 | F12: 数据测试部 | H12: 否 | I12: X20240108000018__慧信工程-监管报送集市建设_第8批次 | J12: 上海复深蓝软件股份有限公司 | L12: A模式 | M12: 数据开发部落 | N12: 数据测试小队 | P12: ADPM需求-X20240108000018[第8批] | Q12: 慧信工程-监管报送集市建设 | S12: 中级 | T12: cs100924@bosc.cn | U12: cs100924 | V12: 条目需求 | X12: 项目 | Y12: X20240108000018 | AB12: 进行中 | AC12: 可行性分析 | AE12: 8.5 | AF12: 数据开发部
A13: 46107 | B13: 指标-工时 | C13: 690 | D13: 任凯 | E13: CS101133 | F13: 数据开发部 | H13: 否 | I13: 一表通配合测试 | J13: 南京科融数据系统股份有限公司 | K13: 监管报送 | L13: B模式 | M13: 监管报送部落 | N13: 银保监报送小队 | O13: 监管可信区 | P13: ADPM需求-X20240108000018[第8批] | Q13: 慧信工程-监管报送集市建设 | S13: 中级 | T13: cs101133@bosc.cn | U13: cs101133 | V13: 系统功能 | W13: 开发 | X13: 项目 | Y13: X20240108000018 | Z13: RTZ | AB13: 进行中 | AC13: 详细设计 | AD13: 重点指标配合测试、新旧线比对配合测试 | AE13: 11.5 | AF13: 数据开发部
A14: 46107 | B14: 指标-工时 | C14: 510 | D14: 单丽可 | E14: CS3225 | F14: 数据开发部 | H14: 否 | I14: 客户经理业绩功能-CRM集市开发 | J14: 上海天正智能数据服务有限公司 | K14: 数据开发 | L14: B模式 | M14: 数据开发部落 | N14: 大数据应用一队 | O14: Hadoop大数据集群 | P14: ADPM需求-X20251104000031[第1批] | Q14: 关于对公CRM客户经理业绩前端页面调整的需求书 | S14: 中级 | T14: cs3225@bosc.cn | U14: cs3225 | V14: 系统功能 | W14: 开发 | X14: 维护需求 | Y14: X20251104000031 | Z14: BDPHADP | AB14: 进行中 | AC14: 已完成 | AD14: 新增作业:E_CRM_C_MNGR_WORK_STC_SUM(对公客户经理工作结构统计表) 初始化和批量脚本开发完成 | AE14: 8.5 | AF14: 数据平台部
A15: 46107 | B15: 指标-工时 | C15: 510 | D15: 徐宥 | E15: CS4237 | F15: 数据测试部 | H15: 否 | I15: X20240108000018__慧信工程-监管报送集市建设_第8批次 | J15: 高伟达软件股份有限公司 | L15: A模式 | M15: 上海科技管理部落 | N15: 配置管理小队（上海） | P15: ADPM需求-X20240108000018[第8批] | Q15: 慧信工程-监管报送集市建设 | S15: 初级 | T15: cs4237@bosc.cn | U15: cs4237 | V15: 条目需求 | W15: 配置管理员 | X15: 项目 | Y15: X20240108000018 | AB15: 进行中 | AC15: 可行性分析 | AE15: 8.5 | AF15: 数据开发部
A16: 46107 | B16: 指标-工时 | C16: 610 | D16: 梁天蕾 | E16: CS1711 | F16: 数据平台部 | H16: 否 | I16: 公司客户关系管理开发-CCRM-X20250409000030 | J16: 高伟达软件股份有限公司 | K16: CRM | L16: B模式 | M16: 信息管理部落 | N16: 零售对公CRM APP小队 | O16: 公司客户关系管理 | P16: ADPM需求-X20250409000030[第1批] | Q16: 投行业务管理平台优化需求 | S16: 中级 | T16: cs1711@bosc.cn | U16: cs1711 | V16: 系统功能 | W16: 开发 | X16: 项目 | Y16: X20250409000030 | Z16: CCRM | AA16: 开发一部 | AB16: 进行中 | AC16: 已完成 | AD16: 接口开发 | AE16: 10.1667 | AF16: 上海开发测试中心
A17: 46107 | B17: 指标-工时 | C17: 510 | D17: 姚彬晖 | E17: CS100416 | F17: 数据开发部 | H17: 否 | I17: X20250305000005-BDPHADP | J17: 北京宇信科技集团股份有限公司 | K17: 数据开发 | L17: B模式 | M17: 监管报送部落 | N17: 监管报送集市小队 | O17: Hadoop大数据集群 | P17: ADPM需求-X20250305000005[第1批] | Q17: 关于江苏金租接入车生态项目的需求书 | S17: 中级 | T17: cs100416@bosc.cn | U17: cs100416 | V17: 系统功能 | W17: 开发 | X17: 年度预算制 | Y17: X20250305000005 | Z17: BDPHADP | AA17: 开发一部 | AB17: 进行中 | AC17: 已完成 | AD17: 1.X20250305000005-江苏金租接入车生态需求:在测试环境跑一表通报表20260313的数据，并配合下游进行测试验证。 2.X20250305000005-江苏金租接入车生态需求:在自动化测试平台测试20260327版本的脚本。 3.现金报送需求：配合下游排查集市“核心收费交易明细”表20251231期“科目代码”、“账号”字段的生产数据问题。 | AE17: 8.5 | AF17: 上海开发测试中心
A18: 46107 | B18: 指标-工时 | C18: 510 | D18: 吴杰 | E18: CS6140 | F18: 信息管理部 | H18: 否 | I18: KPI项目-非标准化下钻页面-UDAS数据开发 | J18: 北京宇信科技集团股份有限公司 | K18: 数据开发 | L18: B模式 | M18: 信息管理部落 | N18: NRP集市小队 | O18: 统一报表及指标平台 | P18: ADPM需求-X20250612000039[第6批] | Q18: 2025年经营指标体系建设 | S18: 高级 | T18: cs6140@bosc.cn | U18: cs6140 | V18: 系统功能 | W18: 开发 | X18: 项目 | Y18: X20250612000039 | Z18: UDAS | AB18: 进行中 | AC18: 已完成 | AD18: 新兴板块-下钻页面指标、管理指标:修改一个存储过程【分行代客客户模型黄金租赁有效户逻辑修改】 | AE18: 8.5 | AF18: 综合管理部
A19: 46107 | B19: 指标-工时 | C19: 510 | D19: 曹婷 | E19: CS100315 | F19: 数据开发部 | H19: 否 | I19: CAFBDM开发任务 | J19: 天阳宏业科技股份有限公司 | K19: 数据开发 | L19: B模式 | M19: 数据开发部落 | N19: 基础数据小队 | O19: 金融基础数据模型计算区 | P19: ADPM需求-X20260204000040[第2批] | Q19: 【反电诈】关于优化警银数据交互功能的需求 | S19: 中级 | T19: cs100315@bosc.cn | U19: cs100315 | V19: 系统功能 | X19: 维护需求 | Y19: X20260204000040 | Z19: CAFBDM | AA19: 基础中台开发团队 | AB19: 进行中 | AC19: 已完成 | AE19: 8.5 | AF19: 苏州开发测试中心
A20: 46107 | B20: 指标-工时 | C20: 510 | D20: 余晶鑫 | E20: CS9091 | F20: 数据开发部 | H20: 否 | I20: 监管可信区-银丰 | J20: 北京银丰新融科技开发有限公司 | K20: 监管报送 | L20: B模式 | M20: 监管报送部落 | N20: 银保监报送小队 | O20: 监管可信区 | P20: ADPM需求-X20250620000012[第1批] | Q20: 监管一表通三期 | S20: 中级 | T20: cs9091@bosc.cn | U20: cs9091 | V20: 系统功能 | X20: 项目 | Y20: X20250620000012 | Z20: RTZ | AB20: 进行中 | AC20: 已完成 | AE20: 8.5 | AF20: 数据开发部
A21: 46107 | B21: 指标-工时 | C21: 510 | D21: 陈粉玲 | E21: CS6565 | F21: 信息管理部 | H21: 否 | I21: 帆软看板开发---蔡、陈 | J21: 上海天正智能数据服务有限公司 | K21: 数据开发 | L21: B模式 | O21: 司库应用计算区 | P21: ADPM需求-X20240423000001[第12批] | Q21: 关于司库进阶版功能建设的需求 | S21: 中级 | T21: cs6565@bosc.cn | U21: cs6565 | V21: 系统功能 | W21: 数据分析助理 | X21: 项目 | Y21: X20240423000001 | Z21: M.TBS.TCA | AA21: 司库开发团队 | AB21: 进行中 | AC21: 已完成 | AD21: 司库数据集团资金日报明细表数据核对 | AE21: 8.5 | AF21: 上海开发测试中心
A22: 46107 | B22: 指标-工时 | C22: 510 | D22: 童加明 | E22: CS6758 | F22: 数据测试部 | H22: 否 | I22: 风险模块功能优化 | J22: 神州数码融信软件有限公司 | L22: A模式 | M22: 数据开发部落 | N22: 数据测试小队 | O22: 司库风险管理 | P22: ADPM需求-X20240423000001[第12批] | Q22: 关于司库进阶版功能建设的需求 | S22: 中级 | T22: cs6758@bosc.cn | U22: cs6758 | V22: 系统功能 | X22: 项目 | Y22: X20240423000001 | Z22: M.TBS.RM | AA22: 司库开发团队 | AB22: 进行中 | AC22: 已完成 | AE22: 8.5 | AF22: 上海开发测试中心
A23: 46107 | B23: 指标-工时 | C23: 255 | D23: 桑双双 | E23: CS9009 | F23: 数据开发部 | H23: 否 | I23: X20260106000017-BDPHADP | J23: 天阳宏业科技股份有限公司 | K23: 数据开发 | L23: B模式 | M23: 数据开发部落 | N23: 大数据应用二队 | O23: Hadoop大数据集群 | P23: ADPM需求-X20260106000017[第1批] | Q23: IRMS票易贷数据迁移功能优化业务需求书-业务功能类V4.5 | S23: 中级 | T23: cs9009@bosc.cn | U23: cs9009 | V23: 系统功能 | W23: 开发 | X23: 年度预算制 | Y23: X20260106000017 | Z23: BDPHADP | AA23: 开发一部 | AB23: 进行中 | AC23: 详细设计 | AD23: 票易贷测试 | AE23: 4.25 | AF23: 上海开发测试中心
A24: 46107 | B24: 指标-工时 | C24: 556 | D24: 吴梦飞 | E24: CS9665 | F24: 数据开发部 | H24: 否 | I24: 一表通配合测试 | J24: 南京科融数据系统股份有限公司 | K24: 监管报送 | L24: B模式 | M24: 监管报送部落 | N24: 银保监报送小队 | O24: 监管可信区 | P24: ADPM需求-X20240108000018[第8批] | Q24: 慧信工程-监管报送集市建设 | S24: 中级 | T24: cs9665@bosc.cn | U24: cs9665 | V24: 系统功能 | X24: 项目 | Y24: X20240108000018 | Z24: RTZ | AB24: 进行中 | AC24: 详细设计 | AD24: 一表通旧线数据与新线数据对比，并分析差异原因 重点指标差异对比 | AE24: 9.2667 | AF24: 数据开发部
A25: 46107 | B25: 指标-工时 | C25: 510 | D25: 王楚齐 | E25: CS8932 | F25: 数据开发部 | H25: 否 | I25: X20240119000030-大数据仓库及应用系统数据时效治理专项优化项目(2024年)-第2批次 | J25: 深圳市长亮科技股份有限公司 | K25: 数据开发 | L25: B模式 | M25: 数据开发部落 | N25: 基础数据小队 | P25: ADPM需求-X20240119000030[第2批] | Q25: 大数据仓库及应用系统数据时效治理专项优化项目(2024年) | S25: 中级 | T25: cs8932@bosc.cn | U25: cs8932 | V25: 条目需求 | W25: 开发 | X25: 项目 | Y25: X20240119000030 | AB25: 进行中 | AC25: 待测试 | AD25: RLG_CHAIN_CCM_COMPANY_ADS 配合CCM迁移切换 | AE25: 8.5 | AF25: 数据开发部
A26: 46107 | B26: 指标-工时 | C26: 550 | D26: 李宇 | E26: CS101206 | F26: 数据开发部 | H26: 否 | I26: 一表通配合测试 | J26: 南京科融数据系统股份有限公司 | K26: 监管报送 | L26: B模式 | M26: 监管报送部落 | N26: 银保监报送小队 | O26: 监管可信区 | P26: ADPM需求-X20240108000018[第8批] | Q26: 慧信工程-监管报送集市建设 | S26: 中级 | T26: cs101206@bosc.cn | U26: cs101206 | V26: 系统功能 | X26: 项目 | Y26: X20240108000018 | Z26: RTZ | AB26: 进行中 | AC26: 详细设计 | AD26: 1.验证重点指标修复后问题 2.开发一表通转east对公信贷分户账逻辑 | AE26: 9.1667 | AF26: 数据开发部
A27: 46107 | B27: 指标-工时 | C27: 510 | D27: 桂贝 | E27: CS0493 | F27: 数据开发部 | H27: 否 | I27: CAFBDM开发 | J27: 上海天正智能数据服务有限公司 | K27: 数据开发 | L27: B模式 | M27: 数据开发部落 | N27: 基础数据小队 | O27: 金融基础数据模型计算区 | P27: ADPM需求-X20251210000003[第2批] | Q27: 运营风险监控平台存量模型优化（重要物品类、账户及交易类等） | S27: 高级 | T27: cs0493@bosc.cn | U27: cs0493 | V27: 系统功能 | W27: 开发 | X27: 维护需求 | Y27: X20251210000003 | Z27: CAFBDM | AA27: 智能创新开发团队 | AB27: 进行中 | AC27: 已完成 | AD27: 整合模型损益开发测试 | AE27: 8.5 | AF27: 苏州开发测试中心
A28: 46107 | B28: 指标-工时 | C28: 255 | D28: 桑双双 | E28: CS9009 | F28: 数据开发部 | H28: 否 | I28: 【数据仓库集群】数据仓库集群配合优化 | J28: 天阳宏业科技股份有限公司 | K28: 数据开发 | L28: B模式 | M28: 数据开发部落 | N28: 大数据应用二队 | O28: Hadoop大数据集群 | P28: ADPM需求-X20250422000007[第2批] | Q28: 零售内评分池对接、中小企业营收取数逻辑优化的运维需求 | S28: 中级 | T28: cs9009@bosc.cn | U28: cs9009 | V28: 系统功能 | W28: 开发 | X28: 维护需求 | Y28: X20250422000007 | Z28: BDPHADP | AA28: 开发七部 | AB28: 进行中 | AC28: 已完成 | AD28: 写白皮书 E_FRM_NRWA_RETAIL_EXPOSURE_2 E_FRM_I9_DEVAL_CRDCARD_MT 写需求概要设计 | AE28: 4.25 | AF28: 上海开发测试中心
A29: 46107 | B29: 指标-工时 | C29: 510 | D29: 周井茹 | E29: CS7628 | F29: 数据开发部 | H29: 否 | I29: MRP开发 | J29: 深圳市长亮科技股份有限公司 | K29: 数据开发 | L29: B模式 | M29: 数据开发部落 | N29: 基础数据小队 | O29: Hadoop大数据集群 | P29: ADPM需求-X20251219000038[第2批] | Q29: udas和数仓对上海地区支行代客业务指标统计适配性改造 | S29: 中级 | T29: cs7628@bosc.cn | U29: cs7628 | V29: 系统功能 | W29: 开发 | X29: 维护需求 | Y29: X20251219000038 | Z29: BDPHADP | AB29: 进行中 | AC29: 已完成 | AD29: 债券积数表查数 中收表测试、低成本负债测试 | AE29: 8.5 | AF29: 数据开发部
A30: 46107 | B30: 指标-工时 | C30: 525 | D30: 刘洲 | E30: CS100308 | F30: 数据测试部 | H30: 否 | I30: X20240108000018__慧信工程-监管报送集市建设_第8批次 | J30: 京北方信息技术股份有限公司 | L30: A模式 | P30: ADPM需求-X20240108000018[第8批] | Q30: 慧信工程-监管报送集市建设 | S30: 中级 | T30: cs100308@bosc.cn | U30: cs100308 | V30: 条目需求 | X30: 项目 | Y30: X20240108000018 | AB30: 进行中 | AC30: 可行性分析 | AE30: 8.75 | AF30: 数据开发部
A31: 46107 | B31: 指标-工时 | C31: 510 | D31: 王娟 | E31: CS0987 | F31: 数据开发部 | H31: 否 | I31: 网点交易需求-掌上行开发 | J31: 北京宇信科技集团股份有限公司 | K31: 数据开发 | L31: B模式 | O31: 掌上行 | P31: ADPM需求-X20250708000021[第2批] | Q31: 网点交易量等指标掌上行展示工作 | S31: 中级 | T31: cs0987@bosc.cn | U31: cs0987 | V31: 系统功能 | W31: 需求分析BA | X31: 维护需求 | Y31: X20250708000021 | Z31: AMBI | AB31: 进行中 | AC31: 已完成 | AE31: 8.5 | AF31: 数据开发部
A32: 46107 | B32: 指标-工时 | C32: 525 | D32: 尚佳宝 | E32: CS100902 | F32: 数据测试部 | H32: 否 | I32: X20240108000018__慧信工程-监管报送集市建设_第8批次 | J32: 上海复深蓝软件股份有限公司 | L32: A模式 | M32: 数据开发部落 | N32: 数据测试小队 | P32: ADPM需求-X20240108000018[第8批] | Q32: 慧信工程-监管报送集市建设 | S32: 中级 | T32: cs100902@bosc.cn | U32: cs100902 | V32: 条目需求 | X32: 项目 | Y32: X20240108000018 | AB32: 进行中 | AC32: 可行性分析 | AE32: 8.75 | AF32: 数据开发部
A33: 46107 | B33: 指标-工时 | C33: 510 | D33: 符伟 | E33: CS0574 | F33: 数据开发部 | H33: 否 | I33: X20251027000041-BDPDWS | J33: 北京宇信科技集团股份有限公司 | K33: 数据开发 | L33: B模式 | M33: 信息管理部落 | N33: NRP集市小队 | O33: DWS数据集群 | P33: ADPM需求-X20251027000041[第1批] | Q33: 南通众和应收账款业务业务需求书 | S33: 中级 | T33: cs0574@bosc.cn | U33: cs0574 | V33: 系统功能 | W33: 开发 | X33: 年度预算制 | Y33: X20251027000041 | Z33: BDPDWS | AA33: 开发一部 | AB33: 进行中 | AC33: 已完成 | AD33: UDAS_F_CORP_LOAN_BAL_MESSAGE\UDAS_F_CORP_CONSLOAN_BAL\UDAS_F_CORP_LOAN_OCCUR_MESSAGE\UDAS_F_CORP_LOAN_INFO 测试验证。 | AE33: 8.5 | AF33: 上海开发测试中心
A34: 46107 | B34: 指标-工时 | C34: 510 | D34: 李梁 | E34: CS100191 | F34: 数据测试部 | H34: 否 | I34: X20240108000018__慧信工程-监管报送集市建设_第8批次 | J34: 中电金信软件有限公司 | L34: A模式 | M34: 数据开发部落 | N34: 数据测试小队 | P34: ADPM需求-X20240108000018[第8批] | Q34: 慧信工程-监管报送集市建设 | S34: 高级 | T34: cs100191@bosc.cn | U34: cs100191 | V34: 条目需求 | X34: 项目 | Y34: X20240108000018 | AB34: 进行中 | AC34: 可行性分析 | AD34: 503518 | AE34: 8.5 | AF34: 数据开发部
A35: 46107 | B35: 指标-工时 | C35: 510 | D35: 孙建国 | E35: CS0375 | F35: 数据平台部 | H35: 否 | I35: UDAS对公模型优化整合分析 | J35: 北京宇信科技集团股份有限公司 | K35: 数据开发 | L35: B模式 | M35: 信息管理部落 | N35: UDAS公共1队 | O35: 掌上行 | P35: ADPM需求-X20231222000020[第6批] | Q35: UDAS业务数据模型迁移 | S35: 中级 | T35: cs0375@bosc.cn | U35: cs0375 | V35: 系统功能 | W35: 开发 | X35: 项目 | Y35: X20231222000020 | Z35: AMBI | AB35: 进行中 | AC35: 已完成 | AD35: 掌上行 20260327版本 在 PI 环境部署测试验证 ； 已完成 100% ； | AE35: 8.5 | AF35: 数据平台部
A36: 46106.964 | B36: 指标-工时 | C36: 510 | D36: 曹树森 | E36: CS8393 | F36: 数据开发部 | H36: 否 | I36: MRP迁移 | J36: 深圳市长亮科技股份有限公司 | K36: 数据开发 | L36: B模式 | M36: 数据开发部落 | N36: 基础数据小队 | O36: Hadoop大数据集群 | Q36: 基于整合模型金融市场领域的MRP迁移改造需求 | S36: 中级 | T36: cs8393@bosc.cn | U36: cs8393 | V36: 系统功能 | W36: 开发 | X36: 维护需求 | Y36: X20260224000012 | Z36: BDPHADP | AB36: 进行中 | AC36: 详细设计 | AD36: 脚本开发开发中1个：企业信用受益权投资流水表，增加补录数据组逻辑，脚本开发自测 | AE36: 8.5 | AF36: 数据开发部
A37: 46106.917 | B37: 指标-工时 | C37: 510 | D37: 胡艳红 | E37: CS7862 | F37: 数据开发部 | H37: 否 | I37: 数仓模型设计--李、胡 | J37: 上海天正智能数据服务有限公司 | K37: 数据开发 | L37: B模式 | M37: 数据开发部落 | N37: 基础数据小队 | O37: 司库应用计算区 | P37: ADPM需求-X20240423000001[第12批] | Q37: 关于司库进阶版功能建设的需求 | S37: 中级 | T37: cs7862@bosc.cn | U37: cs7862 | V37: 系统功能 | W37: 开发 | X37: 项目 | Y37: X20240423000001 | Z37: M.TBS.TCA | AA37: 司库开发团队 | AB37: 进行中 | AC37: 已完成 | AD37: 联调 接口监管报送17接口（应收款项）、监管报送18接口（应付款项），监管报送04接口（债券），监管报送03接口（银行贷款） | AE37: 8.5 | AF37: 上海开发测试中心
A38: 46106.904 | B38: 指标-工时 | C38: 750 | D38: 郑于东 | E38: CS101220 | F38: 信息管理部 | H38: 否 | I38: 产品设计--崔 | J38: 北京宇信科技集团股份有限公司 | K38: 数据开发 | L38: B模式 | M38: 信息管理部落 | N38: UDAS公共1队 | O38: 司库应用计算区 | P38: ADPM需求-X20240423000001[第12批] | Q38: 关于司库进阶版功能建设的需求 | S38: 中级 | T38: cs101220@bosc.cn | U38: cs101220 | V38: 系统功能 | X38: 项目 | Y38: X20240423000001 | Z38: M.TBS.TCA | AA38: 司库开发团队 | AB38: 进行中 | AC38: 已完成 | AD38: 开发宝山国资委-债务融资驾驶舱 和应收应付驾驶舱 | AE38: 12.5 | AF38: 上海开发测试中心
A39: 46106.893 | B39: 指标-工时 | C39: 310 | D39: 扶子懿 | E39: CS100010 | F39: 数据开发部 | H39: 否 | I39: 整合模型追数 | J39: 神州数码融信软件有限公司 | K39: 数据开发 | L39: B模式 | M39: 数据开发部落 | N39: 基础数据小队 | O39: 金融基础数据模型计算区 | Q39: 电信网络诈骗受害人保护项目业务需求书 | S39: 中级 | T39: cs100010@bosc.cn | U39: cs100010 | V39: 系统功能 | W39: 开发 | X39: 项目 | Y39: X20250117000017 | Z39: CAFBDM | AA39: 基础中台开发团队 | AB39: 进行中 | AC39: 详细设计 | AD39: SQLREVIEW生产数据验证。 | AE39: 5.1667 | AF39: 苏州开发测试中心
A40: 46106.86 | B40: 指标-工时 | C40: 85 | D40: 王正超 | E40: 303471 | F40: 数据平台部 | G40: =VLOOKUP(D40,'人员清单-202603'!D:J,7,FALSE) -> 应用开发组 | H40: 是 | I40: crm开发进度对齐会 | M40: 信息管理部落 | N40: 零售对公CRM APP小队 | T40: 303471@bosc.cn | U40: 303471 | V40: 事项任务 | W40: 小队长 | AC40: 进行中 | AE40: 1.4167 | AG40: 项目管理（含外包管理）
A41: 46106.859 | B41: 指标-工时 | C41: 85 | D41: 王正超 | E41: 303471 | F41: 数据平台部 | G41: =VLOOKUP(D41,'人员清单-202603'!D:J,7,FALSE) -> 应用开发组 | H41: 是 | I41: 架构会-crm访问wps | M41: 信息管理部落 | N41: 零售对公CRM APP小队 | T41: 303471@bosc.cn | U41: 303471 | V41: 事项任务 | W41: 小队长 | AC41: 进行中 | AE41: 1.4167 | AG41: 评审（含架构评审、代码评审、CAB等）
A42: 46106.859 | B42: 指标-工时 | C42: 85 | D42: 王正超 | E42: 303471 | F42: 数据平台部 | G42: =VLOOKUP(D42,'人员清单-202603'!D:J,7,FALSE) -> 应用开发组 | H42: 是 | I42: 【会议邀请】CRM接口改造事项讨论 | M42: 信息管理部落 | N42: 零售对公CRM APP小队 | T42: 303471@bosc.cn | U42: 303471 | V42: 事项任务 | W42: 小队长 | AC42: 进行中 | AE42: 1.4167 | AG42: 评审（含架构评审、代码评审、CAB等）
A43: 46106.859 | B43: 指标-工时 | C43: 85 | D43: 王正超 | E43: 303471 | F43: 数据平台部 | G43: =VLOOKUP(D43,'人员清单-202603'!D:J,7,FALSE) -> 应用开发组 | H43: 是 | I43: 关于对公外币账户E开户需求讨论会的会议通知 | M43: 信息管理部落 | N43: 零售对公CRM APP小队 | T43: 303471@bosc.cn | U43: 303471 | V43: 事项任务 | W43: 小队长 | AC43: 进行中 | AE43: 1.4167 | AG43: 评审（含架构评审、代码评审、CAB等）
A44: 46106.839 | B44: 指标-工时 | C44: 255 | D44: 盛万之 | E44: CS7071 | F44: 数据开发部 | H44: 否 | I44: 大数据开发 | J44: 上海天正智能数据服务有限公司 | K44: 数据开发 | L44: B模式 | M44: 数据平台部落 | N44: 大数据入仓小队 | O44: Hadoop大数据集群 | P44: ADPM需求-X20251215000003[第3批] | Q44: 关于抖音电商业务功能优化需求书 | S44: 初级 | T44: cs7071@bosc.cn | U44: cs7071 | V44: 系统功能 | W44: 开发 | X44: 维护需求 | Y44: X20251215000003 | Z44: BDPHADP | AA44: 开发四部 | AB44: 进行中 | AC44: 已完成 | AD44: 修改采集表采集平台开发，抽取测试数据并验证数据准确性 表清单：iccs_cutoff_differ,iccs_cutoff_record | AE44: 4.25 | AF44: 上海开发测试中心
A45: 46106.839 | B45: 指标-工时 | C45: 255 | D45: 盛万之 | E45: CS7071 | F45: 数据开发部 | H45: 否 | I45: finebibi看板 | J45: 上海天正智能数据服务有限公司 | K45: 数据开发 | L45: B模式 | M45: 数据平台部落 | N45: 大数据入仓小队 | O45: Hadoop大数据集群 | P45: ADPM需求-X20251216000025[第1批] | Q45: E变更流程状态及影像、报表查询需求 | S45: 初级 | T45: cs7071@bosc.cn | U45: cs7071 | V45: 系统功能 | W45: 开发 | X45: 维护需求 | Y45: X20251216000025 | Z45: BDPHADP | AA45: 开发四部 | AB45: 进行中 | AC45: 已完成 | AD45: 新入表采集平台开发，抽取测试数据并验证数据准确性 表清单：coi_change_form_info,coi_change_ins_qry_info | AE45: 4.25 | AF45: 苏州开发测试中心
A46: 46106.827 | B46: 指标-工时 | C46: 510 | D46: 楚江江 | E46: CS3509 | F46: 数据开发部 | H46: 否 | I46: 易鑫-BDPHADP-CDA/整合模型 | J46: 深圳市长亮科技股份有限公司 | K46: 数据开发 | L46: B模式 | M46: 数据开发部落 | N46: 基础数据小队 | O46: Hadoop大数据集群 | P46: ADPM需求-X20250923000046[第1批] | Q46: 易鑫商车贷迁移功能优化需求 | S46: 高级 | T46: cs3509@bosc.cn | U46: cs3509 | V46: 系统功能 | W46: 开发 | X46: 年度预算制 | Y46: X20250923000046 | Z46: BDPHADP | AA46: 开发一部 | AB46: 进行中 | AC46: 详细设计 | AE46: 8.5 | AF46: 上海开发测试中心
A47: 46106.813 | B47: 指标-工时 | C47: 660 | D47: 王尧 | E47: CS100377 | F47: 数据开发部 | H47: 否 | I47: RAD&RSD衍生区维护7 | J47: 深圳市长亮科技股份有限公司 | K47: 数据开发 | L47: B模式 | M47: 数据开发部落 | N47: 大数据应用三队 | O47: Hadoop大数据集群 | S47: 中级 | T47: cs100377@bosc.cn | U47: cs100377 | V47: 系统功能 | W47: 开发 | Z47: BDPHADP | AC47: 详细设计 | AD47: 1.打包测试上线包 2.修改上线脚本 3.配合查数调研出数情况 | AE47: 11
A48: 46106.787 | B48: 指标-工时 | C48: 510 | D48: 童勇 | E48: CS8500 | F48: 数据开发部 | H48: 否 | I48: FDM 个贷支行分成 平台贷分成开发 | J48: 神州数码融信软件有限公司 | K48: 数据开发 | L48: B模式 | M48: 数据开发部落 | N48: 基础数据小队 | O48: Hadoop大数据集群 | P48: ADPM需求-X20250612000039[第6批] | Q48: 2025年经营指标体系建设 | S48: 中级 | T48: cs8500@bosc.cn | U48: cs8500 | V48: 系统功能 | W48: 开发 | X48: 项目 | Y48: X20250612000039 | Z48: BDPHADP | AB48: 进行中 | AC48: 已完成 | AE48: 8.5 | AF48: 综合管理部
A49: 46106.786 | B49: 指标-工时 | C49: 400 | D49: 扶子懿 | E49: CS100010 | F49: 数据开发部 | H49: 否 | I49: 票易贷数据迁移_BDPHADP-开发看板 | J49: 神州数码融信软件有限公司 | K49: 数据开发 | L49: B模式 | M49: 数据开发部落 | N49: 基础数据小队 | O49: Hadoop大数据集群 | P49: ADPM需求-X20260106000017[第1批] | Q49: IRMS票易贷数据迁移功能优化业务需求书-业务功能类V4.5 | S49: 中级 | T49: cs100010@bosc.cn | U49: cs100010 | V49: 系统功能 | W49: 开发 | X49: 年度预算制 | Y49: X20260106000017 | Z49: BDPHADP | AA49: 开发一部 | AB49: 进行中 | AC49: 详细设计 | AD49: 整合模型-TP01_CPCT_INR_RTG_RSLT_INF_W 对公客户内部评级结果信息 新增字段，LN_RTG_RSLT_CD 当前评级审定R3代码。 SQLREVIEW生产数据验证。 | AE49: 6.6667 | AF49: 上海开发测试中心
A50: 46106.775 | B50: 指标-工时 | C50: 510 | D50: 杨鑫 | E50: CS4771 | F50: 数据开发部 | H50: 否 | I50: 南通众和_BDPHADP | J50: 上海天正智能数据服务有限公司 | K50: 数据开发 | L50: B模式 | M50: 监管报送部落 | N50: 监管报送集市小队 | O50: Hadoop大数据集群 | P50: ADPM需求-X20251027000041[第1批] | Q50: 南通众和应收账款业务业务需求书 | S50: 中级 | T50: cs4771@bosc.cn | U50: cs4771 | V50: 系统功能 | W50: 开发 | X50: 年度预算制 | Y50: X20251027000041 | Z50: BDPHADP | AA50: 开发一部 | AB50: 进行中 | AC50: 已完成 | AD50: UPR_CRDT_INFO_M 调整 推数测试 | AE50: 8.5 | AF50: 上海开发测试中心
A51: 46106.773 | B51: 指标-工时 | C51: 510 | D51: 张海山 | E51: CS101081 | F51: 数据平台部 | H51: 否 | I51: KPI项目-非标准化下钻页面-UDAS数据开发 | J51: 北京宇信科技集团股份有限公司 | K51: 数据开发 | L51: B模式 | M51: 数据平台部落 | N51: 司库监管报送小队 | O51: 统一报表及指标平台 | P51: ADPM需求-X20250612000039[第6批] | Q51: 2025年经营指标体系建设 | S51: 中级 | T51: cs101081@bosc.cn | U51: cs101081 | V51: 系统功能 | W51: 开发 | X51: 项目 | Y51: X20250612000039 | Z51: UDAS | AB51: 进行中 | AC51: 已完成 | AD51: 新兴板块-下钻页面指标、管理指标:新增/修改指标配置【新增同业机构代发调整项、修改同业机构代发净增指标】 | AE51: 8.5 | AF51: 综合管理部
A52: 46106.771 | B52: 指标-工时 | C52: 620 | D52: 张伟（高伟达） | E52: CS0227 | F52: 数据平台部 | H52: 否 | I52: 对公CRM内个人敏感信息脱敏展示-PC | J52: 高伟达软件股份有限公司 | K52: CRM | L52: B模式 | M52: 信息管理部落 | N52: 零售对公CRM PC小队 | O52: 公司客户关系管理 | P52: ADPM需求-X20251219000026[第1批] | Q52: 关于优化对公CRM个人敏感信息脱敏展示的需求 | S52: 资深 | T52: cs0227@bosc.cn | U52: cs0227 | V52: 系统功能 | W52: 管理人员（小队级） | X52: 维护需求 | Y52: X20251219000026 | Z52: CCRM | AB52: 进行中 | AC52: 已完成 | AD52: 对公CRM内个人敏感信息脱敏数据处理 | AE52: 10.3333 | AF52: 数据平台部
A53: 46106.766 | B53: 指标-工时 | C53: 255 | D53: 李禹凝 | E53: 306190 | F53: 数据开发部 | G53: =VLOOKUP(D53,'人员清单-202603'!D:J,7,FALSE) -> 数仓开发组 | H53: 是 | I53: 分行视图 | M53: 数据开发部落 | N53: 基础数据小队 | T53: 306190@bosc.cn | U53: 306190 | V53: 事项任务 | W53: 开发 | AC53: 进行中 | AE53: 4.25 | AG53: 开发（含模型、应用、数仓等）
A54: 46106.765 | B54: 指标-工时 | C54: 510 | D54: 王琪 | E54: CS3168 | F54: 数据开发部 | H54: 否 | I54: X20251027000041-CAFBDM | J54: 上海天正智能数据服务有限公司 | K54: 数据开发 | L54: B模式 | M54: 数据开发部落 | N54: 基础数据小队 | O54: 金融基础数据模型计算区 | P54: ADPM需求-X20251027000041[第1批] | Q54: 南通众和应收账款业务业务需求书 | S54: 中级 | T54: cs3168@bosc.cn | U54: cs3168 | V54: 系统功能 | W54: 开发 | X54: 年度预算制 | Y54: X20251027000041 | Z54: CAFBDM | AA54: 开发一部 | AB54: 进行中 | AC54: 已完成 | AD54: 配合下游测试 南通众和数据，票易贷迁移测试 | AE54: 8.5 | AF54: 上海开发测试中心
A55: 46106.764 | B55: 指标-工时 | C55: 510 | D55: 陈蕾 | E55: CS100301 | F55: 数据测试部 | H55: 否 | I55: X20240108000018__慧信工程-监管报送集市建设_第8批次 | J55: 深圳市长亮科技股份有限公司 | L55: A模式 | M55: 数据开发部落 | N55: 授信全流程-数据小队 | P55: ADPM需求-X20240108000018[第8批] | Q55: 慧信工程-监管报送集市建设 | S55: 中级 | T55: cs100301@bosc.cn | U55: cs100301 | V55: 条目需求 | X55: 项目 | Y55: X20240108000018 | AB55: 进行中 | AC55: 可行性分析 | AE55: 8.5 | AF55: 数据开发部
A56: 46106.759 | B56: 指标-工时 | C56: 510 | D56: 焦一凯 | E56: CS101254 | F56: 数据平台部 | H56: 否 | I56: 智能问数-skill框架集成 | J56: 北京中科金财科技股份有限公司 | K56: 网络金融银行领域（上海） | L56: B模式 | M56: 数据开发部落 | N56: 智能风控小队 | O56: 司库智能问数 | P56: ADPM需求-X20251124000006[第3批] | Q56: 司库移动端智能问数业务需求 | S56: 中级 | T56: cs101254@bosc.cn | U56: cs101254 | V56: 系统功能 | W56: 开发 | X56: 年度预算制 | Y56: X20251124000006 | Z56: M.TBS.INTQUERY | AB56: 进行中 | AC56: 已完成 | AE56: 8.5 | AF56: 数据平台部
A57: 46106.755 | B57: 指标-工时 | C57: 510 | D57: 刘军伟 | E57: CS101338 | F57: 数据平台部 | H57: 否 | I57: 【例行工作】可视化报表助手应用运维 | J57: 中电金信软件有限公司 | L57: A模式 | M57: 信息管理部落 | N57: BI工具小队 | S57: 中级 | T57: cs101338@bosc.cn | U57: cs101338 | V57: 事项任务 | AC57: 进行中 | AD57: 可视化报表助手运维 | AE57: 8.5 | AG57: 运维
A58: 46106.754 | B58: 指标-工时 | C58: 600 | D58: 张海艳 | E58: CS8843 | F58: 数据测试部 | H58: 否 | I58: X20240108000018__慧信工程-监管报送集市建设_第8批次 | J58: 深圳市长亮科技股份有限公司 | L58: A模式 | M58: 数据开发部落 | N58: 大数据应用一队 | P58: ADPM需求-X20240108000018[第8批] | Q58: 慧信工程-监管报送集市建设 | S58: 中级 | T58: cs8843@bosc.cn | U58: cs8843 | V58: 条目需求 | X58: 项目 | Y58: X20240108000018 | AB58: 进行中 | AC58: 可行性分析 | AE58: 10 | AF58: 数据开发部
A59: 46106.754 | B59: 指标-工时 | C59: 510 | D59: 吴丽华 | E59: CS6364 | F59: 数据开发部 | H59: 否 | I59: MRP迁移 | J59: 上海天正智能数据服务有限公司 | K59: 数据开发 | L59: B模式 | M59: 数据开发部落 | N59: 基础数据小队 | O59: Hadoop大数据集群 | Q59: 基于整合模型金融市场领域的MRP迁移改造需求 | S59: 中级 | T59: cs6364@bosc.cn | U59: cs6364 | V59: 系统功能 | W59: 开发 | X59: 维护需求 | Y59: X20260224000012 | Z59: BDPHADP | AB59: 进行中 | AC59: 详细设计 | AD59: 配合测试人员测试 | AE59: 8.5 | AF59: 数据开发部
A60: 46106.744 | B60: 指标-工时 | C60: 510 | D60: 李广业 | E60: CS8404 | F60: 数据开发部 | H60: 否 | I60: 征信送报送改动 | J60: 天阳宏业科技股份有限公司 | K60: 数据开发 | L60: B模式 | M60: 信用卡业务系统3.0项目组 | N60: 数据组小队 | O60: 征信管理应用计算区 | P60: ADPM需求-X20260211000013[第1批] | Q60: 平安普惠线下模式功能优化业务需求书 | S60: 中级 | T60: cs8404@bosc.cn | U60: cs8404 | V60: 系统功能 | X60: 年度预算制 | Y60: X20260211000013 | Z60: CACRS | AA60: 开发七部 | AB60: 进行中 | AC60: 详细设计 | AD60: 1.通过跑批数据反馈脚本代码逻辑有问题，需要修改脚本逻辑。添加新产品代码41022051-无抵押线下模式 2.重新跑批验证数据 fidi_etl /fidi/cacrs_crpbc/lgy/etl/i_lnacc_w_hlw.sql "--hivevar SHDATA=SHDATA --hivevar FIDI_CRPBC=fidi_cacrs_crpbc --hivevar V_CURR_DATE=20260317 --hivevar V_YEST_DATE=20260316" /fidi/cacrs_crpbc/lgy/log/20260317/etl_i_lnacc_w_hlw_20260317.log fidi_etl /fidi/cacrs_crpbc/lgy/etl/i_lnacc_w.sql "--hivevar SHDATA=SHDATA --hivevar FIDI_CRPBC=fidi_cacrs_crpbc --hivevar V_CURR_DATE=20260317 --hivevar V_YEST_DATE=20260316" /fidi/cacrs_crpbc/lgy/log/20260317/etl_i_lnacc_w_20260317.log fidi_etl /fidi/cacrs_crpbc/lgy/etl/i_rltrepymt_w.sql "--hivevar SHDATA=SHDATA --hivevar FIDI_CRPBC=fidi_cacrs_crpbc --hivevar V_CURR_DATE=20260317 --hivevar V_YEST_DATE=20260316" /fidi/cacrs_crpbc/lgy/log/20260317/etl_i_rltrepymt_w_20260317.log fidi_etl /fidi/cacrs_crpbc/lgy/etl/i_ctr_wrntctr_rel_w.sql "--hivevar SHDATA=SHDATA --hivevar FIDI_CRPBC=fidi_cacrs_crpbc --hivevar V_CURR_DATE=20260317 --hivevar V_YEST_DATE=20260316" /fidi/cacrs_crpbc/lgy/log/20260317/etl_i_ctr_wrntctr_rel_w_20260317.log fidi_etl /fidi/cacrs_crpbc/lgy/etl/i_acctspectrstdspn_a.sql "--hivevar SHDATA=SHDATA --hivevar FIDI_CRPBC=fidi_cacrs_crpbc --hivevar V_CURR_DATE=20260317 --hivevar V_YEST_DATE=20260316" /fidi/cacrs_crpbc/lgy/log/20260317/etl_i_acctspectrstdspn_a_20260317.log fidi_etl /fidi/cacrs_crpbc/lgy/etl/i_c_anp_ci_acctbs.sql "--hivevar SHDATA=SHDATA --hivevar FIDI_CRPBC=fidi_cacrs_crpbc --hivevar V_CURR_DATE=20260317 --hivevar V_YEST_DATE=20260316" /fidi/cacrs_crpbc/lgy/log/20260317/etl_i_c_anp_ci_acctbs_20260317.log fidi_etl /fidi/cacrs_crpbc/lgy/etl/i_c_anp_ci_acctbs_dbt.sql "--hivevar SHDATA=SHDATA --hivevar FIDI_CRPBC=fidi_cacrs_crpbc --hivevar V_CURR_DATE=20260317 --hivevar V_YEST_DATE=20260316" /fidi/cacrs_crpbc/lgy/log/20260317/etl_i_c_anp_ci_acctbs_dbt_20260317.log fidi_etl /fidi/cacrs_crpbc/lgy/etl/i_c_anp_ci_acctbsinf.sql "--hivevar SHDATA=SHDATA --hivevar FIDI_CRPBC=fidi_cacrs_crpbc --hivevar V_CURR_DATE=20260317 --hivevar V_YEST_DATE=20260316" /fidi/cacrs_crpbc/lgy/log/20260317/etl_i_c_anp_ci_acctbsinf_20260317.log fidi_etl /fidi/cacrs_crpbc/lgy/etl/i_c_anp_ci_acctdbtinf.sql "--hivevar SHDATA=SHDATA --hivevar FIDI_CRPBC=fidi_cacrs_crpbc --hivevar V_CURR_DATE=20260317 --hivevar V_YEST_DATE=20260316" /fidi/cacrs_crpbc/lgy/log/20260317/etl_i_c_anp_ci_acctdbtinf_20260317.log fidi_etl /fidi/cacrs_crpbc/lgy/etl/i_c_anp_ci_acctmthlyblginf.sql "--hivevar SHDATA=SHDATA --hivevar FIDI_CRPBC=fidi_cacrs_crpbc --hivevar V_CURR_DATE=20260317 --hivevar V_YEST_DATE=20260316" /fidi/cacrs_crpbc/lgy/log/20260317/etl_i_c_anp_ci_acctmthlyblginf_20260317.log fidi_etl /fidi/cacrs_crpbc/lgy/etl/i_c_anp_ci_motgacltalctrctinf.sql "--hivevar SHDATA=SHDATA --hivevar FIDI_CRPBC=fidi_cacrs_crpbc --hivevar V_CURR_DATE=20260317 --hivevar V_YEST_DATE=20260316" /fidi/cacrs_crpbc/lgy/log/20260317/etl_i_c_anp_ci_motgacltalctrctinf_20260317.log fidi_etl /fidi/cacrs_crpbc/lgy/etl/i_c_anp_ci_rltrepymtinf.sql "--hivevar SHDATA=SHDATA --hivevar FIDI_CRPBC=fidi_cacrs_crpbc --hivevar V_CURR_DATE=20260317 --hivevar V_YEST_DATE=20260316" /fidi/cacrs_crpbc/lgy/log/20260317/etl_i_c_anp_ci_rltrepymtinf_20260317.log fidi_etl /fidi/cacrs_crpbc/lgy/etl/i_c_anp_ci_acctspectrstdspn.sql "--hivevar SHDATA=SHDATA --hivevar FIDI_CRPBC=fidi_cacrs_crpbc --hivevar V_CURR_DATE=20260317 --hivevar V_YEST_DATE=20260316" /fidi/cacrs_crpbc/lgy/log/20260317/etl_i_c_anp_ci_acctspectrstdspn_20260317.log fidi_etl /fidi/cacrs_crpbc/lgy/etl/i_vt_anp_ci_rptdatecode.sql "--hivevar SHDATA=SHDATA --hivevar FIDI_CRPBC=fidi_cacrs_crpbc --hivevar V_CURR_DATE=20260317 --hivevar V_YEST_DATE=20260316" /fidi/cacrs_crpbc/lgy/log/20260317/etl_i_vt_anp_ci_rptdatecode_20260317.log fidi_etl /fidi/cacrs_crpbc/lgy/etl/i_v_anp_ci_acctbs.sql "--hivevar SHDATA=SHDATA --hivevar FIDI_CRPBC=fidi_cacrs_crpbc --hivevar V_CURR_DATE=20260317 --hivevar V_YEST_DATE=20260316" /fidi/cacrs_crpbc/lgy/log/20260317/etl_i_v_anp_ci_acctbs_20260317.log fidi_etl /fidi/cacrs_crpbc/lgy/etl/i_v_anp_ci_acctbsinf.sql "--hivevar SHDATA=SHDATA --hivevar FIDI_CRPBC=fidi_cacrs_crpbc --hivevar V_CURR_DATE=20260317 --hivevar V_YEST_DATE=20260316" /fidi/cacrs_crpbc/lgy/log/20260317/etl_i_v_anp_ci_acctbsinf_20260317.log fidi_etl /fidi/cacrs_crpbc/lgy/etl/i_v_anp_ci_acctdbtinf.sql "--hivevar SHDATA=SHDATA --hivevar FIDI_CRPBC=fidi_cacrs_crpbc --hivevar V_CURR_DATE=20260317 --hivevar V_YEST_DATE=20260316" /fidi/cacrs_crpbc/lgy/log/20260317/etl_i_v_anp_ci_acctdbtinf_20260317.log fidi_etl /fidi/cacrs_crpbc/lgy/etl/i_v_anp_ci_acctmthlyblginf.sql "--hivevar SHDATA=SHDATA --hivevar FIDI_CRPBC=fidi_cacrs_crpbc --hivevar V_CURR_DATE=20260317 --hivevar V_YEST_DATE=20260316" /fidi/cacrs_crpbc/lgy/log/20260317/etl_i_v_anp_ci_acctmthlyblginf_20260317.log fidi_etl /fidi/cacrs_crpbc/lgy/etl/i_v_anp_ci_motgacltalctrctinf.sql "--hivevar SHDATA=SHDATA --hivevar FIDI_CRPBC=fidi_cacrs_crpbc --hivevar V_CURR_DATE=20260317 --hivevar V_YEST_DATE=20260316" /fidi/cacrs_crpbc/lgy/log/20260317/etl_i_v_anp_ci_motgacltalctrctinf_20260317.log fidi_etl /fidi/cacrs_crpbc/lgy/etl/i_v_anp_ci_rltrepymtinf.sql "--hivevar SHDATA=SHDATA --hivevar FIDI_CRPBC=fidi_cacrs_crpbc --hivevar V_CURR_DATE=20260317 --hivevar V_YEST_DATE=20260316" /fidi/cacrs_crpbc/lgy/log/20260317/etl_i_v_anp_ci_rltrepymtinf_20260317.log fidi_etl /fidi/cacrs_crpbc/lgy/etl/i_v_anp_ci_acctspectrstdspn.sql "--hivevar SHDATA=SHDATA --hivevar FIDI_CRPBC=fidi_cacrs_crpbc --hivevar V_CURR_DATE=20260317 --hivevar V_YEST_DATE=20260316" /fidi/cacrs_crpbc/lgy/log/20260317/etl_i_v_anp_ci_acctspectrstdspn_20260317.log fidi_etl /fidi/cacrs_crpbc/lgy/etl/i_p_anp_ci_acctbsinf.sql "--hivevar SHDATA=SHDATA --hivevar FIDI_CRPBC=fidi_cacrs_crpbc --hivevar V_CURR_DATE=20260317 --hivevar V_YEST_DATE=20260316" /fidi/cacrs_crpbc/lgy/log/20260317/etl_i_p_anp_ci_acctbsinf_20260317.log fidi_etl /fidi/cacrs_crpbc/lgy/etl/i_p_anp_ci_acctbs.sql "--hivevar SHDATA=SHDATA --hivevar FIDI_CRPBC=fidi_cacrs_crpbc --hivevar V_CURR_DATE=20260317 --hivevar V_YEST_DATE=20260316" /fidi/cacrs_crpbc/lgy/log/20260317/etl_i_p_anp_ci_acctbs_20260317.log fidi_etl /fidi/cacrs_crpbc/lgy/etl/i_p_anp_ci_acctdbtinf.sql "--hivevar SHDATA=SHDATA --hivevar FIDI_CRPBC=fidi_cacrs_crpbc --hivevar V_CURR_DATE=20260317 --hivevar V_YEST_DATE=20260316" /fidi/cacrs_crpbc/lgy/log/20260317/etl_i_p_anp_ci_acctdbtinf_20260317.log fidi_etl /fidi/cacrs_crpbc/lgy/etl/i_p_anp_ci_acctmthlyblginf.sql "--hivevar SHDATA=SHDATA --hivevar FIDI_CRPBC=fidi_cacrs_crpbc --hivevar V_CURR_DATE=20260317 --hivevar V_YEST_DATE=20260316" /fidi/cacrs_crpbc/lgy/log/20260317/etl_i_p_anp_ci_acctmthlyblginf_20260317.log fidi_etl /fidi/cacrs_crpbc/lgy/etl/i_p_anp_ci_motgacltalctrctinf.sql "--hivevar SHDATA=SHDATA --hivevar FIDI_CRPBC=fidi_cacrs_crpbc --hivevar V_CURR_DATE=20260317 --hivevar V_YEST_DATE=20260316" /fidi/cacrs_crpbc/lgy/log/20260317/etl_i_p_anp_ci_motgacltalctrctinf_20260317.log fidi_etl /fidi/cacrs_crpbc/lgy/etl/i_p_anp_ci_rltrepymtinf.sql "--hivevar SHDATA=SHDATA --hivevar FIDI_CRPBC=fidi_cacrs_crpbc --hivevar V_CURR_DATE=20260317 --hivevar V_YEST_DATE=20260316" /fidi/cacrs_crpbc/lgy/log/20260317/etl_i_p_anp_ci_rltrepymtinf_20260317.log fidi_etl /fidi/cacrs_crpbc/lgy/etl/i_p_anp_ci_acctspectrstdspn.sql "--hivevar SHDATA=SHDATA --hivevar FIDI_CRPBC=fidi_cacrs_crpbc --hivevar V_CURR_DATE=20260317 --hivevar V_YEST_DATE=20260316" /fidi/cacrs_crpbc/lgy/log/20260317/etl_i_p_anp_ci_acctspectrstdspn_20260317.log | AE60: 8.5 | AF60: 上海开发测试中心
A61: 46106.742 | B61: 指标-工时 | C61: 600 | D61: 蔡力捷 | E61: CS3632 | F61: 信息管理部 | H61: 否 | I61: 关于建设重点科技企业金融服务统计表及经营分析看板的需求 | J61: 上海天正智能数据服务有限公司 | K61: 数据开发 | L61: B模式 | O61: 数据仓库集群 | Q61: 关于建设重点科技企业金融服务统计表及经营分析看板的需求 | S61: 高级 | T61: cs3632@bosc.cn | U61: cs3632 | V61: 事项任务 | W61: 数据分析助理 | X61: 维护需求 | Y61: X20250929000029 | Z61: BDAS.DWC | AB61: 进行中 | AC61: 进行中 | AD61: 专项任务--张泠文--反洗钱客户基本身份信息治理看板 --反洗钱客户基本身份信息治理看板（进行中） 专项任务--杨博--中小企业贷款信息 --完成中小企业贷款信息数据支持 | AE61: 10 | AF61: 信息管理部 | AG61: 脚本整理 | AH61: 运维支持
A62: 46106.741 | B62: 指标-工时 | C62: 510 | D62: 蔡家杰 | E62: CS101104 | F62: 数据平台部 | H62: 否 | I62: 司库智能问数-dimension上传和召回检索功能开发 | J62: 北京中科金财科技股份有限公司 | K62: 网络金融银行领域（上海） | L62: B模式 | M62: 数据开发部落 | N62: 智能风控小队 | O62: 司库智能问数 | P62: ADPM需求-X20251124000006[第3批] | Q62: 司库移动端智能问数业务需求 | S62: 初级 | T62: cs101104@bosc.cn | U62: cs101104 | V62: 系统功能 | X62: 年度预算制 | Y62: X20251124000006 | Z62: M.TBS.INTQUERY | AB62: 进行中 | AC62: 已完成 | AE62: 8.5 | AF62: 数据平台部
A63: 46106.731 | B63: 指标-工时 | C63: 510 | D63: 张杜娟 | E63: CS9050 | F63: 数据平台部 | H63: 否 | I63: 云掌柜-AI外呼任务处理 | J63: 北京东方国信科技股份有限公司 | K63: CRM | L63: B模式 | M63: 信息管理部落 | N63: 零售对公CRM APP小队 | O63: 零售客户关系管理 | Q63: 零售CRM营销数字化及AI外呼智能化赋能项目 | S63: 中级 | T63: cs9050@bosc.cn | U63: cs9050 | V63: 系统功能 | W63: 测试 | X63: 项目 | Y63: X20250331000031 | Z63: PCRM | AB63: 进行中 | AC63: 详细设计 | AD63: 1、按照会议内容重新设计AI外呼原型图； 2、和业务老师沟通AI外呼360视图页面的展示及操作； 3、梳理代发的菜单； | AE63: 8.5 | AF63: 综合管理部
A64: 46106.73 | B64: 指标-工时 | C64: 510 | D64: 张陶煜 | E64: CS5324 | F64: 数据开发部 | H64: 否 | I64: 运营集市开发 | J64: 上海天正智能数据服务有限公司 | K64: 数据开发 | L64: B模式 | M64: 智能研发部落 | N64: 运营集市小队 | O64: Hadoop大数据集群 | P64: ADPM需求-X20260212000001[第1批] | Q64: 关于增加风险预警信息e联提示功能等业务需求书 | S64: 中级 | T64: cs5324@bosc.cn | U64: cs5324 | V64: 系统功能 | W64: 开发 | X64: 维护需求 | Y64: X20260212000001 | Z64: BDPHADP | AB64: 进行中 | AC64: 已完成 | AD64: 需求开发 | AE64: 8.5
A65: 46106.725 | B65: 指标-工时 | C65: 120 | D65: 张雅淇 | E65: 303482 | F65: 数据开发部 | G65: =VLOOKUP(D65,'人员清单-202603'!D:J,7,FALSE) -> 应用开发组 | H65: 是 | I65: 工作交接 | M65: 信息管理部落 | N65: UDAS零售数据小队 | T65: 303482@bosc.cn | U65: 303482 | V65: 事项任务 | W65: 小队长 | AC65: 进行中 | AE65: 2 | AG65: 其他
A66: 46106.725 | B66: 指标-工时 | C66: 90 | D66: 张雅淇 | E66: 303482 | F66: 数据开发部 | G66: =VLOOKUP(D66,'人员清单-202603'!D:J,7,FALSE) -> 应用开发组 | H66: 是 | I66: 【例行工作】需求调研及对接 | M66: 信息管理部落 | N66: UDAS零售数据小队 | T66: 303482@bosc.cn | U66: 303482 | V66: 事项任务 | W66: 小队长 | AC66: 进行中 | AE66: 1.5 | AG66: 设计（含可行性方案、概设、详设等）
A67: 46106.725 | B67: 指标-工时 | C67: 300 | D67: 张雅淇 | E67: 303482 | F67: 数据开发部 | G67: =VLOOKUP(D67,'人员清单-202603'!D:J,7,FALSE) -> 应用开发组 | H67: 是 | I67: 【例行工作】生产运维 | M67: 信息管理部落 | N67: UDAS零售数据小队 | T67: 303482@bosc.cn | U67: 303482 | V67: 事项任务 | W67: 小队长 | AC67: 进行中 | AE67: 5 | AG67: 生产运维
A68: 46106.724 | B68: 指标-工时 | C68: 510 | D68: 胡雯 | E68: 304805 | F68: 数据开发部 | G68: =VLOOKUP(D68,'人员清单-202603'!D:J,7,FALSE) -> 应用开发组 | H68: 是 | I68: 日常需求对接 | M68: 信息管理部落 | N68: UDAS基础数据小队 | T68: 304805@bosc.cn | U68: 304805 | V68: 事项任务 | W68: 测试小队长 | AC68: 进行中 | AD68: 科创补录表需求对接+配合测试+大额流入流出数据分类 | AE68: 8.5 | AG68: 需求澄清与分析
A69: 46106.721 | B69: 指标-工时 | C69: 510 | D69: 陈凌云 | E69: CS100875 | F69: 数据测试部 | H69: 否 | I69: X20240108000018__慧信工程-监管报送集市建设_第8批次 | J69: 上海复深蓝软件股份有限公司 | L69: A模式 | M69: 数据开发部落 | N69: 数据测试小队 | P69: ADPM需求-X20240108000018[第8批] | Q69: 慧信工程-监管报送集市建设 | S69: 中级 | T69: cs100875@bosc.cn | U69: cs100875 | V69: 条目需求 | X69: 项目 | Y69: X20240108000018 | AB69: 进行中 | AC69: 可行性分析 | AE69: 8.5 | AF69: 数据开发部
A70: 46106.719 | B70: 指标-工时 | C70: 520 | D70: 刘云龙 | E70: CS1714 | F70: 信息管理部 | H70: 否 | I70: 刘云龙2026Q1 | J70: 上海天正智能数据服务有限公司 | K70: 数据开发 | L70: B模式 | O70: 数据仓库 | S70: 中级 | T70: cs1714@bosc.cn | U70: cs1714 | V70: 系统功能 | W70: 开发 | Z70: EDW | AC70: 详细设计 | AD70: 1、虹口支行（按照新的架构来，可以看下附件中“变动表”中O列是虹口支行所对映的F-R列）账户在2024年1-12月和2025年1-112月期间（1）被管控（智芯前：暂停非柜面、休眠、不收不付；智芯后：被设置状态字）的次数及涉及的账户数；（2）在此期间设置非柜面限额的次数及涉及的账户数；（3）管控和限额的总计的次数及涉及的账户数。--该数据麻烦尽量今天给出 2、其余所有分行、支行，按新的架构，以上3点取数。涉及分行：8家异地分行、总行营业部、浦东分行、上海自贸试验区分行、黄浦支行、徐汇支行、长宁支行、静安支行、普陀支行、杨浦支行、漕河泾支行、闵行支行、宝山支行、嘉定支行、松江支行、青浦支行、奉贤支行、金山支行、崇明支行。 谢谢！ | AE70: 8.6667
A71: 46106.718 | B71: 指标-工时 | C71: 510 | D71: 郭志勇 | E71: CS0898 | F71: 数据开发部 | H71: 否 | I71: 财政卸数调整 | J71: 上海天正智能数据服务有限公司 | K71: 数据开发 | L71: B模式 | M71: 数据平台部落 | N71: 大数据入仓小队 | O71: Hadoop大数据集群 | P71: ADPM需求-X20251218000014[第2批] | Q71: 财政系统报文逻辑优化及修复 | S71: 高级 | T71: cs0898@bosc.cn | U71: cs0898 | V71: 系统功能 | W71: 开发 | X71: 维护需求 | Y71: X20251218000014 | Z71: BDPHADP | AA71: 开发六部 | AB71: 进行中 | AC71: 已完成 | AD71: S85_FBIS_AUTPAYINFO,S85_FBIS_AUTPAYBAKDET策略改动修改 | AE71: 8.5 | AF71: 上海开发测试中心
A72: 46106.718 | B72: 指标-工时 | C72: 510 | D72: 吴佛临 | E72: CS100513 | F72: 数据测试部 | H72: 否 | I72: RAD主体应用功能开发测试-RAD | J72: 京北方信息技术股份有限公司 | L72: A模式 | M72: 数据开发部落 | N72: 数据测试小队 | O72: 信用风险监测预警 | P72: ADPM需求-X20240108000016[第14批] | Q72: 慧信工程-风险底线排查与监测预警系统及全面风险指标体系建设 | S72: 高级 | T72: cs100513@bosc.cn | U72: cs100513 | V72: 系统功能 | X72: 项目 | Y72: X20240108000016 | Z72: RAD | AB72: 进行中 | AC72: 详细设计 | AE72: 8.5 | AF72: 综合管理部
A73: 46106.716 | B73: 指标-工时 | C73: 510 | D73: 金悦 | E73: CS5187 | F73: 数据测试部 | H73: 否 | I73: 掌上行4.5A模式-测试 | J73: 高伟达软件股份有限公司 | L73: A模式 | M73: 信息管理部落 | N73: UDAS公共大队 | O73: 掌上行 | Q73: 掌上行4.5建设项目 | S73: 中级 | T73: cs5187@bosc.cn | U73: cs5187 | V73: 系统功能 | W73: 开发 | X73: 项目 | Y73: X20250724000029 | Z73: AMBI | AB73: 进行中 | AC73: 详细设计 | AD73: "1、结果表重新扫描空值率和码值； 2、检查码值不通过的原因；" | AE73: 8.5 | AF73: 综合管理部
A74: 46106.713 | B74: 指标-工时 | C74: 510 | D74: 唐康振 | E74: CS2868 | F74: 数据测试部 | H74: 否 | I74: 零售催收系统对接新决策引擎 | J74: 上海复深蓝软件股份有限公司 | L74: A模式 | M74: 数据开发部落 | N74: 数据测试小队 | P74: ADPM需求-X20251024000020[第2批] | Q74: 关于零售催收系统对接新决策引擎的优化需求书 | S74: 中级 | T74: cs2868@bosc.cn | U74: cs2868 | V74: 条目需求 | W74: 测试 | X74: 年度预算制 | Y74: X20251024000020 | AA74: 开发二部 | AB74: 进行中 | AC74: 需求验收 | AE74: 8.5 | AF74: 上海开发测试中心
A75: 46106.713 | B75: 指标-工时 | C75: 510 | D75: 蒋北平 | E75: CS6470 | F75: 数据开发部 | H75: 否 | I75: S93-RBW 3个作业需改造以及多轮回归测试 | J75: 上海天正智能数据服务有限公司 | K75: 数据开发 | L75: B模式 | M75: 数据开发部落 | N75: 基础数据小队 | O75: Hadoop大数据集群 | P75: ADPM需求-X20250529000032[第1批] | Q75: 关于网联支付积分抵现功能的开发需求 | S75: 中级 | T75: cs6470@bosc.cn | U75: cs6470 | V75: 系统功能 | W75: 开发 | X75: 年度预算制 | Y75: X20250529000032 | Z75: BDPHADP | AA75: 开发六部 | AB75: 进行中 | AC75: 已完成 | AD75: S93变动影响性分析，脚本口径更改，测试数据配合测试 | AE75: 8.5 | AF75: 上海开发测试中心
A76: 46106.712 | B76: 指标-工时 | C76: 510 | D76: 张龙宇 | E76: CS3436 | F76: 数据开发部 | H76: 否 | I76: 视图底表构建-天正 | J76: 上海天正智能数据服务有限公司 | K76: 数据开发 | L76: B模式 | M76: 数据开发部落 | N76: 基础数据小队 | O76: Hadoop大数据集群 | P76: ADPM需求-X20240926000006[第3批] | Q76: 2024年度经营单位数字化管理建设项目 | S76: 中级 | T76: cs3436@bosc.cn | U76: cs3436 | V76: 系统功能 | W76: 开发 | X76: 项目 | Y76: X20240926000006 | Z76: BDPHADP | AB76: 进行中 | AC76: 已完成 | AD76: RDI_SECU_TRUST_CUST调研 | AE76: 8.5 | AF76: 信息管理部
A77: 46106.712 | B77: 指标-工时 | C77: 510 | D77: 王荧荧 | E77: CS0495 | F77: 数据开发部 | H77: 否 | I77: 视图底表构建-天正 | J77: 上海天正智能数据服务有限公司 | K77: 数据开发 | L77: B模式 | M77: 信息管理部落 | N77: NRP集市小队 | O77: Hadoop大数据集群 | P77: ADPM需求-X20240926000006[第3批] | Q77: 2024年度经营单位数字化管理建设项目 | S77: 高级 | T77: cs0495@bosc.cn | U77: cs0495 | V77: 系统功能 | W77: 测试小队长 | X77: 项目 | Y77: X20240926000006 | Z77: BDPHADP | AB77: 进行中 | AC77: 已完成 | AD77: RDI_A_IND_NEW_CUST_BIZ_ND表数据测试 | AE77: 8.5 | AF77: 信息管理部
A78: 46106.71 | B78: 指标-工时 | C78: 510 | D78: 韩润乾 | E78: CS3585 | F78: 信息管理部 | H78: 否 | I78: 2026Q1 | J78: 深圳市长亮科技股份有限公司 | K78: 数据开发 | L78: B模式 | M78: 数据开发部落 | N78: 大数据应用三队 | O78: Hadoop大数据集群 | Q78: 2026年个人电子渠道竞争力提升数据分析提取需求书 | S78: 中级 | T78: cs3585@bosc.cn | U78: cs3585 | V78: 系统功能 | W78: 开发 | X78: 维护需求 | Y78: X20260121000013 | Z78: BDPHADP | AB78: 进行中 | AC78: 详细设计 | AE78: 8.5 | AF78: 信息管理部
A79: 46106.708 | B79: 指标-工时 | C79: 255 | D79: 吴高宇 | E79: CS2860 | F79: 数据平台部 | H79: 否 | I79: dataops ui设计 | J79: 北京宇信科技集团股份有限公司 | K79: 数据开发 | L79: B模式 | M79: 信息管理部落 | N79: UDAS公共大队 | O79: 数据采集工具 | Q79: 关于数据采集平台交互体验提升的业务需求 | S79: 高级 | T79: cs2860@bosc.cn | U79: cs2860 | V79: 系统功能 | W79: UI设计 | X79: 维护需求 | Y79: X20251106000044 | Z79: DAT | AB79: 进行中 | AC79: 详细设计 | AD79: 环境管理流程修改 | AE79: 4.25 | AF79: 数据平台部
A80: 46106.708 | B80: 指标-工时 | C80: 255 | D80: 吴高宇 | E80: CS2860 | F80: 数据平台部 | H80: 否 | I80: 产品设计--崔 | J80: 北京宇信科技集团股份有限公司 | K80: 数据开发 | L80: B模式 | M80: 信息管理部落 | N80: UDAS公共大队 | O80: 司库应用计算区 | P80: ADPM需求-X20240423000001[第12批] | Q80: 关于司库进阶版功能建设的需求 | S80: 高级 | T80: cs2860@bosc.cn | U80: cs2860 | V80: 系统功能 | W80: UI设计 | X80: 项目 | Y80: X20240423000001 | Z80: M.TBS.TCA | AA80: 司库开发团队 | AB80: 进行中 | AC80: 已完成 | AD80: 应收应付相关报表设计 | AE80: 4.25 | AF80: 上海开发测试中心
A81: 46106.708 | B81: 指标-工时 | C81: 510 | D81: 张嬉云 | E81: CS8696 | F81: 数据测试部 | H81: 否 | I81: X20240108000018__慧信工程-监管报送集市建设_第8批次 | J81: 中电金信软件有限公司 | L81: A模式 | M81: 数据开发部落 | N81: 数据测试小队 | P81: ADPM需求-X20240108000018[第8批] | Q81: 慧信工程-监管报送集市建设 | S81: 中级 | T81: cs8696@bosc.cn | U81: cs8696 | V81: 条目需求 | X81: 项目 | Y81: X20240108000018 | AB81: 进行中 | AC81: 可行性分析 | AE81: 8.5 | AF81: 数据开发部
A82: 46106.707 | B82: 指标-工时 | C82: 510 | D82: 尹天骄 | E82: CS8805 | F82: 信息管理部 | H82: 否 | I82: X20260105000030_实时断点任务名单服务外呼情况分析、客诉团队派单系统分行机构调整、体验团队核身专项分析需求 | J82: 上海天正智能数据服务有限公司 | K82: 数据开发 | L82: B模式 | M82: 数据开发部落 | N82: 大数据应用一队 | O82: Hadoop大数据集群 | Q82: 远程银行中心实时断点任务外呼情况分析需求 | S82: 中级 | T82: cs8805@bosc.cn | U82: cs8805 | V82: 系统功能 | X82: 维护需求 | Y82: X20260105000030 | Z82: BDPHADP | AB82: 进行中 | AC82: 详细设计 | AD82: 顾玄怡-质检大数据模型数据较少原因排查 杨文超-全量派单处理时间及人员，各号码最近外呼情况 | AE82: 8.5 | AF82: 信息管理部
A83: 46106.706 | B83: 指标-工时 | C83: 510 | D83: 杨磊 | E83: CS101351 | F83: 数据开发部 | H83: 否 | I83: 1104配合测试 | J83: 北京宇信科技集团股份有限公司 | K83: 监管报送 | L83: B模式 | M83: 监管报送部落 | N83: 银保监报送小队 | O83: 1104报送 | P83: ADPM需求-X20240108000018[第8批] | Q83: 慧信工程-监管报送集市建设 | S83: 中级 | T83: cs101351@bosc.cn | U83: cs101351 | V83: 系统功能 | W83: 开发 | X83: 项目 | Y83: X20240108000018 | Z83: M.RCI.1104 | AB83: 进行中 | AC83: 详细设计 | AE83: 8.5 | AF83: 数据开发部
A84: 46106.705 | B84: 指标-工时 | C84: 510 | D84: 赵幸 | E84: CS100853 | F84: 信息管理部 | H84: 否 | I84: 11月第一周可疑社团分析 | J84: 博彦科技股份有限公司 | L84: A模式 | M84: 信息管理部落 | N84: 零售业务数据分析小队 | Q84: 关于零售信贷互联网贷款业务的反欺诈图析分析提炼需求 | S84: 高级 | T84: cs100853@bosc.cn | U84: cs100853 | V84: 事项任务 | W84: 开发 | X84: 年度预算制 | Y84: X20260313000021 | AB84: 进行中 | AC84: 进行中 | AE84: 8.5 | AF84: 信息管理部 | AG84: 需求澄清与分析
A85: 46106.705 | B85: 指标-工时 | C85: 510 | D85: 马荣荣 | E85: CS3196 | F85: 数据开发部 | H85: 否 | I85: BDPHADP-大数据配合入仓 | J85: 上海天正智能数据服务有限公司 | K85: 数据开发 | L85: B模式 | M85: 数据平台部落 | N85: 大数据入仓小队 | O85: Hadoop大数据集群 | P85: ADPM需求-X20251113000032[第2批] | Q85: 普惠IRMS系统业务方案功能优化需求书 | S85: 初级 | T85: cs3196@bosc.cn | U85: cs3196 | V85: 系统功能 | W85: 开发 | X85: 年度预算制 | Y85: X20251113000032 | Z85: BDPHADP | AA85: 开发一部 | AB85: 进行中 | AC85: 已完成 | AD85: L10_ LMT_ECIF_CATEGORY_DETAIL,L10_LMT_ECIF_CATEGORY_SYNC_FLOW,L10_LMT_BATCH_ECIF_MERGE_QUOTA_INFO等多张表新表入仓数据加载测试，配合联调测试20260302,20260310等日期加载。 | AE85: 8.5 | AF85: 上海开发测试中心
A86: 46106.704 | B86: 指标-工时 | C86: 510 | D86: 翁世杰 | E86: CS0604 | F86: 数据开发部 | H86: 否 | I86: MRP迁移 | J86: 上海天正智能数据服务有限公司 | K86: 数据开发 | L86: B模式 | M86: 数据开发部落 | N86: 基础数据小队 | O86: Hadoop大数据集群 | Q86: 基于整合模型金融市场领域的MRP迁移改造需求 | S86: 中级 | T86: cs0604@bosc.cn | U86: cs0604 | V86: 系统功能 | W86: 开发 | X86: 维护需求 | Y86: X20260224000012 | Z86: BDPHADP | AB86: 进行中 | AC86: 详细设计 | AD86: mrp_b_t_credit_bond_bal_new_init.py，mrp_b_t_credit_bond_bal_new0200.py映射分析，脚本提测 字段级映射文档维护 | AE86: 8.5 | AF86: 数据开发部
A87: 46106.703 | B87: 指标-工时 | C87: 510 | D87: 陈晨 | E87: 306545 | F87: 数据开发部 | G87: =VLOOKUP(D87,'人员清单-202603'!D:J,7,FALSE) -> 应用开发组 | H87: 是 | I87: 【例行工作】日常运维工作 | M87: 数据开发部落 | N87: 大数据应用一队 | T87: 306545@bosc.cn | U87: 306545 | V87: 事项任务 | W87: 小队长 | AC87: 进行中 | AE87: 8.5 | AG87: 生产运维 | AH87: 运维支持
A88: 46106.703 | B88: 指标-工时 | C88: 510 | D88: 冯莉杰 | E88: CS0326 | F88: 数据开发部 | H88: 否 | I88: 财政卸数调整 | J88: 上海天正智能数据服务有限公司 | K88: 数据开发 | L88: B模式 | M88: 核心系统重构项目组 | N88: 数据小队 | O88: Hadoop大数据集群 | P88: ADPM需求-X20251218000014[第2批] | Q88: 财政系统报文逻辑优化及修复 | S88: 高级 | T88: cs0326@bosc.cn | U88: cs0326 | V88: 系统功能 | W88: 开发 | X88: 维护需求 | Y88: X20251218000014 | Z88: BDPHADP | AA88: 开发六部 | AB88: 进行中 | AC88: 已完成 | AD88: S85_FFPS_AUTPAYINFO_2_H脚本开发、数据加载测试 | AE88: 8.5 | AF88: 上海开发测试中心
A89: 46106.702 | B89: 指标-工时 | C89: 510 | D89: 夏清鹏 | E89: CS7902 | F89: 数据开发部 | H89: 否 | I89: CRM集市代发开发_丰富存量企业营销标签_X20250522000026_2025年零售CRM代发功能优化业务需求书 | J89: 上海天正智能数据服务有限公司 | K89: 数据开发 | L89: B模式 | M89: 数据开发部落 | N89: 基础数据小队 | O89: Hadoop大数据集群 | P89: ADPM需求-X20250522000026[第5批] | Q89: 2025年零售CRM代发功能优化业务需求书 | S89: 高级 | T89: cs7902@bosc.cn | U89: cs7902 | V89: 系统功能 | W89: 开发 | X89: 年度预算制 | Y89: X20250522000026 | Z89: BDPHADP | AB89: 进行中 | AC89: 已完成 | AD89: 作业：CRM_P_INDEX_ORG_CUST_IND 新增字段：当日借记卡新户，E_CRM_P_INDEX_ORG 新增标签：当日借记卡新户数-XH131。执行sqlreview，白皮书，提测。 | AE89: 8.5 | AF89: 数据平台部
A90: 46106.701 | B90: 指标-工时 | C90: 540 | D90: 郭帅 | E90: CS0254 | F90: 信息管理部 | H90: 否 | I90: X20260126000013-2026年对公结算活跃客户经营分析需求书-补充报工 | J90: 上海天正智能数据服务有限公司 | K90: 数据开发 | L90: B模式 | M90: 数据开发部落 | N90: 大数据应用一队 | O90: Hadoop大数据集群 | S90: 中级 | T90: cs0254@bosc.cn | U90: cs0254 | V90: 系统功能 | W90: 开发 | Z90: BDPHADP | AC90: 详细设计 | AD90: 姚蔚--企业满意度评分为满意的客户的网银签约情况数据：需求分析，脚本编写，数据查询，核对数据 | AE90: 9
A91: 46106.701 | B91: 指标-工时 | C91: 510 | D91: 盛健钢 | E91: CS6391 | F91: 数据开发部 | H91: 否 | I91: X20251027000041-CAFBDM | J91: 天阳宏业科技股份有限公司 | K91: 数据开发 | L91: B模式 | M91: 数据开发部落 | N91: 基础数据小队 | O91: 金融基础数据模型计算区 | P91: ADPM需求-X20251027000041[第1批] | Q91: 南通众和应收账款业务业务需求书 | S91: 中级 | T91: cs6391@bosc.cn | U91: cs6391 | V91: 系统功能 | W91: 开发 | X91: 年度预算制 | Y91: X20251027000041 | Z91: CAFBDM | AA91: 开发一部 | AB91: 进行中 | AC91: 已完成 | AE91: 8.5 | AF91: 上海开发测试中心
A92: 46106.699 | B92: 指标-工时 | C92: 510 | D92: 李博雅 | E92: CS0770 | F92: 数据开发部 | H92: 否 | I92: 大数据开发 | J92: 上海天正智能数据服务有限公司 | K92: 数据开发 | L92: B模式 | M92: 数据平台部落 | N92: 大数据入仓小队 | O92: Hadoop大数据集群 | P92: ADPM需求-X20251215000003[第3批] | Q92: 关于抖音电商业务功能优化需求书 | S92: 中级 | T92: cs0770@bosc.cn | U92: cs0770 | V92: 系统功能 | W92: 小队长 | X92: 维护需求 | Y92: X20251215000003 | Z92: BDPHADP | AA92: 开发四部 | AB92: 进行中 | AC92: 已完成 | AD92: iccs_acctbal_monitor_diff,iccs_mch_apply_ntf,iccs_own_mch_risk,iccs_alipay_apply,iccs_order_cncl_idx,iccs_alipay_detail,iccs_bytepay_detail00等抽数入仓及配合上下游联调测试 | AE92: 8.5 | AF92: 上海开发测试中心
A93: 46106.699 | B93: 指标-工时 | C93: 510 | D93: 崔建文 | E93: 304059 | F93: 智能应用一部 | G93: =VLOOKUP(D93,'人员清单-202603'!D:J,7,FALSE) -> 对公应用组 | H93: 是 | I93: 反诈机器学习模型0327版本开发测试 | M93: 智能研发部落 | N93: 对公应用小队 | Q93: 关于反电诈管理项目的需求 | T93: 304059@bosc.cn | U93: 304059 | V93: 事项任务 | W93: 测试小队长 | X93: 项目 | Y93: X20240428000013 | AB93: 进行中 | AC93: 进行中 | AE93: 8.5 | AF93: 智能创新部 | AG93: 开发（含模型、应用、数仓等）
A94: 46106.687 | B94: 指标-工时 | C94: 127 | D94: 李洋 | E94: CS101303 | F94: 数据治理部 | H94: 否 | I94: 根据批注意见修改DCMM5咨询评估项目合同模板 | J94: 方正国际软件（北京）有限公司 | L94: A模式 | M94: 数管科技管理部落 | N94: 数据治理助理小队（数管） | S94: 中级 | T94: cs101303@bosc.cn | U94: cs101303 | V94: 事项任务 | AC94: 进行中 | AE94: 2.1167 | AG94: 培训学习 | AH94: 培训学习
A95: 46106.678 | B95: 指标-工时 | C95: 510 | D95: 戴艳 | E95: CS4953 | F95: 数据开发部 | H95: 否 | I95: KPI项目-非标准化下钻页面-掌上行页面开发 | J95: 北京宇信科技集团股份有限公司 | K95: 数据开发 | L95: B模式 | M95: 信息管理部落 | N95: UDAS基础数据小队 | O95: 掌上行 | P95: ADPM需求-X20250612000039[第6批] | Q95: 2025年经营指标体系建设 | S95: 中级 | T95: cs4953@bosc.cn | U95: cs4953 | V95: 系统功能 | W95: 开发 | X95: 项目 | Y95: X20250612000039 | Z95: AMBI | AB95: 进行中 | AC95: 已完成 | AD95: 指标数据验证，逻辑验证，调整 | AE95: 8.5 | AF95: 综合管理部
A96: 46106.676 | B96: 指标-工时 | C96: 510 | D96: 王言哲 | E96: 304765 | F96: 数据开发部 | G96: =VLOOKUP(D96,'人员清单-202603'!D:J,7,FALSE) -> 应用开发组 | H96: 是 | I96: 工时填报-反洗钱日常需求对接 | M96: 数据开发部落 | N96: 反洗钱小队 | T96: 304765@bosc.cn | U96: 304765 | V96: 事项任务 | W96: 小队长 | AC96: 进行中 | AE96: 8.5 | AG96: 项目管理（含外包管理） | AH96: 流程类事务
A97: 46106.671 | B97: 指标-工时 | C97: 510 | D97: 郝佳佳 | E97: CS4491 | F97: 数据开发部 | H97: 否 | I97: X20251103000036_关于网点汇总数据的优化需求_二批次NRP | J97: 上海天正智能数据服务有限公司 | K97: 数据开发 | L97: B模式 | M97: 信息管理部落 | N97: NRP集市小队 | O97: Hadoop大数据集群 | S97: 中级 | T97: cs4491@bosc.cn | U97: cs4491 | V97: 系统功能 | W97: 开发 | Z97: BDPHADP | AC97: 详细设计 | AD97: 1、需求分析调研类工作 分析X20251103000036需求改造点，涉及大数据NRP_E_MIS_JYDW_2088_RPT_SUM、UDAS_E1_XYK_2100_RPT_SUM作业调整口径调研； 涉及业务提供作业为源系统表及集市表，找对应整合模型的表及字段 | AE97: 8.5
A98: 46106.668 | B98: 指标-工时 | C98: 510 | D98: 李钰 | E98: CS0581 | F98: 数据开发部 | H98: 否 | I98: RBW迁移时效优化天正 | J98: 上海天正智能数据服务有限公司 | K98: 数据开发 | L98: B模式 | M98: 数据开发部落 | N98: 基础数据小队 | O98: Hadoop大数据集群 | P98: ADPM需求-X20240119000030[第2批] | Q98: 大数据仓库及应用系统数据时效治理专项优化项目(2024年) | S98: 中级 | T98: cs0581@bosc.cn | U98: cs0581 | V98: 系统功能 | W98: 开发 | X98: 项目 | Y98: X20240119000030 | Z98: BDPHADP | AB98: 进行中 | AC98: 联调 | AD98: 理财销量业务模型20260320数据验证6个复杂字段，修改脚本逻辑 | AE98: 8.5 | AF98: 数据开发部
A99: 46106.666 | B99: 指标-工时 | C99: 510 | D99: 鞠婉莹 | E99: CS3212 | F99: 信息管理部 | H99: 否 | I99: 鞠婉莹2026Q1 | J99: 上海天正智能数据服务有限公司 | K99: 数据开发 | L99: B模式 | M99: 数据开发部落 | N99: 大数据应用一队 | O99: 数据仓库 | S99: 中级 | T99: cs3212@bosc.cn | U99: cs3212 | V99: 系统功能 | W99: 开发 | Z99: EDW | AC99: 详细设计 | AD99: 专项任务-陈姿-代发新户领取企业明细代码开发，看板搭建和优化 | AE99: 8.5
A100: 46106.661 | B100: 指标-工时 | C100: 510 | D100: 沈子新 | E100: 307311 | F100: 智能应用一部 | G100: =VLOOKUP(D100,'人员清单-202603'!D:J,7,FALSE) -> 对公应用组 | H100: 是 | I100: 信贷场景MVP版本327版本开发 | M100: 智能研发部落 | N100: 对公应用小队 | T100: 307311@bosc.cn | U100: 307311 | V100: 事项任务 | AC100: 进行中 | AE100: 8.5 | AG100: 项目管理（含外包管理） | AH100: 流程类事务
...

Sheet 人员清单-202603
A1: 实际内设部 | B1: EHR内设部 | C1: 内设部是否变动 | D1: 姓名 | E1: 工号 | F1: 现岗位 | G1: 拟岗位 | H1: 岗位是否变动 | I1: 现角色标签 （组长/骨干） | J1: 拟分组
A2: 信息管理部 | B2: 信息管理部 | C2: 0 | D2: 舒宝龙 | E2: 305069 | F2: 数据分析 | G2: 数据分析 | H2: 0 | I2: 组长 | J2: 负责人 | K2: =C2+H2 -> 0
A3: 信息管理部 | B3: 信息管理部 | C3: 0 | D3: 任若琳 | E3: 307309 | F3: 数据分析 | G3: 需求分析 | H3: 1 | J3: 服务管理组 | K3: =C3+H3 -> 1
A4: 信息管理部 | B4: 信息管理部 | C4: 0 | D4: 成绘茜 | E4: 307444 | F4: 数据分析 | G4: 需求分析 | H4: 1 | J4: 服务管理组 | K4: =C4+H4 -> 1
A5: 信息管理部 | B5: 信息管理部 | C5: 0 | D5: 陆应佳玥 | E5: 305199 | F5: 数据分析 | G5: 需求分析 | H5: 1 | J5: 服务管理组 | K5: =C5+H5 -> 1
A6: 信息管理部 | B6: 信息管理部 | C6: 0 | D6: 李小萌 | E6: 306533 | F6: 数据分析 | G6: 需求分析 | H6: 1 | J6: 服务管理组 | K6: =C6+H6 -> 1
A7: 信息管理部 | B7: 信息管理部 | C7: 0 | D7: 宋轲 | E7: 307028 | F7: 数据分析 | G7: 数据分析 | H7: 0 | J7: 服务支持组 | K7: =C7+H7 -> 0
A8: 信息管理部 | B8: 信息管理部 | C8: 0 | D8: 张文婉 | E8: 304804 | F8: 数据分析 | G8: 数据分析 | H8: 0 | J8: 服务支持组 | K8: =C8+H8 -> 0
A9: 信息管理部 | B9: 信息管理部 | C9: 0 | D9: 刘雅雯 | E9: 307443 | F9: 数据分析 | G9: 数据分析 | H9: 0 | J9: 服务支持组 | K9: =C9+H9 -> 0
A10: 信息管理部 | B10: 信息管理部 | C10: 0 | D10: 孙菡悦 | E10: 305446 | F10: 数据分析 | G10: 数据分析 | H10: 0 | J10: 服务支持组 | K10: =C10+H10 -> 0
A11: 信息管理部 | B11: 信息管理部 | C11: 0 | D11: 刘思言 | E11: 305409 | F11: 数据分析 | G11: 数据分析 | H11: 0 | J11: 服务支持组 | K11: =C11+H11 -> 0
A12: 信息管理部 | B12: 信息管理部 | C12: 0 | D12: 谢丹伶 | E12: 305588 | F12: 数据分析 | G12: 数据分析 | H12: 0 | J12: 服务支持组 | K12: =C12+H12 -> 0
A13: 数据测试部 | B13: 综合管理部 | C13: 1 | D13: 杨萍 | E13: 306253 | F13: 数据测试 | G13: 负责人 | H13: 1 | I13: 组长 | J13: 负责人 | K13: =C13+H13 -> 2
A14: 数据测试部 | B14: 综合管理部 | C14: 1 | D14: 马亦沁 | E14: 305419 | F14: 数据测试 | G14: 数据测试 | H14: 0 | J14: 测试管理组 | K14: =C14+H14 -> 1
A15: 数据测试部 | B15: 综合管理部 | C15: 1 | D15: 蒋书润 | E15: 306762 | F15: 数据测试 | G15: 数据测试 | H15: 0 | J15: 测试管理组 | K15: =C15+H15 -> 1
A16: 数据测试部 | B16: 综合管理部 | C16: 1 | D16: 陈世辉 | E16: 306537 | F16: 数据测试 | G16: 数据测试 | H16: 0 | I16: 骨干 | J16: 测试管理组 | K16: =C16+H16 -> 1
A17: 数据测试部 | B17: 综合管理部 | C17: 1 | D17: 曹翔 | E17: 306530 | F17: 数据测试 | G17: 数据测试 | H17: 0 | J17: 测试管理组 | K17: =C17+H17 -> 1
A18: 数据开发部 | B18: 数据开发部 | C18: 0 | D18: 顾恺 | E18: 319914 | F18: 负责人 | G18: 负责人 | H18: 0 | J18: 负责人 | K18: =C18+H18 -> 0
A19: 数据开发部 | B19: 数据开发部 | C19: 0 | D19: 杨青 | E19: 302330 | F19: 数据研发 | G19: 架构管理 | H19: 1 | J19: 协管 | K19: =C19+H19 -> 1
A20: 数据开发部 | B20: 数据开发部 | C20: 0 | D20: 黄哲睿 | E20: 302570 | F20: 数据研发 | G20: 架构管理 | H20: 1 | I20: 组长 | J20: 模型设计组 | K20: =C20+H20 -> 1
A21: 数据开发部 | B21: 数据开发部 | C21: 0 | D21: 林幸 | E21: 304814 | F21: 数据研发 | G21: 数据研发 | H21: 0 | I21: 骨干 | J21: 模型设计组 | K21: =C21+H21 -> 0
A22: 数据开发部 | B22: 数据开发部 | C22: 0 | D22: 姚志环 | E22: 303494 | F22: 数据研发 | G22: 数据研发 | H22: 0 | I22: 骨干 | J22: 模型设计组 | K22: =C22+H22 -> 0
A23: 数据开发部 | B23: 数据开发部 | C23: 0 | D23: 窦博文 | E23: 303569 | F23: 数据研发 | G23: 架构管理 | H23: 1 | J23: 模型设计组 | K23: =C23+H23 -> 1
A24: 数据开发部 | B24: 数据开发部 | C24: 0 | D24: 田振宇 | E24: 305405 | F24: 数据研发 | G24: 数据研发 | H24: 0 | J24: 模型设计组 | K24: =C24+H24 -> 0
A25: 数据开发部 | B25: 数据开发部 | C25: 0 | D25: 陆慧 | E25: 306252 | F25: 数据研发 | G25: 架构管理 | H25: 1 | I25: 骨干 | J25: 模型设计组 | K25: =C25+H25 -> 1
A26: 数据开发部 | B26: 数据开发部 | C26: 0 | D26: 周影 | E26: 303060 | F26: 数据研发 | G26: 数据研发 | H26: 0 | I26: 骨干 | J26: 模型设计组 | K26: =C26+H26 -> 0
A27: 数据开发部 | B27: 数据开发部 | C27: 0 | D27: 郑卞钰 | E27: 304792 | F27: 数据研发 | G27: 数据研发 | H27: 0 | J27: 模型设计组 | K27: =C27+H27 -> 0
A28: 数据开发部 | B28: 数据开发部 | C28: 0 | D28: 潘修滔 | E28: 305341 | F28: 数据研发 | G28: 数据研发 | H28: 0 | J28: 模型设计组 | K28: =C28+H28 -> 0
A29: 数据开发部 | B29: 数据开发部 | C29: 0 | D29: 赵雅婷 | E29: 306177 | F29: 数据研发 | G29: 数据研发 | H29: 0 | J29: 模型设计组 | K29: =C29+H29 -> 0
A30: 数据开发部 | B30: 数据开发部 | C30: 0 | D30: 兰昕蕾 | E30: 304064 | F30: 数据研发 | G30: 数据研发 | H30: 0 | I30: 组长 | J30: 数仓开发组 | K30: =C30+H30 -> 0
A31: 数据开发部 | B31: 数据开发部 | C31: 0 | D31: 袁凯 | E31: 305432 | F31: 数据研发 | G31: 数据研发 | H31: 0 | J31: 数仓开发组 | K31: =C31+H31 -> 0
A32: 数据开发部 | B32: 数据开发部 | C32: 0 | D32: 王萌萌 | E32: 306175 | F32: 数据研发 | G32: 数据研发 | H32: 0 | J32: 数仓开发组 | K32: =C32+H32 -> 0
A33: 数据开发部 | B33: 数据开发部 | C33: 0 | D33: 连静 | E33: 306532 | F33: 数据研发 | G33: 数据研发 | H33: 0 | J33: 数仓开发组 | K33: =C33+H33 -> 0
A34: 数据开发部 | B34: 数据开发部 | C34: 0 | D34: 曹婕 | E34: 305401 | F34: 数据研发 | G34: 数据研发 | H34: 0 | J34: 数仓开发组 | K34: =C34+H34 -> 0
A35: 数据开发部 | B35: 数据开发部 | C35: 0 | D35: 李禹凝 | E35: 306190 | F35: 数据研发 | G35: 数据研发 | H35: 0 | J35: 数仓开发组 | K35: =C35+H35 -> 0
A36: 数据开发部 | B36: 数据开发部 | C36: 0 | D36: 吴越 | E36: 307139 | F36: 数据研发 | G36: 数据研发 | H36: 0 | J36: 数仓开发组 | K36: =C36+H36 -> 0
A37: 数据开发部 | B37: 数据开发部 | C37: 0 | D37: 诸倩铷 | E37: 306187 | F37: 数据研发 | G37: 数据研发 | H37: 0 | J37: 数仓开发组 | K37: =C37+H37 -> 0
A38: 数据开发部 | B38: 数据开发部 | C38: 0 | D38: 罗仁杰 | E38: 319957 | F38: 数据研发 | G38: 数据研发 | H38: 0 | I38: 组长 | J38: 数据接入组 | K38: =C38+H38 -> 0
A39: 数据开发部 | B39: 数据开发部 | C39: 0 | D39: 李卓辉 | E39: 302476 | F39: 数据研发 | G39: 数据研发 | H39: 0 | J39: 数据接入组 | K39: =C39+H39 -> 0
A40: 数据开发部 | B40: 数据开发部 | C40: 0 | D40: 李凯文 | E40: 305481 | F40: 数据研发 | G40: 数据研发 | H40: 0 | J40: 数据接入组 | K40: =C40+H40 -> 0
A41: 数据开发部 | B41: 数据开发部 | C41: 0 | D41: 杜乐 | E41: 306534 | F41: 数据研发 | G41: 数据研发 | H41: 0 | J41: 数据接入组 | K41: =C41+H41 -> 0
A42: 数据开发部 | B42: 数据开发部 | C42: 0 | D42: 邹小芳 | E42: 305042 | F42: 数据研发 | G42: 数据研发 | H42: 0 | I42: 组长 | J42: 应用开发组 | K42: =C42+H42 -> 0
A43: 数据开发部 | B43: 数据开发部 | C43: 0 | D43: 马富强 | E43: 305026 | F43: 数据研发 | G43: 数据研发 | H43: 0 | I43: 骨干 | J43: 应用开发组 | K43: =C43+H43 -> 0
A44: 数据开发部 | B44: 数据开发部 | C44: 0 | D44: 胡庆 | E44: 306171 | F44: 数据研发 | G44: 数据研发 | H44: 0 | J44: 应用开发组 | K44: =C44+H44 -> 0
A45: 数据开发部 | B45: 数据开发部 | C45: 0 | D45: 陈科宇 | E45: 303447 | F45: 数据研发 | G45: 数据研发 | H45: 0 | J45: 应用开发组 | K45: =C45+H45 -> 0
A46: 数据开发部 | B46: 数据开发部 | C46: 0 | D46: 张倩 | E46: 305396 | F46: 数据研发 | G46: 数据研发 | H46: 0 | J46: 应用开发组 | K46: =C46+H46 -> 0
A47: 数据开发部 | B47: 数据开发部 | C47: 0 | D47: 陈晨 | E47: 306545 | F47: 数据研发 | G47: 数据研发 | H47: 0 | J47: 应用开发组 | K47: =C47+H47 -> 0
A48: 数据开发部 | B48: 数据开发部 | C48: 0 | D48: 骆静龙 | E48: 305421 | F48: 数据研发 | G48: 数据研发 | H48: 0 | I48: 骨干 | J48: 应用开发组 | K48: =C48+H48 -> 0
A49: 数据开发部 | B49: 数据开发部 | C49: 0 | D49: 陈佳宁 | E49: 307133 | F49: 数据研发 | G49: 数据研发 | H49: 0 | J49: 应用开发组 | K49: =C49+H49 -> 0
A50: 数据开发部 | B50: 数据开发部 | C50: 0 | D50: 张雅淇 | E50: 303482 | F50: 数据研发 | G50: 数据研发 | H50: 0 | J50: 应用开发组 | K50: =C50+H50 -> 0
A51: 数据开发部 | B51: 数据开发部 | C51: 0 | D51: 陈笑轩 | E51: 304812 | F51: 数据研发 | G51: 数据研发 | H51: 0 | J51: 应用开发组 | K51: =C51+H51 -> 0
A52: 数据开发部 | B52: 数据开发部 | C52: 0 | D52: 梅苏源 | E52: 306525 | F52: 数据研发 | G52: 数据研发 | H52: 0 | J52: 应用开发组 | K52: =C52+H52 -> 0
A53: 数据开发部 | B53: 数据开发部 | C53: 0 | D53: 胡雯 | E53: 304805 | F53: 数据研发 | G53: 数据研发 | H53: 0 | J53: 应用开发组 | K53: =C53+H53 -> 0
A54: 数据开发部 | B54: 数据开发部 | C54: 0 | D54: 阮靖龙 | E54: 306523 | F54: 数据研发 | G54: 数据研发 | H54: 0 | J54: 应用开发组 | K54: =C54+H54 -> 0
A55: 数据开发部 | B55: 数据开发部 | C55: 0 | D55: 王言哲 | E55: 304765 | F55: 数据研发 | G55: 数据研发 | H55: 0 | I55: 骨干 | J55: 应用开发组 | K55: =C55+H55 -> 0
A56: 数据开发部 | B56: 数据开发部 | C56: 0 | D56: 王子枫 | E56: 305473 | F56: 数据研发 | G56: 数据研发 | H56: 0 | J56: 应用开发组 | K56: =C56+H56 -> 0
A57: 数据开发部 | B57: 数据开发部 | C57: 0 | D57: 丁晨 | E57: 304795 | F57: 数据研发 | G57: 数据研发 | H57: 0 | I57: 组长 | J57: 应用开发组 | K57: =C57+H57 -> 0
A58: 数据开发部 | B58: 数据开发部 | C58: 0 | D58: 周龙 | E58: 301732 | F58: 数据研发 | G58: 数据研发 | H58: 0 | I58: 骨干 | J58: 应用开发组 | K58: =C58+H58 -> 0
A59: 数据开发部 | B59: 数据开发部 | C59: 0 | D59: 钱磊 | E59: 305087 | F59: 数据研发 | G59: 数据研发 | H59: 0 | J59: 应用开发组 | K59: =C59+H59 -> 0
A60: 数据开发部 | B60: 数据开发部 | C60: 0 | D60: 龚毅磊 | E60: 306066 | F60: 数据研发 | G60: 数据研发 | H60: 0 | J60: 应用开发组 | K60: =C60+H60 -> 0
A61: 数据开发部 | B61: 数据开发部 | C61: 0 | D61: 吴小倩 | E61: 304799 | F61: 数据研发 | G61: 数据研发 | H61: 0 | J61: 应用开发组 | K61: =C61+H61 -> 0
A62: 数据开发部 | B62: 数据开发部 | C62: 0 | D62: 景丞 | E62: 305888 | F62: 数据研发 | G62: 数据研发 | H62: 0 | J62: 应用开发组 | K62: =C62+H62 -> 0
A63: 数据开发部 | B63: 数据开发部 | C63: 0 | D63: 康冉 | E63: 303473 | F63: 数据研发 | G63: 数据研发 | H63: 0 | I63: 骨干 | J63: 应用开发组 | K63: =C63+H63 -> 0
A64: 数据开发部 | B64: 数据开发部 | C64: 0 | D64: 卫彩萍 | E64: 306527 | F64: 数据研发 | G64: 数据研发 | H64: 0 | J64: 应用开发组 | K64: =C64+H64 -> 0
A65: 数据开发部 | B65: 数据开发部 | C65: 0 | D65: 刘梦颖 | E65: 305907 | F65: 数据研发 | G65: 数据研发 | H65: 0 | J65: 应用开发组 | K65: =C65+H65 -> 0
A66: 数据开发部 | B66: 数据开发部 | C66: 0 | D66: 徐倩茹 | E66: 307138 | F66: 数据研发 | G66: 数据研发 | H66: 0 | J66: 应用开发组 | K66: =C66+H66 -> 0
A67: 数据平台部 | B67: 数据平台部 | C67: 0 | D67: 吴证 | E67: 306844 | F67: 数据研发 | G67: 负责人 | H67: 1 | J67: 负责人 | K67: =C67+H67 -> 1
A68: 数据平台部 | B68: 数据平台部 | C68: 0 | D68: 曹宁远 | E68: 303401 | F68: 数据研发 | G68: 应用研发 | H68: 1 | I68: 组长 | J68: 工具开发组 | K68: =C68+H68 -> 1
A69: 数据平台部 | B69: 数据平台部 | C69: 0 | D69: 伍恒 | E69: 302573 | F69: 数据研发 | G69: 应用研发 | H69: 1 | I69: 骨干 | J69: 工具开发组 | K69: =C69+H69 -> 1
A70: 数据平台部 | B70: 数据平台部 | C70: 0 | D70: 濮敏 | E70: 303930 | F70: 数据研发 | G70: 应用研发 | H70: 1 | J70: 工具开发组 | K70: =C70+H70 -> 1
A71: 数据平台部 | B71: 数据平台部 | C71: 0 | D71: 沈志贇 | E71: 305350 | F71: 数据研发 | G71: 应用研发 | H71: 1 | J71: 工具开发组 | K71: =C71+H71 -> 1
A72: 数据平台部 | B72: 数据平台部 | C72: 0 | D72: 朱文川 | E72: 305484 | F72: 数据研发 | G72: 应用研发 | H72: 1 | I72: 骨干 | J72: 工具开发组 | K72: =C72+H72 -> 1
A73: 数据平台部 | B73: 数据平台部 | C73: 0 | D73: 王双钰 | E73: 305184 | F73: 数据研发 | G73: 应用研发 | H73: 1 | J73: 工具开发组 | K73: =C73+H73 -> 1
A74: 数据平台部 | B74: 数据平台部 | C74: 0 | D74: 吕丽丽 | E74: 306191 | F74: 数据研发 | G74: 应用研发 | H74: 1 | J74: 工具开发组 | K74: =C74+H74 -> 1
A75: 数据平台部 | B75: 数据平台部 | C75: 0 | D75: 陈玉思 | E75: 306538 | F75: 数据研发 | G75: 应用研发 | H75: 1 | J75: 工具开发组 | K75: =C75+H75 -> 1
A76: 数据平台部 | B76: 数据平台部 | C76: 0 | D76: 鞠爱宁 | E76: 302551 | F76: 数据研发 | G76: 应用研发 | H76: 1 | I76: 组长 | J76: 数据服务组 | K76: =C76+H76 -> 1
A77: 数据平台部 | B77: 数据平台部 | C77: 0 | D77: 周浩 | E77: 303415 | F77: 数据研发 | G77: 应用研发 | H77: 1 | J77: 数据服务组 | K77: =C77+H77 -> 1
A78: 数据平台部 | B78: 数据平台部 | C78: 0 | D78: 胡帆 | E78: 304775 | F78: 数据研发 | G78: 应用研发 | H78: 1 | I78: 骨干 | J78: 数据服务组 | K78: =C78+H78 -> 1
A79: 数据平台部 | B79: 数据平台部 | C79: 0 | D79: 安新宜 | E79: 305188 | F79: 数据研发 | G79: 应用研发 | H79: 1 | J79: 数据服务组 | K79: =C79+H79 -> 1
A80: 数据平台部 | B80: 数据平台部 | C80: 0 | D80: 张放 | E80: 305337 | F80: 数据研发 | G80: 应用研发 | H80: 1 | J80: 数据服务组 | K80: =C80+H80 -> 1
A81: 数据平台部 | B81: 数据平台部 | C81: 0 | D81: 王新蕾 | E81: 306539 | F81: 数据研发 | G81: 应用研发 | H81: 1 | J81: 数据服务组 | K81: =C81+H81 -> 1
A82: 数据平台部 | B82: 数据平台部 | C82: 0 | D82: 任欣宇 | E82: 307135 | F82: 数据研发 | G82: 应用研发 | H82: 1 | J82: 数据服务组 | K82: =C82+H82 -> 1
A83: 数据平台部 | B83: 数据平台部 | C83: 0 | D83: 刘金良 | E83: 307351 | F83: 数据研发 | G83: 应用研发 | H83: 1 | J83: 数据服务组 | K83: =C83+H83 -> 1
A84: 数据平台部 | B84: 数据平台部 | C84: 0 | D84: 万珊红 | E84: 304077 | F84: 数据研发 | G84: 应用研发 | H84: 1 | J84: 数据服务组 | K84: =C84+H84 -> 1
A85: 数据平台部 | B85: 数据平台部 | C85: 0 | D85: 陆凯华 | E85: 304826 | F85: 数据研发 | G85: 应用研发 | H85: 1 | I85: 骨干 | J85: 数据服务组 | K85: =C85+H85 -> 1
A86: 数据平台部 | B86: 数据平台部 | C86: 0 | D86: 白迪 | E86: 303028 | F86: 数据研发 | G86: 架构管理 | H86: 1 | J86: 协管 | K86: =C86+H86 -> 1
A87: 数据平台部 | B87: 数据平台部 | C87: 0 | D87: 魏佳翔 | E87: 306836 | F87: 数据研发 | G87: 应用研发 | H87: 1 | I87: 组长 | J87: 应用开发组 | K87: =C87+H87 -> 1
A88: 数据平台部 | B88: 数据平台部 | C88: 0 | D88: 王正超 | E88: 303471 | F88: 数据研发 | G88: 应用研发 | H88: 1 | I88: 骨干 | J88: 应用开发组 | K88: =C88+H88 -> 1
A89: 数据平台部 | B89: 数据平台部 | C89: 0 | D89: 梅凯磊 | E89: 304855 | F89: 数据研发 | G89: 应用研发 | H89: 1 | J89: 应用开发组 | K89: =C89+H89 -> 1
A90: 数据平台部 | B90: 数据平台部 | C90: 0 | D90: 李敏吉 | E90: 306531 | F90: 数据研发 | G90: 应用研发 | H90: 1 | J90: 应用开发组 | K90: =C90+H90 -> 1
A91: 数据平台部 | B91: 数据平台部 | C91: 0 | D91: 刘惠 | E91: 305266 | F91: 数据研发 | G91: 应用研发 | H91: 1 | J91: 应用开发组 | K91: =C91+H91 -> 1
A92: 数据平台部 | B92: 数据平台部 | C92: 0 | D92: 嵇雅娟 | E92: 305131 | F92: 数据研发 | G92: 应用研发 | H92: 1 | I92: 骨干 | J92: 应用开发组 | K92: =C92+H92 -> 1
A93: 数据平台部 | B93: 数据平台部 | C93: 0 | D93: 佟嘉欣 | E93: 307134 | F93: 数据研发 | G93: 应用研发 | H93: 1 | J93: 应用开发组 | K93: =C93+H93 -> 1
A94: 数据平台部 | B94: 数据平台部 | C94: 0 | D94: 张顺 | E94: 307136 | F94: 数据研发 | G94: 应用研发 | H94: 1 | J94: 应用开发组 | K94: =C94+H94 -> 1
A95: 数据平台部 | B95: 数据开发部 | C95: 1 | D95: 张必歌 | E95: 304793 | F95: 数据研发 | G95: 应用研发 | H95: 1 | J95: 应用开发组 | K95: =C95+H95 -> 2
A96: 数据平台部 | B96: 数据平台部 | C96: 0 | D96: 史朋飞 | E96: 307234 | F96: 数据研发 | G96: 架构管理 | H96: 1 | I96: 组长 | J96: 运维支持组 | K96: =C96+H96 -> 1
A97: 数据平台部 | B97: 数据平台部 | C97: 0 | D97: 李天卓 | E97: 303450 | F97: 数据研发 | G97: 架构管理 | H97: 1 | I97: 骨干 | J97: 运维支持组 | K97: =C97+H97 -> 1
A98: 数据平台部 | B98: 数据平台部 | C98: 0 | D98: 冯晓煜 | E98: 303436 | F98: 数据研发 | G98: 架构管理 | H98: 1 | J98: 运维支持组 | K98: =C98+H98 -> 1
A99: 数据平台部 | B99: 数据平台部 | C99: 0 | D99: 冯潇 | E99: 304085 | F99: 数据研发 | G99: 架构管理 | H99: 1 | J99: 运维支持组 | K99: =C99+H99 -> 1
A100: 数据平台部 | B100: 数据平台部 | C100: 0 | D100: 陈朗 | E100: 306526 | F100: 数据研发 | G100: 架构管理 | H100: 1 | J100: 运维支持组 | K100: =C100+H100 -> 1
...
