Workbook

Sheet 2.1 全量203人-11月
A1: 序号 | B1: 姓名 | C1: 基本信息 | I1: 岗位信息 | O1: 党工团任职情况 | R1: 行内、行外荣誉 | S1: 主动学习与对外输出 | X1: 考勤数据 | AD1: 工作饱和度量化（开发类岗位） | AL1: 综合主观评价 | AS1: 备注 | AT1: 加工指标
C2: 团队 | D2: 组 | E2: 性别 | F2: 累计工龄 | G2: 最高学历 | H2: 最高学历毕业院校 | I2: 科长/组长/骨干标识 | J2: 产品经理/架构师标识 | K2: 产品经理/架构师负责应用个数 | L2: 岗位变动次数 | M2: 现在的工作岗位 | N2: 校招/社招标识 | O2: 党组织 | P2: 工会小组 | Q2: 团委 | S2: 年度参加培训次数 | T2: 查看知识库会议纪要次数(3个月) | U2: 年度部门内培训次数 | V2: 年度部门外培训次数 | W2: 近2年带教人数 | X2: 平均加班时长 | Y2: 工作时长高于部门均值 | Z2: 1h以下 | AA2: 加班1-2h频次 | AB2: 加班2-4h频次 | AC2: 加班4h以上频次 | AD2: 牵头项目数量 | AE2: 牵头需求数量 | AF2: 主管应用系统数量（近六个月有变更的数量） | AG2: 新paso体系参与应用数量 | AH2: 二季度变更任务数 | AI2: 三季度变更任务数 | AK2: 饱和度量化 不饱和：平均加班时长1h以下/无变更任务无主管应用非组长骨干/科长评定不饱和 超负荷：季度变更任务≥10/加班4H以上超过30次/平均加班时长3H以上/科长评定超负荷 | AL2: 领导力 | AM2: 专业能力 | AN2: 工作态度 | AO2: 团队合作 | AP2: 累计 | AQ2: 归类 | AR2: 其他特质 | AT2: 饱和度指标
A3: 1 | B3: 黄哲睿 | C3: 数据开发部 | D3: 模型设计组 | E3: 男 | F3: 8 | G3: 大学本科 | H3: 南京大学 | I3: 组长 | J3: 架构师 | K3: 2 | L3: 0 | M3: 数据研发 | N3: 校园招聘 | Q3: 团委书记 | R3: 24数据文化优秀贡献者 | S3: =VLOOKUP(B3,'[2]62人'!$B:$R,17,FALSE) -> 1 | T3: 5 | X3: =VLOOKUP(B3,[4]考勤分析!$A:$I,4,FALSE) -> 4.6505208 | Y3: =VLOOKUP(B3,[4]考勤分析!$A:$I,5,FALSE) -> TRUE | Z3: =VLOOKUP(B3,[4]考勤分析!$A:$I,6,FALSE) -> 9 | AA3: =VLOOKUP(B3,[4]考勤分析!$A:$I,7,FALSE) -> 2 | AB3: =VLOOKUP(B3,[4]考勤分析!$A:$I,8,FALSE) -> 20 | AC3: =VLOOKUP(B3,[4]考勤分析!$A:$I,9,FALSE) -> 41 | AD3: 0 | AE3: 1 | AF3: 0 | AG3: 1 | AH3: 0 | AI3: 0 | AK3: =VLOOKUP(B3,[3]总表!$B:$W,22,FALSE) -> 超负荷 | AL3: 3 | AM3: 3 | AN3: 2 | AO3: 2 | AP3: =SUM(AL3:AO3) -> 10 | AQ3: 4-高潜培养对象 | AR3: 团队内人缘较好，有意见领袖的潜质 | AT3: =COUNTA(I3,J3,K3,O3,P3,Q3,W3) -> 4
A4: 2 | B4: 陆慧 | C4: 数据开发部 | D4: 模型设计组 | E4: 女 | F4: 14 | G4: 研究生 | H4: 南京大学 | I4: 骨干 | J4: 架构师 | K4: 5 | L4: 0 | M4: 数据研发 | N4: 社会招聘 | S4: =VLOOKUP(B4,'[2]62人'!$B:$R,17,FALSE) -> 2 | T4: 0 | W4: 1 | X4: =VLOOKUP(B4,[4]考勤分析!$A:$I,4,FALSE) -> 3.0414665 | Y4: =VLOOKUP(B4,[4]考勤分析!$A:$I,5,FALSE) -> TRUE | Z4: =VLOOKUP(B4,[4]考勤分析!$A:$I,6,FALSE) -> 16 | AA4: =VLOOKUP(B4,[4]考勤分析!$A:$I,7,FALSE) -> 16 | AB4: =VLOOKUP(B4,[4]考勤分析!$A:$I,8,FALSE) -> 24 | AC4: =VLOOKUP(B4,[4]考勤分析!$A:$I,9,FALSE) -> 12 | AD4: 0 | AE4: 0 | AF4: 0 | AG4: 1 | AH4: 0 | AI4: 0 | AK4: =VLOOKUP(B4,[3]总表!$B:$W,22,FALSE) -> 适中 | AL4: 1 | AM4: 3 | AN4: 3 | AO4: 2 | AP4: =SUM(AL4:AO4) -> 9 | AQ4: 1.1-专业能力强，但领导力较弱 | AR4: 埋头苦干型
A5: 3 | B5: 罗仁杰 | C5: 数据开发部 | D5: 需求接入组 | E5: 男 | F5: 21 | G5: 大学本科 | H5: 兰州理工大学 | I5: 组长 | J5: 架构师 | K5: 1 | L5: 1 | M5: 数据研发 | N5: 社会招聘 | R5: 23五星质量奖 | S5: =VLOOKUP(B5,'[2]62人'!$B:$R,17,FALSE) -> 16 | T5: 0 | X5: =VLOOKUP(B5,[4]考勤分析!$A:$I,4,FALSE) -> 3.1066158 | Y5: =VLOOKUP(B5,[4]考勤分析!$A:$I,5,FALSE) -> TRUE | Z5: =VLOOKUP(B5,[4]考勤分析!$A:$I,6,FALSE) -> 8 | AA5: =VLOOKUP(B5,[4]考勤分析!$A:$I,7,FALSE) -> 19 | AB5: =VLOOKUP(B5,[4]考勤分析!$A:$I,8,FALSE) -> 32 | AC5: =VLOOKUP(B5,[4]考勤分析!$A:$I,9,FALSE) -> 12 | AD5: 0 | AE5: 5 | AF5: 1 | AG5: 1 | AH5: 24 | AI5: 13 | AK5: =VLOOKUP(B5,[3]总表!$B:$W,22,FALSE) -> 超负荷 | AL5: 1 | AM5: 2 | AN5: 1 | AO5: 2 | AP5: =SUM(AL5:AO5) -> 6 | AQ5: 3-不作为优先培养对象 | AR5: 敬业，工龄长缺乏内驱力下，职等较高
A6: 4 | B6: 李卓辉 | C6: 数据开发部 | D6: 需求接入组 | E6: 男 | F6: 19 | G6: 研究生 | H6: 华东师范大学 | L6: 1 | M6: 数据研发 | N6: 社会招聘 | S6: =VLOOKUP(B6,'[2]62人'!$B:$R,17,FALSE) -> 15 | T6: 0 | X6: =VLOOKUP(B6,[4]考勤分析!$A:$I,4,FALSE) -> 2.1227375 | Y6: =VLOOKUP(B6,[4]考勤分析!$A:$I,5,FALSE) -> FALSE | Z6: =VLOOKUP(B6,[4]考勤分析!$A:$I,6,FALSE) -> 5 | AA6: =VLOOKUP(B6,[4]考勤分析!$A:$I,7,FALSE) -> 12 | AB6: =VLOOKUP(B6,[4]考勤分析!$A:$I,8,FALSE) -> 45 | AC6: =VLOOKUP(B6,[4]考勤分析!$A:$I,9,FALSE) -> 0 | AD6: 0 | AE6: 0 | AF6: 0 | AG6: 1 | AH6: 0 | AI6: 1 | AK6: =VLOOKUP(B6,[3]总表!$B:$W,22,FALSE) -> 不饱和 | AL6: 1 | AM6: 2 | AN6: 1 | AO6: 1 | AP6: =SUM(AL6:AO6) -> 5 | AQ6: 3-不作为优先培养对象 | AR6: 敬业，工龄长缺乏内驱力，职等较高
A7: 5 | B7: 兰昕蕾 | C7: 数据开发部 | D7: 数仓开发组 | E7: 女 | F7: 5 | G7: 研究生 | H7: 华东师范大学 | I7: 组长 | L7: 0 | M7: 数据研发 | N7: 校园招聘 | S7: =VLOOKUP(B7,'[2]62人'!$B:$R,17,FALSE) -> 14 | T7: 2 | U7: 3 | W7: 1 | X7: =VLOOKUP(B7,[4]考勤分析!$A:$I,4,FALSE) -> 3.9940217 | Y7: =VLOOKUP(B7,[4]考勤分析!$A:$I,5,FALSE) -> TRUE | Z7: =VLOOKUP(B7,[4]考勤分析!$A:$I,6,FALSE) -> 7 | AA7: =VLOOKUP(B7,[4]考勤分析!$A:$I,7,FALSE) -> 4 | AB7: =VLOOKUP(B7,[4]考勤分析!$A:$I,8,FALSE) -> 33 | AC7: =VLOOKUP(B7,[4]考勤分析!$A:$I,9,FALSE) -> 25 | AD7: 0 | AE7: 2 | AF7: 0 | AG7: 1 | AH7: 8 | AI7: 7 | AK7: =VLOOKUP(B7,[3]总表!$B:$W,22,FALSE) -> 超负荷 | AL7: 2 | AM7: 3 | AN7: 3 | AO7: 3 | AP7: =SUM(AL7:AO7) -> 11 | AQ7: 1.1-专业能力强，但领导力较弱 | AR7: 有思想、有潜力 值得培养
A8: 6 | B8: 邹小芳 | C8: 数据开发部 | D8: 数仓开发组 | E8: 女 | F8: 12 | G8: 大学本科 | H8: 江西财经大学 | I8: 组长 | L8: 0 | M8: 数据研发 | N8: 社会招聘 | S8: =VLOOKUP(B8,'[2]62人'!$B:$R,17,FALSE) -> 6 | T8: 0 | W8: 1 | X8: =VLOOKUP(B8,[4]考勤分析!$A:$I,4,FALSE) -> 3.2647607 | Y8: =VLOOKUP(B8,[4]考勤分析!$A:$I,5,FALSE) -> TRUE | Z8: =VLOOKUP(B8,[4]考勤分析!$A:$I,6,FALSE) -> 13 | AA8: =VLOOKUP(B8,[4]考勤分析!$A:$I,7,FALSE) -> 14 | AB8: =VLOOKUP(B8,[4]考勤分析!$A:$I,8,FALSE) -> 25 | AC8: =VLOOKUP(B8,[4]考勤分析!$A:$I,9,FALSE) -> 13 | AD8: 0 | AE8: 2 | AF8: 0 | AG8: 2 | AH8: 0 | AI8: 0 | AK8: =VLOOKUP(B8,[3]总表!$B:$W,22,FALSE) -> 超负荷 | AL8: 1 | AM8: 2 | AN8: 2 | AO8: 2 | AP8: =SUM(AL8:AO8) -> 7 | AQ8: 3-不作为优先培养对象 | AR8: 认真 没有出彩
A9: 7 | B9: 丁晨 | C9: 数据开发部 | D9: 数仓开发组 | E9: 男 | F9: 4 | G9: 研究生 | H9: 南京信息工程大学 | I9: 组长 | L9: 0 | M9: 数据研发 | N9: 校园招聘 | R9: 24五星质量奖 | S9: =VLOOKUP(B9,'[2]62人'!$B:$R,17,FALSE) -> 9 | T9: 1 | V9: 1 | X9: =VLOOKUP(B9,[4]考勤分析!$A:$I,4,FALSE) -> 3.8408638 | Y9: =VLOOKUP(B9,[4]考勤分析!$A:$I,5,FALSE) -> TRUE | Z9: =VLOOKUP(B9,[4]考勤分析!$A:$I,6,FALSE) -> 8 | AA9: =VLOOKUP(B9,[4]考勤分析!$A:$I,7,FALSE) -> 4 | AB9: =VLOOKUP(B9,[4]考勤分析!$A:$I,8,FALSE) -> 34 | AC9: =VLOOKUP(B9,[4]考勤分析!$A:$I,9,FALSE) -> 27 | AD9: 0 | AE9: 2 | AF9: 1 | AG9: 3 | AH9: 10 | AI9: 6 | AK9: =VLOOKUP(B9,[3]总表!$B:$W,22,FALSE) -> 超负荷 | AL9: 2 | AM9: 3 | AN9: 3 | AO9: 2 | AP9: =SUM(AL9:AO9) -> 10 | AQ9: 1.1-专业能力强，但领导力较弱 | AR9: 有思想、有潜力 值得培养
A10: 8 | B10: 周龙 | C10: 数据开发部 | D10: 应用开发组 | E10: 男 | F10: 10 | G10: 大学本科 | H10: 北京科技大学 | I10: 骨干 | J10: 产品经理 | K10: 2 | L10: 1 | M10: 数据研发 | N10: 社会招聘 | S10: =VLOOKUP(B10,'[2]62人'!$B:$R,17,FALSE) -> 7 | T10: 0 | W10: 1 | X10: =VLOOKUP(B10,[4]考勤分析!$A:$I,4,FALSE) -> 2.897921 | Y10: =VLOOKUP(B10,[4]考勤分析!$A:$I,5,FALSE) -> TRUE | Z10: =VLOOKUP(B10,[4]考勤分析!$A:$I,6,FALSE) -> 12 | AA10: =VLOOKUP(B10,[4]考勤分析!$A:$I,7,FALSE) -> 12 | AB10: =VLOOKUP(B10,[4]考勤分析!$A:$I,8,FALSE) -> 32 | AC10: =VLOOKUP(B10,[4]考勤分析!$A:$I,9,FALSE) -> 8 | AD10: 0 | AE10: 3 | AF10: 1 | AG10: 0 | AH10: 0 | AI10: 0 | AK10: =VLOOKUP(B10,[3]总表!$B:$W,22,FALSE) -> 超负荷 | AL10: 2 | AM10: 3 | AN10: 2 | AO10: 2 | AP10: =SUM(AL10:AO10) -> 9 | AQ10: 1.1-专业能力强，但领导力较弱 | AR10: 有一定思想 可被激发
A11: 9 | B11: 史朋飞 | C11: 数据平台部 | D11: 运维支持组 | E11: 男 | F11: 13 | G11: 大学本科 | H11: 河南理工大学 | I11: 组长 | J11: 架构师 | K11: 3 | L11: 0 | M11: 数据研发 | N11: 社会招聘 | S11: =VLOOKUP(B11,'[2]62人'!$B:$R,17,FALSE) -> 2 | T11: 0 | X11: =VLOOKUP(B11,[4]考勤分析!$A:$I,4,FALSE) -> 2.6378429 | Y11: =VLOOKUP(B11,[4]考勤分析!$A:$I,5,FALSE) -> TRUE | Z11: =VLOOKUP(B11,[4]考勤分析!$A:$I,6,FALSE) -> 11 | AA11: =VLOOKUP(B11,[4]考勤分析!$A:$I,7,FALSE) -> 4 | AB11: =VLOOKUP(B11,[4]考勤分析!$A:$I,8,FALSE) -> 45 | AC11: =VLOOKUP(B11,[4]考勤分析!$A:$I,9,FALSE) -> 4 | AD11: 0 | AE11: 0 | AF11: 1 | AG11: 5 | AH11: 2 | AI11: 2 | AK11: =VLOOKUP(B11,[3]总表!$B:$W,22,FALSE) -> 超负荷 | AL11: 2 | AM11: 3 | AN11: 3 | AO11: 2 | AP11: =SUM(AL11:AO11) -> 10 | AQ11: 1.1-专业能力强，但领导力较弱 | AR11: 社招入行，渴望被认可，工作积极性较强
A12: 10 | B12: 李天卓 | C12: 数据平台部 | D12: 运维支持组 | E12: 男 | F12: 6 | G12: 研究生 | H12: 上海师范大学 | I12: 骨干 | J12: 架构师 | K12: 2 | L12: 0 | M12: 数据研发 | N12: 校园招聘 | R12: 23技术能手 | S12: =VLOOKUP(B12,'[2]62人'!$B:$R,17,FALSE) -> 12 | T12: 0 | X12: =VLOOKUP(B12,[4]考勤分析!$A:$I,4,FALSE) -> 2.3013007 | Y12: =VLOOKUP(B12,[4]考勤分析!$A:$I,5,FALSE) -> TRUE | Z12: =VLOOKUP(B12,[4]考勤分析!$A:$I,6,FALSE) -> 9 | AA12: =VLOOKUP(B12,[4]考勤分析!$A:$I,7,FALSE) -> 30 | AB12: =VLOOKUP(B12,[4]考勤分析!$A:$I,8,FALSE) -> 17 | AC12: =VLOOKUP(B12,[4]考勤分析!$A:$I,9,FALSE) -> 7 | AD12: 0 | AE12: 0 | AF12: 2 | AG12: 1 | AH12: 0 | AI12: 1 | AK12: =VLOOKUP(B12,[3]总表!$B:$W,22,FALSE) -> 超负荷 | AL12: 1 | AM12: 2 | AN12: 2 | AO12: 2 | AP12: =SUM(AL12:AO12) -> 7 | AQ12: 3-不作为优先培养对象 | AR12: 技术型男生中表达较可的，踏实，工作有一定积极性
A13: 11 | B13: 曹宁远 | C13: 数据平台部 | D13: 工具开发组 | E13: 男 | F13: 6 | G13: 研究生 | H13: 北京理工大学 | I13: 组长 | J13: 架构师 | K13: 6 | L13: 0 | M13: 数据研发 | N13: 校园招聘 | S13: =VLOOKUP(B13,'[2]62人'!$B:$R,17,FALSE) -> 8 | T13: 0 | U13: 1 | V13: 1 | W13: 1 | X13: =VLOOKUP(B13,[4]考勤分析!$A:$I,4,FALSE) -> 1.4162366 | Y13: =VLOOKUP(B13,[4]考勤分析!$A:$I,5,FALSE) -> FALSE | Z13: =VLOOKUP(B13,[4]考勤分析!$A:$I,6,FALSE) -> 21 | AA13: =VLOOKUP(B13,[4]考勤分析!$A:$I,7,FALSE) -> 24 | AB13: =VLOOKUP(B13,[4]考勤分析!$A:$I,8,FALSE) -> 15 | AC13: =VLOOKUP(B13,[4]考勤分析!$A:$I,9,FALSE) -> 2 | AD13: 1 | AE13: 0 | AF13: 1 | AG13: 5 | AH13: 0 | AI13: 0 | AK13: =VLOOKUP(B13,[3]总表!$B:$W,22,FALSE) -> 适中 | AL13: 1 | AM13: 3 | AN13: 2 | AO13: 2 | AP13: =SUM(AL13:AO13) -> 8 | AQ13: 1.2-专业能力强，但领导力较弱，建议走技术路线 | AR13: 建议走技术线
A14: 12 | B14: 伍恒 | C14: 数据平台部 | D14: 工具开发组 | E14: 男 | F14: 8 | G14: 研究生 | H14: 武汉科技大学 | I14: 骨干 | L14: 0 | M14: 数据研发 | N14: 校园招聘 | R14: 23研究与创新奖 | S14: =VLOOKUP(B14,'[2]62人'!$B:$R,17,FALSE) -> 6 | T14: 0 | X14: =VLOOKUP(B14,[4]考勤分析!$A:$I,4,FALSE) -> 2.3839689 | Y14: =VLOOKUP(B14,[4]考勤分析!$A:$I,5,FALSE) -> TRUE | Z14: =VLOOKUP(B14,[4]考勤分析!$A:$I,6,FALSE) -> 12 | AA14: =VLOOKUP(B14,[4]考勤分析!$A:$I,7,FALSE) -> 32 | AB14: =VLOOKUP(B14,[4]考勤分析!$A:$I,8,FALSE) -> 5 | AC14: =VLOOKUP(B14,[4]考勤分析!$A:$I,9,FALSE) -> 10 | AD14: 1 | AE14: 1 | AF14: 2 | AG14: 2 | AH14: 11 | AI14: 38 | AK14: =VLOOKUP(B14,[3]总表!$B:$W,22,FALSE) -> 超负荷 | AL14: 1 | AM14: 3 | AN14: 2 | AO14: 2 | AP14: =SUM(AL14:AO14) -> 8 | AQ14: 1.2-专业能力强，但领导力较弱，建议走技术路线 | AR14: 建议走技术线
A15: 13 | B15: 王正超 | C15: 数据平台部 | D15: 应用开发组 | E15: 男 | F15: 6 | G15: 研究生 | H15: 北京交通大学 | I15: 骨干 | L15: 1 | M15: 数据研发 | N15: 校园招聘 | S15: =VLOOKUP(B15,'[2]62人'!$B:$R,17,FALSE) -> 9 | T15: 18 | U15: 2 | W15: 1 | X15: =VLOOKUP(B15,[4]考勤分析!$A:$I,4,FALSE) -> 3.1960769 | Y15: =VLOOKUP(B15,[4]考勤分析!$A:$I,5,FALSE) -> TRUE | Z15: =VLOOKUP(B15,[4]考勤分析!$A:$I,6,FALSE) -> 7 | AA15: =VLOOKUP(B15,[4]考勤分析!$A:$I,7,FALSE) -> 13 | AB15: =VLOOKUP(B15,[4]考勤分析!$A:$I,8,FALSE) -> 30 | AC15: =VLOOKUP(B15,[4]考勤分析!$A:$I,9,FALSE) -> 15 | AD15: 1 | AE15: 14 | AF15: 1 | AG15: 3 | AH15: 14 | AI15: 16 | AK15: =VLOOKUP(B15,[3]总表!$B:$W,22,FALSE) -> 超负荷 | AL15: 2 | AM15: 3 | AN15: 3 | AO15: 2 | AP15: =SUM(AL15:AO15) -> 10 | AQ15: 1.1-专业能力强，但领导力较弱 | AR15: 老黄牛类型
A16: 14 | B16: 嵇雅娟 | C16: 数据平台部 | D16: 应用开发组 | E16: 女 | F16: 11 | G16: 大学本科 | H16: 中国科学技术大学 | I16: 骨干 | L16: 1 | M16: 数据研发 | N16: 社会招聘 | S16: =VLOOKUP(B16,'[2]62人'!$B:$R,17,FALSE) -> 23 | T16: 0 | W16: 1 | X16: =VLOOKUP(B16,[4]考勤分析!$A:$I,4,FALSE) -> 1.9198387 | Y16: =VLOOKUP(B16,[4]考勤分析!$A:$I,5,FALSE) -> FALSE | Z16: =VLOOKUP(B16,[4]考勤分析!$A:$I,6,FALSE) -> 32 | AA16: =VLOOKUP(B16,[4]考勤分析!$A:$I,7,FALSE) -> 21 | AB16: =VLOOKUP(B16,[4]考勤分析!$A:$I,8,FALSE) -> 2 | AC16: =VLOOKUP(B16,[4]考勤分析!$A:$I,9,FALSE) -> 7 | AD16: 0 | AE16: 5 | AF16: 3 | AG16: 2 | AH16: 5 | AI16: 9 | AK16: =VLOOKUP(B16,[3]总表!$B:$W,22,FALSE) -> 适中 | AL16: 1 | AM16: 2 | AN16: 2 | AO16: 2 | AP16: =SUM(AL16:AO16) -> 7 | AQ16: 3-不作为优先培养对象 | AR16: 中规中矩
A17: 15 | B17: 鞠爱宁 | C17: 数据平台部 | D17: 数据服务组 | E17: 男 | F17: 8 | G17: 研究生 | H17: 上海大学 | I17: 组长 | J17: 架构师 | K17: 8 | L17: 1 | M17: 数据研发 | N17: 校园招聘 | R17: 24技术能手 | S17: =VLOOKUP(B17,'[2]62人'!$B:$R,17,FALSE) -> 5 | T17: 24 | U17: 1 | X17: =VLOOKUP(B17,[4]考勤分析!$A:$I,4,FALSE) -> 3.0539359 | Y17: =VLOOKUP(B17,[4]考勤分析!$A:$I,5,FALSE) -> TRUE | Z17: =VLOOKUP(B17,[4]考勤分析!$A:$I,6,FALSE) -> 4 | AA17: =VLOOKUP(B17,[4]考勤分析!$A:$I,7,FALSE) -> 8 | AB17: =VLOOKUP(B17,[4]考勤分析!$A:$I,8,FALSE) -> 37 | AC17: =VLOOKUP(B17,[4]考勤分析!$A:$I,9,FALSE) -> 16 | AD17: 0 | AE17: 1 | AF17: 1 | AG17: 2 | AH17: 10 | AI17: 11 | AK17: =VLOOKUP(B17,[3]总表!$B:$W,22,FALSE) -> 超负荷 | AL17: 2 | AM17: 3 | AN17: 2 | AO17: 2 | AP17: =SUM(AL17:AO17) -> 9 | AQ17: 1.1-专业能力强，但领导力较弱 | AR17: 渴望被认可，缺少机会
A18: 16 | B18: 魏佳翔 | C18: 数据平台部 | D18: 数据服务组 | E18: 男 | F18: 12 | G18: 大学本科 | H18: 大连海事大学 | I18: 组长 | J18: 架构师 | K18: 12 | L18: 1 | M18: 数据研发 | N18: 社会招聘 | S18: =VLOOKUP(B18,'[2]62人'!$B:$R,17,FALSE) -> 11 | T18: 0 | X18: =VLOOKUP(B18,[4]考勤分析!$A:$I,4,FALSE) -> 1.6090694 | Y18: =VLOOKUP(B18,[4]考勤分析!$A:$I,5,FALSE) -> FALSE | Z18: =VLOOKUP(B18,[4]考勤分析!$A:$I,6,FALSE) -> 30 | AA18: =VLOOKUP(B18,[4]考勤分析!$A:$I,7,FALSE) -> 18 | AB18: =VLOOKUP(B18,[4]考勤分析!$A:$I,8,FALSE) -> 5 | AC18: =VLOOKUP(B18,[4]考勤分析!$A:$I,9,FALSE) -> 7 | AD18: 0 | AE18: 1 | AF18: 0 | AG18: 2 | AH18: 0 | AI18: 0 | AK18: =VLOOKUP(B18,[3]总表!$B:$W,22,FALSE) -> 超负荷 | AL18: 2 | AM18: 4 | AN18: 3 | AO18: 2 | AP18: =SUM(AL18:AO18) -> 11 | AQ18: 4-高潜培养对象 | AR18: 揭榜挂帅人选，有实力做专业性对抗； 擅长处理并发任务，工作效率高（从任务完成度和考勤来看）
A19: 17 | B19: 刘燕玲 | C19: 数据治理部 | D19: 标准质量组 | E19: 女 | F19: 10 | G19: 研究生 | H19: 复旦大学 | I19: 组长 | L19: 0 | M19: 数据治理 | N19: 社会招聘 | R19: 24五星质量奖/25行外获奖1 | S19: =VLOOKUP(B19,'[2]62人'!$B:$R,17,FALSE) -> 12 | T19: 0 | U19: 1 | X19: =VLOOKUP(B19,[4]考勤分析!$A:$I,4,FALSE) -> 0.7407286 | Y19: =VLOOKUP(B19,[4]考勤分析!$A:$I,5,FALSE) -> FALSE | Z19: =VLOOKUP(B19,[4]考勤分析!$A:$I,6,FALSE) -> 52 | AA19: =VLOOKUP(B19,[4]考勤分析!$A:$I,7,FALSE) -> 5 | AB19: =VLOOKUP(B19,[4]考勤分析!$A:$I,8,FALSE) -> 3 | AC19: =VLOOKUP(B19,[4]考勤分析!$A:$I,9,FALSE) -> 1 | AD19: 0 | AE19: 0 | AF19: 0 | AG19: 0 | AH19: 0 | AI19: 0 | AK19: =VLOOKUP(B19,[3]总表!$B:$W,22,FALSE) -> #N/A | AL19: 2 | AM19: 2 | AN19: 2 | AO19: 2 | AP19: =SUM(AL19:AO19) -> 8 | AQ19: 2-可培养的二梯队 | AR19: 综合能力都可
A20: 18 | B20: 于璐 | C20: 数据治理部 | D20: 标准质量组 | E20: 女 | F20: 8 | G20: 大学本科 | H20: 合肥工业大学 | I20: 骨干 | J20: 产品经理 | K20: 4 | L20: 1 | M20: 数据治理 | N20: 校园招聘 | R20: 24最佳合作服务奖/24数据文化优秀贡献者 | S20: =VLOOKUP(B20,'[2]62人'!$B:$R,17,FALSE) -> 11 | T20: 2 | U20: 2 | W20: 1 | X20: =VLOOKUP(B20,[4]考勤分析!$A:$I,4,FALSE) -> 0.81636612 | Y20: =VLOOKUP(B20,[4]考勤分析!$A:$I,5,FALSE) -> FALSE | Z20: =VLOOKUP(B20,[4]考勤分析!$A:$I,6,FALSE) -> 42 | AA20: =VLOOKUP(B20,[4]考勤分析!$A:$I,7,FALSE) -> 18 | AB20: =VLOOKUP(B20,[4]考勤分析!$A:$I,8,FALSE) -> 1 | AC20: =VLOOKUP(B20,[4]考勤分析!$A:$I,9,FALSE) -> 0 | AD20: 0 | AE20: 1 | AF20: 0 | AG20: 0 | AH20: 0 | AI20: 0 | AK20: =VLOOKUP(B20,[3]总表!$B:$W,22,FALSE) -> #N/A | AL20: 1 | AM20: 2 | AN20: 2 | AO20: 2 | AP20: =SUM(AL20:AO20) -> 7 | AQ20: 3-不作为优先培养对象 | AR20: 中规中矩
A21: 19 | B21: 米俊文 | C21: 数据治理部 | D21: 架构安全组 | E21: 男 | F21: 16 | G21: 研究生 | H21: 同济大学 | I21: 骨干 | L21: 0 | M21: 架构管理 | N21: 社会招聘 | S21: =VLOOKUP(B21,'[2]62人'!$B:$R,17,FALSE) -> 7 | T21: 1 | V21: 1 | X21: =VLOOKUP(B21,[4]考勤分析!$A:$I,4,FALSE) -> 1.885904 | Y21: =VLOOKUP(B21,[4]考勤分析!$A:$I,5,FALSE) -> TRUE | Z21: =VLOOKUP(B21,[4]考勤分析!$A:$I,6,FALSE) -> 6 | AA21: =VLOOKUP(B21,[4]考勤分析!$A:$I,7,FALSE) -> 32 | AB21: =VLOOKUP(B21,[4]考勤分析!$A:$I,8,FALSE) -> 20 | AC21: =VLOOKUP(B21,[4]考勤分析!$A:$I,9,FALSE) -> 1 | AD21: 0 | AE21: 0 | AF21: 0 | AG21: 0 | AH21: 0 | AI21: 0 | AK21: =VLOOKUP(B21,[3]总表!$B:$W,22,FALSE) -> #N/A | AL21: 1 | AM21: 3 | AN21: 2 | AO21: 2 | AP21: =SUM(AL21:AO21) -> 8 | AQ21: 1.2-专业能力强，但领导力较弱，建议走技术路线 | AR21: 没有管理张力
A22: 20 | B22: 庄家宙 | C22: 数据治理部 | D22: 架构安全组 | E22: 男 | F22: 17 | G22: 大学本科 | H22: 华东师范大学 | I22: 组长 | J22: 产品经理 | K22: 2 | L22: 0 | M22: 数据安全 | N22: 社会招聘 | S22: =VLOOKUP(B22,'[2]62人'!$B:$R,17,FALSE) -> 7 | T22: 3 | X22: =VLOOKUP(B22,[4]考勤分析!$A:$I,4,FALSE) -> 1.3275627 | Y22: =VLOOKUP(B22,[4]考勤分析!$A:$I,5,FALSE) -> TRUE | Z22: =VLOOKUP(B22,[4]考勤分析!$A:$I,6,FALSE) -> 3 | AA22: =VLOOKUP(B22,[4]考勤分析!$A:$I,7,FALSE) -> 59 | AB22: =VLOOKUP(B22,[4]考勤分析!$A:$I,8,FALSE) -> 0 | AC22: =VLOOKUP(B22,[4]考勤分析!$A:$I,9,FALSE) -> 0 | AD22: 0 | AE22: 0 | AF22: 0 | AG22: 0 | AH22: 0 | AI22: 0 | AK22: =VLOOKUP(B22,[3]总表!$B:$W,22,FALSE) -> #N/A | AL22: 2 | AM22: 2 | AN22: 2 | AO22: 2 | AP22: =SUM(AL22:AO22) -> 8 | AQ22: 3-不作为优先培养对象 | AR22: 老古板，缺少新型思维
A23: 21 | B23: 舒宝龙 | C23: 信息管理部 | D23: 分行BP | E23: 男 | F23: 4 | G23: 研究生 | H23: 南方卫理公会大学 | I23: 组长 | L23: 0 | M23: 数据分析 | N23: 社会招聘 | S23: =VLOOKUP(B23,'[2]62人'!$B:$R,17,FALSE) -> 1 | T23: 0 | X23: =VLOOKUP(B23,[4]考勤分析!$A:$I,4,FALSE) -> 0.43922685 | Y23: =VLOOKUP(B23,[4]考勤分析!$A:$I,5,FALSE) -> FALSE | Z23: =VLOOKUP(B23,[4]考勤分析!$A:$I,6,FALSE) -> 49 | AA23: =VLOOKUP(B23,[4]考勤分析!$A:$I,7,FALSE) -> 9 | AB23: =VLOOKUP(B23,[4]考勤分析!$A:$I,8,FALSE) -> 2 | AC23: =VLOOKUP(B23,[4]考勤分析!$A:$I,9,FALSE) -> 0 | AD23: 0 | AE23: 0 | AF23: 0 | AG23: 0 | AH23: 0 | AI23: 0 | AK23: =VLOOKUP(B23,[3]总表!$B:$W,22,FALSE) -> #N/A | AL23: 2 | AM23: 1 | AN23: 1 | AO23: 2 | AP23: =SUM(AL23:AO23) -> 6 | AR23: 双刃剑
A24: 22 | B24: 陆应佳玥 | C24: 信息管理部 | D24: 分行BP | E24: 女 | F24: 3 | G24: 研究生 | H24: 悉尼大学 | L24: 0 | M24: 数据分析 | N24: 校园招聘 | S24: =VLOOKUP(B24,'[2]62人'!$B:$R,17,FALSE) -> 14 | T24: 0 | W24: 2 | X24: =VLOOKUP(B24,[4]考勤分析!$A:$I,4,FALSE) -> 0.34355191 | Y24: =VLOOKUP(B24,[4]考勤分析!$A:$I,5,FALSE) -> FALSE | Z24: =VLOOKUP(B24,[4]考勤分析!$A:$I,6,FALSE) -> 59 | AA24: =VLOOKUP(B24,[4]考勤分析!$A:$I,7,FALSE) -> 0 | AB24: =VLOOKUP(B24,[4]考勤分析!$A:$I,8,FALSE) -> 0 | AC24: =VLOOKUP(B24,[4]考勤分析!$A:$I,9,FALSE) -> 2 | AD24: 0 | AE24: 0 | AF24: 0 | AG24: 0 | AH24: 0 | AI24: 0 | AK24: =VLOOKUP(B24,[3]总表!$B:$W,22,FALSE) -> #N/A | AL24: 1 | AM24: 2 | AN24: 2 | AO24: 2 | AP24: =SUM(AL24:AO24) -> 7 | AQ24: 3-不作为优先培养对象 | AR24: 中规中矩
A25: 23 | B25: 胡承萱 | C25: 信息管理部 | D25: 非零BP | E25: 女 | F25: 4 | G25: 研究生 | H25: 哥伦比亚大学 | I25: 组长 | L25: 0 | M25: 数据分析 | N25: 校园招聘 | S25: =VLOOKUP(B25,'[2]62人'!$B:$R,17,FALSE) -> 15 | T25: 6 | W25: 1 | X25: =VLOOKUP(B25,[4]考勤分析!$A:$I,4,FALSE) -> 2.7296147 | Y25: =VLOOKUP(B25,[4]考勤分析!$A:$I,5,FALSE) -> TRUE | Z25: =VLOOKUP(B25,[4]考勤分析!$A:$I,6,FALSE) -> 7 | AA25: =VLOOKUP(B25,[4]考勤分析!$A:$I,7,FALSE) -> 0 | AB25: =VLOOKUP(B25,[4]考勤分析!$A:$I,8,FALSE) -> 54 | AC25: =VLOOKUP(B25,[4]考勤分析!$A:$I,9,FALSE) -> 1 | AD25: 2 | AE25: 0 | AF25: 0 | AG25: 0 | AH25: 0 | AI25: 0 | AK25: =VLOOKUP(B25,[3]总表!$B:$W,22,FALSE) -> #N/A | AL25: 2 | AM25: 3 | AN25: 3 | AO25: 3 | AP25: =SUM(AL25:AO25) -> 11 | AQ25: 1.1-专业能力强，但领导力较弱 | AR25: 有冲劲
A26: 24 | B26: 王亮 | C26: 信息管理部 | D26: 非零BP | E26: 男 | F26: 6 | G26: 研究生 | H26: 上海大学 | I26: 骨干 | L26: 0 | M26: 数据分析 | N26: 校园招聘 | S26: =VLOOKUP(B26,'[2]62人'!$B:$R,17,FALSE) -> 10 | T26: 0 | X26: =VLOOKUP(B26,[4]考勤分析!$A:$I,4,FALSE) -> #N/A | Y26: =VLOOKUP(B26,[4]考勤分析!$A:$I,5,FALSE) -> #N/A | Z26: =VLOOKUP(B26,[4]考勤分析!$A:$I,6,FALSE) -> #N/A | AA26: =VLOOKUP(B26,[4]考勤分析!$A:$I,7,FALSE) -> #N/A | AB26: =VLOOKUP(B26,[4]考勤分析!$A:$I,8,FALSE) -> #N/A | AC26: =VLOOKUP(B26,[4]考勤分析!$A:$I,9,FALSE) -> #N/A | AD26: 0 | AE26: 0 | AF26: 0 | AG26: 0 | AH26: 0 | AI26: 0 | AK26: =VLOOKUP(B26,[3]总表!$B:$W,22,FALSE) -> #N/A | AL26: 1 | AM26: 2 | AN26: 2 | AO26: 2 | AP26: =SUM(AL26:AO26) -> 7 | AQ26: 3-不作为优先培养对象 | AR26: 一般
A27: 25 | B27: 曹婉茹 | C27: 信息管理部 | D27: 零售BP | E27: 女 | F27: 6 | G27: 研究生 | H27: 北京师范大学 | I27: 组长 | L27: 0 | M27: 数据分析 | N27: 校园招聘 | O27: 第三党支部组织委员 | S27: =VLOOKUP(B27,'[2]62人'!$B:$R,17,FALSE) -> 8 | T27: 0 | X27: =VLOOKUP(B27,[4]考勤分析!$A:$I,4,FALSE) -> 1.2239253 | Y27: =VLOOKUP(B27,[4]考勤分析!$A:$I,5,FALSE) -> FALSE | Z27: =VLOOKUP(B27,[4]考勤分析!$A:$I,6,FALSE) -> 30 | AA27: =VLOOKUP(B27,[4]考勤分析!$A:$I,7,FALSE) -> 17 | AB27: =VLOOKUP(B27,[4]考勤分析!$A:$I,8,FALSE) -> 12 | AC27: =VLOOKUP(B27,[4]考勤分析!$A:$I,9,FALSE) -> 2 | AD27: 1 | AE27: 7 | AF27: 0 | AG27: 0 | AH27: 0 | AI27: 0 | AK27: =VLOOKUP(B27,[3]总表!$B:$W,22,FALSE) -> #N/A | AL27: 2 | AM27: 2 | AN27: 2 | AO27: 2 | AP27: =SUM(AL27:AO27) -> 8 | AQ27: 2-可培养的二梯队 | AR27: 内敛，综合能力可以
A28: 26 | B28: 杨陆 | C28: 信息管理部 | D28: 零售BP | E28: 女 | F28: 4 | G28: 研究生 | H28: 南京师范大学 | I28: 骨干 | J28: 产品经理 | K28: 2 | L28: 0 | M28: 数据分析 | N28: 校园招聘 | P28: 工会会员代表 | S28: =VLOOKUP(B28,'[2]62人'!$B:$R,17,FALSE) -> 6 | T28: 0 | X28: =VLOOKUP(B28,[4]考勤分析!$A:$I,4,FALSE) -> 0.92281019 | Y28: =VLOOKUP(B28,[4]考勤分析!$A:$I,5,FALSE) -> FALSE | Z28: =VLOOKUP(B28,[4]考勤分析!$A:$I,6,FALSE) -> 41 | AA28: =VLOOKUP(B28,[4]考勤分析!$A:$I,7,FALSE) -> 15 | AB28: =VLOOKUP(B28,[4]考勤分析!$A:$I,8,FALSE) -> 3 | AC28: =VLOOKUP(B28,[4]考勤分析!$A:$I,9,FALSE) -> 1 | AD28: 0 | AE28: 0 | AF28: 0 | AG28: 0 | AH28: 0 | AI28: 0 | AK28: =VLOOKUP(B28,[3]总表!$B:$W,22,FALSE) -> #N/A | AL28: 2 | AM28: 2 | AN28: 2 | AO28: 2 | AP28: =SUM(AL28:AO28) -> 8 | AQ28: 2-可培养的二梯队 | AR28: 偏外向，敢表达
A29: 27 | B29: 郭庆睿 | C29: 信息统计部 | D29: 管理信息组 | E29: 男 | F29: 8 | G29: 研究生 | H29: 复旦大学 | I29: 组长 | L29: 2 | M29: 数据分析 | N29: 校园招聘 | S29: =VLOOKUP(B29,'[2]62人'!$B:$R,17,FALSE) -> 8 | T29: 3 | X29: =VLOOKUP(B29,[4]考勤分析!$A:$I,4,FALSE) -> 3.0276953 | Y29: =VLOOKUP(B29,[4]考勤分析!$A:$I,5,FALSE) -> TRUE | Z29: =VLOOKUP(B29,[4]考勤分析!$A:$I,6,FALSE) -> 9 | AA29: =VLOOKUP(B29,[4]考勤分析!$A:$I,7,FALSE) -> 3 | AB29: =VLOOKUP(B29,[4]考勤分析!$A:$I,8,FALSE) -> 36 | AC29: =VLOOKUP(B29,[4]考勤分析!$A:$I,9,FALSE) -> 16 | AD29: 0 | AE29: 0 | AF29: 0 | AG29: 0 | AH29: 0 | AI29: 0 | AK29: =VLOOKUP(B29,[3]总表!$B:$W,22,FALSE) -> #N/A | AL29: 2 | AM29: 3 | AN29: 3 | AO29: 3 | AP29: =SUM(AL29:AO29) -> 11 | AQ29: 1.1-专业能力强，但领导力较弱 | AR29: 有良好的大局观
A30: 28 | B30: 王素雅 | C30: 信息统计部 | D30: 管理信息组 | E30: 女 | F30: 6 | G30: 研究生 | H30: 华中师范大学 | I30: 骨干 | J30: 产品经理 | K30: 4 | L30: 1 | M30: 数据分析 | N30: 校园招聘 | S30: =VLOOKUP(B30,'[2]62人'!$B:$R,17,FALSE) -> 10 | T30: 0 | W30: 1 | X30: =VLOOKUP(B30,[4]考勤分析!$A:$I,4,FALSE) -> 1.9007213 | Y30: =VLOOKUP(B30,[4]考勤分析!$A:$I,5,FALSE) -> TRUE | Z30: =VLOOKUP(B30,[4]考勤分析!$A:$I,6,FALSE) -> 19 | AA30: =VLOOKUP(B30,[4]考勤分析!$A:$I,7,FALSE) -> 17 | AB30: =VLOOKUP(B30,[4]考勤分析!$A:$I,8,FALSE) -> 21 | AC30: =VLOOKUP(B30,[4]考勤分析!$A:$I,9,FALSE) -> 5 | AD30: 0 | AE30: 1 | AF30: 0 | AG30: 0 | AH30: 0 | AI30: 0 | AK30: =VLOOKUP(B30,[3]总表!$B:$W,22,FALSE) -> #N/A | AL30: 1 | AM30: 2 | AN30: 2 | AO30: 3 | AP30: =SUM(AL30:AO30) -> 8 | AQ30: 3-不作为优先培养对象 | AR30: 有冲劲，当前偏个人发展型
A31: 29 | B31: 张伟亮 | C31: 信息统计部 | D31: 监管数据治理 | E31: 男 | F31: 7 | G31: 研究生 | H31: 西南交通大学 | I31: 组长 | J31: 产品经理 | K31: 2 | L31: 1 | M31: 监管统计 | N31: 校园招聘 | S31: =VLOOKUP(B31,'[2]62人'!$B:$R,17,FALSE) -> 11 | T31: 4 | X31: =VLOOKUP(B31,[4]考勤分析!$A:$I,4,FALSE) -> 3.347878 | Y31: =VLOOKUP(B31,[4]考勤分析!$A:$I,5,FALSE) -> TRUE | Z31: =VLOOKUP(B31,[4]考勤分析!$A:$I,6,FALSE) -> 5 | AA31: =VLOOKUP(B31,[4]考勤分析!$A:$I,7,FALSE) -> 3 | AB31: =VLOOKUP(B31,[4]考勤分析!$A:$I,8,FALSE) -> 35 | AC31: =VLOOKUP(B31,[4]考勤分析!$A:$I,9,FALSE) -> 18 | AD31: 0 | AE31: 0 | AF31: 0 | AG31: 0 | AH31: 0 | AI31: 0 | AK31: =VLOOKUP(B31,[3]总表!$B:$W,22,FALSE) -> #N/A | AL31: 2 | AM31: 3 | AN31: 3 | AO31: 2 | AP31: =SUM(AL31:AO31) -> 10 | AQ31: 1.1-专业能力强，但领导力较弱 | AR31: 渴望被提拔，有进取心，需要转型引导
A32: 30 | B32: 王书祥 | C32: 信息统计部 | D32: 监管数据治理 | E32: 男 | F32: 11 | G32: 大学本科 | H32: 上海对外经贸大学 | I32: 骨干 | J32: 产品经理 | K32: 1 | L32: 0 | M32: 监管统计 | N32: 社会招聘 | S32: =VLOOKUP(B32,'[2]62人'!$B:$R,17,FALSE) -> 10 | T32: 0 | X32: =VLOOKUP(B32,[4]考勤分析!$A:$I,4,FALSE) -> 1.8831713 | Y32: =VLOOKUP(B32,[4]考勤分析!$A:$I,5,FALSE) -> TRUE | Z32: =VLOOKUP(B32,[4]考勤分析!$A:$I,6,FALSE) -> 13 | AA32: =VLOOKUP(B32,[4]考勤分析!$A:$I,7,FALSE) -> 15 | AB32: =VLOOKUP(B32,[4]考勤分析!$A:$I,8,FALSE) -> 31 | AC32: =VLOOKUP(B32,[4]考勤分析!$A:$I,9,FALSE) -> 1 | AD32: 0 | AE32: 0 | AF32: 0 | AG32: 0 | AH32: 0 | AI32: 0 | AK32: =VLOOKUP(B32,[3]总表!$B:$W,22,FALSE) -> #N/A | AL32: 1 | AM32: 2 | AN32: 2 | AO32: 2 | AP32: =SUM(AL32:AO32) -> 7 | AQ32: 3-不作为优先培养对象 | AR32: 中规中矩
A33: 31 | B33: 王新 | C33: 信息统计部 | D33: 监管统计组 | E33: 男 | F33: 9 | G33: 大学本科 | H33: 吉林大学 | I33: 组长 | J33: 产品经理 | K33: 2 | L33: 0 | M33: 数据分析 | N33: 社会招聘 | S33: =VLOOKUP(B33,'[2]62人'!$B:$R,17,FALSE) -> 14 | T33: 19 | X33: =VLOOKUP(B33,[4]考勤分析!$A:$I,4,FALSE) -> 1.6084409 | Y33: =VLOOKUP(B33,[4]考勤分析!$A:$I,5,FALSE) -> FALSE | Z33: =VLOOKUP(B33,[4]考勤分析!$A:$I,6,FALSE) -> 23 | AA33: =VLOOKUP(B33,[4]考勤分析!$A:$I,7,FALSE) -> 23 | AB33: =VLOOKUP(B33,[4]考勤分析!$A:$I,8,FALSE) -> 8 | AC33: =VLOOKUP(B33,[4]考勤分析!$A:$I,9,FALSE) -> 8 | AD33: 0 | AE33: 0 | AF33: 0 | AG33: 0 | AH33: 0 | AI33: 0 | AK33: =VLOOKUP(B33,[3]总表!$B:$W,22,FALSE) -> #N/A | AL33: 1 | AM33: 3 | AN33: 2 | AO33: 2 | AP33: =SUM(AL33:AO33) -> 8 | AQ33: 1.1-专业能力强，但领导力较弱 | AR33: 欠缺管理张力
A34: 32 | B34: 杨婧 | C34: 智能创新部 | D34: AI产品运营组 | E34: 女 | F34: 5 | G34: 研究生 | H34: 中国科学技术大学 | I34: 组长 | J34: 产品经理 | K34: 1 | L34: 0 | M34: 数据研发 | N34: 校园招聘 | R34: 23/24数据文化优秀贡献者/24研究与创新奖 | S34: =VLOOKUP(B34,'[2]62人'!$B:$R,17,FALSE) -> 14 | T34: 0 | W34: 3 | X34: =VLOOKUP(B34,[4]考勤分析!$A:$I,4,FALSE) -> 2.7654645 | Y34: =VLOOKUP(B34,[4]考勤分析!$A:$I,5,FALSE) -> TRUE | Z34: =VLOOKUP(B34,[4]考勤分析!$A:$I,6,FALSE) -> 9 | AA34: =VLOOKUP(B34,[4]考勤分析!$A:$I,7,FALSE) -> 14 | AB34: =VLOOKUP(B34,[4]考勤分析!$A:$I,8,FALSE) -> 20 | AC34: =VLOOKUP(B34,[4]考勤分析!$A:$I,9,FALSE) -> 18 | AD34: 0 | AE34: 1 | AF34: 1 | AG34: 2 | AH34: 0 | AI34: 0 | AK34: =VLOOKUP(B34,[3]总表!$B:$W,22,FALSE) -> 超负荷 | AL34: 1 | AM34: 3 | AN34: 3 | AO34: 2 | AP34: =SUM(AL34:AO34) -> 9 | AQ34: 1.1-专业能力强，但领导力较弱 | AR34: 有培养潜力，因年限较短缺乏更深入的思考，需要引导
A35: 33 | B35: 邱玥 | C35: 智能创新部 | D35: AI产品运营组 | E35: 女 | F35: 3 | G35: 研究生 | H35: 东华大学 | I35: 骨干 | L35: 0 | M35: 数据研发 | N35: 校园招聘 | S35: =VLOOKUP(B35,'[2]62人'!$B:$R,17,FALSE) -> 16 | T35: 0 | W35: 1 | X35: =VLOOKUP(B35,[4]考勤分析!$A:$I,4,FALSE) -> 1.4472996 | Y35: =VLOOKUP(B35,[4]考勤分析!$A:$I,5,FALSE) -> FALSE | Z35: =VLOOKUP(B35,[4]考勤分析!$A:$I,6,FALSE) -> 14 | AA35: =VLOOKUP(B35,[4]考勤分析!$A:$I,7,FALSE) -> 39 | AB35: =VLOOKUP(B35,[4]考勤分析!$A:$I,8,FALSE) -> 7 | AC35: =VLOOKUP(B35,[4]考勤分析!$A:$I,9,FALSE) -> 1 | AD35: 1 | AE35: 1 | AF35: 1 | AG35: 2 | AH35: 2 | AI35: 4 | AK35: =VLOOKUP(B35,[3]总表!$B:$W,22,FALSE) -> 适中 | AL35: 1 | AM35: 2 | AN35: 2 | AO35: 2 | AP35: =SUM(AL35:AO35) -> 7 | AQ35: 3-不作为优先培养对象 | AR35: 中规中矩、内敛
A36: 3 | B36: 李响 | C36: 智能创新部 | D36: AI基础研发组 | E36: 男 | F36: 13 | G36: 大学本科 | H36: 哈尔滨工业大学 | I36: 组长 | J36: 架构师 | K36: 5 | L36: 1 | M36: 数据研发 | N36: 社会招聘 | S36: =VLOOKUP(B36,'[2]62人'!$B:$R,17,FALSE) -> 7 | T36: 1 | U36: 1 | W36: 2 | X36: =VLOOKUP(B36,[4]考勤分析!$A:$I,4,FALSE) -> 1.297161 | Y36: =VLOOKUP(B36,[4]考勤分析!$A:$I,5,FALSE) -> FALSE | Z36: =VLOOKUP(B36,[4]考勤分析!$A:$I,6,FALSE) -> 35 | AA36: =VLOOKUP(B36,[4]考勤分析!$A:$I,7,FALSE) -> 16 | AB36: =VLOOKUP(B36,[4]考勤分析!$A:$I,8,FALSE) -> 5 | AC36: =VLOOKUP(B36,[4]考勤分析!$A:$I,9,FALSE) -> 3 | AD36: 2 | AE36: 0 | AF36: 2 | AG36: 5 | AH36: 16 | AI36: 13 | AK36: =VLOOKUP(B36,[3]总表!$B:$W,22,FALSE) -> 超负荷 | AL36: 1 | AM36: 4 | AN36: 2 | AO36: 2 | AP36: =SUM(AL36:AO36) -> 9 | AQ36: 1.1-专业能力强，但领导力较弱 | AR36: 技术型
A37: 35 | B37: 于中宝 | C37: 智能创新部 | D37: AI基础研发组 | E37: 男 | F37: 6 | G37: 研究生 | H37: 华东理工大学 | I37: 骨干 | J37: 架构师 | K37: 6 | L37: 0 | M37: 数据研发 | N37: 校园招聘 | R37: 23数据文化优秀贡献者/24年度宣传大使 | S37: =VLOOKUP(B37,'[2]62人'!$B:$R,17,FALSE) -> 12 | T37: 4 | W37: 2 | X37: =VLOOKUP(B37,[4]考勤分析!$A:$I,4,FALSE) -> 1.9853808 | Y37: =VLOOKUP(B37,[4]考勤分析!$A:$I,5,FALSE) -> FALSE | Z37: =VLOOKUP(B37,[4]考勤分析!$A:$I,6,FALSE) -> 9 | AA37: =VLOOKUP(B37,[4]考勤分析!$A:$I,7,FALSE) -> 34 | AB37: =VLOOKUP(B37,[4]考勤分析!$A:$I,8,FALSE) -> 12 | AC37: =VLOOKUP(B37,[4]考勤分析!$A:$I,9,FALSE) -> 7 | AD37: 2 | AE37: 2 | AF37: 1 | AG37: 3 | AH37: 9 | AI37: 5 | AK37: =VLOOKUP(B37,[3]总表!$B:$W,22,FALSE) -> 超负荷 | AL37: 2 | AM37: 2 | AN37: 2 | AO37: 3 | AP37: =SUM(AL37:AO37) -> 9 | AQ37: 2-可培养的二梯队 | AR37: 有落差感，需要正确引导培养
A38: 36 | B38: 杨萍 | C38: 综合管理部 | D38: 测试管理组 | E38: 女 | F38: 11 | G38: 研究生 | H38: 上海大学 | I38: 组长 | L38: 1 | M38: 数据测试 | N38: 社会招聘 | S38: =VLOOKUP(B38,'[2]62人'!$B:$R,17,FALSE) -> 11 | T38: 0 | X38: =VLOOKUP(B38,[4]考勤分析!$A:$I,4,FALSE) -> 3.1222595 | Y38: =VLOOKUP(B38,[4]考勤分析!$A:$I,5,FALSE) -> TRUE | Z38: =VLOOKUP(B38,[4]考勤分析!$A:$I,6,FALSE) -> 5 | AA38: =VLOOKUP(B38,[4]考勤分析!$A:$I,7,FALSE) -> 13 | AB38: =VLOOKUP(B38,[4]考勤分析!$A:$I,8,FALSE) -> 31 | AC38: =VLOOKUP(B38,[4]考勤分析!$A:$I,9,FALSE) -> 18 | AD38: 0 | AE38: 0 | AF38: 0 | AG38: 0 | AH38: 0 | AI38: 0 | AK38: =VLOOKUP(B38,[3]总表!$B:$W,22,FALSE) -> #N/A | AL38: 3 | AM38: 4 | AN38: 3 | AO38: 3 | AP38: =SUM(AL38:AO38) -> 13 | AQ38: 4-高潜培养对象 | AR38: 可以考虑轮岗
A39: 37 | B39: 蒋书润 | C39: 综合管理部 | D39: 测试管理组 | E39: 女 | F39: 3 | G39: 研究生 | H39: 南加州大学 | L39: 0 | M39: 数据测试 | N39: 校园招聘 | R39: 24最佳新人 | S39: =VLOOKUP(B39,'[2]62人'!$B:$R,17,FALSE) -> 13 | T39: 11 | X39: =VLOOKUP(B39,[4]考勤分析!$A:$I,4,FALSE) -> 1.4125941 | Y39: =VLOOKUP(B39,[4]考勤分析!$A:$I,5,FALSE) -> FALSE | Z39: =VLOOKUP(B39,[4]考勤分析!$A:$I,6,FALSE) -> 26 | AA39: =VLOOKUP(B39,[4]考勤分析!$A:$I,7,FALSE) -> 22 | AB39: =VLOOKUP(B39,[4]考勤分析!$A:$I,8,FALSE) -> 13 | AC39: =VLOOKUP(B39,[4]考勤分析!$A:$I,9,FALSE) -> 1 | AD39: 0 | AE39: 0 | AF39: 0 | AG39: 0 | AH39: 0 | AI39: 0 | AK39: =VLOOKUP(B39,[3]总表!$B:$W,22,FALSE) -> #N/A | AL39: 2 | AM39: 2 | AN39: 3 | AO39: 3 | AP39: =SUM(AL39:AO39) -> 10 | AQ39: 4-高潜培养对象 | AR39: 有魄力，有担当，有潜在的管理张力
A40: 38 | B40: 黄佳佳 | C40: 综合管理部 | D40: 项目管理团队 | E40: 男 | F40: 7 | G40: 研究生 | H40: 东华大学 | I40: 骨干 | L40: 1 | M40: 项目管理 | N40: 校园招聘 | O40: 第三党支部纪检委员 | S40: =VLOOKUP(B40,'[2]62人'!$B:$R,17,FALSE) -> 15 | T40: 5 | X40: =VLOOKUP(B40,[4]考勤分析!$A:$I,4,FALSE) -> 3.0750231 | Y40: =VLOOKUP(B40,[4]考勤分析!$A:$I,5,FALSE) -> TRUE | Z40: =VLOOKUP(B40,[4]考勤分析!$A:$I,6,FALSE) -> 4 | AA40: =VLOOKUP(B40,[4]考勤分析!$A:$I,7,FALSE) -> 11 | AB40: =VLOOKUP(B40,[4]考勤分析!$A:$I,8,FALSE) -> 29 | AC40: =VLOOKUP(B40,[4]考勤分析!$A:$I,9,FALSE) -> 16 | AD40: 3 | AE40: 0 | AF40: 0 | AG40: 0 | AH40: 0 | AI40: 0 | AK40: =VLOOKUP(B40,[3]总表!$B:$W,22,FALSE) -> #N/A | AL40: 2 | AM40: 2 | AN40: 2 | AO40: 2 | AP40: =SUM(AL40:AO40) -> 8 | AQ40: 3-不作为优先培养对象 | AR40: 老黄牛型，需要突破
A41: 39 | B41: 曾敏锐 | C41: 综合管理部 | D41: 项目管理团队 | E41: 女 | F41: 14 | G41: 大学本科 | H41: 山东财政学院 | I41: 组长 | L41: 1 | M41: 项目管理 | N41: 社会招聘 | R41: 23最佳合作服务奖 | S41: =VLOOKUP(B41,'[2]62人'!$B:$R,17,FALSE) -> 5 | T41: 0 | U41: 1 | X41: =VLOOKUP(B41,[4]考勤分析!$A:$I,4,FALSE) -> 2.8070858 | Y41: =VLOOKUP(B41,[4]考勤分析!$A:$I,5,FALSE) -> TRUE | Z41: =VLOOKUP(B41,[4]考勤分析!$A:$I,6,FALSE) -> 7 | AA41: =VLOOKUP(B41,[4]考勤分析!$A:$I,7,FALSE) -> 10 | AB41: =VLOOKUP(B41,[4]考勤分析!$A:$I,8,FALSE) -> 26 | AC41: =VLOOKUP(B41,[4]考勤分析!$A:$I,9,FALSE) -> 14 | AD41: 1 | AE41: 0 | AF41: 0 | AG41: 0 | AH41: 0 | AI41: 0 | AK41: =VLOOKUP(B41,[3]总表!$B:$W,22,FALSE) -> #N/A | AL41: 1 | AM41: 3 | AN41: 3 | AO41: 2 | AP41: =SUM(AL41:AO41) -> 9 | AQ41: 3-不作为优先培养对象
A42: 40 | B42: 李梦霄 | C42: 智能创新部 | D42: 风险模型团队 | E42: 女 | F42: 6 | G42: 研究生 | H42: 华东理工大学 | I42: 组长 | L42: 0 | M42: 数据研发 | N42: 校园招聘 | O42: 第二党支部组织委员 | R42: 23数据文化优秀贡献者 | S42: =VLOOKUP(B42,'[2]62人'!$B:$R,17,FALSE) -> 17 | T42: 27 | W42: 1 | X42: =VLOOKUP(B42,[4]考勤分析!$A:$I,4,FALSE) -> 1.8206093 | Y42: =VLOOKUP(B42,[4]考勤分析!$A:$I,5,FALSE) -> FALSE | Z42: =VLOOKUP(B42,[4]考勤分析!$A:$I,6,FALSE) -> 14 | AA42: =VLOOKUP(B42,[4]考勤分析!$A:$I,7,FALSE) -> 22 | AB42: =VLOOKUP(B42,[4]考勤分析!$A:$I,8,FALSE) -> 24 | AC42: =VLOOKUP(B42,[4]考勤分析!$A:$I,9,FALSE) -> 2 | AD42: 1 | AE42: 0 | AF42: 0 | AG42: 2 | AH42: 0 | AI42: 0 | AK42: =VLOOKUP(B42,[3]总表!$B:$W,22,FALSE) -> 适中 | AL42: 2 | AM42: 3 | AN42: 3 | AO42: 3 | AP42: =SUM(AL42:AO42) -> 11 | AQ42: 1.1-专业能力强，但领导力较弱 | AR42: 有潜力，值得培养，心思细腻，需要引导
A43: 41 | B43: 于俊杰 | C43: 智能创新部 | D43: 风险模型团队 | E43: 男 | F43: 3 | G43: 研究生 | H43: 华东理工大学 | L43: 0 | M43: 数据研发 | N43: 校园招聘 | S43: =VLOOKUP(B43,'[2]62人'!$B:$R,17,FALSE) -> 19 | T43: 6 | X43: =VLOOKUP(B43,[4]考勤分析!$A:$I,4,FALSE) -> 1.5562977 | Y43: =VLOOKUP(B43,[4]考勤分析!$A:$I,5,FALSE) -> FALSE | Z43: =VLOOKUP(B43,[4]考勤分析!$A:$I,6,FALSE) -> 27 | AA43: =VLOOKUP(B43,[4]考勤分析!$A:$I,7,FALSE) -> 21 | AB43: =VLOOKUP(B43,[4]考勤分析!$A:$I,8,FALSE) -> 12 | AC43: =VLOOKUP(B43,[4]考勤分析!$A:$I,9,FALSE) -> 4 | AD43: 1 | AE43: 0 | AF43: 1 | AG43: 1 | AH43: 0 | AI43: 9 | AK43: =VLOOKUP(B43,[3]总表!$B:$W,22,FALSE) -> 适中 | AL43: 1 | AM43: 2 | AN43: 2 | AO43: 2 | AP43: =SUM(AL43:AO43) -> 7 | AQ43: 3-不作为优先培养对象 | AR43: 中规中矩
A44: 42 | B44: 周影 | C44: 数据开发部 | D44: 仓库开发组 | E44: 女 | F44: 7 | G44: 研究生 | H44: 湖南大学 | I44: 骨干 | L44: 0 | M44: 数据研发 | N44: 校园招聘 | S44: =VLOOKUP(B44,'[2]62人'!$B:$R,17,FALSE) -> 9 | T44: 12 | U44: 1 | W44: 2 | X44: =VLOOKUP(B44,[4]考勤分析!$A:$I,4,FALSE) -> 3.1683172 | Y44: =VLOOKUP(B44,[4]考勤分析!$A:$I,5,FALSE) -> TRUE | Z44: =VLOOKUP(B44,[4]考勤分析!$A:$I,6,FALSE) -> 9 | AA44: =VLOOKUP(B44,[4]考勤分析!$A:$I,7,FALSE) -> 19 | AB44: =VLOOKUP(B44,[4]考勤分析!$A:$I,8,FALSE) -> 28 | AC44: =VLOOKUP(B44,[4]考勤分析!$A:$I,9,FALSE) -> 13 | AD44: 0 | AE44: 3 | AF44: 0 | AG44: 1 | AH44: 0 | AI44: 0 | AK44: =VLOOKUP(B44,[3]总表!$B:$W,22,FALSE) -> 超负荷 | AL44: 1 | AM44: 3 | AN44: 3 | AO44: 3 | AP44: =SUM(AL44:AO44) -> 10 | AQ44: 1.1-专业能力强，但领导力较弱
A45: 43 | B45: 康冉 | C45: 综合管理部 | D45: 项目管理团队 | E45: 女 | F45: 6 | G45: 研究生 | H45: 南京师范大学 | I45: 骨干 | L45: 2 | M45: 数据研发 | N45: 校园招聘 | O45: 第二党支部纪检委员 | Q45: 团委学习委员 | S45: =VLOOKUP(B45,'[2]62人'!$B:$R,17,FALSE) -> 12 | T45: 0 | W45: 1 | X45: =VLOOKUP(B45,[4]考勤分析!$A:$I,4,FALSE) -> 1.8193421 | Y45: =VLOOKUP(B45,[4]考勤分析!$A:$I,5,FALSE) -> FALSE | Z45: =VLOOKUP(B45,[4]考勤分析!$A:$I,6,FALSE) -> 21 | AA45: =VLOOKUP(B45,[4]考勤分析!$A:$I,7,FALSE) -> 13 | AB45: =VLOOKUP(B45,[4]考勤分析!$A:$I,8,FALSE) -> 19 | AC45: =VLOOKUP(B45,[4]考勤分析!$A:$I,9,FALSE) -> 4 | AD45: 3 | AE45: 15 | AF45: 1 | AG45: 1 | AH45: 0 | AI45: 10 | AK45: =VLOOKUP(B45,[3]总表!$B:$W,22,FALSE) -> 超负荷 | AL45: 1 | AM45: 3 | AN45: 3 | AO45: 2 | AP45: =SUM(AL45:AO45) -> 9 | AQ45: 1.1-专业能力强，但领导力较弱
A46: 44 | B46: 姚志环 | C46: 数据开发部 | D46: 仓库开发组 | E46: 女 | F46: 6 | G46: 研究生 | H46: 华东理工大学 | I46: 骨干 | L46: 0 | M46: 数据研发 | N46: 校园招聘 | S46: =VLOOKUP(B46,'[2]62人'!$B:$R,17,FALSE) -> 14 | T46: 0 | W46: 2 | X46: =VLOOKUP(B46,[4]考勤分析!$A:$I,4,FALSE) -> 2.3037163 | Y46: =VLOOKUP(B46,[4]考勤分析!$A:$I,5,FALSE) -> FALSE | Z46: =VLOOKUP(B46,[4]考勤分析!$A:$I,6,FALSE) -> 12 | AA46: =VLOOKUP(B46,[4]考勤分析!$A:$I,7,FALSE) -> 35 | AB46: =VLOOKUP(B46,[4]考勤分析!$A:$I,8,FALSE) -> 10 | AC46: =VLOOKUP(B46,[4]考勤分析!$A:$I,9,FALSE) -> 9 | AD46: 0 | AE46: 0 | AF46: 0 | AG46: 1 | AH46: 4 | AI46: 7 | AK46: =VLOOKUP(B46,[3]总表!$B:$W,22,FALSE) -> 适中 | AL46: 1 | AM46: 3 | AN46: 3 | AO46: 2 | AP46: =SUM(AL46:AO46) -> 9 | AQ46: 1.1-专业能力强，但领导力较弱
A47: 45 | B47: 林幸 | C47: 数据开发部 | D47: 仓库开发组 | E47: 女 | F47: 4 | G47: 研究生 | H47: 东北大学 | I47: 骨干 | L47: 0 | M47: 数据研发 | N47: 校园招聘 | S47: =VLOOKUP(B47,'[2]62人'!$B:$R,17,FALSE) -> 12 | T47: 0 | X47: =VLOOKUP(B47,[4]考勤分析!$A:$I,4,FALSE) -> 3.7605682 | Y47: =VLOOKUP(B47,[4]考勤分析!$A:$I,5,FALSE) -> TRUE | Z47: =VLOOKUP(B47,[4]考勤分析!$A:$I,6,FALSE) -> 6 | AA47: =VLOOKUP(B47,[4]考勤分析!$A:$I,7,FALSE) -> 4 | AB47: =VLOOKUP(B47,[4]考勤分析!$A:$I,8,FALSE) -> 37 | AC47: =VLOOKUP(B47,[4]考勤分析!$A:$I,9,FALSE) -> 19 | AD47: 1 | AE47: 3 | AF47: 1 | AG47: 1 | AH47: 8 | AI47: 9 | AK47: =VLOOKUP(B47,[3]总表!$B:$W,22,FALSE) -> 超负荷 | AL47: 1 | AM47: 3 | AN47: 3 | AO47: 2 | AP47: =SUM(AL47:AO47) -> 9 | AQ47: 2-可培养的二梯队
A48: 46 | B48: 骆静龙 | C48: 数据开发部 | D48: 应用开发组 | E48: 男 | F48: 3 | G48: 大学本科 | H48: 华东师范大学 | I48: 骨干 | L48: 1 | M48: 数据研发 | N48: 校园招聘 | R48: 23五星质量奖 | S48: =VLOOKUP(B48,'[2]62人'!$B:$R,17,FALSE) -> 15 | T48: 0 | W48: 1 | X48: =VLOOKUP(B48,[4]考勤分析!$A:$I,4,FALSE) -> 2.7584962 | Y48: =VLOOKUP(B48,[4]考勤分析!$A:$I,5,FALSE) -> TRUE | Z48: =VLOOKUP(B48,[4]考勤分析!$A:$I,6,FALSE) -> 7 | AA48: =VLOOKUP(B48,[4]考勤分析!$A:$I,7,FALSE) -> 11 | AB48: =VLOOKUP(B48,[4]考勤分析!$A:$I,8,FALSE) -> 31 | AC48: =VLOOKUP(B48,[4]考勤分析!$A:$I,9,FALSE) -> 9 | AD48: 0 | AE48: 1 | AF48: 0 | AG48: 1 | AH48: 15 | AI48: 10 | AK48: =VLOOKUP(B48,[3]总表!$B:$W,22,FALSE) -> 超负荷 | AL48: 2 | AM48: 3 | AN48: 4 | AO48: 2 | AP48: =SUM(AL48:AO48) -> 11 | AQ48: 1.1-专业能力强，但领导力较弱
A49: 47 | B49: 王言哲 | C49: 数据开发部 | D49: 应用开发组 | E49: 男 | F49: 4 | G49: 大学本科 | H49: 华东师范大学 | I49: 骨干 | L49: 0 | M49: 数据研发 | N49: 校园招聘 | S49: =VLOOKUP(B49,'[2]62人'!$B:$R,17,FALSE) -> 17 | T49: 0 | X49: =VLOOKUP(B49,[4]考勤分析!$A:$I,4,FALSE) -> 2.2961287 | Y49: =VLOOKUP(B49,[4]考勤分析!$A:$I,5,FALSE) -> FALSE | Z49: =VLOOKUP(B49,[4]考勤分析!$A:$I,6,FALSE) -> 5 | AA49: =VLOOKUP(B49,[4]考勤分析!$A:$I,7,FALSE) -> 38 | AB49: =VLOOKUP(B49,[4]考勤分析!$A:$I,8,FALSE) -> 13 | AC49: =VLOOKUP(B49,[4]考勤分析!$A:$I,9,FALSE) -> 7 | AD49: 0 | AE49: 8 | AF49: 0 | AG49: 1 | AH49: 20 | AI49: 19 | AK49: =VLOOKUP(B49,[3]总表!$B:$W,22,FALSE) -> 超负荷 | AL49: 2 | AM49: 3 | AN49: 3 | AO49: 2 | AP49: =SUM(AL49:AO49) -> 10 | AQ49: 2-可培养的二梯队
A50: 48 | B50: 马富强 | C50: 数据开发部 | D50: 仓库开发组 | E50: 男 | F50: 8 | G50: 大学本科 | H50: 上海理工大学 | I50: 骨干 | L50: 0 | M50: 数据研发 | N50: 社会招聘 | S50: =VLOOKUP(B50,'[2]62人'!$B:$R,17,FALSE) -> 14 | T50: 4 | W50: 1 | X50: =VLOOKUP(B50,[4]考勤分析!$A:$I,4,FALSE) -> 3.5342172 | Y50: =VLOOKUP(B50,[4]考勤分析!$A:$I,5,FALSE) -> TRUE | Z50: =VLOOKUP(B50,[4]考勤分析!$A:$I,6,FALSE) -> 7 | AA50: =VLOOKUP(B50,[4]考勤分析!$A:$I,7,FALSE) -> 5 | AB50: =VLOOKUP(B50,[4]考勤分析!$A:$I,8,FALSE) -> 43 | AC50: =VLOOKUP(B50,[4]考勤分析!$A:$I,9,FALSE) -> 11 | AD50: 0 | AE50: 1 | AF50: 0 | AG50: 1 | AH50: 10 | AI50: 13 | AK50: =VLOOKUP(B50,[3]总表!$B:$W,22,FALSE) -> 超负荷 | AL50: 1 | AM50: 3 | AN50: 3 | AO50: 2 | AP50: =SUM(AL50:AO50) -> 9 | AQ50: 1.1-专业能力强，但领导力较弱
A51: 49 | B51: 胡帆 | C51: 数据平台部 | D51: 数据服务组 | E51: 男 | F51: 4 | G51: 研究生 | H51: 华东理工大学 | I51: 骨干 | J51: 架构师 | K51: 3 | L51: 1 | M51: 数据研发 | N51: 校园招聘 | S51: =VLOOKUP(B51,'[2]62人'!$B:$R,17,FALSE) -> 14 | T51: 0 | X51: =VLOOKUP(B51,[4]考勤分析!$A:$I,4,FALSE) -> 2.6569086 | Y51: =VLOOKUP(B51,[4]考勤分析!$A:$I,5,FALSE) -> TRUE | Z51: =VLOOKUP(B51,[4]考勤分析!$A:$I,6,FALSE) -> 15 | AA51: =VLOOKUP(B51,[4]考勤分析!$A:$I,7,FALSE) -> 2 | AB51: =VLOOKUP(B51,[4]考勤分析!$A:$I,8,FALSE) -> 29 | AC51: =VLOOKUP(B51,[4]考勤分析!$A:$I,9,FALSE) -> 16 | AD51: 0 | AE51: 0 | AF51: 1 | AG51: 1 | AH51: 8 | AI51: 10 | AK51: =VLOOKUP(B51,[3]总表!$B:$W,22,FALSE) -> 适中 | AL51: 2 | AM51: 3 | AN51: 4 | AO51: 3 | AP51: =SUM(AL51:AO51) -> 12 | AQ51: 4-高潜培养对象
A52: 50 | B52: 陆凯华 | C52: 数据平台部 | D52: 数据服务组 | E52: 男 | F52: #VALUE! | G52: 研究生 | H52: 苏州大学 | I52: 骨干 | L52: 1 | M52: 数据研发 | N52: 校园招聘 | O52: 第一党支部组织委员 | S52: =VLOOKUP(B52,'[2]62人'!$B:$R,17,FALSE) -> 12 | T52: 0 | W52: 1 | X52: =VLOOKUP(B52,[4]考勤分析!$A:$I,4,FALSE) -> 5.4052778 | Y52: =VLOOKUP(B52,[4]考勤分析!$A:$I,5,FALSE) -> TRUE | Z52: =VLOOKUP(B52,[4]考勤分析!$A:$I,6,FALSE) -> 10 | AA52: =VLOOKUP(B52,[4]考勤分析!$A:$I,7,FALSE) -> 13 | AB52: =VLOOKUP(B52,[4]考勤分析!$A:$I,8,FALSE) -> 11 | AC52: =VLOOKUP(B52,[4]考勤分析!$A:$I,9,FALSE) -> 43 | AD52: 1 | AE52: 4 | AF52: 3 | AG52: 4 | AH52: 21 | AI52: 35 | AK52: =VLOOKUP(B52,[3]总表!$B:$W,22,FALSE) -> 超负荷 | AL52: 2 | AM52: 3 | AN52: 4 | AO52: 2 | AP52: =SUM(AL52:AO52) -> 11 | AQ52: 2-可培养的二梯队
A53: 51 | B53: 朱文川 | C53: 数据平台部 | D53: 工具开发组 | E53: 男 | F53: 3 | G53: 研究生 | H53: 上海大学 | I53: 骨干 | L53: 0 | M53: 数据研发 | N53: 校园招聘 | S53: =VLOOKUP(B53,'[2]62人'!$B:$R,17,FALSE) -> 11 | T53: 0 | W53: 1 | X53: =VLOOKUP(B53,[4]考勤分析!$A:$I,4,FALSE) -> 1.4821609 | Y53: =VLOOKUP(B53,[4]考勤分析!$A:$I,5,FALSE) -> FALSE | Z53: =VLOOKUP(B53,[4]考勤分析!$A:$I,6,FALSE) -> 30 | AA53: =VLOOKUP(B53,[4]考勤分析!$A:$I,7,FALSE) -> 31 | AB53: =VLOOKUP(B53,[4]考勤分析!$A:$I,8,FALSE) -> 1 | AC53: =VLOOKUP(B53,[4]考勤分析!$A:$I,9,FALSE) -> 6 | AD53: 0 | AE53: 0 | AF53: 0 | AG53: 2 | AH53: 6 | AI53: 6 | AK53: =VLOOKUP(B53,[3]总表!$B:$W,22,FALSE) -> 适中 | AL53: 1 | AM53: 3 | AN53: 4 | AO53: 3 | AP53: =SUM(AL53:AO53) -> 11 | AQ53: 2-可培养的二梯队
A54: 52 | B54: 王璐珊 | C54: 信息管理部 | D54: 零售BP | E54: 女 | F54: 5 | G54: 研究生 | H54: 南开大学 | I54: 骨干 | J54: 产品经理 | K54: 1 | L54: 1 | M54: 数据分析 | N54: 校园招聘 | S54: =VLOOKUP(B54,'[2]62人'!$B:$R,17,FALSE) -> 11 | T54: 0 | W54: 1 | X54: =VLOOKUP(B54,[4]考勤分析!$A:$I,4,FALSE) -> 1.5592593 | Y54: =VLOOKUP(B54,[4]考勤分析!$A:$I,5,FALSE) -> TRUE | Z54: =VLOOKUP(B54,[4]考勤分析!$A:$I,6,FALSE) -> 21 | AA54: =VLOOKUP(B54,[4]考勤分析!$A:$I,7,FALSE) -> 30 | AB54: =VLOOKUP(B54,[4]考勤分析!$A:$I,8,FALSE) -> 5 | AC54: =VLOOKUP(B54,[4]考勤分析!$A:$I,9,FALSE) -> 7 | AD54: 0 | AE54: 2 | AF54: 0 | AG54: 0 | AH54: 0 | AI54: 0 | AK54: =VLOOKUP(B54,[3]总表!$B:$W,22,FALSE) -> #N/A | AL54: 2 | AM54: 3 | AN54: 3 | AO54: 3 | AP54: =SUM(AL54:AO54) -> 11 | AQ54: 2-可培养的二梯队
A55: 53 | B55: 俞振飞 | C55: 信息管理部 | D55: 非零BP | E55: 女 | F55: 4 | G55: 研究生 | H55: 波士顿大学 | I55: 骨干 | L55: 1 | M55: 数据分析 | N55: 校园招聘 | S55: =VLOOKUP(B55,'[2]62人'!$B:$R,17,FALSE) -> 11 | T55: 0 | W55: 2 | X55: =VLOOKUP(B55,[4]考勤分析!$A:$I,4,FALSE) -> 1.7435036 | Y55: =VLOOKUP(B55,[4]考勤分析!$A:$I,5,FALSE) -> TRUE | Z55: =VLOOKUP(B55,[4]考勤分析!$A:$I,6,FALSE) -> 16 | AA55: =VLOOKUP(B55,[4]考勤分析!$A:$I,7,FALSE) -> 26 | AB55: =VLOOKUP(B55,[4]考勤分析!$A:$I,8,FALSE) -> 18 | AC55: =VLOOKUP(B55,[4]考勤分析!$A:$I,9,FALSE) -> 2 | AD55: 0 | AE55: 1 | AF55: 0 | AG55: 0 | AH55: 0 | AI55: 0 | AK55: =VLOOKUP(B55,[3]总表!$B:$W,22,FALSE) -> #N/A | AL55: 1 | AM55: 3 | AN55: 3 | AO55: 2 | AP55: =SUM(AL55:AO55) -> 9 | AQ55: 2-可培养的二梯队
A56: 54 | B56: 汪乐乐 | C56: 信息管理部 | D56: 分行BP | E56: 女 | F56: 3 | G56: 研究生 | H56: 东南大学 | I56: 骨干 | J56: 产品经理 | K56: 3 | L56: 1 | M56: 数据分析 | N56: 校园招聘 | S56: =VLOOKUP(B56,'[2]62人'!$B:$R,17,FALSE) -> 8 | T56: 0 | W56: 2 | X56: =VLOOKUP(B56,[4]考勤分析!$A:$I,4,FALSE) -> 1.1912067 | Y56: =VLOOKUP(B56,[4]考勤分析!$A:$I,5,FALSE) -> FALSE | Z56: =VLOOKUP(B56,[4]考勤分析!$A:$I,6,FALSE) -> 35 | AA56: =VLOOKUP(B56,[4]考勤分析!$A:$I,7,FALSE) -> 13 | AB56: =VLOOKUP(B56,[4]考勤分析!$A:$I,8,FALSE) -> 12 | AC56: =VLOOKUP(B56,[4]考勤分析!$A:$I,9,FALSE) -> 1 | AD56: 0 | AE56: 0 | AF56: 0 | AG56: 0 | AH56: 0 | AI56: 0 | AK56: =VLOOKUP(B56,[3]总表!$B:$W,22,FALSE) -> #N/A | AL56: 1 | AM56: 3 | AN56: 3 | AO56: 2 | AP56: =SUM(AL56:AO56) -> 9 | AQ56: 2-可培养的二梯队
A57: 55 | B57: 姚蜜 | C57: 信息统计部 | D57: 管理信息应用 | E57: 女 | F57: 5 | G57: 研究生 | H57: 华中师范大学 | I57: 骨干 | L57: 1 | M57: 数据分析 | N57: 校园招聘 | S57: =VLOOKUP(B57,'[2]62人'!$B:$R,17,FALSE) -> 9 | T57: 3 | W57: 1 | X57: =VLOOKUP(B57,[4]考勤分析!$A:$I,4,FALSE) -> 1.6048889 | Y57: =VLOOKUP(B57,[4]考勤分析!$A:$I,5,FALSE) -> FALSE | Z57: =VLOOKUP(B57,[4]考勤分析!$A:$I,6,FALSE) -> 20 | AA57: =VLOOKUP(B57,[4]考勤分析!$A:$I,7,FALSE) -> 23 | AB57: =VLOOKUP(B57,[4]考勤分析!$A:$I,8,FALSE) -> 15 | AC57: =VLOOKUP(B57,[4]考勤分析!$A:$I,9,FALSE) -> 2 | AD57: 0 | AE57: 0 | AF57: 0 | AG57: 0 | AH57: 0 | AI57: 0 | AK57: =VLOOKUP(B57,[3]总表!$B:$W,22,FALSE) -> #N/A | AL57: 1 | AM57: 3 | AN57: 3 | AO57: 2 | AP57: =SUM(AL57:AO57) -> 9 | AQ57: 2-可培养的二梯队
A58: 56 | B58: 李然 | C58: 信息统计部 | D58: 监管统计 | E58: 男 | F58: 20 | G58: 研究生 | H58: 南新罕布什尔大学 | I58: 骨干 | J58: 产品经理 | K58: 1 | L58: 1 | M58: 监管统计 | N58: 社会招聘 | S58: =VLOOKUP(B58,'[2]62人'!$B:$R,17,FALSE) -> 10 | T58: 0 | X58: =VLOOKUP(B58,[4]考勤分析!$A:$I,4,FALSE) -> 2.0634677 | Y58: =VLOOKUP(B58,[4]考勤分析!$A:$I,5,FALSE) -> TRUE | Z58: =VLOOKUP(B58,[4]考勤分析!$A:$I,6,FALSE) -> 7 | AA58: =VLOOKUP(B58,[4]考勤分析!$A:$I,7,FALSE) -> 23 | AB58: =VLOOKUP(B58,[4]考勤分析!$A:$I,8,FALSE) -> 31 | AC58: =VLOOKUP(B58,[4]考勤分析!$A:$I,9,FALSE) -> 1 | AD58: 0 | AE58: 0 | AF58: 0 | AG58: 0 | AH58: 0 | AI58: 0 | AK58: =VLOOKUP(B58,[3]总表!$B:$W,22,FALSE) -> #N/A | AL58: 2 | AM58: 3 | AN58: 4 | AO58: 2 | AP58: =SUM(AL58:AO58) -> 11 | AQ58: 2-可培养的二梯队
A59: 57 | B59: 崔建文 | C59: 智能创新部 | D59: 模型开发组 | E59: 男 | F59: 5 | G59: 研究生 | H59: 厦门大学 | I59: 骨干 | L59: 0 | M59: 数据研发 | N59: 校园招聘 | R59: 23/24数据文化优秀贡献者/25专利1 | S59: =VLOOKUP(B59,'[2]62人'!$B:$R,17,FALSE) -> 14 | T59: 0 | X59: =VLOOKUP(B59,[4]考勤分析!$A:$I,4,FALSE) -> 2.0639954 | Y59: =VLOOKUP(B59,[4]考勤分析!$A:$I,5,FALSE) -> TRUE | Z59: =VLOOKUP(B59,[4]考勤分析!$A:$I,6,FALSE) -> 21 | AA59: =VLOOKUP(B59,[4]考勤分析!$A:$I,7,FALSE) -> 7 | AB59: =VLOOKUP(B59,[4]考勤分析!$A:$I,8,FALSE) -> 26 | AC59: =VLOOKUP(B59,[4]考勤分析!$A:$I,9,FALSE) -> 6 | AD59: 1 | AE59: 2 | AF59: 0 | AG59: 1 | AH59: 0 | AI59: 0 | AK59: =VLOOKUP(B59,[3]总表!$B:$W,22,FALSE) -> 适中 | AL59: 1 | AM59: 3 | AN59: 3 | AO59: 2 | AP59: =SUM(AL59:AO59) -> 9 | AQ59: 2-可培养的二梯队
A60: 58 | B60: 贾世林 | C60: 智能创新部 | D60: AI基础研发组 | E60: 男 | F60: 5 | G60: 研究生 | H60: 上海师范大学 | I60: 骨干 | L60: 0 | M60: 数据研发 | N60: 社会招聘 | R60: 23数据文化优秀贡献者/25专利1 | S60: =VLOOKUP(B60,'[2]62人'!$B:$R,17,FALSE) -> 11 | T60: 0 | U60: 1 | W60: 1 | X60: =VLOOKUP(B60,[4]考勤分析!$A:$I,4,FALSE) -> 1.8426254 | Y60: =VLOOKUP(B60,[4]考勤分析!$A:$I,5,FALSE) -> FALSE | Z60: =VLOOKUP(B60,[4]考勤分析!$A:$I,6,FALSE) -> 13 | AA60: =VLOOKUP(B60,[4]考勤分析!$A:$I,7,FALSE) -> 28 | AB60: =VLOOKUP(B60,[4]考勤分析!$A:$I,8,FALSE) -> 15 | AC60: =VLOOKUP(B60,[4]考勤分析!$A:$I,9,FALSE) -> 6 | AD60: 1 | AE60: 1 | AF60: 1 | AG60: 1 | AH60: 7 | AI60: 12 | AK60: =VLOOKUP(B60,[3]总表!$B:$W,22,FALSE) -> 超负荷 | AL60: 1 | AM60: 3 | AN60: 3 | AO60: 3 | AP60: =SUM(AL60:AO60) -> 10 | AQ60: 2-可培养的二梯队
A61: 59 | B61: 陆文捷 | C61: 智能创新部 | D61: 模型开发组 | E61: 女 | F61: =VLOOKUP(B61,[1]累计工龄!A:B,2,FALSE) -> 1 | G61: 研究生 | H61: 苏州大学 | I61: 骨干 | L61: 0 | M61: 数据研发 | N61: 校园招聘 | R61: 24最佳新人/25专利1 | S61: =VLOOKUP(B61,'[2]62人'!$B:$R,17,FALSE) -> 18 | T61: 0 | W61: 1 | X61: =VLOOKUP(B61,[4]考勤分析!$A:$I,4,FALSE) -> 1.5502285 | Y61: =VLOOKUP(B61,[4]考勤分析!$A:$I,5,FALSE) -> FALSE | Z61: =VLOOKUP(B61,[4]考勤分析!$A:$I,6,FALSE) -> 21 | AA61: =VLOOKUP(B61,[4]考勤分析!$A:$I,7,FALSE) -> 20 | AB61: =VLOOKUP(B61,[4]考勤分析!$A:$I,8,FALSE) -> 20 | AC61: =VLOOKUP(B61,[4]考勤分析!$A:$I,9,FALSE) -> 1 | AD61: 0 | AE61: 0 | AF61: 0 | AG61: 0 | AH61: 0 | AI61: 0 | AK61: 适中 | AL61: 2 | AM61: 5 | AN61: 4 | AO61: 2 | AP61: =SUM(AL61:AO61) -> 13 | AQ61: 4-高潜培养对象
A62: 60 | B62: 陆雨欣 | C62: 综合管理部 | D62: 项目管理团队 | E62: 女 | F62: 6 | G62: 研究生 | H62: 加州大学戴维斯分校 | I62: 骨干 | L62: 1 | M62: 项目管理 | N62: 校园招聘 | S62: =VLOOKUP(B62,'[2]62人'!$B:$R,17,FALSE) -> 6 | T62: 26 | U62: 3 | X62: =VLOOKUP(B62,[4]考勤分析!$A:$I,4,FALSE) -> 1.9955182 | Y62: =VLOOKUP(B62,[4]考勤分析!$A:$I,5,FALSE) -> FALSE | Z62: =VLOOKUP(B62,[4]考勤分析!$A:$I,6,FALSE) -> 8 | AA62: =VLOOKUP(B62,[4]考勤分析!$A:$I,7,FALSE) -> 44 | AB62: =VLOOKUP(B62,[4]考勤分析!$A:$I,8,FALSE) -> 8 | AC62: =VLOOKUP(B62,[4]考勤分析!$A:$I,9,FALSE) -> 7 | AD62: 4 | AE62: 7 | AF62: 0 | AG62: 0 | AH62: 0 | AI62: 0 | AK62: =VLOOKUP(B62,[3]总表!$B:$W,22,FALSE) -> #N/A | AL62: 1 | AM62: 3 | AN62: 3 | AO62: 2 | AP62: =SUM(AL62:AO62) -> 9 | AQ62: 2-可培养的二梯队
A63: 61 | B63: 许阿云 | C63: 综合管理部 | D63: 综合管理组 | E63: 女 | F63: 6 | G63: 研究生 | H63: 华中师范大学 | I63: 骨干 | L63: 1 | M63: 综合管理 | N63: 校园招聘 | O63: 党总支宣传委员、 第一党支部书记 | P63: 工会会员代表 | S63: =VLOOKUP(B63,'[2]62人'!$B:$R,17,FALSE) -> 11 | T63: 4 | X63: =VLOOKUP(B63,[4]考勤分析!$A:$I,4,FALSE) -> 2.205097 | Y63: =VLOOKUP(B63,[4]考勤分析!$A:$I,5,FALSE) -> TRUE | Z63: =VLOOKUP(B63,[4]考勤分析!$A:$I,6,FALSE) -> 7 | AA63: =VLOOKUP(B63,[4]考勤分析!$A:$I,7,FALSE) -> 25 | AB63: =VLOOKUP(B63,[4]考勤分析!$A:$I,8,FALSE) -> 27 | AC63: =VLOOKUP(B63,[4]考勤分析!$A:$I,9,FALSE) -> 4 | AD63: 0 | AE63: 0 | AF63: 0 | AG63: 0 | AH63: 0 | AI63: 0 | AK63: =VLOOKUP(B63,[3]总表!$B:$W,22,FALSE) -> #N/A | AL63: 2 | AM63: 3 | AN63: 3 | AO63: 3 | AP63: =SUM(AL63:AO63) -> 11 | AQ63: 2-可培养的二梯队
A64: 62 | B64: 陈世辉 | C64: 综合管理部 | D64: 测试管理组 | E64: 男 | F64: =VLOOKUP(B64,[1]累计工龄!A:B,2,FALSE) -> 1 | G64: 大学本科 | H64: 上海对外经贸大学 | I64: 骨干 | L64: 0 | M64: 数据测试 | N64: 校园招聘 | R64: 23最佳新人\24最佳合作服务奖 | S64: =VLOOKUP(B64,'[2]62人'!$B:$R,17,FALSE) -> 12 | T64: 2 | X64: =VLOOKUP(B64,[4]考勤分析!$A:$I,4,FALSE) -> 2.9023979 | Y64: =VLOOKUP(B64,[4]考勤分析!$A:$I,5,FALSE) -> TRUE | Z64: =VLOOKUP(B64,[4]考勤分析!$A:$I,6,FALSE) -> 14 | AA64: =VLOOKUP(B64,[4]考勤分析!$A:$I,7,FALSE) -> 18 | AB64: =VLOOKUP(B64,[4]考勤分析!$A:$I,8,FALSE) -> 22 | AC64: =VLOOKUP(B64,[4]考勤分析!$A:$I,9,FALSE) -> 14 | AD64: 0 | AE64: 0 | AF64: 0 | AG64: 0 | AH64: 0 | AI64: 0 | AK64: =VLOOKUP(B64,[3]总表!$B:$W,22,FALSE) -> #N/A | AL64: 1 | AM64: 3 | AN64: 4 | AO64: 3 | AP64: =SUM(AL64:AO64) -> 11 | AQ64: 2-可培养的二梯队
A65: 63 | B65: 杨晓彦 | C65: 综合管理部 | D65: 负责人 | E65: 女 | F65: 8 | G65: 研究生 | H65: 伊利诺伊大学厄巴纳-香槟分校 | I65: 科长 | L65: 1 | M65: 负责人 | N65: 校园招聘 | S65: =VLOOKUP(B65,'[2]62人'!$B:$R,17,FALSE) -> 10 | T65: 0 | U65: 1 | X65: =VLOOKUP(B65,[4]考勤分析!$A:$I,4,FALSE) -> 2.243638 | Y65: =VLOOKUP(B65,[4]考勤分析!$A:$I,5,FALSE) -> TRUE | Z65: =VLOOKUP(B65,[4]考勤分析!$A:$I,6,FALSE) -> 8 | AA65: =VLOOKUP(B65,[4]考勤分析!$A:$I,7,FALSE) -> 17 | AB65: =VLOOKUP(B65,[4]考勤分析!$A:$I,8,FALSE) -> 33 | AC65: =VLOOKUP(B65,[4]考勤分析!$A:$I,9,FALSE) -> 4 | AD65: 0 | AE65: 0 | AF65: 0 | AG65: 0 | AH65: 0 | AI65: 0 | AK65: =VLOOKUP(B65,[3]总表!$B:$W,22,FALSE) -> #N/A
A66: 64 | B66: 顾小萍 | C66: 综合管理部 | D66: 综合管理组 | E66: 女 | F66: 20 | G66: 研究生 | H66: 东华大学 | L66: 2 | M66: 综合管理 | N66: 校园招聘 | S66: =VLOOKUP(B66,'[2]62人'!$B:$R,17,FALSE) -> 15 | T66: 1 | X66: =VLOOKUP(B66,[4]考勤分析!$A:$I,4,FALSE) -> 2.7398241 | Y66: =VLOOKUP(B66,[4]考勤分析!$A:$I,5,FALSE) -> TRUE | Z66: =VLOOKUP(B66,[4]考勤分析!$A:$I,6,FALSE) -> 1 | AA66: =VLOOKUP(B66,[4]考勤分析!$A:$I,7,FALSE) -> 14 | AB66: =VLOOKUP(B66,[4]考勤分析!$A:$I,8,FALSE) -> 39 | AC66: =VLOOKUP(B66,[4]考勤分析!$A:$I,9,FALSE) -> 6 | AD66: 0 | AE66: 0 | AF66: 0 | AG66: 0 | AH66: 0 | AI66: 0 | AK66: =VLOOKUP(B66,[3]总表!$B:$W,22,FALSE) -> #N/A
A67: 65 | B67: 武燕蓉 | C67: 综合管理部 | D67: 综合管理组 | E67: 女 | F67: 31 | G67: 大学本科 | H67: 上海工程技术大学 | L67: 2 | M67: 综合管理 | N67: 校园招聘 | R67: 24风雨同舟/24数据文化优秀贡献者 | S67: =VLOOKUP(B67,'[2]62人'!$B:$R,17,FALSE) -> 12 | T67: 0 | X67: =VLOOKUP(B67,[4]考勤分析!$A:$I,4,FALSE) -> 0.81278333 | Y67: =VLOOKUP(B67,[4]考勤分析!$A:$I,5,FALSE) -> FALSE | Z67: =VLOOKUP(B67,[4]考勤分析!$A:$I,6,FALSE) -> 42 | AA67: =VLOOKUP(B67,[4]考勤分析!$A:$I,7,FALSE) -> 7 | AB67: =VLOOKUP(B67,[4]考勤分析!$A:$I,8,FALSE) -> 1 | AC67: =VLOOKUP(B67,[4]考勤分析!$A:$I,9,FALSE) -> 0 | AD67: 0 | AE67: 0 | AF67: 0 | AG67: 0 | AH67: 0 | AI67: 0 | AK67: =VLOOKUP(B67,[3]总表!$B:$W,22,FALSE) -> #N/A
A68: 66 | B68: 胡超亭 | C68: 综合管理部 | D68: 综合管理组 | E68: 女 | F68: 5 | G68: 研究生 | H68: 华东理工大学 | L68: 1 | M68: 综合管理 | N68: 校园招聘 | S68: =VLOOKUP(B68,'[2]62人'!$B:$R,17,FALSE) -> 16 | T68: 8 | U68: 2 | X68: =VLOOKUP(B68,[4]考勤分析!$A:$I,4,FALSE) -> 1.9936918 | Y68: =VLOOKUP(B68,[4]考勤分析!$A:$I,5,FALSE) -> FALSE | Z68: =VLOOKUP(B68,[4]考勤分析!$A:$I,6,FALSE) -> 3 | AA68: =VLOOKUP(B68,[4]考勤分析!$A:$I,7,FALSE) -> 36 | AB68: =VLOOKUP(B68,[4]考勤分析!$A:$I,8,FALSE) -> 21 | AC68: =VLOOKUP(B68,[4]考勤分析!$A:$I,9,FALSE) -> 2 | AD68: 0 | AE68: 0 | AF68: 0 | AG68: 0 | AH68: 0 | AI68: 0 | AK68: =VLOOKUP(B68,[3]总表!$B:$W,22,FALSE) -> #N/A
A69: 67 | B69: 宋子夜 | C69: 综合管理部 | D69: 综合管理组 | E69: 女 | F69: 4 | G69: 研究生 | H69: 东南大学 | L69: 1 | M69: 综合管理 | N69: 校园招聘 | S69: =VLOOKUP(B69,'[2]62人'!$B:$R,17,FALSE) -> 12 | T69: 2 | U69: 1 | X69: =VLOOKUP(B69,[4]考勤分析!$A:$I,4,FALSE) -> 2.2394444 | Y69: =VLOOKUP(B69,[4]考勤分析!$A:$I,5,FALSE) -> TRUE | Z69: =VLOOKUP(B69,[4]考勤分析!$A:$I,6,FALSE) -> 7 | AA69: =VLOOKUP(B69,[4]考勤分析!$A:$I,7,FALSE) -> 23 | AB69: =VLOOKUP(B69,[4]考勤分析!$A:$I,8,FALSE) -> 30 | AC69: =VLOOKUP(B69,[4]考勤分析!$A:$I,9,FALSE) -> 3 | AD69: 0 | AE69: 0 | AF69: 0 | AG69: 0 | AH69: 0 | AI69: 0 | AK69: =VLOOKUP(B69,[3]总表!$B:$W,22,FALSE) -> #N/A
A70: 68 | B70: 马亦沁 | C70: 综合管理部 | D70: 测试管理组 | E70: 女 | F70: 3 | G70: 大学本科 | H70: 上海大学 | L70: 1 | M70: 数据测试 | N70: 校园招聘 | R70: 24技术能手 | S70: =VLOOKUP(B70,'[2]62人'!$B:$R,17,FALSE) -> 15 | T70: 0 | X70: =VLOOKUP(B70,[4]考勤分析!$A:$I,4,FALSE) -> 1.5886632 | Y70: =VLOOKUP(B70,[4]考勤分析!$A:$I,5,FALSE) -> FALSE | Z70: =VLOOKUP(B70,[4]考勤分析!$A:$I,6,FALSE) -> 32 | AA70: =VLOOKUP(B70,[4]考勤分析!$A:$I,7,FALSE) -> 8 | AB70: =VLOOKUP(B70,[4]考勤分析!$A:$I,8,FALSE) -> 20 | AC70: =VLOOKUP(B70,[4]考勤分析!$A:$I,9,FALSE) -> 4 | AD70: 0 | AE70: 0 | AF70: 0 | AG70: 0 | AH70: 0 | AI70: 0 | AK70: =VLOOKUP(B70,[3]总表!$B:$W,22,FALSE) -> #N/A
A71: 69 | B71: 曹翔 | C71: 综合管理部 | D71: 测试管理组 | E71: 女 | F71: =VLOOKUP(B71,累计工龄!A:B,2,FALSE) -> 1 | G71: 研究生 | H71: 上海海洋大学 | L71: 0 | M71: 数据测试 | N71: 校园招聘 | R71: 24研究与创新奖 | S71: =VLOOKUP(B71,'[2]62人'!$B:$R,17,FALSE) -> 15 | T71: 2 | X71: =VLOOKUP(B71,[4]考勤分析!$A:$I,4,FALSE) -> 1.7807286 | Y71: =VLOOKUP(B71,[4]考勤分析!$A:$I,5,FALSE) -> FALSE | Z71: =VLOOKUP(B71,[4]考勤分析!$A:$I,6,FALSE) -> 7 | AA71: =VLOOKUP(B71,[4]考勤分析!$A:$I,7,FALSE) -> 38 | AB71: =VLOOKUP(B71,[4]考勤分析!$A:$I,8,FALSE) -> 15 | AC71: =VLOOKUP(B71,[4]考勤分析!$A:$I,9,FALSE) -> 1 | AD71: 0 | AE71: 0 | AF71: 0 | AG71: 0 | AH71: 0 | AI71: 0 | AK71: =VLOOKUP(B71,[3]总表!$B:$W,22,FALSE) -> #N/A
A72: 70 | B72: 乐洋 | C72: 综合管理部 | D72: 项目管理团队 | E72: 男 | F72: 20 | G72: 研究生 | H72: 东华大学 | L72: 2 | M72: 项目管理 | N72: 社会招聘 | S72: =VLOOKUP(B72,'[2]62人'!$B:$R,17,FALSE) -> 9 | T72: 0 | U72: 1 | X72: =VLOOKUP(B72,[4]考勤分析!$A:$I,4,FALSE) -> 3.0290148 | Y72: =VLOOKUP(B72,[4]考勤分析!$A:$I,5,FALSE) -> TRUE | Z72: =VLOOKUP(B72,[4]考勤分析!$A:$I,6,FALSE) -> 11 | AA72: =VLOOKUP(B72,[4]考勤分析!$A:$I,7,FALSE) -> 10 | AB72: =VLOOKUP(B72,[4]考勤分析!$A:$I,8,FALSE) -> 25 | AC72: =VLOOKUP(B72,[4]考勤分析!$A:$I,9,FALSE) -> 18 | AD72: 0 | AE72: 0 | AF72: 0 | AG72: 0 | AH72: 0 | AI72: 0 | AK72: =VLOOKUP(B72,[3]总表!$B:$W,22,FALSE) -> #N/A
A73: 71 | B73: 王枫 | C73: 综合管理部 | D73: 项目管理团队 | E73: 男 | F73: 10 | G73: 大学本科 | H73: 四川大学 | L73: 4 | M73: 项目管理 | N73: 校园招聘 | S73: =VLOOKUP(B73,'[2]62人'!$B:$R,17,FALSE) -> 14 | T73: 0 | X73: =VLOOKUP(B73,[4]考勤分析!$A:$I,4,FALSE) -> 0.89510018 | Y73: =VLOOKUP(B73,[4]考勤分析!$A:$I,5,FALSE) -> FALSE | Z73: =VLOOKUP(B73,[4]考勤分析!$A:$I,6,FALSE) -> 46 | AA73: =VLOOKUP(B73,[4]考勤分析!$A:$I,7,FALSE) -> 11 | AB73: =VLOOKUP(B73,[4]考勤分析!$A:$I,8,FALSE) -> 4 | AC73: =VLOOKUP(B73,[4]考勤分析!$A:$I,9,FALSE) -> 0 | AD73: 3 | AE73: 0 | AF73: 0 | AG73: 0 | AH73: 0 | AI73: 0 | AK73: =VLOOKUP(B73,[3]总表!$B:$W,22,FALSE) -> #N/A
A74: 72 | B74: 刘召龙 | C74: 综合管理部 | D74: 项目管理团队 | E74: 男 | F74: 25 | G74: 大学本科 | H74: 上海大学 | L74: 1 | M74: 项目管理 | N74: 社会招聘 | S74: =VLOOKUP(B74,'[2]62人'!$B:$R,17,FALSE) -> 16 | T74: 0 | X74: =VLOOKUP(B74,[4]考勤分析!$A:$I,4,FALSE) -> 0.59381944 | Y74: =VLOOKUP(B74,[4]考勤分析!$A:$I,5,FALSE) -> FALSE | Z74: =VLOOKUP(B74,[4]考勤分析!$A:$I,6,FALSE) -> 8 | AA74: =VLOOKUP(B74,[4]考勤分析!$A:$I,7,FALSE) -> 4 | AB74: =VLOOKUP(B74,[4]考勤分析!$A:$I,8,FALSE) -> 0 | AC74: =VLOOKUP(B74,[4]考勤分析!$A:$I,9,FALSE) -> 0 | AD74: 5 | AE74: 5 | AF74: 0 | AG74: 0 | AH74: 0 | AI74: 0 | AK74: =VLOOKUP(B74,[3]总表!$B:$W,22,FALSE) -> #N/A
A75: 73 | B75: 占桐 | C75: 综合管理部 | D75: 2025届校招 | E75: 女 | F75: 0 | G75: 研究生 | H75: 伦敦国王学院 | L75: 0 | M75: 综合管理 | N75: 校园招聘 | S75: =VLOOKUP(B75,'[2]62人'!$B:$R,17,FALSE) -> 6 | T75: 0 | X75: =VLOOKUP(B75,[4]考勤分析!$A:$I,4,FALSE) -> 0.86770282 | Y75: =VLOOKUP(B75,[4]考勤分析!$A:$I,5,FALSE) -> FALSE | Z75: =VLOOKUP(B75,[4]考勤分析!$A:$I,6,FALSE) -> 51 | AA75: =VLOOKUP(B75,[4]考勤分析!$A:$I,7,FALSE) -> 11 | AB75: =VLOOKUP(B75,[4]考勤分析!$A:$I,8,FALSE) -> 0 | AC75: =VLOOKUP(B75,[4]考勤分析!$A:$I,9,FALSE) -> 1 | AD75: 0 | AE75: 0 | AF75: 0 | AG75: 0 | AH75: 0 | AI75: 0 | AK75: =VLOOKUP(B75,[3]总表!$B:$W,22,FALSE) -> #N/A
A76: 74 | B76: 陈彦百 | C76: 综合管理部 | D76: 2025届校招 | E76: 男 | F76: 0 | G76: 研究生 | H76: 澳大利亚国立大学 | L76: 0 | M76: 综合管理 | N76: 校园招聘 | S76: =VLOOKUP(B76,'[2]62人'!$B:$R,17,FALSE) -> 5 | T76: 2 | X76: =VLOOKUP(B76,[4]考勤分析!$A:$I,4,FALSE) -> 0.94238536 | Y76: =VLOOKUP(B76,[4]考勤分析!$A:$I,5,FALSE) -> FALSE | Z76: =VLOOKUP(B76,[4]考勤分析!$A:$I,6,FALSE) -> 45 | AA76: =VLOOKUP(B76,[4]考勤分析!$A:$I,7,FALSE) -> 15 | AB76: =VLOOKUP(B76,[4]考勤分析!$A:$I,8,FALSE) -> 2 | AC76: =VLOOKUP(B76,[4]考勤分析!$A:$I,9,FALSE) -> 1 | AD76: 0 | AE76: 0 | AF76: 0 | AG76: 0 | AH76: 0 | AI76: 0 | AK76: =VLOOKUP(B76,[3]总表!$B:$W,22,FALSE) -> #N/A
A77: 75 | B77: 任若琳 | C77: 综合管理部 | D77: 2025届校招 | E77: 女 | F77: 0 | G77: 研究生 | H77: 香港大学 | L77: 0 | M77: 综合管理 | N77: 校园招聘 | S77: =VLOOKUP(B77,'[2]62人'!$B:$R,17,FALSE) -> 6 | T77: 2 | X77: =VLOOKUP(B77,[4]考勤分析!$A:$I,4,FALSE) -> 0.45403439 | Y77: =VLOOKUP(B77,[4]考勤分析!$A:$I,5,FALSE) -> FALSE | Z77: =VLOOKUP(B77,[4]考勤分析!$A:$I,6,FALSE) -> 60 | AA77: =VLOOKUP(B77,[4]考勤分析!$A:$I,7,FALSE) -> 3 | AB77: =VLOOKUP(B77,[4]考勤分析!$A:$I,8,FALSE) -> 0 | AC77: =VLOOKUP(B77,[4]考勤分析!$A:$I,9,FALSE) -> 0 | AD77: 0 | AE77: 0 | AF77: 0 | AG77: 0 | AH77: 0 | AI77: 0 | AK77: =VLOOKUP(B77,[3]总表!$B:$W,22,FALSE) -> #N/A
A78: 76 | B78: 沈子新 | C78: 综合管理部 | D78: 2025届校招 | E78: 女 | F78: 0 | G78: 研究生 | H78: 南加州大学 | L78: 0 | M78: 综合管理 | N78: 校园招聘 | S78: =VLOOKUP(B78,'[2]62人'!$B:$R,17,FALSE) -> 5 | T78: 3 | X78: =VLOOKUP(B78,[4]考勤分析!$A:$I,4,FALSE) -> 0.76149642 | Y78: =VLOOKUP(B78,[4]考勤分析!$A:$I,5,FALSE) -> FALSE | Z78: =VLOOKUP(B78,[4]考勤分析!$A:$I,6,FALSE) -> 49 | AA78: =VLOOKUP(B78,[4]考勤分析!$A:$I,7,FALSE) -> 12 | AB78: =VLOOKUP(B78,[4]考勤分析!$A:$I,8,FALSE) -> 0 | AC78: =VLOOKUP(B78,[4]考勤分析!$A:$I,9,FALSE) -> 1 | AD78: 0 | AE78: 0 | AF78: 0 | AG78: 0 | AH78: 0 | AI78: 0 | AK78: =VLOOKUP(B78,[3]总表!$B:$W,22,FALSE) -> #N/A
A79: 77 | B79: 张雨轩 | C79: 综合管理部 | D79: 2025届校招 | E79: 男 | F79: 0 | G79: 研究生 | H79: 圣路易斯华盛顿大学 | L79: 0 | M79: 轮岗培训 | N79: 校园招聘 | S79: =VLOOKUP(B79,'[2]62人'!$B:$R,17,FALSE) -> 8 | T79: 8 | X79: =VLOOKUP(B79,[4]考勤分析!$A:$I,4,FALSE) -> 1.8335802 | Y79: =VLOOKUP(B79,[4]考勤分析!$A:$I,5,FALSE) -> FALSE | Z79: =VLOOKUP(B79,[4]考勤分析!$A:$I,6,FALSE) -> 17 | AA79: =VLOOKUP(B79,[4]考勤分析!$A:$I,7,FALSE) -> 20 | AB79: =VLOOKUP(B79,[4]考勤分析!$A:$I,8,FALSE) -> 25 | AC79: =VLOOKUP(B79,[4]考勤分析!$A:$I,9,FALSE) -> 1 | AD79: 0 | AE79: 0 | AF79: 0 | AG79: 0 | AH79: 0 | AI79: 0 | AK79: =VLOOKUP(B79,[3]总表!$B:$W,22,FALSE) -> #N/A
A80: 78 | B80: 温皓文 | C80: 综合管理部 | D80: 2025届校招 | E80: 男 | F80: 0 | L80: 0 | M80: 轮岗培训 | N80: 校园招聘 | S80: =VLOOKUP(B80,'[2]62人'!$B:$R,17,FALSE) -> 10 | T80: 1 | X80: =VLOOKUP(B80,[4]考勤分析!$A:$I,4,FALSE) -> 1.1087231 | Y80: =VLOOKUP(B80,[4]考勤分析!$A:$I,5,FALSE) -> FALSE | Z80: =VLOOKUP(B80,[4]考勤分析!$A:$I,6,FALSE) -> 23 | AA80: =VLOOKUP(B80,[4]考勤分析!$A:$I,7,FALSE) -> 34 | AB80: =VLOOKUP(B80,[4]考勤分析!$A:$I,8,FALSE) -> 5 | AC80: =VLOOKUP(B80,[4]考勤分析!$A:$I,9,FALSE) -> 0 | AD80: 0 | AE80: 0 | AF80: 0 | AG80: 0 | AH80: 0 | AI80: 0 | AK80: =VLOOKUP(B80,[3]总表!$B:$W,22,FALSE) -> #N/A
A81: 79 | B81: 朱嘉玮 | C81: 综合管理部 | D81: 2025届校招 | E81: 男 | F81: 0 | L81: 0 | M81: 轮岗培训 | N81: 校园招聘 | S81: =VLOOKUP(B81,'[2]62人'!$B:$R,17,FALSE) -> 8 | T81: 1 | X81: =VLOOKUP(B81,[4]考勤分析!$A:$I,4,FALSE) -> 0.49823925 | Y81: =VLOOKUP(B81,[4]考勤分析!$A:$I,5,FALSE) -> FALSE | Z81: =VLOOKUP(B81,[4]考勤分析!$A:$I,6,FALSE) -> 57 | AA81: =VLOOKUP(B81,[4]考勤分析!$A:$I,7,FALSE) -> 5 | AB81: =VLOOKUP(B81,[4]考勤分析!$A:$I,8,FALSE) -> 0 | AC81: =VLOOKUP(B81,[4]考勤分析!$A:$I,9,FALSE) -> 0 | AD81: 0 | AE81: 0 | AF81: 0 | AG81: 0 | AH81: 0 | AI81: 0 | AK81: =VLOOKUP(B81,[3]总表!$B:$W,22,FALSE) -> #N/A
A82: 80 | B82: 吕晶 | C82: 综合管理部 | D82: 2025届校招 | E82: 女 | F82: 0 | L82: 0 | M82: 轮岗培训 | N82: 校园招聘 | S82: =VLOOKUP(B82,'[2]62人'!$B:$R,17,FALSE) -> 10 | T82: 6 | X82: =VLOOKUP(B82,[4]考勤分析!$A:$I,4,FALSE) -> 0.55059588 | Y82: =VLOOKUP(B82,[4]考勤分析!$A:$I,5,FALSE) -> FALSE | Z82: =VLOOKUP(B82,[4]考勤分析!$A:$I,6,FALSE) -> 58 | AA82: =VLOOKUP(B82,[4]考勤分析!$A:$I,7,FALSE) -> 3 | AB82: =VLOOKUP(B82,[4]考勤分析!$A:$I,8,FALSE) -> 1 | AC82: =VLOOKUP(B82,[4]考勤分析!$A:$I,9,FALSE) -> 0 | AD82: 0 | AE82: 0 | AF82: 0 | AG82: 0 | AH82: 0 | AI82: 0 | AK82: =VLOOKUP(B82,[3]总表!$B:$W,22,FALSE) -> #N/A
A83: 81 | B83: 刘雅雯 | C83: 综合管理部 | D83: 2025届校招 | E83: 女 | F83: 0 | L83: 0 | M83: 轮岗培训 | N83: 校园招聘 | S83: =VLOOKUP(B83,'[2]62人'!$B:$R,17,FALSE) -> 13 | T83: 13 | X83: =VLOOKUP(B83,[4]考勤分析!$A:$I,4,FALSE) -> 0.55214727 | Y83: =VLOOKUP(B83,[4]考勤分析!$A:$I,5,FALSE) -> FALSE | Z83: =VLOOKUP(B83,[4]考勤分析!$A:$I,6,FALSE) -> 59 | AA83: =VLOOKUP(B83,[4]考勤分析!$A:$I,7,FALSE) -> 3 | AB83: =VLOOKUP(B83,[4]考勤分析!$A:$I,8,FALSE) -> 1 | AC83: =VLOOKUP(B83,[4]考勤分析!$A:$I,9,FALSE) -> 0 | AD83: 0 | AE83: 0 | AF83: 0 | AG83: 0 | AH83: 0 | AI83: 0 | AK83: =VLOOKUP(B83,[3]总表!$B:$W,22,FALSE) -> #N/A
A84: 82 | B84: 成绘茜 | C84: 综合管理部 | D84: 2025届校招 | E84: 女 | F84: 0 | L84: 0 | M84: 轮岗培训 | N84: 校园招聘 | S84: =VLOOKUP(B84,'[2]62人'!$B:$R,17,FALSE) -> 17 | T84: 20 | X84: =VLOOKUP(B84,[4]考勤分析!$A:$I,4,FALSE) -> 0.46601254 | Y84: =VLOOKUP(B84,[4]考勤分析!$A:$I,5,FALSE) -> FALSE | Z84: =VLOOKUP(B84,[4]考勤分析!$A:$I,6,FALSE) -> 58 | AA84: =VLOOKUP(B84,[4]考勤分析!$A:$I,7,FALSE) -> 3 | AB84: =VLOOKUP(B84,[4]考勤分析!$A:$I,8,FALSE) -> 1 | AC84: =VLOOKUP(B84,[4]考勤分析!$A:$I,9,FALSE) -> 0 | AD84: 0 | AE84: 0 | AF84: 0 | AG84: 0 | AH84: 0 | AI84: 0 | AK84: =VLOOKUP(B84,[3]总表!$B:$W,22,FALSE) -> #N/A
A85: 83 | B85: 罗辰昊 | C85: 综合管理部 | D85: 2025届校招 | E85: 男 | F85: 0 | L85: 0 | M85: 轮岗培训 | N85: 校园招聘 | S85: =VLOOKUP(B85,'[2]62人'!$B:$R,17,FALSE) -> 12 | T85: 0 | X85: =VLOOKUP(B85,[4]考勤分析!$A:$I,4,FALSE) -> 0.98210317 | Y85: =VLOOKUP(B85,[4]考勤分析!$A:$I,5,FALSE) -> FALSE | Z85: =VLOOKUP(B85,[4]考勤分析!$A:$I,6,FALSE) -> 40 | AA85: =VLOOKUP(B85,[4]考勤分析!$A:$I,7,FALSE) -> 18 | AB85: =VLOOKUP(B85,[4]考勤分析!$A:$I,8,FALSE) -> 3 | AC85: =VLOOKUP(B85,[4]考勤分析!$A:$I,9,FALSE) -> 2 | AD85: 0 | AE85: 0 | AF85: 0 | AG85: 0 | AH85: 0 | AI85: 0 | AK85: =VLOOKUP(B85,[3]总表!$B:$W,22,FALSE) -> #N/A
A86: 84 | B86: 张漫 | C86: 综合管理部 | D86: 2025届校招 | E86: 女 | F86: 0 | L86: 0 | M86: 轮岗培训 | N86: 校园招聘 | S86: =VLOOKUP(B86,'[2]62人'!$B:$R,17,FALSE) -> 6 | T86: 7 | X86: =VLOOKUP(B86,[4]考勤分析!$A:$I,4,FALSE) -> 0.73634921 | Y86: =VLOOKUP(B86,[4]考勤分析!$A:$I,5,FALSE) -> FALSE | Z86: =VLOOKUP(B86,[4]考勤分析!$A:$I,6,FALSE) -> 49 | AA86: =VLOOKUP(B86,[4]考勤分析!$A:$I,7,FALSE) -> 11 | AB86: =VLOOKUP(B86,[4]考勤分析!$A:$I,8,FALSE) -> 2 | AC86: =VLOOKUP(B86,[4]考勤分析!$A:$I,9,FALSE) -> 1 | AD86: 0 | AE86: 0 | AF86: 0 | AG86: 0 | AH86: 0 | AI86: 0 | AK86: =VLOOKUP(B86,[3]总表!$B:$W,22,FALSE) -> #N/A
A87: 85 | B87: 宛蕾 | C87: 综合管理部 | D87: 2025届校招 | E87: 女 | F87: 0 | L87: 0 | M87: 轮岗培训 | N87: 校园招聘 | S87: =VLOOKUP(B87,'[2]62人'!$B:$R,17,FALSE) -> 11 | T87: 0 | X87: =VLOOKUP(B87,[4]考勤分析!$A:$I,4,FALSE) -> 0.33802867 | Y87: =VLOOKUP(B87,[4]考勤分析!$A:$I,5,FALSE) -> FALSE | Z87: =VLOOKUP(B87,[4]考勤分析!$A:$I,6,FALSE) -> 62 | AA87: =VLOOKUP(B87,[4]考勤分析!$A:$I,7,FALSE) -> 0 | AB87: =VLOOKUP(B87,[4]考勤分析!$A:$I,8,FALSE) -> 0 | AC87: =VLOOKUP(B87,[4]考勤分析!$A:$I,9,FALSE) -> 0 | AD87: 0 | AE87: 0 | AF87: 0 | AG87: 0 | AH87: 0 | AI87: 0 | AK87: =VLOOKUP(B87,[3]总表!$B:$W,22,FALSE) -> #N/A
A88: 86 | B88: 姚陈潇 | C88: 综合管理部 | D88: 2025届校招 | E88: 女 | F88: 0 | L88: 0 | M88: 轮岗培训 | N88: 校园招聘 | S88: =VLOOKUP(B88,'[2]62人'!$B:$R,17,FALSE) -> 15 | T88: 0 | X88: =VLOOKUP(B88,[4]考勤分析!$A:$I,4,FALSE) -> 0.550681 | Y88: =VLOOKUP(B88,[4]考勤分析!$A:$I,5,FALSE) -> FALSE | Z88: =VLOOKUP(B88,[4]考勤分析!$A:$I,6,FALSE) -> 58 | AA88: =VLOOKUP(B88,[4]考勤分析!$A:$I,7,FALSE) -> 2 | AB88: =VLOOKUP(B88,[4]考勤分析!$A:$I,8,FALSE) -> 1 | AC88: =VLOOKUP(B88,[4]考勤分析!$A:$I,9,FALSE) -> 1 | AD88: 0 | AE88: 0 | AF88: 0 | AG88: 0 | AH88: 0 | AI88: 0 | AK88: =VLOOKUP(B88,[3]总表!$B:$W,22,FALSE) -> #N/A
A89: 87 | B89: 朱宇畅 | C89: 综合管理部 | D89: 2025届校招 | E89: 女 | F89: 0 | L89: 0 | M89: 轮岗培训 | N89: 校园招聘 | S89: =VLOOKUP(B89,'[2]62人'!$B:$R,17,FALSE) -> 13 | T89: 19 | X89: =VLOOKUP(B89,[4]考勤分析!$A:$I,4,FALSE) -> 1.0216667 | Y89: =VLOOKUP(B89,[4]考勤分析!$A:$I,5,FALSE) -> FALSE | Z89: =VLOOKUP(B89,[4]考勤分析!$A:$I,6,FALSE) -> 50 | AA89: =VLOOKUP(B89,[4]考勤分析!$A:$I,7,FALSE) -> 5 | AB89: =VLOOKUP(B89,[4]考勤分析!$A:$I,8,FALSE) -> 3 | AC89: =VLOOKUP(B89,[4]考勤分析!$A:$I,9,FALSE) -> 1 | AD89: 0 | AE89: 0 | AF89: 0 | AG89: 0 | AH89: 0 | AI89: 0 | AK89: =VLOOKUP(B89,[3]总表!$B:$W,22,FALSE) -> #N/A
A90: 88 | B90: 廖宇杰 | C90: 综合管理部 | D90: 2025届校招 | E90: 男 | F90: 0 | L90: 0 | M90: 轮岗培训 | N90: 校园招聘 | S90: =VLOOKUP(B90,'[2]62人'!$B:$R,17,FALSE) -> 4 | T90: 1 | X90: =VLOOKUP(B90,[4]考勤分析!$A:$I,4,FALSE) -> 0.95938069 | Y90: =VLOOKUP(B90,[4]考勤分析!$A:$I,5,FALSE) -> FALSE | Z90: =VLOOKUP(B90,[4]考勤分析!$A:$I,6,FALSE) -> 45 | AA90: =VLOOKUP(B90,[4]考勤分析!$A:$I,7,FALSE) -> 12 | AB90: =VLOOKUP(B90,[4]考勤分析!$A:$I,8,FALSE) -> 1 | AC90: =VLOOKUP(B90,[4]考勤分析!$A:$I,9,FALSE) -> 3 | AD90: 0 | AE90: 0 | AF90: 0 | AG90: 0 | AH90: 0 | AI90: 0 | AK90: =VLOOKUP(B90,[3]总表!$B:$W,22,FALSE) -> #N/A
A91: 89 | B91: 陈睿菁 | C91: 综合管理部 | D91: 2025届校招 | E91: 女 | F91: 0 | L91: 0 | M91: 轮岗培训 | N91: 校园招聘 | S91: =VLOOKUP(B91,'[2]62人'!$B:$R,17,FALSE) -> 11 | T91: 0 | X91: =VLOOKUP(B91,[4]考勤分析!$A:$I,4,FALSE) -> 0.76289875 | Y91: =VLOOKUP(B91,[4]考勤分析!$A:$I,5,FALSE) -> FALSE | Z91: =VLOOKUP(B91,[4]考勤分析!$A:$I,6,FALSE) -> 51 | AA91: =VLOOKUP(B91,[4]考勤分析!$A:$I,7,FALSE) -> 7 | AB91: =VLOOKUP(B91,[4]考勤分析!$A:$I,8,FALSE) -> 4 | AC91: =VLOOKUP(B91,[4]考勤分析!$A:$I,9,FALSE) -> 0 | AD91: 0 | AE91: 0 | AF91: 0 | AG91: 0 | AH91: 0 | AI91: 0 | AK91: =VLOOKUP(B91,[3]总表!$B:$W,22,FALSE) -> #N/A
A92: 90 | B92: 单曙兵 | C92: 数据治理部 | D92: 负责人 | E92: 男 | F92: 15 | G92: 研究生 | H92: 中国科学技术大学/ 同济大学 | I92: 科长 | L92: 0 | M92: 负责人 | N92: 社会招聘 | O92: 党总支群工委员、 第三党支部书记 | R92: 2025行外发文1/行外获奖2 | S92: =VLOOKUP(B92,'[2]62人'!$B:$R,17,FALSE) -> 3 | T92: 0 | U92: 2 | X92: =VLOOKUP(B92,[4]考勤分析!$A:$I,4,FALSE) -> 1.2310009 | Y92: =VLOOKUP(B92,[4]考勤分析!$A:$I,5,FALSE) -> TRUE | Z92: =VLOOKUP(B92,[4]考勤分析!$A:$I,6,FALSE) -> 28 | AA92: =VLOOKUP(B92,[4]考勤分析!$A:$I,7,FALSE) -> 21 | AB92: =VLOOKUP(B92,[4]考勤分析!$A:$I,8,FALSE) -> 13 | AC92: =VLOOKUP(B92,[4]考勤分析!$A:$I,9,FALSE) -> 1 | AD92: 0 | AE92: 0 | AF92: 0 | AG92: 0 | AH92: 0 | AI92: 0 | AK92: =VLOOKUP(B92,[3]总表!$B:$W,22,FALSE) -> #N/A
A93: 91 | B93: 李凯达 | C93: 数据治理部 | D93: 架构安全组 | E93: 男 | F93: 3 | G93: 大学本科 | H93: 天津大学 | L93: 0 | M93: 数据安全 | N93: 校园招聘 | S93: =VLOOKUP(B93,'[2]62人'!$B:$R,17,FALSE) -> 7 | T93: 0 | X93: =VLOOKUP(B93,[4]考勤分析!$A:$I,4,FALSE) -> 1.5382258 | Y93: =VLOOKUP(B93,[4]考勤分析!$A:$I,5,FALSE) -> TRUE | Z93: =VLOOKUP(B93,[4]考勤分析!$A:$I,6,FALSE) -> 21 | AA93: =VLOOKUP(B93,[4]考勤分析!$A:$I,7,FALSE) -> 15 | AB93: =VLOOKUP(B93,[4]考勤分析!$A:$I,8,FALSE) -> 26 | AC93: =VLOOKUP(B93,[4]考勤分析!$A:$I,9,FALSE) -> 0 | AD93: 0 | AE93: 0 | AF93: 0 | AG93: 0 | AH93: 0 | AI93: 0 | AK93: =VLOOKUP(B93,[3]总表!$B:$W,22,FALSE) -> #N/A
A94: 92 | B94: 傅潜林 | C94: 数据治理部 | D94: 标准资产组 | E94: 男 | F94: 4 | G94: 研究生 | H94: 悉尼大学 | L94: 0 | M94: 数据治理 | N94: 社会招聘 | S94: =VLOOKUP(B94,'[2]62人'!$B:$R,17,FALSE) -> 1 | T94: 0 | X94: =VLOOKUP(B94,[4]考勤分析!$A:$I,4,FALSE) -> 0.46687739 | Y94: =VLOOKUP(B94,[4]考勤分析!$A:$I,5,FALSE) -> FALSE | Z94: =VLOOKUP(B94,[4]考勤分析!$A:$I,6,FALSE) -> 58 | AA94: =VLOOKUP(B94,[4]考勤分析!$A:$I,7,FALSE) -> 0 | AB94: =VLOOKUP(B94,[4]考勤分析!$A:$I,8,FALSE) -> 0 | AC94: =VLOOKUP(B94,[4]考勤分析!$A:$I,9,FALSE) -> 0 | AD94: 0 | AE94: 0 | AF94: 0 | AG94: 0 | AH94: 0 | AI94: 0 | AK94: =VLOOKUP(B94,[3]总表!$B:$W,22,FALSE) -> #N/A
A95: 93 | B95: 王玉祥 | C95: 数据治理部 | D95: 标准资产组 | E95: 男 | F95: 20 | G95: 研究生 | H95: 同济大学 | L95: 0 | M95: 数据治理 | N95: 社会招聘 | S95: =VLOOKUP(B95,'[2]62人'!$B:$R,17,FALSE) -> 1 | T95: 0 | W95: 1 | X95: =VLOOKUP(B95,[4]考勤分析!$A:$I,4,FALSE) -> 0.49258197 | Y95: =VLOOKUP(B95,[4]考勤分析!$A:$I,5,FALSE) -> FALSE | Z95: =VLOOKUP(B95,[4]考勤分析!$A:$I,6,FALSE) -> 58 | AA95: =VLOOKUP(B95,[4]考勤分析!$A:$I,7,FALSE) -> 3 | AB95: =VLOOKUP(B95,[4]考勤分析!$A:$I,8,FALSE) -> 0 | AC95: =VLOOKUP(B95,[4]考勤分析!$A:$I,9,FALSE) -> 0 | AD95: 0 | AE95: 0 | AF95: 0 | AG95: 0 | AH95: 0 | AI95: 0 | AK95: =VLOOKUP(B95,[3]总表!$B:$W,22,FALSE) -> #N/A
A96: 94 | B96: 李焕彰 | C96: 信息管理部 | D96: 负责人 | E96: 男 | F96: 14 | G96: 大学本科 | H96: 上海理工大学 | I96: 科长 | L96: 0 | M96: 负责人 | N96: 社会招聘 | S96: =VLOOKUP(B96,'[2]62人'!$B:$R,17,FALSE) -> 10 | T96: 0 | U96: 4 | X96: =VLOOKUP(B96,[4]考勤分析!$A:$I,4,FALSE) -> 4.5525128 | Y96: =VLOOKUP(B96,[4]考勤分析!$A:$I,5,FALSE) -> TRUE | Z96: =VLOOKUP(B96,[4]考勤分析!$A:$I,6,FALSE) -> 8 | AA96: =VLOOKUP(B96,[4]考勤分析!$A:$I,7,FALSE) -> 3 | AB96: =VLOOKUP(B96,[4]考勤分析!$A:$I,8,FALSE) -> 5 | AC96: =VLOOKUP(B96,[4]考勤分析!$A:$I,9,FALSE) -> 49 | AD96: 0 | AE96: 0 | AF96: 0 | AG96: 0 | AH96: 0 | AI96: 0 | AK96: =VLOOKUP(B96,[3]总表!$B:$W,22,FALSE) -> #N/A
A97: 95 | B97: 孙菡悦 | C97: 信息管理部 | D97: 分行BP | E97: 女 | F97: 3 | G97: 研究生 | H97: 华东师范大学 | L97: 0 | M97: 数据分析 | N97: 校园招聘 | R97: 24数据文化优秀贡献者 | S97: =VLOOKUP(B97,'[2]62人'!$B:$R,17,FALSE) -> 10 | T97: 0 | U97: 2 | W97: 2 | X97: =VLOOKUP(B97,[4]考勤分析!$A:$I,4,FALSE) -> 0.48395944 | Y97: =VLOOKUP(B97,[4]考勤分析!$A:$I,5,FALSE) -> FALSE | Z97: =VLOOKUP(B97,[4]考勤分析!$A:$I,6,FALSE) -> 57 | AA97: =VLOOKUP(B97,[4]考勤分析!$A:$I,7,FALSE) -> 5 | AB97: =VLOOKUP(B97,[4]考勤分析!$A:$I,8,FALSE) -> 0 | AC97: =VLOOKUP(B97,[4]考勤分析!$A:$I,9,FALSE) -> 1 | AD97: 1 | AE97: 2 | AF97: 0 | AG97: 0 | AH97: 0 | AI97: 0 | AK97: =VLOOKUP(B97,[3]总表!$B:$W,22,FALSE) -> #N/A
A98: 96 | B98: 刘思言 | C98: 信息管理部 | D98: 分行BP | E98: 男 | F98: 3 | G98: 研究生 | H98: 上海财经大学 | L98: 0 | M98: 数据分析 | N98: 校园招聘 | S98: =VLOOKUP(B98,'[2]62人'!$B:$R,17,FALSE) -> 11 | T98: 0 | W98: 2 | X98: =VLOOKUP(B98,[4]考勤分析!$A:$I,4,FALSE) -> 0.49654827 | Y98: =VLOOKUP(B98,[4]考勤分析!$A:$I,5,FALSE) -> FALSE | Z98: =VLOOKUP(B98,[4]考勤分析!$A:$I,6,FALSE) -> 61 | AA98: =VLOOKUP(B98,[4]考勤分析!$A:$I,7,FALSE) -> 0 | AB98: =VLOOKUP(B98,[4]考勤分析!$A:$I,8,FALSE) -> 0 | AC98: =VLOOKUP(B98,[4]考勤分析!$A:$I,9,FALSE) -> 0 | AD98: 0 | AE98: 0 | AF98: 0 | AG98: 0 | AH98: 0 | AI98: 0 | AK98: =VLOOKUP(B98,[3]总表!$B:$W,22,FALSE) -> #N/A
A99: 97 | B99: 李小萌 | C99: 信息管理部 | D99: 分行BP | E99: 女 | F99: =VLOOKUP(B99,累计工龄!A:B,2,FALSE) -> 1 | G99: 研究生 | H99: 大连理工大学 | L99: 0 | M99: 数据分析 | N99: 校园招聘 | S99: =VLOOKUP(B99,'[2]62人'!$B:$R,17,FALSE) -> 14 | T99: 0 | W99: 2 | X99: =VLOOKUP(B99,[4]考勤分析!$A:$I,4,FALSE) -> 0.63308743 | Y99: =VLOOKUP(B99,[4]考勤分析!$A:$I,5,FALSE) -> FALSE | Z99: =VLOOKUP(B99,[4]考勤分析!$A:$I,6,FALSE) -> 52 | AA99: =VLOOKUP(B99,[4]考勤分析!$A:$I,7,FALSE) -> 4 | AB99: =VLOOKUP(B99,[4]考勤分析!$A:$I,8,FALSE) -> 1 | AC99: =VLOOKUP(B99,[4]考勤分析!$A:$I,9,FALSE) -> 4 | AD99: 0 | AE99: 0 | AF99: 0 | AG99: 0 | AH99: 0 | AI99: 0 | AK99: =VLOOKUP(B99,[3]总表!$B:$W,22,FALSE) -> #N/A
A100: 98 | B100: 宋轲 | C100: 信息管理部 | D100: 分行BP | E100: 女 | F100: 8 | G100: 研究生 | H100: 上海交通大学 | L100: 0 | M100: 数据分析 | N100: 社会招聘 | S100: =VLOOKUP(B100,'[2]62人'!$B:$R,17,FALSE) -> 4 | T100: 0 | X100: =VLOOKUP(B100,[4]考勤分析!$A:$I,4,FALSE) -> 1.3371435 | Y100: =VLOOKUP(B100,[4]考勤分析!$A:$I,5,FALSE) -> FALSE | Z100: =VLOOKUP(B100,[4]考勤分析!$A:$I,6,FALSE) -> 14 | AA100: =VLOOKUP(B100,[4]考勤分析!$A:$I,7,FALSE) -> 41 | AB100: =VLOOKUP(B100,[4]考勤分析!$A:$I,8,FALSE) -> 5 | AC100: =VLOOKUP(B100,[4]考勤分析!$A:$I,9,FALSE) -> 0 | AD100: 0 | AE100: 0 | AF100: 0 | AG100: 0 | AH100: 0 | AI100: 0 | AK100: =VLOOKUP(B100,[3]总表!$B:$W,22,FALSE) -> #N/A
...

Sheet 2.2 工作负荷分析-开发类岗位
A1: 序号 | B1: 姓名 | C1: 基本信息 | J1: 工作饱和度量化 | W1: 饱和度量化 不饱和：平均加班时长1h以下/无变更任务无主管应用非组长骨干/科长评定不饱和 超负荷：季度变更任务≥10/加班4H以上超过30次/平均加班时长3H以上/科长评定超负荷 | X1: 工作内容 | AE1: 岗职适配程度
C2: 团队 | D2: 组 | E2: 性别 | F2: 累计工龄 | G2: 最高学历 | H2: 最高学历毕业院校 | I2: 组长/骨干标识 | J2: 平均加班时长 | K2: 工作时长高于部门均值 | L2: 1h以下 | M2: 加班1-2h频次 | N2: 加班2-4h频次 | O2: 加班4h以上频次 | P2: 牵头项目数量 | Q2: 牵头需求数量 | R2: 主管应用系统数量（近六个月有变更的数量） | S2: 新paso体系参与应用数量 | T2: 二季度变更任务数 | U2: 三季度变更任务数 | V2: 截止三季度扣分事件或缺陷 | X2: 当前重点工作项（前期已收集） | Y2: 当前P0级工作任务（主要投入的工程/项目/研发系统） | Z2: P0级工作投入占比 | AA2: 当前P1级工作任务（次要工作任务） | AB2: P1级工作投入占比 | AC2: 其余工作任务（如无可不填） | AD2: 如该员工休假，B角人员是谁（如无请填写无） | AE2: 任务难度与人员职级、技能匹配程度 任务难度远高/远低于个人能力 任务难度略高/略低于个人能力 基本适配 | AF2: 个人状态 不饱和 适中 超负荷
A3: 1 | B3: 黄哲睿 | C3: 数据开发部 | D3: 模型设计组 | E3: 男 | F3: 7 | G3: 大学本科 | H3: 南京大学 | I3: 组长 | J3: =VLOOKUP(B3,[3]加班情况分析!D:G,4,FALSE) -> 3.9553763 | K3: =VLOOKUP(B3,[3]加班情况分析!D:H,5,FALSE) -> TRUE | L3: =VLOOKUP(B3,[3]加班情况分析!D:L,6,FALSE) -> 8 | M3: =VLOOKUP($B3,[3]加班情况分析!$D:$L,7,FALSE) -> 2 | N3: =VLOOKUP($B3,[3]加班情况分析!$D:$L,8,FALSE) -> 12 | O3: =VLOOKUP(B3,[3]加班情况分析!D:L,9,FALSE) -> 40 | Q3: =VLOOKUP(B3,'[3]牵头需求（当前进行中）'!A:B,2,FALSE) -> 1 | S3: 1 | W3: 超负荷 | X3: 智芯工程牵头、数据架构（数据模型） | Y3: 组长，牵头模型组建立、数据架构数仓部分工作，智芯工作收尾 | Z3: 0.5 | AA3: 研究数据仓库肩负暨整体切换整合模型方案 | AB3: 0.5 | AE3: 任务难度略高/略低于个人能力 | AF3: 适中
A4: 2 | B4: 陆慧 | C4: 数据开发部 | D4: 模型设计组 | E4: 女 | F4: 13 | G4: 研究生 | H4: 南京大学 | I4: 骨干 | J4: =VLOOKUP(B4,[3]加班情况分析!D:G,4,FALSE) -> 2.7979837 | K4: =VLOOKUP(B4,[3]加班情况分析!D:H,5,FALSE) -> TRUE | L4: =VLOOKUP(B4,[3]加班情况分析!D:L,6,FALSE) -> 10 | M4: =VLOOKUP($B4,[3]加班情况分析!$D:$L,7,FALSE) -> 4 | N4: =VLOOKUP($B4,[3]加班情况分析!$D:$L,8,FALSE) -> 32 | O4: =VLOOKUP(B4,[3]加班情况分析!D:L,9,FALSE) -> 12 | S4: 1 | W4: 适中 | X4: 智芯工程整合模型（核心存款）、公共领域模型设计 | Y4: 牵头具体模型设计工作，参与整体切换方案、整合模型规范制定等工作 | Z4: 0.8 | AA4: 智芯整合模型收尾 | AB4: 0.2 | AE4: 基本适配 | AF4: 适中
A5: 3 | B5: 罗仁杰 | C5: 数据开发部 | D5: 需求接入组 | E5: 男 | F5: 20 | G5: 大学本科 | H5: 兰州理工大学 | I5: 组长 | J5: =VLOOKUP(B5,[3]加班情况分析!D:G,4,FALSE) -> 2.8332375 | K5: =VLOOKUP(B5,[3]加班情况分析!D:H,5,FALSE) -> TRUE | L5: =VLOOKUP(B5,[3]加班情况分析!D:L,6,FALSE) -> 3 | M5: =VLOOKUP($B5,[3]加班情况分析!$D:$L,7,FALSE) -> 10 | N5: =VLOOKUP($B5,[3]加班情况分析!$D:$L,8,FALSE) -> 38 | O5: =VLOOKUP(B5,[3]加班情况分析!D:L,9,FALSE) -> 7 | Q5: =VLOOKUP(B5,'[3]牵头需求（当前进行中）'!A:B,2,FALSE) -> 5 | R5: =VLOOKUP(B5,[3]主管应用系统数量!I:J,2,FALSE) -> 1 | S5: 1 | T5: =VLOOKUP(B5,[3]二季度变更任务!A:B,2,FALSE) -> 24 | U5: =VLOOKUP(B5,[3]三季度变更任务!A:B,2,FALSE) -> 13 | W5: 超负荷 | X5: 批量治理，批量运营，采集平台推广 | Y5: 牵头数据接入组工作，批量治理，批量运营，采集平台推广 | Z5: 0.7 | AA5: 采集平台推广，各类配合改造项目需求入仓工作 | AB5: 0.3 | AE5: 任务难度略高/略低于个人能力 | AF5: 适中
A6: 4 | B6: 李卓辉 | C6: 数据开发部 | D6: 需求接入组 | E6: 男 | F6: 18 | G6: 研究生 | H6: 华东师范大学 | I6: 骨干候选人 | J6: =VLOOKUP(B6,[3]加班情况分析!D:G,4,FALSE) -> 2.4295151 | K6: =VLOOKUP(B6,[3]加班情况分析!D:H,5,FALSE) -> FALSE | L6: =VLOOKUP(B6,[3]加班情况分析!D:L,6,FALSE) -> 0 | M6: =VLOOKUP($B6,[3]加班情况分析!$D:$L,7,FALSE) -> 10 | N6: =VLOOKUP($B6,[3]加班情况分析!$D:$L,8,FALSE) -> 49 | O6: =VLOOKUP(B6,[3]加班情况分析!D:L,9,FALSE) -> 0 | S6: 1 | U6: =VLOOKUP(B6,[3]三季度变更任务!A:B,2,FALSE) -> 1 | W6: 不饱和 | X6: 一表通衍生区应用 | Y6: 一表通衍生区，配合罗仁杰数据治理 | Z6: 1 | AE6: 任务难度略高/略低于个人能力 | AF6: 不饱和
A7: 5 | B7: 兰昕蕾 | C7: 数据开发部 | D7: 数仓开发组 | E7: 女 | F7: 4 | G7: 研究生 | H7: 华东师范大学 | I7: 组长 | J7: =VLOOKUP(B7,[3]加班情况分析!D:G,4,FALSE) -> 3.6498497 | K7: =VLOOKUP(B7,[3]加班情况分析!D:H,5,FALSE) -> TRUE | L7: =VLOOKUP(B7,[3]加班情况分析!D:L,6,FALSE) -> 3 | M7: =VLOOKUP($B7,[3]加班情况分析!$D:$L,7,FALSE) -> 4 | N7: =VLOOKUP($B7,[3]加班情况分析!$D:$L,8,FALSE) -> 24 | O7: =VLOOKUP(B7,[3]加班情况分析!D:L,9,FALSE) -> 30 | Q7: =VLOOKUP(B7,'[3]牵头需求（当前进行中）'!A:B,2,FALSE) -> 2 | S7: 1 | T7: =VLOOKUP(B7,[3]二季度变更任务!A:B,2,FALSE) -> 8 | U7: =VLOOKUP(B7,[3]三季度变更任务!A:B,2,FALSE) -> 7 | W7: 超负荷 | X7: 智芯工程、渠道集市、特征集市、图谱集市 | Y7: 组长牵头数仓开发组工作 | Z7: 0.5 | AA7: 对数据仓库开发工艺流程dataops、开发规范、减负等工作具体落地 | AB7: 0.5 | AE7: 任务难度略高/略低于个人能力 | AF7: 适中
A8: 6 | B8: 邹小芳 | C8: 数据开发部 | D8: 数仓开发组 | E8: 女 | F8: 11 | G8: 大学本科 | H8: 江西财经大学 | I8: 组长 | J8: =VLOOKUP(B8,[3]加班情况分析!D:G,4,FALSE) -> 2.6259748 | K8: =VLOOKUP(B8,[3]加班情况分析!D:H,5,FALSE) -> TRUE | L8: =VLOOKUP(B8,[3]加班情况分析!D:L,6,FALSE) -> 5 | M8: =VLOOKUP($B8,[3]加班情况分析!$D:$L,7,FALSE) -> 13 | N8: =VLOOKUP($B8,[3]加班情况分析!$D:$L,8,FALSE) -> 27 | O8: =VLOOKUP(B8,[3]加班情况分析!D:L,9,FALSE) -> 8 | Q8: =VLOOKUP(B8,'[3]牵头需求（当前进行中）'!A:B,2,FALSE) -> 2 | S8: 2 | W8: 超负荷 | X8: 征信牵头人 | Y8: 组长，数据应用组牵头人，征信牵头人 | Z8: 1 | AE8: 任务难度略高/略低于个人能力 | AF8: 超负荷
A9: 7 | B9: 丁晨 | C9: 数据开发部 | D9: 数仓开发组 | E9: 男 | F9: 3 | G9: 研究生 | H9: 南京信息工程大学 | I9: 组长 | J9: =VLOOKUP(B9,[3]加班情况分析!D:G,4,FALSE) -> 3.8709426 | K9: =VLOOKUP(B9,[3]加班情况分析!D:H,5,FALSE) -> TRUE | L9: =VLOOKUP(B9,[3]加班情况分析!D:L,6,FALSE) -> 1 | M9: =VLOOKUP($B9,[3]加班情况分析!$D:$L,7,FALSE) -> 4 | N9: =VLOOKUP($B9,[3]加班情况分析!$D:$L,8,FALSE) -> 23 | O9: =VLOOKUP(B9,[3]加班情况分析!D:L,9,FALSE) -> 33 | Q9: =VLOOKUP(B9,'[3]牵头需求（当前进行中）'!A:B,2,FALSE) -> 2 | R9: =VLOOKUP(B9,[3]主管应用系统数量!I:J,2,FALSE) -> 1 | S9: 3 | T9: =VLOOKUP(B9,[3]二季度变更任务!A:B,2,FALSE) -> 10 | U9: =VLOOKUP(B9,[3]三季度变更任务!A:B,2,FALSE) -> 6 | W9: 超负荷 | X9: 智芯工程、整合模型（核心公共）、金融市场集市 | Y9: 组长，拟纳入数据应用组，与邹小芳搭配 | Z9: 0.5 | AA9: 牵头机构改造工作 | AB9: 0.5 | AE9: 任务难度略高/略低于个人能力 | AF9: 适中
A10: 8 | B10: 康冉 | C10: 数据开发部 | D10: 项目管理团队 | E10: 女 | F10: =VLOOKUP(B10,[1]累计工龄!A:B,2,FALSE) -> 5 | G10: 研究生 | H10: 南京师范大学 | I10: 骨干 | J10: =VLOOKUP(B10,[3]加班情况分析!D:G,4,FALSE) -> 2.3188715 | K10: =VLOOKUP(B10,[3]加班情况分析!D:H,5,FALSE) -> FALSE | L10: =VLOOKUP(B10,[3]加班情况分析!D:L,6,FALSE) -> 11 | M10: =VLOOKUP($B10,[3]加班情况分析!$D:$L,7,FALSE) -> 7 | N10: =VLOOKUP($B10,[3]加班情况分析!$D:$L,8,FALSE) -> 24 | O10: =VLOOKUP(B10,[3]加班情况分析!D:L,9,FALSE) -> 6 | P10: =VLOOKUP(B10,'[3]牵头项目（当前进行中）'!A:B,2,FALSE) -> 3 | Q10: =VLOOKUP(B10,'[3]牵头需求（当前进行中）'!A:B,2,FALSE) -> 15 | R10: =VLOOKUP(B10,[3]主管应用系统数量!I:J,2,FALSE) -> 1 | S10: 1 | U10: =VLOOKUP(B10,[3]三季度变更任务!A:B,2,FALSE) -> 10 | W10: 超负荷 | Y10: 1104报送 | Z10: 1 | AE10: 基本适配 | AF10: 适中
A11: 67 | B11: 钱磊 | C11: 数据开发部 | D11: 应用开发组/监管报送 | E11: 男 | F11: 9 | G11: 大学本科 | H11: 海南大学 | I11: / | J11: =VLOOKUP(B11,[3]加班情况分析!D:G,4,FALSE) -> 4.0337366 | K11: =VLOOKUP(B11,[3]加班情况分析!D:H,5,FALSE) -> TRUE | L11: =VLOOKUP(B11,[3]加班情况分析!D:L,6,FALSE) -> 1 | M11: =VLOOKUP($B11,[3]加班情况分析!$D:$L,7,FALSE) -> 6 | N11: =VLOOKUP($B11,[3]加班情况分析!$D:$L,8,FALSE) -> 23 | O11: =VLOOKUP(B11,[3]加班情况分析!D:L,9,FALSE) -> 32 | P11: =VLOOKUP(B11,'[3]牵头项目（当前进行中）'!A:B,2,FALSE) -> 1 | Q11: =VLOOKUP(B11,'[3]牵头需求（当前进行中）'!A:B,2,FALSE) -> 7 | R11: =VLOOKUP(B11,[3]主管应用系统数量!I:J,2,FALSE) -> 1 | S11: 1 | T11: =VLOOKUP(B11,[3]二季度变更任务!A:B,2,FALSE) -> 1 | U11: =VLOOKUP(B11,[3]三季度变更任务!A:B,2,FALSE) -> 8 | W11: 超负荷 | X11: 新线监管组件、大集中、FAL | Y11: 新线监管组件、大集中、FAL | Z11: 1 | AE11: 基本适配 | AF11: 超负荷
A12: 10 | B12: 史朋飞 | C12: 数据平台部 | D12: 运维支持组 | E12: 男 | F12: 12 | G12: 大学本科 | H12: 河南理工大学 | I12: 组长 | J12: =VLOOKUP(B12,[3]加班情况分析!D:G,4,FALSE) -> 2.7478302 | K12: =VLOOKUP(B12,[3]加班情况分析!D:H,5,FALSE) -> TRUE | L12: =VLOOKUP(B12,[3]加班情况分析!D:L,6,FALSE) -> 3 | M12: =VLOOKUP($B12,[3]加班情况分析!$D:$L,7,FALSE) -> 5 | N12: =VLOOKUP($B12,[3]加班情况分析!$D:$L,8,FALSE) -> 42 | O12: =VLOOKUP(B12,[3]加班情况分析!D:L,9,FALSE) -> 3 | R12: =VLOOKUP(B12,[3]主管应用系统数量!I:J,2,FALSE) -> 1 | S12: 5 | T12: =VLOOKUP(B12,[3]二季度变更任务!A:B,2,FALSE) -> 2 | U12: =VLOOKUP(B12,[3]三季度变更任务!A:B,2,FALSE) -> 2 | V12: =VLOOKUP(B12,[3]责任事件及缺陷!A:B,2,FALSE) -> 1 | W12: 超负荷 | X12: 大数据集群运维监控治理、数仓任务调优、hadoop集群信创、分析圈客一体化、分行数字化、一表通、标签管理平台 | Y12: 大数据平台支持组负责工作，hadoop平台治理运维，hadoop信创调研 | Z12: 0.7 | AA12: 一体化运营平台cdp技术负责人 | AB12: 0.3 | AD12: 李天卓 | AE12: 基本适配 | AF12: 超负荷
A13: 11 | B13: 李天卓 | C13: 数据平台部 | D13: 运维支持组 | E13: 男 | F13: 5 | G13: 研究生 | H13: 上海师范大学 | I13: 骨干 | J13: =VLOOKUP(B13,[3]加班情况分析!D:G,4,FALSE) -> 2.278179 | K13: =VLOOKUP(B13,[3]加班情况分析!D:H,5,FALSE) -> TRUE | L13: =VLOOKUP(B13,[3]加班情况分析!D:L,6,FALSE) -> 3 | M13: =VLOOKUP($B13,[3]加班情况分析!$D:$L,7,FALSE) -> 33 | N13: =VLOOKUP($B13,[3]加班情况分析!$D:$L,8,FALSE) -> 11 | O13: =VLOOKUP(B13,[3]加班情况分析!D:L,9,FALSE) -> 7 | R13: =VLOOKUP(B13,[3]主管应用系统数量!I:J,2,FALSE) -> 2 | S13: 1 | U13: =VLOOKUP(B13,[3]三季度变更任务!A:B,2,FALSE) -> 1 | W13: 超负荷 | X13: 大数据平台运维优化、计算区平台开发治理、大数据规范优化修订、平台其他疑难杂症解决 | Y13: hadoop平台治理运维，hadoop信创调研。 | Z13: 0.6 | AA13: 司库数据中台建设牵头架构师，技术负责人 | AB13: 0.4 | AD13: 史朋飞 | AE13: 基本适配 | AF13: 超负荷
A14: 70 | B14: 吴小倩 | C14: 数据开发部 | D14: 应用开发组/监管报送 | E14: 女 | F14: 3 | G14: 大学本科 | H14: 电子科技大学 | I14: / | J14: =VLOOKUP(B14,[3]加班情况分析!D:G,4,FALSE) -> 3.0573878 | K14: =VLOOKUP(B14,[3]加班情况分析!D:H,5,FALSE) -> TRUE | L14: =VLOOKUP(B14,[3]加班情况分析!D:L,6,FALSE) -> 6 | M14: =VLOOKUP($B14,[3]加班情况分析!$D:$L,7,FALSE) -> 11 | N14: =VLOOKUP($B14,[3]加班情况分析!$D:$L,8,FALSE) -> 17 | O14: =VLOOKUP(B14,[3]加班情况分析!D:L,9,FALSE) -> 18 | P14: =VLOOKUP(B14,'[3]牵头项目（当前进行中）'!A:B,2,FALSE) -> 2 | Q14: =VLOOKUP(B14,'[3]牵头需求（当前进行中）'!A:B,2,FALSE) -> 5 | R14: =VLOOKUP(B14,[3]主管应用系统数量!I:J,2,FALSE) -> 1 | S14: 2 | U14: =VLOOKUP(B14,[3]三季度变更任务!A:B,2,FALSE) -> 14 | V14: =VLOOKUP(B14,[3]责任事件及缺陷!A:B,2,FALSE) -> 1 | W14: 超负荷 | X14: 审计署报送2.0、客户风险、支付信息报送、信息科技非现场监管 | Y14: 审计署报送2.0、客户风险、支付信息报送、信息科技非现场监管 | Z14: 1 | AE14: 基本适配 | AF14: 适中
A15: 13 | B15: 伍恒 | C15: 数据平台部 | D15: 工具开发组 | E15: 男 | F15: 7 | G15: 研究生 | H15: 武汉科技大学 | I15: 骨干 | J15: =VLOOKUP(B15,[3]加班情况分析!D:G,4,FALSE) -> 2.7303723 | K15: =VLOOKUP(B15,[3]加班情况分析!D:H,5,FALSE) -> TRUE | L15: =VLOOKUP(B15,[3]加班情况分析!D:L,6,FALSE) -> 5 | M15: =VLOOKUP($B15,[3]加班情况分析!$D:$L,7,FALSE) -> 25 | N15: =VLOOKUP($B15,[3]加班情况分析!$D:$L,8,FALSE) -> 8 | O15: =VLOOKUP(B15,[3]加班情况分析!D:L,9,FALSE) -> 9 | P15: =VLOOKUP(B15,'[3]牵头项目（当前进行中）'!A:B,2,FALSE) -> 1 | Q15: =VLOOKUP(B15,'[3]牵头需求（当前进行中）'!A:B,2,FALSE) -> 1 | R15: =VLOOKUP(B15,[3]主管应用系统数量!I:J,2,FALSE) -> 2 | S15: 2 | T15: =VLOOKUP(B15,[3]二季度变更任务!A:B,2,FALSE) -> 11 | U15: =VLOOKUP(B15,[3]三季度变更任务!A:B,2,FALSE) -> 38 | W15: 超负荷 | X15: 数据采集 | Y15: 数据采集后端开发 | Z15: 1 | AD15: 濮敏 | AE15: 基本适配 | AF15: 适中
A16: 14 | B16: 王正超 | C16: 数据平台部 | D16: 应用开发组 | E16: 男 | F16: 5 | G16: 研究生 | H16: 北京交通大学 | I16: 骨干 | J16: =VLOOKUP(B16,[3]加班情况分析!D:G,4,FALSE) -> 2.746523 | K16: =VLOOKUP(B16,[3]加班情况分析!D:H,5,FALSE) -> TRUE | L16: =VLOOKUP(B16,[3]加班情况分析!D:L,6,FALSE) -> 6 | M16: =VLOOKUP($B16,[3]加班情况分析!$D:$L,7,FALSE) -> 9 | N16: =VLOOKUP($B16,[3]加班情况分析!$D:$L,8,FALSE) -> 33 | O16: =VLOOKUP(B16,[3]加班情况分析!D:L,9,FALSE) -> 10 | P16: =VLOOKUP(B16,'[3]牵头项目（当前进行中）'!A:B,2,FALSE) -> 1 | Q16: =VLOOKUP(B16,'[3]牵头需求（当前进行中）'!A:B,2,FALSE) -> 14 | R16: =VLOOKUP(B16,[3]主管应用系统数量!I:J,2,FALSE) -> 1 | S16: 3 | T16: =VLOOKUP(B16,[3]二季度变更任务!A:B,2,FALSE) -> 14 | U16: =VLOOKUP(B16,[3]三季度变更任务!A:B,2,FALSE) -> 16 | V16: =VLOOKUP(B16,[3]责任事件及缺陷!A:B,2,FALSE) -> 2 | W16: 超负荷 | X16: CRM、PCCM、数库外部数据 | Y16: CRM小组负责人，主要负责对公crm，领导零售和同业crm | Z16: 1 | AD16: 佟嘉欣 | AE16: 基本适配 | AF16: 超负荷
A17: 15 | B17: 嵇雅娟 | C17: 数据平台部 | D17: 应用开发组 | E17: 女 | F17: 10 | G17: 大学本科 | H17: 中国科学技术大学 | I17: 骨干 | J17: =VLOOKUP(B17,[3]加班情况分析!D:G,4,FALSE) -> 1.1071405 | K17: =VLOOKUP(B17,[3]加班情况分析!D:H,5,FALSE) -> FALSE | L17: =VLOOKUP(B17,[3]加班情况分析!D:L,6,FALSE) -> 21 | M17: =VLOOKUP($B17,[3]加班情况分析!$D:$L,7,FALSE) -> 26 | N17: =VLOOKUP($B17,[3]加班情况分析!$D:$L,8,FALSE) -> 4 | O17: =VLOOKUP(B17,[3]加班情况分析!D:L,9,FALSE) -> 0 | Q17: =VLOOKUP(B17,'[3]牵头需求（当前进行中）'!A:B,2,FALSE) -> 5 | R17: =VLOOKUP(B17,[3]主管应用系统数量!I:J,2,FALSE) -> 3 | S17: 2 | T17: =VLOOKUP(B17,[3]二季度变更任务!A:B,2,FALSE) -> 5 | U17: =VLOOKUP(B17,[3]三季度变更任务!A:B,2,FALSE) -> 9 | V17: =VLOOKUP(B17,[3]责任事件及缺陷!A:B,2,FALSE) -> 3 | W17: 适中 | X17: 反洗钱报送、反洗钱综合管理系统、自贸区报送、智芯、技改、信创 | Y17: 反洗钱小组负责人 | Z17: 1 | AD17: 张顺 | AE17: 基本适配 | AF17: 适中
A18: 16 | B18: 鞠爱宁 | C18: 数据平台部 | D18: 数据服务组 | E18: 男 | F18: 7 | G18: 研究生 | H18: 上海大学 | I18: 组长 | J18: =VLOOKUP(B18,[3]加班情况分析!D:G,4,FALSE) -> 3.1462903 | K18: =VLOOKUP(B18,[3]加班情况分析!D:H,5,FALSE) -> TRUE | L18: =VLOOKUP(B18,[3]加班情况分析!D:L,6,FALSE) -> 1 | M18: =VLOOKUP($B18,[3]加班情况分析!$D:$L,7,FALSE) -> 6 | N18: =VLOOKUP($B18,[3]加班情况分析!$D:$L,8,FALSE) -> 38 | O18: =VLOOKUP(B18,[3]加班情况分析!D:L,9,FALSE) -> 17 | Q18: =VLOOKUP(B18,'[3]牵头需求（当前进行中）'!A:B,2,FALSE) -> 1 | R18: =VLOOKUP(B18,[3]主管应用系统数量!I:J,2,FALSE) -> 1 | S18: 2 | T18: =VLOOKUP(B18,[3]二季度变更任务!A:B,2,FALSE) -> 10 | U18: =VLOOKUP(B18,[3]三季度变更任务!A:B,2,FALSE) -> 11 | V18: =VLOOKUP(B18,[3]责任事件及缺陷!A:B,2,FALSE) -> 2 | W18: 超负荷 | X18: 数据服务、实时平台、外数迁移、慧信工程 | Y18: 实时平台、数据服务中心、RAD | Z18: 0.6 | AA18: 外部数据、架构、面试 | AB18: 0.4 | AD18: 安新宜、刘金良 | AE18: 基本适配 | AF18: 适中
A19: 17 | B19: 魏佳翔 | C19: 数据平台部 | D19: 数据服务组 | E19: 男 | F19: 11 | G19: 大学本科 | H19: 大连海事大学 | I19: 组长 | J19: =VLOOKUP(B19,[3]加班情况分析!D:G,4,FALSE) -> 1.5513262 | K19: =VLOOKUP(B19,[3]加班情况分析!D:H,5,FALSE) -> FALSE | L19: =VLOOKUP(B19,[3]加班情况分析!D:L,6,FALSE) -> 34 | M19: =VLOOKUP($B19,[3]加班情况分析!$D:$L,7,FALSE) -> 14 | N19: =VLOOKUP($B19,[3]加班情况分析!$D:$L,8,FALSE) -> 8 | O19: =VLOOKUP(B19,[3]加班情况分析!D:L,9,FALSE) -> 6 | Q19: =VLOOKUP(B19,'[3]牵头需求（当前进行中）'!A:B,2,FALSE) -> 1 | S19: 2 | W19: 超负荷 | X19: 架构设计，UDAS、掌上行、RAD、RSD的应用开发和管理 | Y19: 应用开发组负责人，udas，掌上行 | Z19: 0.5 | AA19: 智能问数，司库风险模块 | AB19: 0.5 | AE19: 基本适配 | AF19: 超负荷
A20: 18 | B20: 杨婧 | C20: 智能创新部 | D20: AI产品运营组 | E20: 女 | F20: 4 | G20: 研究生 | H20: 中国科学技术大学 | I20: 组长 | J20: =VLOOKUP(B20,[3]加班情况分析!D:G,4,FALSE) -> 2.9616803 | K20: =VLOOKUP(B20,[3]加班情况分析!D:H,5,FALSE) -> TRUE | L20: =VLOOKUP(B20,[3]加班情况分析!D:L,6,FALSE) -> 7 | M20: =VLOOKUP($B20,[3]加班情况分析!$D:$L,7,FALSE) -> 11 | N20: =VLOOKUP($B20,[3]加班情况分析!$D:$L,8,FALSE) -> 26 | O20: =VLOOKUP(B20,[3]加班情况分析!D:L,9,FALSE) -> 17 | Q20: =VLOOKUP(B20,'[3]牵头需求（当前进行中）'!A:B,2,FALSE) -> 1 | R20: =VLOOKUP(B20,[3]主管应用系统数量!I:J,2,FALSE) -> 1 | S20: 2 | W20: 超负荷 | X20: 1、尽调助手 2、研报解读 3、数字化档案建设 4、风险合规智能化应用 5、办公助手建设 6、尽调报告辅助生成（hiagent智能体平台） 7、长文本智能分析优化需求 8、校招面试 | Y20: 尽调助手、数字化档案建设 | Z20: 0.5 | AA20: 研报解读 办公助手建设 | AB20: 0.2 | AC20: 协助团队负责人团队管理工作，负责AI产品运营组日常管理工作 材料准备工作：总行监管、分行监管、人行、以及其他公司的调研材料 | AD20: 无 | AE20: 基本适配 | AF20: 超负荷
A21: 19 | B21: 邱玥 | C21: 智能创新部 | D21: AI产品运营组 | E21: 女 | F21: 2 | G21: 研究生 | H21: 东华大学 | I21: 骨干 | J21: =VLOOKUP(B21,[3]加班情况分析!D:G,4,FALSE) -> 1.6532104 | K21: =VLOOKUP(B21,[3]加班情况分析!D:H,5,FALSE) -> FALSE | L21: =VLOOKUP(B21,[3]加班情况分析!D:L,6,FALSE) -> 7 | M21: =VLOOKUP($B21,[3]加班情况分析!$D:$L,7,FALSE) -> 47 | N21: =VLOOKUP($B21,[3]加班情况分析!$D:$L,8,FALSE) -> 5 | O21: =VLOOKUP(B21,[3]加班情况分析!D:L,9,FALSE) -> 2 | P21: =VLOOKUP(B21,'[3]牵头项目（当前进行中）'!A:B,2,FALSE) -> 1 | Q21: =VLOOKUP(B21,'[3]牵头需求（当前进行中）'!A:B,2,FALSE) -> 1 | R21: =VLOOKUP(B21,[3]主管应用系统数量!I:J,2,FALSE) -> 1 | S21: 2 | T21: =VLOOKUP(B21,[3]二季度变更任务!A:B,2,FALSE) -> 2 | U21: =VLOOKUP(B21,[3]三季度变更任务!A:B,2,FALSE) -> 4 | V21: =VLOOKUP(B21,[3]责任事件及缺陷!A:B,2,FALSE) -> 3 | W21: 适中 | X21: 1、零售CRM场景建设 2、数据部助理 3、知识运营体系建设 4、e搜技改&零星需求 | Y21: 零售CRM场景建设 | Z21: 0.4 | AA21: e搜技改&零星需求 | AB21: 0.3 | AD21: 蒋捷 | AE21: 基本适配 | AF21: 适中
A22: 20 | B22: 李响 | C22: 智能创新部 | D22: AI基础研发组 | E22: 男 | F22: 12 | G22: 大学本科 | H22: 哈尔滨工业大学 | I22: 组长 | J22: =VLOOKUP(B22,[3]加班情况分析!D:G,4,FALSE) -> 1.4479646 | K22: =VLOOKUP(B22,[3]加班情况分析!D:H,5,FALSE) -> FALSE | L22: =VLOOKUP(B22,[3]加班情况分析!D:L,6,FALSE) -> 25 | M22: =VLOOKUP($B22,[3]加班情况分析!$D:$L,7,FALSE) -> 21 | N22: =VLOOKUP($B22,[3]加班情况分析!$D:$L,8,FALSE) -> 6 | O22: =VLOOKUP(B22,[3]加班情况分析!D:L,9,FALSE) -> 3 | P22: =VLOOKUP(B22,'[3]牵头项目（当前进行中）'!A:B,2,FALSE) -> 2 | R22: =VLOOKUP(B22,[3]主管应用系统数量!I:J,2,FALSE) -> 2 | S22: 5 | T22: =VLOOKUP(B22,[3]二季度变更任务!A:B,2,FALSE) -> 16 | U22: =VLOOKUP(B22,[3]三季度变更任务!A:B,2,FALSE) -> 13 | V22: =VLOOKUP(B22,[3]责任事件及缺陷!A:B,2,FALSE) -> 1 | W22: 超负荷 | X22: 1、向量知识库项目 2、会话式人工智能服务技改 3、AIGC项目中客服场景建设 4、校招面试 | Y22: AIGC项目中客服场景建设 | Z22: 0.1 | AA22: 向量知识库建设 | AB22: 0.15 | AC22: "协助团队负责人团队管理工作，负责AI基础研发日常管理工作 | AD22: 无 | AE22: 任务难度略高/略低于个人能力 | AF22: 适中
A23: 21 | B23: 于中宝 | C23: 智能创新部 | D23: AI基础研发组 | E23: 男 | F23: 5 | G23: 研究生 | H23: 华东理工大学 | I23: 骨干 | J23: =VLOOKUP(B23,[3]加班情况分析!D:G,4,FALSE) -> 2.2854211 | K23: =VLOOKUP(B23,[3]加班情况分析!D:H,5,FALSE) -> TRUE | L23: =VLOOKUP(B23,[3]加班情况分析!D:L,6,FALSE) -> 3 | M23: =VLOOKUP($B23,[3]加班情况分析!$D:$L,7,FALSE) -> 36 | N23: =VLOOKUP($B23,[3]加班情况分析!$D:$L,8,FALSE) -> 14 | O23: =VLOOKUP(B23,[3]加班情况分析!D:L,9,FALSE) -> 9 | P23: =VLOOKUP(B23,'[3]牵头项目（当前进行中）'!A:B,2,FALSE) -> 2 | Q23: =VLOOKUP(B23,'[3]牵头需求（当前进行中）'!A:B,2,FALSE) -> 2 | R23: =VLOOKUP(B23,[3]主管应用系统数量!I:J,2,FALSE) -> 1 | S23: 3 | T23: =VLOOKUP(B23,[3]二季度变更任务!A:B,2,FALSE) -> 9 | U23: =VLOOKUP(B23,[3]三季度变更任务!A:B,2,FALSE) -> 5 | W23: 超负荷 | X23: 1、关联图谱平台技改项目 2、大模型应用项目（800w项目需求对接梳理工作） 3、知识图谱在员工异常行为检测方面的应用 4、隐私计算外部产品引入 5、AI手机银行2.0 6、校招面试 | Y23: 大模型应用项目、关联图谱平台技改项目 | Z23: 0.4 | AA23: 隐私计算外部产品引入、知识图谱在员工异常行为检测方面的应用 | AB23: 0.35 | AE23: 基本适配 | AF23: 超负荷
A24: 22 | B24: 李梦霄 | C24: 智能创新部 | D24: 风险模型团队 | E24: 女 | F24: 5 | G24: 研究生 | H24: 华东理工大学 | I24: 组长 | J24: =VLOOKUP(B24,[3]加班情况分析!D:G,4,FALSE) -> 1.9988183 | K24: =VLOOKUP(B24,[3]加班情况分析!D:H,5,FALSE) -> FALSE | L24: =VLOOKUP(B24,[3]加班情况分析!D:L,6,FALSE) -> 11 | M24: =VLOOKUP($B24,[3]加班情况分析!$D:$L,7,FALSE) -> 19 | N24: =VLOOKUP($B24,[3]加班情况分析!$D:$L,8,FALSE) -> 27 | O24: =VLOOKUP(B24,[3]加班情况分析!D:L,9,FALSE) -> 2 | P24: =VLOOKUP(B24,'[3]牵头项目（当前进行中）'!A:B,2,FALSE) -> 1 | S24: 2 | W24: 适中 | X24: 1、模型管理 2、反电诈统筹 3、AI产品问题协助统筹 4、信用风险模型 5、校招面试 | Y24: 反电诈工作牵头 | Z24: 0.3 | AA24: AI模型资产 | AB24: 0.4 | AC24: 协助团队负责人团队管理工作，负责风险模型组日常管理工作 材料准备工作：协助编写汇报材料准备工作 | AD24: 无 | AE24: 基本适配 | AF24: 适中
A25: 23 | B25: 于俊杰 | C25: 智能创新部 | D25: 风险模型团队 | E25: 男 | F25: 2 | G25: 研究生 | H25: 华东理工大学 | I25: 骨干候选人 | J25: =VLOOKUP(B25,[3]加班情况分析!D:G,4,FALSE) -> 1.867327 | K25: =VLOOKUP(B25,[3]加班情况分析!D:H,5,FALSE) -> FALSE | L25: =VLOOKUP(B25,[3]加班情况分析!D:L,6,FALSE) -> 20 | M25: =VLOOKUP($B25,[3]加班情况分析!$D:$L,7,FALSE) -> 24 | N25: =VLOOKUP($B25,[3]加班情况分析!$D:$L,8,FALSE) -> 9 | O25: =VLOOKUP(B25,[3]加班情况分析!D:L,9,FALSE) -> 8 | P25: =VLOOKUP(B25,'[3]牵头项目（当前进行中）'!A:B,2,FALSE) -> 1 | R25: =VLOOKUP(B25,[3]主管应用系统数量!I:J,2,FALSE) -> 1 | S25: 1 | U25: =VLOOKUP(B25,[3]三季度变更任务!A:B,2,FALSE) -> 9 | W25: 适中 | X25: 1、MLOPS开发建设 2、大数据建模平台运维 | Y25: MLOPS开发建设 | Z25: 0.6 | AA25: 大数据建模平台运维 | AB25: 0.4 | AD25: 无 | AE25: 基本适配 | AF25: 适中
A26: 24 | B26: 周影 | C26: 数据开发部 | D26: 仓库开发组 | E26: 女 | F26: 6 | G26: 研究生 | H26: 湖南大学 | I26: 骨干 | J26: =VLOOKUP(B26,[3]加班情况分析!D:G,4,FALSE) -> 3.3079483 | K26: =VLOOKUP(B26,[3]加班情况分析!D:H,5,FALSE) -> TRUE | L26: =VLOOKUP(B26,[3]加班情况分析!D:L,6,FALSE) -> 0 | M26: =VLOOKUP($B26,[3]加班情况分析!$D:$L,7,FALSE) -> 12 | N26: =VLOOKUP($B26,[3]加班情况分析!$D:$L,8,FALSE) -> 30 | O26: =VLOOKUP(B26,[3]加班情况分析!D:L,9,FALSE) -> 15 | Q26: =VLOOKUP(B26,'[3]牵头需求（当前进行中）'!A:B,2,FALSE) -> 3 | S26: 1 | W26: 超负荷 | X26: 智芯工程、整合模型（核心存款）、零售领域模型设计 | Y26: 整合模型（核心存款）、零售领域模型设计 | Z26: 1 | AE26: 基本适配 | AF26: 适中
A27: 25 | B27: 姚志环 | C27: 数据开发部 | D27: 仓库开发组 | E27: 女 | F27: 5 | G27: 研究生 | H27: 华东理工大学 | I27: 骨干 | J27: =VLOOKUP(B27,[3]加班情况分析!D:G,4,FALSE) -> 1.9892433 | K27: =VLOOKUP(B27,[3]加班情况分析!D:H,5,FALSE) -> FALSE | L27: =VLOOKUP(B27,[3]加班情况分析!D:L,6,FALSE) -> 6 | M27: =VLOOKUP($B27,[3]加班情况分析!$D:$L,7,FALSE) -> 33 | N27: =VLOOKUP($B27,[3]加班情况分析!$D:$L,8,FALSE) -> 14 | O27: =VLOOKUP(B27,[3]加班情况分析!D:L,9,FALSE) -> 5 | S27: 1 | T27: =VLOOKUP(B27,[3]二季度变更任务!A:B,2,FALSE) -> 4 | U27: =VLOOKUP(B27,[3]三季度变更任务!A:B,2,FALSE) -> 7 | W27: 适中 | X27: 两大工程、对公领域模型设计、票易贷项目 | Y27: 对公领域模型设计 | Z27: 1 | AE27: 基本适配 | AF27: 适中
A28: 26 | B28: 林幸 | C28: 数据开发部 | D28: 仓库开发组 | E28: 女 | F28: 3 | G28: 研究生 | H28: 东北大学 | I28: 骨干 | J28: =VLOOKUP(B28,[3]加班情况分析!D:G,4,FALSE) -> 3.2112524 | K28: =VLOOKUP(B28,[3]加班情况分析!D:H,5,FALSE) -> TRUE | L28: =VLOOKUP(B28,[3]加班情况分析!D:L,6,FALSE) -> 5 | M28: =VLOOKUP($B28,[3]加班情况分析!$D:$L,7,FALSE) -> 7 | N28: =VLOOKUP($B28,[3]加班情况分析!$D:$L,8,FALSE) -> 30 | O28: =VLOOKUP(B28,[3]加班情况分析!D:L,9,FALSE) -> 15 | P28: =VLOOKUP(B28,'[3]牵头项目（当前进行中）'!A:B,2,FALSE) -> 1 | Q28: =VLOOKUP(B28,'[3]牵头需求（当前进行中）'!A:B,2,FALSE) -> 3 | R28: =VLOOKUP(B28,[3]主管应用系统数量!I:J,2,FALSE) -> 1 | S28: 1 | T28: =VLOOKUP(B28,[3]二季度变更任务!A:B,2,FALSE) -> 8 | U28: =VLOOKUP(B28,[3]三季度变更任务!A:B,2,FALSE) -> 9 | W28: 超负荷 | X28: 两大工程整合模型、计财集市、FTP项目 | Y28: 计财集市、司库项目 | Z28: 1 | AE28: 基本适配 | AF28: 适中
A29: 27 | B29: 骆静龙 | C29: 数据开发部 | D29: 应用开发组 | E29: 男 | F29: 2 | G29: 大学本科 | H29: 华东师范大学 | I29: 骨干 | J29: =VLOOKUP(B29,[3]加班情况分析!D:G,4,FALSE) -> 2.6957957 | K29: =VLOOKUP(B29,[3]加班情况分析!D:H,5,FALSE) -> TRUE | L29: =VLOOKUP(B29,[3]加班情况分析!D:L,6,FALSE) -> 5 | M29: =VLOOKUP($B29,[3]加班情况分析!$D:$L,7,FALSE) -> 10 | N29: =VLOOKUP($B29,[3]加班情况分析!$D:$L,8,FALSE) -> 33 | O29: =VLOOKUP(B29,[3]加班情况分析!D:L,9,FALSE) -> 11 | Q29: =VLOOKUP(B29,'[3]牵头需求（当前进行中）'!A:B,2,FALSE) -> 1 | S29: 1 | T29: =VLOOKUP(B29,[3]二季度变更任务!A:B,2,FALSE) -> 15 | U29: =VLOOKUP(B29,[3]三季度变更任务!A:B,2,FALSE) -> 10 | V29: =VLOOKUP(B29,[3]责任事件及缺陷!A:B,2,FALSE) -> 2 | W29: 超负荷 | X29: NRP集市（UDAS,hadoop侧） | Y29: NRP集市（UDAS,hadoop侧） | Z29: 1 | AE29: 基本适配 | AF29: 适中
A30: 28 | B30: 王言哲 | C30: 数据开发部 | D30: 应用开发组 | E30: 男 | F30: 3 | G30: 大学本科 | H30: 华东师范大学 | I30: 骨干 | J30: =VLOOKUP(B30,[3]加班情况分析!D:G,4,FALSE) -> 2.2557423 | K30: =VLOOKUP(B30,[3]加班情况分析!D:H,5,FALSE) -> FALSE | L30: =VLOOKUP(B30,[3]加班情况分析!D:L,6,FALSE) -> 1 | M30: =VLOOKUP($B30,[3]加班情况分析!$D:$L,7,FALSE) -> 39 | N30: =VLOOKUP($B30,[3]加班情况分析!$D:$L,8,FALSE) -> 17 | O30: =VLOOKUP(B30,[3]加班情况分析!D:L,9,FALSE) -> 4 | Q30: =VLOOKUP(B30,'[3]牵头需求（当前进行中）'!A:B,2,FALSE) -> 8 | S30: 1 | T30: =VLOOKUP(B30,[3]二季度变更任务!A:B,2,FALSE) -> 20 | U30: =VLOOKUP(B30,[3]三季度变更任务!A:B,2,FALSE) -> 19 | W30: 超负荷 | X30: 反洗钱报送 | Y30: 反洗钱报送 | Z30: 1 | AE30: 基本适配 | AF30: 适中
A31: 29 | B31: 马富强 | C31: 数据开发部 | D31: 仓库开发组 | E31: 男 | F31: 7 | G31: 大学本科 | H31: 上海理工大学 | I31: 骨干 | J31: =VLOOKUP(B31,[3]加班情况分析!D:G,4,FALSE) -> 3.151064 | K31: =VLOOKUP(B31,[3]加班情况分析!D:H,5,FALSE) -> TRUE | L31: =VLOOKUP(B31,[3]加班情况分析!D:L,6,FALSE) -> 1 | M31: =VLOOKUP($B31,[3]加班情况分析!$D:$L,7,FALSE) -> 2 | N31: =VLOOKUP($B31,[3]加班情况分析!$D:$L,8,FALSE) -> 50 | O31: =VLOOKUP(B31,[3]加班情况分析!D:L,9,FALSE) -> 6 | Q31: =VLOOKUP(B31,'[3]牵头需求（当前进行中）'!A:B,2,FALSE) -> 1 | S31: 1 | T31: =VLOOKUP(B31,[3]二季度变更任务!A:B,2,FALSE) -> 10 | U31: =VLOOKUP(B31,[3]三季度变更任务!A:B,2,FALSE) -> 13 | V31: =VLOOKUP(B31,[3]责任事件及缺陷!A:B,2,FALSE) -> 1 | W31: 超负荷 | X31: 风险集市牵头人 | Y31: 风险集市牵头人 | Z31: 1 | AE31: 基本适配 | AF31: 适中
A32: 30 | B32: 胡帆 | C32: 数据平台部 | D32: 数据服务组 | E32: 男 | F32: 3 | G32: 研究生 | H32: 华东理工大学 | I32: 骨干 | J32: =VLOOKUP(B32,[3]加班情况分析!D:G,4,FALSE) -> 2.6456657 | K32: =VLOOKUP(B32,[3]加班情况分析!D:H,5,FALSE) -> TRUE | L32: =VLOOKUP(B32,[3]加班情况分析!D:L,6,FALSE) -> 12 | M32: =VLOOKUP($B32,[3]加班情况分析!$D:$L,7,FALSE) -> 4 | N32: =VLOOKUP($B32,[3]加班情况分析!$D:$L,8,FALSE) -> 29 | O32: =VLOOKUP(B32,[3]加班情况分析!D:L,9,FALSE) -> 13 | R32: =VLOOKUP(B32,[3]主管应用系统数量!I:J,2,FALSE) -> 1 | S32: 1 | T32: =VLOOKUP(B32,[3]二季度变更任务!A:B,2,FALSE) -> 8 | U32: =VLOOKUP(B32,[3]三季度变更任务!A:B,2,FALSE) -> 10 | W32: 适中 | X32: RSD应用负责人 | Y32: RSD | Z32: 0.8 | AA32: 架构、AI代码助手 | AB32: 0.2 | AD32: 魏佳翔、曾敏锐 | AE32: 基本适配 | AF32: 适中
A33: 31 | B33: 陆凯华 | C33: 数据平台部 | D33: 数据服务组 | E33: 男 | F33: `1 | G33: 研究生 | H33: 苏州大学 | I33: 骨干 | J33: =VLOOKUP(B33,[3]加班情况分析!D:G,4,FALSE) -> 3.9148197 | K33: =VLOOKUP(B33,[3]加班情况分析!D:H,5,FALSE) -> TRUE | L33: =VLOOKUP(B33,[3]加班情况分析!D:L,6,FALSE) -> 11 | M33: =VLOOKUP($B33,[3]加班情况分析!$D:$L,7,FALSE) -> 11 | N33: =VLOOKUP($B33,[3]加班情况分析!$D:$L,8,FALSE) -> 8 | O33: =VLOOKUP(B33,[3]加班情况分析!D:L,9,FALSE) -> 27 | P33: =VLOOKUP(B33,'[3]牵头项目（当前进行中）'!A:B,2,FALSE) -> 1 | Q33: =VLOOKUP(B33,'[3]牵头需求（当前进行中）'!A:B,2,FALSE) -> 4 | R33: =VLOOKUP(B33,[3]主管应用系统数量!I:J,2,FALSE) -> 3 | S33: 4 | T33: =VLOOKUP(B33,[3]二季度变更任务!A:B,2,FALSE) -> 21 | U33: =VLOOKUP(B33,[3]三季度变更任务!A:B,2,FALSE) -> 35 | V33: =VLOOKUP(B33,[3]责任事件及缺陷!A:B,2,FALSE) -> 3 | W33: 超负荷 | X33: 联机服务集群、外部数据、企业资金流共享平台 | Y33: 外部数据、联机服务集群、RAD | Z33: 0.8 | AA33: 企业资金流共享平台 | AB33: 0.2 | AC33: 流程分析平台 | AD33: 任欣宇 | AE33: 基本适配 | AF33: 适中
A34: 32 | B34: 朱文川 | C34: 数据平台部 | D34: 工具开发组 | E34: 男 | F34: 2 | G34: 研究生 | H34: 上海大学 | I34: 骨干 | J34: =VLOOKUP(B34,[3]加班情况分析!D:G,4,FALSE) -> 1.5535153 | K34: =VLOOKUP(B34,[3]加班情况分析!D:H,5,FALSE) -> FALSE | L34: =VLOOKUP(B34,[3]加班情况分析!D:L,6,FALSE) -> 16 | M34: =VLOOKUP($B34,[3]加班情况分析!$D:$L,7,FALSE) -> 36 | N34: =VLOOKUP($B34,[3]加班情况分析!$D:$L,8,FALSE) -> 0 | O34: =VLOOKUP(B34,[3]加班情况分析!D:L,9,FALSE) -> 6 | S34: 2 | T34: =VLOOKUP(B34,[3]二季度变更任务!A:B,2,FALSE) -> 6 | U34: =VLOOKUP(B34,[3]三季度变更任务!A:B,2,FALSE) -> 6 | W34: 适中 | X34: Stella、调度、dataops开发 | Y34: dataops数据测试模块开发 | Z34: 0.8 | AA34: 调度开发 | AB34: 0.2 | AD34: 陈玉思 | AE34: 基本适配 | AF34: 适中
A35: 33 | B35: 崔建文 | C35: 智能创新部 | D35: 模型开发组 | E35: 男 | F35: 4 | G35: 研究生 | H35: 厦门大学 | I35: 骨干 | J35: =VLOOKUP(B35,[3]加班情况分析!D:G,4,FALSE) -> 2.7256206 | K35: =VLOOKUP(B35,[3]加班情况分析!D:H,5,FALSE) -> TRUE | L35: =VLOOKUP(B35,[3]加班情况分析!D:L,6,FALSE) -> 9 | M35: =VLOOKUP($B35,[3]加班情况分析!$D:$L,7,FALSE) -> 4 | N35: =VLOOKUP($B35,[3]加班情况分析!$D:$L,8,FALSE) -> 25 | O35: =VLOOKUP(B35,[3]加班情况分析!D:L,9,FALSE) -> 9 | P35: =VLOOKUP(B35,'[3]牵头项目（当前进行中）'!A:B,2,FALSE) -> 1 | Q35: =VLOOKUP(B35,'[3]牵头需求（当前进行中）'!A:B,2,FALSE) -> 2 | S35: 1 | W35: 适中 | X35: 1、反电诈模型建设 2、智能财报分析 3、校招面试 | Y35: 反电诈联合办公（牵头） | Z35: 0.6 | AA35: 智能财报分析 | AB35: 0.3 | AD35: 无 | AE35: 基本适配 | AF35: 适中
A36: 34 | B36: 贾世林 | C36: 智能创新部 | D36: AI基础研发组 | E36: 男 | F36: 4 | G36: 研究生 | H36: 上海师范大学 | I36: 骨干 | J36: =VLOOKUP(B36,[3]加班情况分析!D:G,4,FALSE) -> 1.9630242 | K36: =VLOOKUP(B36,[3]加班情况分析!D:H,5,FALSE) -> FALSE | L36: =VLOOKUP(B36,[3]加班情况分析!D:L,6,FALSE) -> 12 | M36: =VLOOKUP($B36,[3]加班情况分析!$D:$L,7,FALSE) -> 33 | N36: =VLOOKUP($B36,[3]加班情况分析!$D:$L,8,FALSE) -> 12 | O36: =VLOOKUP(B36,[3]加班情况分析!D:L,9,FALSE) -> 5 | P36: =VLOOKUP(B36,'[3]牵头项目（当前进行中）'!A:B,2,FALSE) -> 1 | Q36: =VLOOKUP(B36,'[3]牵头需求（当前进行中）'!A:B,2,FALSE) -> 1 | R36: =VLOOKUP(B36,[3]主管应用系统数量!I:J,2,FALSE) -> 1 | S36: 1 | T36: =VLOOKUP(B36,[3]二季度变更任务!A:B,2,FALSE) -> 7 | U36: =VLOOKUP(B36,[3]三季度变更任务!A:B,2,FALSE) -> 12 | V36: =VLOOKUP(B36,[3]责任事件及缺陷!A:B,2,FALSE) -> 1 | W36: 超负荷 | X36: AIGC生成式技术综合应用之企业级知识问答体系建设 1.大模型底座（千帆）平台负责人 2.负责大模型基础资源(GPU)以及各类开源模型行内引入、部署以及维护 3.大模型网关建设 4.AIGC生成式技术综合应用之企业级知识问答体系建设项目经理 5、校招面试 | Y36: 大模型基础服务部署、大模型平台建设 | Z36: 0.6 | AA36: 大模型网关 | AB36: 0.2 | AD36: 无 | AE36: 任务难度略高/略低于个人能力 | AF36: 超负荷
A37: 35 | B37: 陆文捷 | C37: 智能创新部 | D37: 模型开发组 | E37: 女 | F37: 1 | G37: 研究生 | H37: 苏州大学 | I37: 骨干 | J37: =VLOOKUP(B37,[3]加班情况分析!D:G,4,FALSE) -> 1.6193109 | K37: =VLOOKUP(B37,[3]加班情况分析!D:H,5,FALSE) -> FALSE | L37: =VLOOKUP(B37,[3]加班情况分析!D:L,6,FALSE) -> 15 | M37: =VLOOKUP($B37,[3]加班情况分析!$D:$L,7,FALSE) -> 20 | N37: =VLOOKUP($B37,[3]加班情况分析!$D:$L,8,FALSE) -> 16 | O37: =VLOOKUP(B37,[3]加班情况分析!D:L,9,FALSE) -> 1 | S37: 0 | W37: 不饱和 | X37: 1、智能对标/安全管控模型 2、数据血缘链路梳理 3、脚本转白皮书 | Y37: 脚本转白皮书、基于大模型的数据血缘链路梳理 | Z37: 0.5 | AA37: 智能对标/安全管控模型建设 | AB37: 0.5 | AD37: 无 | AE37: 基本适配 | AF37: 适中
A38: 36 | B38: 白迪 | C38: 数据平台部 | D38: 工具开发组&数据服务组负责人 | E38: 男 | F38: 6 | G38: 研究生 | H38: 东华大学 | I38: / | J38: =VLOOKUP(B38,[3]加班情况分析!D:G,4,FALSE) -> 2.0511558 | K38: =VLOOKUP(B38,[3]加班情况分析!D:H,5,FALSE) -> TRUE | L38: =VLOOKUP(B38,[3]加班情况分析!D:L,6,FALSE) -> 9 | M38: =VLOOKUP($B38,[3]加班情况分析!$D:$L,7,FALSE) -> 35 | N38: =VLOOKUP($B38,[3]加班情况分析!$D:$L,8,FALSE) -> 3 | O38: =VLOOKUP(B38,[3]加班情况分析!D:L,9,FALSE) -> 9 | S38: 0 | X38: 工具开发组&数据服务组管理工作 | Y38: 参与应用设计，推进团队应用自主研发 | Z38: 1 | AD38: 吴证 | AE38: 基本适配 | AF38: 适中
A39: 37 | B39: 濮敏 | C39: 数据平台部 | D39: 工具开发组 | E39: 女 | F39: 4 | G39: 研究生 | H39: 华东师范大学 | I39: / | J39: =VLOOKUP(B39,[3]加班情况分析!D:G,4,FALSE) -> 0.62686441 | K39: =VLOOKUP(B39,[3]加班情况分析!D:H,5,FALSE) -> FALSE | L39: =VLOOKUP(B39,[3]加班情况分析!D:L,6,FALSE) -> 56 | M39: =VLOOKUP($B39,[3]加班情况分析!$D:$L,7,FALSE) -> 3 | N39: =VLOOKUP($B39,[3]加班情况分析!$D:$L,8,FALSE) -> 0 | O39: =VLOOKUP(B39,[3]加班情况分析!D:L,9,FALSE) -> 0 | R39: =VLOOKUP(B39,[3]主管应用系统数量!I:J,2,FALSE) -> 1 | S39: 2 | T39: =VLOOKUP(B39,[3]二季度变更任务!A:B,2,FALSE) -> 2 | W39: 不饱和 | X39: 数据采集 | Y39: 数据采集前端开发 | Z39: 1 | AD39: 伍恒 | AE39: 基本适配 | AF39: 适中
A40: 38 | B40: 沈志贇 | C40: 数据平台部 | D40: 工具开发组 | E40: 男 | F40: 2 | G40: 大学本科 | H40: 上海大学 | I40: / | J40: =VLOOKUP(B40,[3]加班情况分析!D:G,4,FALSE) -> 1.4096553 | K40: =VLOOKUP(B40,[3]加班情况分析!D:H,5,FALSE) -> FALSE | L40: =VLOOKUP(B40,[3]加班情况分析!D:L,6,FALSE) -> 16 | M40: =VLOOKUP($B40,[3]加班情况分析!$D:$L,7,FALSE) -> 36 | N40: =VLOOKUP($B40,[3]加班情况分析!$D:$L,8,FALSE) -> 0 | O40: =VLOOKUP(B40,[3]加班情况分析!D:L,9,FALSE) -> 2 | Q40: =VLOOKUP(B40,'[3]牵头需求（当前进行中）'!A:B,2,FALSE) -> 2 | R40: =VLOOKUP(B40,[3]主管应用系统数量!I:J,2,FALSE) -> 1 | S40: 1 | T40: =VLOOKUP(B40,[3]二季度变更任务!A:B,2,FALSE) -> 1 | U40: =VLOOKUP(B40,[3]三季度变更任务!A:B,2,FALSE) -> 3 | W40: 适中 | X40: 数据采集 | Y40: 数据采集后端开发 | Z40: 1 | AD40: 伍恒 | AE40: 基本适配 | AF40: 适中
A41: 39 | B41: 王双钰 | C41: 数据平台部 | D41: 工具开发组 | E41: 女 | F41: 2 | G41: 研究生 | H41: 爱丁堡大学 | I41: / | J41: =VLOOKUP(B41,[3]加班情况分析!D:G,4,FALSE) -> 0.8265113 | K41: =VLOOKUP(B41,[3]加班情况分析!D:H,5,FALSE) -> FALSE | L41: =VLOOKUP(B41,[3]加班情况分析!D:L,6,FALSE) -> 41 | M41: =VLOOKUP($B41,[3]加班情况分析!$D:$L,7,FALSE) -> 18 | N41: =VLOOKUP($B41,[3]加班情况分析!$D:$L,8,FALSE) -> 0 | O41: =VLOOKUP(B41,[3]加班情况分析!D:L,9,FALSE) -> 0 | Q41: =VLOOKUP(B41,'[3]牵头需求（当前进行中）'!A:B,2,FALSE) -> 1 | S41: 1 | T41: =VLOOKUP(B41,[3]二季度变更任务!A:B,2,FALSE) -> 1 | U41: =VLOOKUP(B41,[3]三季度变更任务!A:B,2,FALSE) -> 3 | W41: 不饱和 | X41: Stella、调度、dataops项目需求管理及开发 | Y41: dataops项目需求管理及数据测试模块开发 | Z41: 0.7 | AA41: stella、调度项目管理、开发、运维 | AB41: 0.3 | AC41: 分行血缘解析 | AD41: 曹宁远 | AE41: 基本适配 | AF41: 适中
A42: 40 | B42: 吕丽丽 | C42: 数据平台部 | D42: 工具开发组 | E42: 女 | F42: 2 | G42: 研究生 | H42: 华威大学 | I42: / | J42: =VLOOKUP(B42,[3]加班情况分析!D:G,4,FALSE) -> 0.92640326 | K42: =VLOOKUP(B42,[3]加班情况分析!D:H,5,FALSE) -> FALSE | L42: =VLOOKUP(B42,[3]加班情况分析!D:L,6,FALSE) -> 41 | M42: =VLOOKUP($B42,[3]加班情况分析!$D:$L,7,FALSE) -> 15 | N42: =VLOOKUP($B42,[3]加班情况分析!$D:$L,8,FALSE) -> 1 | O42: =VLOOKUP(B42,[3]加班情况分析!D:L,9,FALSE) -> 1 | S42: 2 | W42: 不饱和 | X42: Stella、调度、dataops开发、部署 | Y42: dataops数据测试模块开发、部署 | Z42: 0.7 | AA42: stella、调度项目开发、部署、运维 | AB42: 0.3 | AD42: 朱文川 | AE42: 基本适配 | AF42: 适中
A43: 41 | B43: 陈玉思 | C43: 数据平台部 | D43: 工具开发组 | E43: 女 | F43: 1 | G43: 研究生 | H43: 河海大学 | I43: / | J43: =VLOOKUP(B43,[3]加班情况分析!D:G,4,FALSE) -> 1.2019769 | K43: =VLOOKUP(B43,[3]加班情况分析!D:H,5,FALSE) -> FALSE | L43: =VLOOKUP(B43,[3]加班情况分析!D:L,6,FALSE) -> 35 | M43: =VLOOKUP($B43,[3]加班情况分析!$D:$L,7,FALSE) -> 18 | N43: =VLOOKUP($B43,[3]加班情况分析!$D:$L,8,FALSE) -> 6 | O43: =VLOOKUP(B43,[3]加班情况分析!D:L,9,FALSE) -> 1 | S43: 2 | U43: =VLOOKUP(B43,[3]三季度变更任务!A:B,2,FALSE) -> 1 | W43: 适中 | X43: Stella、调度、dataops开发、测试 | Y43: dataops数据测试模块开发、测试 | Z43: 0.7 | AA43: stella、调度项目开发、测试、运维 | AB43: 0.3 | AC43: 数据对标小工具 | AD43: 吕丽丽 | AE43: 基本适配 | AF43: 适中
A44: 42 | B44: 周浩 | C44: 数据平台部 | D44: 数据服务组 | E44: 男 | F44: 5 | G44: 研究生 | H44: 太原理工大学 | I44: / | J44: =VLOOKUP(B44,[3]加班情况分析!D:G,4,FALSE) -> 2.4487286 | K44: =VLOOKUP(B44,[3]加班情况分析!D:H,5,FALSE) -> TRUE | L44: =VLOOKUP(B44,[3]加班情况分析!D:L,6,FALSE) -> 6 | M44: =VLOOKUP($B44,[3]加班情况分析!$D:$L,7,FALSE) -> 17 | N44: =VLOOKUP($B44,[3]加班情况分析!$D:$L,8,FALSE) -> 20 | O44: =VLOOKUP(B44,[3]加班情况分析!D:L,9,FALSE) -> 9 | Q44: =VLOOKUP(B44,'[3]牵头需求（当前进行中）'!A:B,2,FALSE) -> 2 | R44: =VLOOKUP(B44,[3]主管应用系统数量!I:J,2,FALSE) -> 3 | S44: 3 | T44: =VLOOKUP(B44,[3]二季度变更任务!A:B,2,FALSE) -> 8 | U44: =VLOOKUP(B44,[3]三季度变更任务!A:B,2,FALSE) -> 14 | V44: =VLOOKUP(B44,[3]责任事件及缺陷!A:B,2,FALSE) -> 1 | W44: 超负荷 | X44: RAD应用负责人、外部数据接入与管理、大智慧舆情 | Y44: RAD | Z44: 0.9 | AA44: 大智慧舆情、外数平台 | AB44: 0.1 | AD44: 魏佳翔、曾敏锐 | AE44: 任务难度略高/略低于个人能力 | AF44: 超负荷
A45: 43 | B45: 安新宜 | C45: 数据平台部 | D45: 数据服务组 | E45: 女 | F45: 2 | G45: 研究生 | H45: 南加州大学 | I45: / | J45: =VLOOKUP(B45,[3]加班情况分析!D:G,4,FALSE) -> 2.6151435 | K45: =VLOOKUP(B45,[3]加班情况分析!D:H,5,FALSE) -> TRUE | L45: =VLOOKUP(B45,[3]加班情况分析!D:L,6,FALSE) -> 21 | M45: =VLOOKUP($B45,[3]加班情况分析!$D:$L,7,FALSE) -> 13 | N45: =VLOOKUP($B45,[3]加班情况分析!$D:$L,8,FALSE) -> 4 | O45: =VLOOKUP(B45,[3]加班情况分析!D:L,9,FALSE) -> 22 | Q45: =VLOOKUP(B45,'[3]牵头需求（当前进行中）'!A:B,2,FALSE) -> 1 | S45: 1 | T45: =VLOOKUP(B45,[3]二季度变更任务!A:B,2,FALSE) -> 12 | U45: =VLOOKUP(B45,[3]三季度变更任务!A:B,2,FALSE) -> 19 | W45: 超负荷 | X45: 数据服务中心 | Y45: 数据服务中心 | Z45: 0.9 | AA45: 联机服务集群 | AB45: 0.1 | AD45: 鞠爱宁 | AE45: 基本适配 | AF45: 适中
A46: 44 | B46: 张放 | C46: 数据平台部 | D46: 数据服务组 | E46: 男 | F46: 2 | G46: 研究生 | H46: 南开大学 | I46: / | J46: =VLOOKUP(B46,[3]加班情况分析!D:G,4,FALSE) -> 3.7372904 | K46: =VLOOKUP(B46,[3]加班情况分析!D:H,5,FALSE) -> TRUE | L46: =VLOOKUP(B46,[3]加班情况分析!D:L,6,FALSE) -> 5 | M46: =VLOOKUP($B46,[3]加班情况分析!$D:$L,7,FALSE) -> 11 | N46: =VLOOKUP($B46,[3]加班情况分析!$D:$L,8,FALSE) -> 12 | O46: =VLOOKUP(B46,[3]加班情况分析!D:L,9,FALSE) -> 25 | P46: =VLOOKUP(B46,'[3]牵头项目（当前进行中）'!A:B,2,FALSE) -> 1 | Q46: =VLOOKUP(B46,'[3]牵头需求（当前进行中）'!A:B,2,FALSE) -> 3 | R46: =VLOOKUP(B46,[3]主管应用系统数量!I:J,2,FALSE) -> 2 | S46: 1 | T46: =VLOOKUP(B46,[3]二季度变更任务!A:B,2,FALSE) -> 21 | U46: =VLOOKUP(B46,[3]三季度变更任务!A:B,2,FALSE) -> 27 | W46: 超负荷 | X46: 人行征信应用负责人 | Y46: 慧信工程-征信管理项目经理、技术经理，人行征信应用负责人 | Z46: 1 | AD46: 万珊红 | AE46: 基本适配 | AF46: 适中
A47: 45 | B47: 任欣宇 | C47: 数据平台部 | D47: 数据服务组 | E47: 男 | F47: 0 | G47: 研究生 | H47: 长安大学 | I47: / | J47: =VLOOKUP(B47,[3]加班情况分析!D:G,4,FALSE) -> 2.3363796 | K47: =VLOOKUP(B47,[3]加班情况分析!D:H,5,FALSE) -> TRUE | L47: =VLOOKUP(B47,[3]加班情况分析!D:L,6,FALSE) -> 23 | M47: =VLOOKUP($B47,[3]加班情况分析!$D:$L,7,FALSE) -> 12 | N47: =VLOOKUP($B47,[3]加班情况分析!$D:$L,8,FALSE) -> 8 | O47: =VLOOKUP(B47,[3]加班情况分析!D:L,9,FALSE) -> 17 | Q47: =VLOOKUP(B47,'[3]牵头需求（当前进行中）'!A:B,2,FALSE) -> 1 | S47: 1 | T47: =VLOOKUP(B47,[3]二季度变更任务!A:B,2,FALSE) -> 23 | U47: =VLOOKUP(B47,[3]三季度变更任务!A:B,2,FALSE) -> 36 | V47: =VLOOKUP(B47,[3]责任事件及缺陷!A:B,2,FALSE) -> 2 | W47: 超负荷 | X47: 外部数据管理 | Y47: 外数平台 | Z47: 0.9 | AA47: 数据服务中心 | AB47: 0.1 | AD47: 陆凯华、安新宜 | AE47: 基本适配 | AF47: 适中
A48: 46 | B48: 刘金良 | C48: 数据平台部 | D48: 数据服务组 | E48: 男 | F48: 12 | G48: 研究生 | H48: 浙江工业大学 | I48: / | J48: =VLOOKUP(B48,[3]加班情况分析!D:G,4,FALSE) -> 2.8252726 | K48: =VLOOKUP(B48,[3]加班情况分析!D:H,5,FALSE) -> TRUE | L48: =VLOOKUP(B48,[3]加班情况分析!D:L,6,FALSE) -> 1 | M48: =VLOOKUP($B48,[3]加班情况分析!$D:$L,7,FALSE) -> 6 | N48: =VLOOKUP($B48,[3]加班情况分析!$D:$L,8,FALSE) -> 42 | O48: =VLOOKUP(B48,[3]加班情况分析!D:L,9,FALSE) -> 5 | R48: =VLOOKUP(B48,[3]主管应用系统数量!I:J,2,FALSE) -> 1 | S48: 3 | T48: =VLOOKUP(B48,[3]二季度变更任务!A:B,2,FALSE) -> 1 | U48: =VLOOKUP(B48,[3]三季度变更任务!A:B,2,FALSE) -> 2 | W48: 适中 | X48: 架构、实时开发平台、数据采集平台 | Y48: 实时开发平台、数据采集平台、DataOps | Z48: 0.8 | AA48: 架构 | AB48: 0.2 | AD48: 鞠爱宁 | AE48: 基本适配 | AF48: 适中
A49: 47 | B49: 吴证 | C49: 数据平台部 | D49: 应用开发组&运维支持组负责人 | E49: 男 | F49: 17 | G49: 研究生 | H49: 上海交通大学 | I49: / | J49: =VLOOKUP(B49,[3]加班情况分析!D:G,4,FALSE) -> 1.8344242 | K49: =VLOOKUP(B49,[3]加班情况分析!D:H,5,FALSE) -> FALSE | L49: =VLOOKUP(B49,[3]加班情况分析!D:L,6,FALSE) -> 12 | M49: =VLOOKUP($B49,[3]加班情况分析!$D:$L,7,FALSE) -> 25 | N49: =VLOOKUP($B49,[3]加班情况分析!$D:$L,8,FALSE) -> 17 | O49: =VLOOKUP(B49,[3]加班情况分析!D:L,9,FALSE) -> 1 | S49: 0 | X49: 应用开发组&运维支持组管理工作 | Y49: 负责平台部应用建设和平台支持 | Z49: 1 | AD49: 白迪 | AE49: 基本适配 | AF49: 超负荷
A50: 48 | B50: 梅凯磊 | C50: 数据平台部 | D50: 应用开发组 | E50: 男 | F50: 3 | G50: 研究生 | H50: 华东师范大学 | I50: / | J50: =VLOOKUP(B50,[3]加班情况分析!D:G,4,FALSE) -> 1.4830021 | K50: =VLOOKUP(B50,[3]加班情况分析!D:H,5,FALSE) -> FALSE | L50: =VLOOKUP(B50,[3]加班情况分析!D:L,6,FALSE) -> 24 | M50: =VLOOKUP($B50,[3]加班情况分析!$D:$L,7,FALSE) -> 20 | N50: =VLOOKUP($B50,[3]加班情况分析!$D:$L,8,FALSE) -> 4 | O50: =VLOOKUP(B50,[3]加班情况分析!D:L,9,FALSE) -> 4 | P50: =VLOOKUP(B50,'[3]牵头项目（当前进行中）'!A:B,2,FALSE) -> 2 | Q50: =VLOOKUP(B50,'[3]牵头需求（当前进行中）'!A:B,2,FALSE) -> 4 | R50: =VLOOKUP(B50,[3]主管应用系统数量!I:J,2,FALSE) -> 2 | S50: 2 | T50: =VLOOKUP(B50,[3]二季度变更任务!A:B,2,FALSE) -> 9 | U50: =VLOOKUP(B50,[3]三季度变更任务!A:B,2,FALSE) -> 13 | W50: 适中 | X50: UDAS、掌上行 | Y50: udas，掌上行应用技术负责人 | Z50: 0.5 | AA50: 智能问数和司库风险模块建设 | AB50: 0.5 | AD50: 魏佳翔 | AE50: 基本适配 | AF50: 适中
A51: 49 | B51: 李敏吉 | C51: 数据平台部 | D51: 应用开发组 | E51: 男 | F51: 1 | G51: 研究生 | H51: 华东师范大学 | I51: / | J51: =VLOOKUP(B51,[3]加班情况分析!D:G,4,FALSE) -> 2.2777166 | K51: =VLOOKUP(B51,[3]加班情况分析!D:H,5,FALSE) -> TRUE | L51: =VLOOKUP(B51,[3]加班情况分析!D:L,6,FALSE) -> 12 | M51: =VLOOKUP($B51,[3]加班情况分析!$D:$L,7,FALSE) -> 22 | N51: =VLOOKUP($B51,[3]加班情况分析!$D:$L,8,FALSE) -> 12 | O51: =VLOOKUP(B51,[3]加班情况分析!D:L,9,FALSE) -> 13 | P51: =VLOOKUP(B51,'[3]牵头项目（当前进行中）'!A:B,2,FALSE) -> 1 | Q51: =VLOOKUP(B51,'[3]牵头需求（当前进行中）'!A:B,2,FALSE) -> 3 | R51: =VLOOKUP(B51,[3]主管应用系统数量!I:J,2,FALSE) -> 3 | S51: 3 | T51: =VLOOKUP(B51,[3]二季度变更任务!A:B,2,FALSE) -> 5 | U51: =VLOOKUP(B51,[3]三季度变更任务!A:B,2,FALSE) -> 5 | W51: 超负荷 | X51: 可视化报表助手、数据门户、SAS | Y51: Finebi，SAS，数据门户应用技术负责人 | Z51: 0.5 | AA51: 司库 | AE51: 基本适配 | AF51: 超负荷
A52: 50 | B52: 万珊红 | C52: 数据平台部 | D52: 应用开发组 | E52: 女 | F52: 4 | G52: 研究生 | H52: 武汉大学 | I52: / | J52: =VLOOKUP(B52,[3]加班情况分析!D:G,4,FALSE) -> 3.4544192 | K52: =VLOOKUP(B52,[3]加班情况分析!D:H,5,FALSE) -> TRUE | L52: =VLOOKUP(B52,[3]加班情况分析!D:L,6,FALSE) -> 15 | M52: =VLOOKUP($B52,[3]加班情况分析!$D:$L,7,FALSE) -> 9 | N52: =VLOOKUP($B52,[3]加班情况分析!$D:$L,8,FALSE) -> 4 | O52: =VLOOKUP(B52,[3]加班情况分析!D:L,9,FALSE) -> 27 | Q52: =VLOOKUP(B52,'[3]牵头需求（当前进行中）'!A:B,2,FALSE) -> 1 | R52: =VLOOKUP(B52,[3]主管应用系统数量!I:J,2,FALSE) -> 2 | S52: 1 | T52: =VLOOKUP(B52,[3]二季度变更任务!A:B,2,FALSE) -> 15 | U52: =VLOOKUP(B52,[3]三季度变更任务!A:B,2,FALSE) -> 19 | V52: =VLOOKUP(B52,[3]责任事件及缺陷!A:B,2,FALSE) -> 3 | W52: 超负荷 | X52: 人行征信、魔镜、信用查询网关 | Y52: 慧信征信，魔镜技术负责人 | Z52: 1 | AD52: 张放 | AE52: 基本适配 | AF52: 适中
A53: 51 | B53: 刘惠 | C53: 数据平台部 | D53: 应用开发组 | E53: 女 | F53: 8 | G53: 研究生 | H53: 浙江大学 | I53: / | J53: =VLOOKUP(B53,[3]加班情况分析!D:G,4,FALSE) -> 0.84174691 | K53: =VLOOKUP(B53,[3]加班情况分析!D:H,5,FALSE) -> FALSE | L53: =VLOOKUP(B53,[3]加班情况分析!D:L,6,FALSE) -> 41 | M53: =VLOOKUP($B53,[3]加班情况分析!$D:$L,7,FALSE) -> 1 | N53: =VLOOKUP($B53,[3]加班情况分析!$D:$L,8,FALSE) -> 1 | O53: =VLOOKUP(B53,[3]加班情况分析!D:L,9,FALSE) -> 2 | P53: =VLOOKUP(B53,'[3]牵头项目（当前进行中）'!A:B,2,FALSE) -> 1 | Q53: =VLOOKUP(B53,'[3]牵头需求（当前进行中）'!A:B,2,FALSE) -> 2 | R53: =VLOOKUP(B53,[3]主管应用系统数量!I:J,2,FALSE) -> 1 | S53: 2 | T53: =VLOOKUP(B53,[3]二季度变更任务!A:B,2,FALSE) -> 3 | U53: =VLOOKUP(B53,[3]三季度变更任务!A:B,2,FALSE) -> 2 | W53: 不饱和 | X53: 审计二期项目、试衣间项目、血缘平台 | Y53: 审计二期项目、试衣间项目、血缘平台 | Z53: 1 | AE53: 基本适配 | AF53: 适中
A54: 52 | B54: 佟嘉欣 | C54: 数据平台部 | D54: 应用开发组 | E54: 女 | F54: 0 | G54: 研究生 | H54: 华东师范大学 | I54: / | J54: =VLOOKUP(B54,[3]加班情况分析!D:G,4,FALSE) -> 2.20125 | K54: =VLOOKUP(B54,[3]加班情况分析!D:H,5,FALSE) -> TRUE | L54: =VLOOKUP(B54,[3]加班情况分析!D:L,6,FALSE) -> 23 | M54: =VLOOKUP($B54,[3]加班情况分析!$D:$L,7,FALSE) -> 20 | N54: =VLOOKUP($B54,[3]加班情况分析!$D:$L,8,FALSE) -> 4 | O54: =VLOOKUP(B54,[3]加班情况分析!D:L,9,FALSE) -> 15 | Q54: =VLOOKUP(B54,'[3]牵头需求（当前进行中）'!A:B,2,FALSE) -> 11 | S54: 1 | T54: =VLOOKUP(B54,[3]二季度变更任务!A:B,2,FALSE) -> 3 | U54: =VLOOKUP(B54,[3]三季度变更任务!A:B,2,FALSE) -> 10 | V54: =VLOOKUP(B54,[3]责任事件及缺陷!A:B,2,FALSE) -> 1 | W54: 适中 | X54: CRM | Y54: 主要负责零售crm | Z54: 1 | AD54: 王正超 | AE54: 基本适配 | AF54: 适中
A55: 53 | B55: 张顺 | C55: 数据平台部 | D55: 应用开发组 | E55: 女 | F55: 0 | G55: 研究生 | H55: 大连理工大学 | I55: / | J55: =VLOOKUP(B55,[3]加班情况分析!D:G,4,FALSE) -> 1.0663935 | K55: =VLOOKUP(B55,[3]加班情况分析!D:H,5,FALSE) -> FALSE | L55: =VLOOKUP(B55,[3]加班情况分析!D:L,6,FALSE) -> 28 | M55: =VLOOKUP($B55,[3]加班情况分析!$D:$L,7,FALSE) -> 30 | N55: =VLOOKUP($B55,[3]加班情况分析!$D:$L,8,FALSE) -> 2 | O55: =VLOOKUP(B55,[3]加班情况分析!D:L,9,FALSE) -> 0 | S55: 1 | T55: =VLOOKUP(B55,[3]二季度变更任务!A:B,2,FALSE) -> 3 | W55: 适中 | X55: 反洗钱报送、反洗钱综合管理系统、反洗钱技改项目 | Y55: 反洗钱报送、反洗钱综合管理系统、反洗钱技改项目 | Z55: 0.9 | AA55: 应用信创项目管理 | AB55: 0.1 | AD55: 嵇雅娟 | AE55: 基本适配 | AF55: 适中
A56: 54 | B56: 冯晓煜 | C56: 数据平台部 | D56: 运维支持组 | E56: 男 | F56: 5 | G56: 研究生 | H56: 东华大学 | I56: / | J56: =VLOOKUP(B56,[3]加班情况分析!D:G,4,FALSE) -> 1.6710667 | K56: =VLOOKUP(B56,[3]加班情况分析!D:H,5,FALSE) -> FALSE | L56: =VLOOKUP(B56,[3]加班情况分析!D:L,6,FALSE) -> 11 | M56: =VLOOKUP($B56,[3]加班情况分析!$D:$L,7,FALSE) -> 28 | N56: =VLOOKUP($B56,[3]加班情况分析!$D:$L,8,FALSE) -> 9 | O56: =VLOOKUP(B56,[3]加班情况分析!D:L,9,FALSE) -> 2 | S56: 1 | T56: =VLOOKUP(B56,[3]二季度变更任务!A:B,2,FALSE) -> 1 | U56: =VLOOKUP(B56,[3]三季度变更任务!A:B,2,FALSE) -> 2 | W56: 超负荷 | X56: DWS云平台&集群运维优化、数据同步&脱敏、数仓工具开发 | Y56: DWS数仓负责人 | Z56: 1 | AE56: 基本适配 | AF56: 超负荷
A57: 55 | B57: 冯潇 | C57: 数据平台部 | D57: 运维支持组 | E57: 女 | F57: 4 | G57: 研究生 | H57: 华东师范大学 | I57: / | J57: =VLOOKUP(B57,[3]加班情况分析!D:G,4,FALSE) -> 2.11335 | K57: =VLOOKUP(B57,[3]加班情况分析!D:H,5,FALSE) -> TRUE | L57: =VLOOKUP(B57,[3]加班情况分析!D:L,6,FALSE) -> 12 | M57: =VLOOKUP($B57,[3]加班情况分析!$D:$L,7,FALSE) -> 18 | N57: =VLOOKUP($B57,[3]加班情况分析!$D:$L,8,FALSE) -> 12 | O57: =VLOOKUP(B57,[3]加班情况分析!D:L,9,FALSE) -> 8 | P57: =VLOOKUP(B57,'[3]牵头项目（当前进行中）'!A:B,2,FALSE) -> 1 | R57: =VLOOKUP(B57,[3]主管应用系统数量!I:J,2,FALSE) -> 1 | S57: 2 | T57: =VLOOKUP(B57,[3]二季度变更任务!A:B,2,FALSE) -> 3 | U57: =VLOOKUP(B57,[3]三季度变更任务!A:B,2,FALSE) -> 5 | W57: 适中 | X57: 大数据集群运维、数仓任务调优、数据安全脱敏网关、用户即席查询治理和优化、大数据元数据知识同步数据门户 | Y57: hadoop平台运维，时效治理 | Z57: 0.8 | AA57: 数据查询网关 | AB57: 0.2 | AD57: 陈朗 | AE57: 基本适配 | AF57: 适中
A58: 56 | B58: 陈朗 | C58: 数据平台部 | D58: 运维支持组 | E58: 男 | F58: 1 | G58: 大学本科 | H58: 上海理工大学 | I58: / | J58: =VLOOKUP(B58,[3]加班情况分析!D:G,4,FALSE) -> 1.1193927 | K58: =VLOOKUP(B58,[3]加班情况分析!D:H,5,FALSE) -> FALSE | L58: =VLOOKUP(B58,[3]加班情况分析!D:L,6,FALSE) -> 30 | M58: =VLOOKUP($B58,[3]加班情况分析!$D:$L,7,FALSE) -> 25 | N58: =VLOOKUP($B58,[3]加班情况分析!$D:$L,8,FALSE) -> 4 | O58: =VLOOKUP(B58,[3]加班情况分析!D:L,9,FALSE) -> 0 | P58: =VLOOKUP(B58,'[3]牵头项目（当前进行中）'!A:B,2,FALSE) -> 1 | R58: =VLOOKUP(B58,[3]主管应用系统数量!I:J,2,FALSE) -> 1 | S58: 1 | T58: =VLOOKUP(B58,[3]二季度变更任务!A:B,2,FALSE) -> 7 | U58: =VLOOKUP(B58,[3]三季度变更任务!A:B,2,FALSE) -> 7 | W58: 适中 | X58: 大数据集群运维、数仓任务SQL调优、一表通、数据同步事项 | Y58: hadoop平台运维 | Z58: 0.7 | AA58: 一表通3期 | AB58: 0.3 | AD58: 冯潇 | AE58: 基本适配 | AF58: 适中
A59: 57 | B59: 王新蕾 | C59: 数据平台部 | D59: 待定 | E59: 女 | F59: 1 | G59: 研究生 | H59: 中国科学技术大学 | I59: / | J59: =VLOOKUP(B59,[3]加班情况分析!D:G,4,FALSE) -> 0 | K59: =VLOOKUP(B59,[3]加班情况分析!D:H,5,FALSE) -> FALSE | L59: =VLOOKUP(B59,[3]加班情况分析!D:L,6,FALSE) -> 14 | M59: =VLOOKUP($B59,[3]加班情况分析!$D:$L,7,FALSE) -> 0 | N59: =VLOOKUP($B59,[3]加班情况分析!$D:$L,8,FALSE) -> 0 | O59: =VLOOKUP(B59,[3]加班情况分析!D:L,9,FALSE) -> 0 | S59: 0 | W59: 不饱和 | X59: 休假中
A60: 58 | B60: 顾恺 | C60: 数据开发部 | D60: 负责人 | E60: 男 | F60: 19 | G60: 大学本科 | H60: 东华大学 | I60: / | J60: =VLOOKUP(B60,[3]加班情况分析!D:G,4,FALSE) -> 3.6404599 | K60: =VLOOKUP(B60,[3]加班情况分析!D:H,5,FALSE) -> TRUE | L60: =VLOOKUP(B60,[3]加班情况分析!D:L,6,FALSE) -> 2 | M60: =VLOOKUP($B60,[3]加班情况分析!$D:$L,7,FALSE) -> 9 | N60: =VLOOKUP($B60,[3]加班情况分析!$D:$L,8,FALSE) -> 17 | O60: =VLOOKUP(B60,[3]加班情况分析!D:L,9,FALSE) -> 33 | S60: 0 | X60: 数据开发部全面管理工作
A61: 59 | B61: 杨青 | C61: 数据开发部 | D61: 负责人 | E61: 女 | F61: 14 | G61: 研究生 | H61: 东华大学 | I61: / | J61: =VLOOKUP(B61,[3]加班情况分析!D:G,4,FALSE) -> 3.1591898 | K61: =VLOOKUP(B61,[3]加班情况分析!D:H,5,FALSE) -> TRUE | L61: =VLOOKUP(B61,[3]加班情况分析!D:L,6,FALSE) -> 5 | M61: =VLOOKUP($B61,[3]加班情况分析!$D:$L,7,FALSE) -> 9 | N61: =VLOOKUP($B61,[3]加班情况分析!$D:$L,8,FALSE) -> 30 | O61: =VLOOKUP(B61,[3]加班情况分析!D:L,9,FALSE) -> 16 | S61: 0 | X61: 数据开发部协管工作
A62: 60 | B62: 田振宇 | C62: 数据开发部 | D62: 模型设计组 | E62: 男 | F62: 2 | G62: 研究生 | H62: 上海大学 | I62: / | J62: =VLOOKUP(B62,[3]加班情况分析!D:G,4,FALSE) -> 1.7437671 | K62: =VLOOKUP(B62,[3]加班情况分析!D:H,5,FALSE) -> FALSE | L62: =VLOOKUP(B62,[3]加班情况分析!D:L,6,FALSE) -> 13 | M62: =VLOOKUP($B62,[3]加班情况分析!$D:$L,7,FALSE) -> 20 | N62: =VLOOKUP($B62,[3]加班情况分析!$D:$L,8,FALSE) -> 24 | O62: =VLOOKUP(B62,[3]加班情况分析!D:L,9,FALSE) -> 0 | S62: 1 | T62: =VLOOKUP(B62,[3]二季度变更任务!A:B,2,FALSE) -> 3 | W62: 适中 | X62: 慧信工程、数仓P层、整合模型 | Y62: 整合模型 | Z62: 1 | AE62: 基本适配 | AF62: 适中
A63: 61 | B63: 陈科宇 | C63: 数据开发部 | D63: 应用开发组/风险管理 | E63: 女 | F63: 5 | G63: 大学本科 | H63: 江南大学 | I63: / | J63: =VLOOKUP(B63,[3]加班情况分析!D:G,4,FALSE) -> 2.7367429 | K63: =VLOOKUP(B63,[3]加班情况分析!D:H,5,FALSE) -> TRUE | L63: =VLOOKUP(B63,[3]加班情况分析!D:L,6,FALSE) -> 1 | M63: =VLOOKUP($B63,[3]加班情况分析!$D:$L,7,FALSE) -> 18 | N63: =VLOOKUP($B63,[3]加班情况分析!$D:$L,8,FALSE) -> 20 | O63: =VLOOKUP(B63,[3]加班情况分析!D:L,9,FALSE) -> 12 | S63: 1 | T63: =VLOOKUP(B63,[3]二季度变更任务!A:B,2,FALSE) -> 2 | U63: =VLOOKUP(B63,[3]三季度变更任务!A:B,2,FALSE) -> 3 | W63: 适中 | X63: RSD应用衍生区 | Y63: RSD应用衍生区 | Z63: 1 | AE63: 基本适配 | AF63: 适中
A64: 62 | B64: 胡庆 | C64: 数据开发部 | D64: 应用开发组/风险管理 | E64: 男 | F64: 2 | G64: 研究生 | H64: 上海对外经贸大学 | I64: / | J64: =VLOOKUP(B64,[3]加班情况分析!D:G,4,FALSE) -> 2.5948563 | K64: =VLOOKUP(B64,[3]加班情况分析!D:H,5,FALSE) -> FALSE | L64: =VLOOKUP(B64,[3]加班情况分析!D:L,6,FALSE) -> 0 | M64: =VLOOKUP($B64,[3]加班情况分析!$D:$L,7,FALSE) -> 19 | N64: =VLOOKUP($B64,[3]加班情况分析!$D:$L,8,FALSE) -> 30 | O64: =VLOOKUP(B64,[3]加班情况分析!D:L,9,FALSE) -> 9 | Q64: =VLOOKUP(B64,'[3]牵头需求（当前进行中）'!A:B,2,FALSE) -> 1 | S64: 1 | T64: =VLOOKUP(B64,[3]二季度变更任务!A:B,2,FALSE) -> 7 | U64: =VLOOKUP(B64,[3]三季度变更任务!A:B,2,FALSE) -> 3 | W64: 适中 | X64: RAD应用衍生区 | Y64: RAD应用衍生区 | Z64: 1 | AE64: 基本适配 | AF64: 适中
A65: 63 | B65: 张倩 | C65: 数据开发部 | D65: 应用开发组/风险管理 | E65: 女 | F65: 2 | G65: 研究生 | H65: 上海财经大学 | I65: / | J65: =VLOOKUP(B65,[3]加班情况分析!D:G,4,FALSE) -> 2.3872076 | K65: =VLOOKUP(B65,[3]加班情况分析!D:H,5,FALSE) -> FALSE | L65: =VLOOKUP(B65,[3]加班情况分析!D:L,6,FALSE) -> 2 | M65: =VLOOKUP($B65,[3]加班情况分析!$D:$L,7,FALSE) -> 22 | N65: =VLOOKUP($B65,[3]加班情况分析!$D:$L,8,FALSE) -> 31 | O65: =VLOOKUP(B65,[3]加班情况分析!D:L,9,FALSE) -> 2 | Q65: =VLOOKUP(B65,'[3]牵头需求（当前进行中）'!A:B,2,FALSE) -> 2 | S65: 1 | T65: =VLOOKUP(B65,[3]二季度变更任务!A:B,2,FALSE) -> 6 | U65: =VLOOKUP(B65,[3]三季度变更任务!A:B,2,FALSE) -> 9 | W65: 适中 | X65: 征信报送 | Y65: 征信报送 | Z65: 1 | AE65: 基本适配 | AF65: 适中
A66: 64 | B66: 龚毅磊 | C66: 数据开发部 | D66: 应用开发组/监管报送 | E66: 男 | F66: 2 | G66: 研究生 | H66: 香港中文大学 | I66: / | J66: =VLOOKUP(B66,[3]加班情况分析!D:G,4,FALSE) -> 2.8185484 | K66: =VLOOKUP(B66,[3]加班情况分析!D:H,5,FALSE) -> TRUE | L66: =VLOOKUP(B66,[3]加班情况分析!D:L,6,FALSE) -> 2 | M66: =VLOOKUP($B66,[3]加班情况分析!$D:$L,7,FALSE) -> 11 | N66: =VLOOKUP($B66,[3]加班情况分析!$D:$L,8,FALSE) -> 42 | O66: =VLOOKUP(B66,[3]加班情况分析!D:L,9,FALSE) -> 7 | P66: =VLOOKUP(B66,'[3]牵头项目（当前进行中）'!A:B,2,FALSE) -> 1 | Q66: =VLOOKUP(B66,'[3]牵头需求（当前进行中）'!A:B,2,FALSE) -> 7 | R66: =VLOOKUP(B66,[3]主管应用系统数量!I:J,2,FALSE) -> 1 | S66: 2 | T66: =VLOOKUP(B66,[3]二季度变更任务!A:B,2,FALSE) -> 17 | U66: =VLOOKUP(B66,[3]三季度变更任务!A:B,2,FALSE) -> 11 | W66: 超负荷 | X66: 旧线监管集市、利率报备、利率明细、LPR报表、非居民涉税、账户报送1.0、2.0 | Y66: 旧线监管集市、利率报备、利率明细、LPR报表、非居民涉税、账户报送1.0、2.0 | Z66: 1 | AE66: 基本适配 | AF66: 适中
A67: 65 | B67: 景丞 | C67: 数据开发部 | D67: 应用开发组/监管报送 | E67: 女 | F67: 6 | G67: 大学本科 | H67: 南京理工大学 | I67: / | J67: =VLOOKUP(B67,[3]加班情况分析!D:G,4,FALSE) -> 2.7698228 | K67: =VLOOKUP(B67,[3]加班情况分析!D:H,5,FALSE) -> TRUE | L67: =VLOOKUP(B67,[3]加班情况分析!D:L,6,FALSE) -> 6 | M67: =VLOOKUP($B67,[3]加班情况分析!$D:$L,7,FALSE) -> 11 | N67: =VLOOKUP($B67,[3]加班情况分析!$D:$L,8,FALSE) -> 30 | O67: =VLOOKUP(B67,[3]加班情况分析!D:L,9,FALSE) -> 11 | P67: =VLOOKUP(B67,'[3]牵头项目（当前进行中）'!A:B,2,FALSE) -> 1 | Q67: =VLOOKUP(B67,'[3]牵头需求（当前进行中）'!A:B,2,FALSE) -> 28 | R67: =VLOOKUP(B67,[3]主管应用系统数量!I:J,2,FALSE) -> 1 | S67: 5 | T67: =VLOOKUP(B67,[3]二季度变更任务!A:B,2,FALSE) -> 9 | U67: =VLOOKUP(B67,[3]三季度变更任务!A:B,2,FALSE) -> 22 | W67: 适中 | X67: EAST、信用卡主题报表、跨应用数据检核 | Y67: EAST、信用卡主题报表、跨应用数据检核 | Z67: 1 | AE67: 基本适配 | AF67: 适中
A68: 66 | B68: 刘梦颖 | C68: 数据开发部 | D68: 应用开发组/监管报送 | E68: 女 | F68: 6 | G68: 研究生 | H68: 上海大学 | I68: / | J68: =VLOOKUP(B68,[3]加班情况分析!D:G,4,FALSE) -> 2.6191166 | K68: =VLOOKUP(B68,[3]加班情况分析!D:H,5,FALSE) -> TRUE | L68: =VLOOKUP(B68,[3]加班情况分析!D:L,6,FALSE) -> 4 | M68: =VLOOKUP($B68,[3]加班情况分析!$D:$L,7,FALSE) -> 10 | N68: =VLOOKUP($B68,[3]加班情况分析!$D:$L,8,FALSE) -> 42 | O68: =VLOOKUP(B68,[3]加班情况分析!D:L,9,FALSE) -> 5 | P68: =VLOOKUP(B68,'[3]牵头项目（当前进行中）'!A:B,2,FALSE) -> 2 | Q68: =VLOOKUP(B68,'[3]牵头需求（当前进行中）'!A:B,2,FALSE) -> 8 | R68: =VLOOKUP(B68,[3]主管应用系统数量!I:J,2,FALSE) -> 2 | S68: 1 | U68: =VLOOKUP(B68,[3]三季度变更任务!A:B,2,FALSE) -> 12 | W68: 超负荷 | X68: 金融基础数据、一表通三期项目 | Y68: 金融基础数据、一表通三期项目 | Z68: 1 | AE68: 基本适配 | AF68: 适中
A69: 9 | B69: 周龙 | C69: 数据开发部 | D69: 应用开发组 | E69: 男 | F69: 9 | G69: 大学本科 | H69: 北京科技大学 | I69: 骨干 | J69: =VLOOKUP(B69,[3]加班情况分析!D:G,4,FALSE) -> 3.1480932 | K69: =VLOOKUP(B69,[3]加班情况分析!D:H,5,FALSE) -> TRUE | L69: =VLOOKUP(B69,[3]加班情况分析!D:L,6,FALSE) -> 7 | M69: =VLOOKUP($B69,[3]加班情况分析!$D:$L,7,FALSE) -> 7 | N69: =VLOOKUP($B69,[3]加班情况分析!$D:$L,8,FALSE) -> 28 | O69: =VLOOKUP(B69,[3]加班情况分析!D:L,9,FALSE) -> 17 | Q69: =VLOOKUP(B69,'[3]牵头需求（当前进行中）'!A:B,2,FALSE) -> 3 | R69: =VLOOKUP(B69,[3]主管应用系统数量!I:J,2,FALSE) -> 1 | S69: 0 | W69: 超负荷 | X69: 监管报送UPR集市 | Y69: 监管报送UPR集市 | Z69: 0.6 | AA69: 监管报送架构师、产品经理 | AB69: 0.4 | AE69: 基本适配 | AF69: 适中
A70: 68 | B70: 王子枫 | C70: 数据开发部 | D70: 应用开发组/监管报送 | E70: 男 | F70: 2 | G70: 大学本科 | H70: 上海师范大学 | I70: / | J70: =VLOOKUP(B70,[3]加班情况分析!D:G,4,FALSE) -> 2.9717077 | K70: =VLOOKUP(B70,[3]加班情况分析!D:H,5,FALSE) -> TRUE | L70: =VLOOKUP(B70,[3]加班情况分析!D:L,6,FALSE) -> 2 | M70: =VLOOKUP($B70,[3]加班情况分析!$D:$L,7,FALSE) -> 15 | N70: =VLOOKUP($B70,[3]加班情况分析!$D:$L,8,FALSE) -> 28 | O70: =VLOOKUP(B70,[3]加班情况分析!D:L,9,FALSE) -> 16 | S70: 0 | T70: =VLOOKUP(B70,[3]二季度变更任务!A:B,2,FALSE) -> 8 | U70: =VLOOKUP(B70,[3]三季度变更任务!A:B,2,FALSE) -> 3 | V70: =VLOOKUP(B70,[3]责任事件及缺陷!A:B,2,FALSE) -> 1 | W70: 适中 | X70: 反洗钱报送 | Y70: 反洗钱报送 | Z70: 1 | AE70: 基本适配 | AF70: 适中
A71: 69 | B71: 卫彩萍 | C71: 数据开发部 | D71: 应用开发组/监管报送 | E71: 女 | F71: 1 | G71: 研究生 | H71: 东华大学 | I71: / | J71: =VLOOKUP(B71,[3]加班情况分析!D:G,4,FALSE) -> 2.9730172 | K71: =VLOOKUP(B71,[3]加班情况分析!D:H,5,FALSE) -> TRUE | L71: =VLOOKUP(B71,[3]加班情况分析!D:L,6,FALSE) -> 8 | M71: =VLOOKUP($B71,[3]加班情况分析!$D:$L,7,FALSE) -> 12 | N71: =VLOOKUP($B71,[3]加班情况分析!$D:$L,8,FALSE) -> 20 | O71: =VLOOKUP(B71,[3]加班情况分析!D:L,9,FALSE) -> 18 | P71: =VLOOKUP(B71,'[3]牵头项目（当前进行中）'!A:B,2,FALSE) -> 1 | Q71: =VLOOKUP(B71,'[3]牵头需求（当前进行中）'!A:B,2,FALSE) -> 2 | S71: 7 | T71: =VLOOKUP(B71,[3]二季度变更任务!A:B,2,FALSE) -> 14 | U71: =VLOOKUP(B71,[3]三季度变更任务!A:B,2,FALSE) -> 17 | W71: 超负荷 | X71: 区域特色、审计署1.0、现金统计报送、税务账户信息报送 | Y71: 区域特色、审计署1.0、现金统计报送、税务账户信息报送 | Z71: 1 | AE71: 基本适配 | AF71: 适中
A72: 12 | B72: 曹宁远 | C72: 数据平台部 | D72: 工具开发组 | E72: 男 | F72: 5 | G72: 研究生 | H72: 北京理工大学 | I72: 组长 | J72: =VLOOKUP(B72,[3]加班情况分析!D:G,4,FALSE) -> 2.0047563 | K72: =VLOOKUP(B72,[3]加班情况分析!D:H,5,FALSE) -> FALSE | L72: =VLOOKUP(B72,[3]加班情况分析!D:L,6,FALSE) -> 12 | M72: =VLOOKUP($B72,[3]加班情况分析!$D:$L,7,FALSE) -> 23 | N72: =VLOOKUP($B72,[3]加班情况分析!$D:$L,8,FALSE) -> 14 | O72: =VLOOKUP(B72,[3]加班情况分析!D:L,9,FALSE) -> 8 | P72: =VLOOKUP(B72,'[3]牵头项目（当前进行中）'!A:B,2,FALSE) -> 1 | R72: =VLOOKUP(B72,[3]主管应用系统数量!I:J,2,FALSE) -> 1 | S72: 5 | W72: 适中 | X72: Stella、调度、dataops架构管理 | Y72: 工具开发组负责人；DataOps产品、架构、项目管理；司库监管报送模块架构管理 | Z72: 0.9 | AA72: stella、调度产品、架构、运维 | AB72: 0.1 | AD72: 王双钰 | AE72: 基本适配 | AF72: 适中
A73: 71 | B73: 徐倩茹 | C73: 数据开发部 | D73: 应用开发组/监管报送 | E73: 女 | F73: 4 | G73: 研究生 | H73: 东北财经大学 | I73: / | J73: =VLOOKUP(B73,[3]加班情况分析!D:G,4,FALSE) -> 1.2779074 | K73: =VLOOKUP(B73,[3]加班情况分析!D:H,5,FALSE) -> FALSE | L73: =VLOOKUP(B73,[3]加班情况分析!D:L,6,FALSE) -> 32 | M73: =VLOOKUP($B73,[3]加班情况分析!$D:$L,7,FALSE) -> 18 | N73: =VLOOKUP($B73,[3]加班情况分析!$D:$L,8,FALSE) -> 9 | O73: =VLOOKUP(B73,[3]加班情况分析!D:L,9,FALSE) -> 1 | Q73: =VLOOKUP(B73,'[3]牵头需求（当前进行中）'!A:B,2,FALSE) -> 3 | S73: 1 | W73: 适中 | X73: 支付结算合规明细、标准化存贷款（成都）、保证贷款、大额现金、非居民涉税 | Y73: 支付结算合规明细、标准化存贷款（成都）、保证贷款、大额现金、非居民涉税 | Z73: 1 | AE73: 基本适配 | AF73: 适中
A74: 72 | B74: 陈佳宁 | C74: 数据开发部 | D74: 应用开发组/经营管理 | E74: 女 | F74: 0 | G74: 研究生 | H74: 中南财经政法大学 | I74: / | J74: =VLOOKUP(B74,[3]加班情况分析!D:G,4,FALSE) -> 1.5636528 | K74: =VLOOKUP(B74,[3]加班情况分析!D:H,5,FALSE) -> FALSE | L74: =VLOOKUP(B74,[3]加班情况分析!D:L,6,FALSE) -> 24 | M74: =VLOOKUP($B74,[3]加班情况分析!$D:$L,7,FALSE) -> 17 | N74: =VLOOKUP($B74,[3]加班情况分析!$D:$L,8,FALSE) -> 18 | O74: =VLOOKUP(B74,[3]加班情况分析!D:L,9,FALSE) -> 1 | S74: 1 | W74: 不饱和 | X74: NRP集市（UDAS,hadoop侧） | Y74: NRP集市（UDAS,hadoop侧） | Z74: 1 | AE74: 基本适配 | AF74: 适中
A75: 73 | B75: 陈笑轩 | C75: 数据开发部 | D75: 应用开发组/经营管理 | E75: 女 | F75: 3 | G75: 研究生 | H75: 悉尼大学 | I75: / | J75: =VLOOKUP(B75,[3]加班情况分析!D:G,4,FALSE) -> 1.54125 | K75: =VLOOKUP(B75,[3]加班情况分析!D:H,5,FALSE) -> FALSE | L75: =VLOOKUP(B75,[3]加班情况分析!D:L,6,FALSE) -> 12 | M75: =VLOOKUP($B75,[3]加班情况分析!$D:$L,7,FALSE) -> 30 | N75: =VLOOKUP($B75,[3]加班情况分析!$D:$L,8,FALSE) -> 12 | O75: =VLOOKUP(B75,[3]加班情况分析!D:L,9,FALSE) -> 0 | Q75: =VLOOKUP(B75,'[3]牵头需求（当前进行中）'!A:B,2,FALSE) -> 1 | S75: 1 | T75: =VLOOKUP(B75,[3]二季度变更任务!A:B,2,FALSE) -> 7 | U75: =VLOOKUP(B75,[3]三季度变更任务!A:B,2,FALSE) -> 1 | W75: 适中 | X75: NRP集市（UDAS,DWS侧） | Y75: NRP集市（UDAS,DWS侧） | Z75: 1 | AE75: 基本适配 | AF75: 适中
A76: 74 | B76: 胡雯 | C76: 数据开发部 | D76: 应用开发组/经营管理 | E76: 女 | F76: 3 | G76: 大学本科 | H76: 上海财经大学 | I76: / | J76: =VLOOKUP(B76,[3]加班情况分析!D:G,4,FALSE) -> 1.3294444 | K76: =VLOOKUP(B76,[3]加班情况分析!D:H,5,FALSE) -> FALSE | L76: =VLOOKUP(B76,[3]加班情况分析!D:L,6,FALSE) -> 14 | M76: =VLOOKUP($B76,[3]加班情况分析!$D:$L,7,FALSE) -> 38 | N76: =VLOOKUP($B76,[3]加班情况分析!$D:$L,8,FALSE) -> 7 | O76: =VLOOKUP(B76,[3]加班情况分析!D:L,9,FALSE) -> 2 | Q76: =VLOOKUP(B76,'[3]牵头需求（当前进行中）'!A:B,2,FALSE) -> 25 | S76: 1 | T76: =VLOOKUP(B76,[3]二季度变更任务!A:B,2,FALSE) -> 10 | U76: =VLOOKUP(B76,[3]三季度变更任务!A:B,2,FALSE) -> 4 | W76: 适中 | X76: UDAS（对公、风险） | Y76: UDAS（对公、风险） | Z76: 1 | AE76: 基本适配 | AF76: 适中
A77: 75 | B77: 梅苏源 | C77: 数据开发部 | D77: 应用开发组/经营管理 | E77: 男 | F77: 1 | G77: 研究生 | H77: 合肥工业大学 | I77: / | J77: =VLOOKUP(B77,[3]加班情况分析!D:G,4,FALSE) -> 1.6349955 | K77: =VLOOKUP(B77,[3]加班情况分析!D:H,5,FALSE) -> FALSE | L77: =VLOOKUP(B77,[3]加班情况分析!D:L,6,FALSE) -> 8 | M77: =VLOOKUP($B77,[3]加班情况分析!$D:$L,7,FALSE) -> 45 | N77: =VLOOKUP($B77,[3]加班情况分析!$D:$L,8,FALSE) -> 6 | O77: =VLOOKUP(B77,[3]加班情况分析!D:L,9,FALSE) -> 3 | Q77: =VLOOKUP(B77,'[3]牵头需求（当前进行中）'!A:B,2,FALSE) -> 12 | S77: 1 | T77: =VLOOKUP(B77,[3]二季度变更任务!A:B,2,FALSE) -> 11 | U77: =VLOOKUP(B77,[3]三季度变更任务!A:B,2,FALSE) -> 3 | W77: 适中 | X77: UDAS（金市、网金、运营等） | Y77: UDAS（金市、网金、运营等） | Z77: 1 | AE77: 基本适配 | AF77: 适中
A78: 76 | B78: 阮靖龙 | C78: 数据开发部 | D78: 应用开发组/经营管理 | E78: 男 | F78: 1 | G78: 研究生 | H78: 华中师范大学 | I78: / | J78: =VLOOKUP(B78,[3]加班情况分析!D:G,4,FALSE) -> 1.3716803 | K78: =VLOOKUP(B78,[3]加班情况分析!D:H,5,FALSE) -> FALSE | L78: =VLOOKUP(B78,[3]加班情况分析!D:L,6,FALSE) -> 18 | M78: =VLOOKUP($B78,[3]加班情况分析!$D:$L,7,FALSE) -> 39 | N78: =VLOOKUP($B78,[3]加班情况分析!$D:$L,8,FALSE) -> 3 | O78: =VLOOKUP(B78,[3]加班情况分析!D:L,9,FALSE) -> 1 | Q78: =VLOOKUP(B78,'[3]牵头需求（当前进行中）'!A:B,2,FALSE) -> 4 | S78: 2 | T78: =VLOOKUP(B78,[3]二季度变更任务!A:B,2,FALSE) -> 2 | U78: =VLOOKUP(B78,[3]三季度变更任务!A:B,2,FALSE) -> 1 | W78: 适中 | X78: CRM集市 | Y78: CRM集市 | Z78: 1 | AE78: 基本适配 | AF78: 适中
A79: 77 | B79: 张雅淇 | C79: 数据开发部 | D79: 应用开发组/经营管理 | E79: 女 | F79: 5 | G79: 大学本科 | H79: 东北大学 | I79: / | J79: =VLOOKUP(B79,[3]加班情况分析!D:G,4,FALSE) -> 1.4558106 | K79: =VLOOKUP(B79,[3]加班情况分析!D:H,5,FALSE) -> FALSE | L79: =VLOOKUP(B79,[3]加班情况分析!D:L,6,FALSE) -> 29 | M79: =VLOOKUP($B79,[3]加班情况分析!$D:$L,7,FALSE) -> 16 | N79: =VLOOKUP($B79,[3]加班情况分析!$D:$L,8,FALSE) -> 12 | O79: =VLOOKUP(B79,[3]加班情况分析!D:L,9,FALSE) -> 4 | Q79: =VLOOKUP(B79,'[3]牵头需求（当前进行中）'!A:B,2,FALSE) -> 23 | S79: 1 | T79: =VLOOKUP(B79,[3]二季度变更任务!A:B,2,FALSE) -> 9 | U79: =VLOOKUP(B79,[3]三季度变更任务!A:B,2,FALSE) -> 3 | W79: 适中 | X79: UDAS(牵头及零售) | Y79: UDAS(牵头及零售) | Z79: 1 | AE79: 基本适配 | AF79: 适中
A80: 78 | B80: 陈晨 | C80: 数据开发部 | D80: 数仓开发组 | E80: 男 | F80: 1 | G80: 研究生 | H80: 上海大学 | I80: / | J80: =VLOOKUP(B80,[3]加班情况分析!D:G,4,FALSE) -> 3.3190815 | K80: =VLOOKUP(B80,[3]加班情况分析!D:H,5,FALSE) -> TRUE | L80: =VLOOKUP(B80,[3]加班情况分析!D:L,6,FALSE) -> 4 | M80: =VLOOKUP($B80,[3]加班情况分析!$D:$L,7,FALSE) -> 3 | N80: =VLOOKUP($B80,[3]加班情况分析!$D:$L,8,FALSE) -> 42 | O80: =VLOOKUP(B80,[3]加班情况分析!D:L,9,FALSE) -> 13 | Q80: =VLOOKUP(B80,'[3]牵头需求（当前进行中）'!A:B,2,FALSE) -> 12 | S80: 2 | T80: =VLOOKUP(B80,[3]二季度变更任务!A:B,2,FALSE) -> 19 | U80: =VLOOKUP(B80,[3]三季度变更任务!A:B,2,FALSE) -> 11 | V80: =VLOOKUP(B80,[3]责任事件及缺陷!A:B,2,FALSE) -> 1 | W80: 超负荷 | X80: 征信报送 | Y80: 征信报送 | Z80: 1 | AE80: 基本适配 | AF80: 超负荷
A81: 79 | B81: 袁凯 | C81: 数据开发部 | D81: 数仓开发组 | E81: 男 | F81: 2 | G81: 研究生 | H81: 中国科学院大学 | I81: / | J81: =VLOOKUP(B81,[3]加班情况分析!D:G,4,FALSE) -> 2.7864117 | K81: =VLOOKUP(B81,[3]加班情况分析!D:H,5,FALSE) -> TRUE | L81: =VLOOKUP(B81,[3]加班情况分析!D:L,6,FALSE) -> 4 | M81: =VLOOKUP($B81,[3]加班情况分析!$D:$L,7,FALSE) -> 12 | N81: =VLOOKUP($B81,[3]加班情况分析!$D:$L,8,FALSE) -> 32 | O81: =VLOOKUP(B81,[3]加班情况分析!D:L,9,FALSE) -> 13 | Q81: =VLOOKUP(B81,'[3]牵头需求（当前进行中）'!A:B,2,FALSE) -> 14 | S81: 1 | T81: =VLOOKUP(B81,[3]二季度变更任务!A:B,2,FALSE) -> 3 | U81: =VLOOKUP(B81,[3]三季度变更任务!A:B,2,FALSE) -> 12 | W81: 超负荷 | X81: 零售集市、接口集市、公共集市 | Y81: 零售集市、接口集市、公共集市 | Z81: 1 | AE81: 基本适配 | AF81: 超负荷
A82: 80 | B82: 王萌萌 | C82: 数据开发部 | D82: 数仓开发组 | E82: 女 | F82: 2 | G82: 研究生 | H82: 上海市计算技术研究所 | I82: / | J82: =VLOOKUP(B82,[3]加班情况分析!D:G,4,FALSE) -> 3.5245278 | K82: =VLOOKUP(B82,[3]加班情况分析!D:H,5,FALSE) -> TRUE | L82: =VLOOKUP(B82,[3]加班情况分析!D:L,6,FALSE) -> 2 | M82: =VLOOKUP($B82,[3]加班情况分析!$D:$L,7,FALSE) -> 9 | N82: =VLOOKUP($B82,[3]加班情况分析!$D:$L,8,FALSE) -> 27 | O82: =VLOOKUP(B82,[3]加班情况分析!D:L,9,FALSE) -> 22 | Q82: =VLOOKUP(B82,'[3]牵头需求（当前进行中）'!A:B,2,FALSE) -> 4 | S82: 3 | T82: =VLOOKUP(B82,[3]二季度变更任务!A:B,2,FALSE) -> 8 | U82: =VLOOKUP(B82,[3]三季度变更任务!A:B,2,FALSE) -> 6 | V82: =VLOOKUP(B82,[3]责任事件及缺陷!A:B,2,FALSE) -> 1 | W82: 超负荷 | X82: 零售集市、实时数仓零售板块、标签管理 | Y82: 零售集市、实时数仓零售板块、标签管理 | Z82: 1 | AE82: 基本适配 | AF82: 适中
A83: 81 | B83: 赵雅婷 | C83: 数据开发部 | D83: 数仓开发组 | E83: 女 | F83: 2 | G83: 研究生 | H83: 东华大学 | I83: / | J83: =VLOOKUP(B83,[3]加班情况分析!D:G,4,FALSE) -> 2.7855354 | K83: =VLOOKUP(B83,[3]加班情况分析!D:H,5,FALSE) -> TRUE | L83: =VLOOKUP(B83,[3]加班情况分析!D:L,6,FALSE) -> 2 | M83: =VLOOKUP($B83,[3]加班情况分析!$D:$L,7,FALSE) -> 10 | N83: =VLOOKUP($B83,[3]加班情况分析!$D:$L,8,FALSE) -> 34 | O83: =VLOOKUP(B83,[3]加班情况分析!D:L,9,FALSE) -> 9 | S83: 1 | T83: =VLOOKUP(B83,[3]二季度变更任务!A:B,2,FALSE) -> 2 | W83: 适中 | X83: 智芯工程、公共集市、整合模型（核心账卡折） | Y83: 公共集市、整合模型（核心账卡折） | Z83: 1 | AE83: 基本适配 | AF83: 适中
A84: 82 | B84: 李禹凝 | C84: 数据开发部 | D84: 数仓开发组 | E84: 女 | F84: 2 | G84: 研究生 | H84: 伦敦国王学院 | I84: / | J84: =VLOOKUP(B84,[3]加班情况分析!D:G,4,FALSE) -> 2.3855055 | K84: =VLOOKUP(B84,[3]加班情况分析!D:H,5,FALSE) -> FALSE | L84: =VLOOKUP(B84,[3]加班情况分析!D:L,6,FALSE) -> 2 | M84: =VLOOKUP($B84,[3]加班情况分析!$D:$L,7,FALSE) -> 22 | N84: =VLOOKUP($B84,[3]加班情况分析!$D:$L,8,FALSE) -> 33 | O84: =VLOOKUP(B84,[3]加班情况分析!D:L,9,FALSE) -> 4 | Q84: =VLOOKUP(B84,'[3]牵头需求（当前进行中）'!A:B,2,FALSE) -> 1 | S84: 1 | W84: 适中 | X84: 智芯工程、公共集市 | Y84: 公共集市 | Z84: 1 | AE84: 基本适配 | AF84: 适中
A85: 83 | B85: 潘修滔 | C85: 数据开发部 | D85: 数仓开发组 | E85: 男 | F85: 2 | G85: 研究生 | H85: 浙江理工大学 | I85: / | J85: =VLOOKUP(B85,[3]加班情况分析!D:G,4,FALSE) -> 1.8499537 | K85: =VLOOKUP(B85,[3]加班情况分析!D:H,5,FALSE) -> FALSE | L85: =VLOOKUP(B85,[3]加班情况分析!D:L,6,FALSE) -> 3 | M85: =VLOOKUP($B85,[3]加班情况分析!$D:$L,7,FALSE) -> 38 | N85: =VLOOKUP($B85,[3]加班情况分析!$D:$L,8,FALSE) -> 17 | O85: =VLOOKUP(B85,[3]加班情况分析!D:L,9,FALSE) -> 2 | Q85: =VLOOKUP(B85,'[3]牵头需求（当前进行中）'!A:B,2,FALSE) -> 2 | S85: 1 | T85: =VLOOKUP(B85,[3]二季度变更任务!A:B,2,FALSE) -> 6 | U85: =VLOOKUP(B85,[3]三季度变更任务!A:B,2,FALSE) -> 6 | V85: =VLOOKUP(B85,[3]责任事件及缺陷!A:B,2,FALSE) -> 1 | W85: 适中 | X85: 信用卡集市 | Y85: 信用卡集市 | Z85: 1 | AE85: 基本适配 | AF85: 适中
A86: 84 | B86: 曹婕 | C86: 数据开发部 | D86: 数仓开发组 | E86: 女 | F86: 2 | G86: 研究生 | H86: 中国地质大学（北京） | I86: / | Q86: =VLOOKUP(B86,'[3]牵头需求（当前进行中）'!A:B,2,FALSE) -> 1 | S86: 1 | T86: =VLOOKUP(B86,[3]二季度变更任务!A:B,2,FALSE) -> 3 | V86: =VLOOKUP(B86,[3]责任事件及缺陷!A:B,2,FALSE) -> 1 | W86: 适中 | X86: 对公集市（休假中） | Y86: 对公集市（休假中） | Z86: 1 | AE86: 基本适配 | AF86: 适中
A87: 85 | B87: 郑卞钰 | C87: 数据开发部 | D87: 数仓开发组 | E87: 女 | F87: 3 | G87: 研究生 | H87: 华中科技大学 | I87: / | J87: =VLOOKUP(B87,[3]加班情况分析!D:G,4,FALSE) -> 2.7863988 | K87: =VLOOKUP(B87,[3]加班情况分析!D:H,5,FALSE) -> TRUE | L87: =VLOOKUP(B87,[3]加班情况分析!D:L,6,FALSE) -> 3 | M87: =VLOOKUP($B87,[3]加班情况分析!$D:$L,7,FALSE) -> 9 | N87: =VLOOKUP($B87,[3]加班情况分析!$D:$L,8,FALSE) -> 36 | O87: =VLOOKUP(B87,[3]加班情况分析!D:L,9,FALSE) -> 8 | Q87: =VLOOKUP(B87,'[3]牵头需求（当前进行中）'!A:B,2,FALSE) -> 6 | S87: 1 | T87: =VLOOKUP(B87,[3]二季度变更任务!A:B,2,FALSE) -> 13 | U87: =VLOOKUP(B87,[3]三季度变更任务!A:B,2,FALSE) -> 11 | V87: =VLOOKUP(B87,[3]责任事件及缺陷!A:B,2,FALSE) -> 1 | W87: 超负荷 | X87: 两大工程、整合模型、小金风险集市、零售风险集市 | Y87: 整合模型、小金风险集市、零售风险集市 | Z87: 1 | AE87: 基本适配 | AF87: 适中
A88: 86 | B88: 诸倩铷 | C88: 数据开发部 | D88: 数仓开发组 | E88: 女 | F88: 2 | G88: 研究生 | H88: 新加坡国立大学 | I88: / | J88: =VLOOKUP(B88,[3]加班情况分析!D:G,4,FALSE) -> 1.9333829 | K88: =VLOOKUP(B88,[3]加班情况分析!D:H,5,FALSE) -> FALSE | L88: =VLOOKUP(B88,[3]加班情况分析!D:L,6,FALSE) -> 3 | M88: =VLOOKUP($B88,[3]加班情况分析!$D:$L,7,FALSE) -> 23 | N88: =VLOOKUP($B88,[3]加班情况分析!$D:$L,8,FALSE) -> 29 | O88: =VLOOKUP(B88,[3]加班情况分析!D:L,9,FALSE) -> 1 | Q88: =VLOOKUP(B88,'[3]牵头需求（当前进行中）'!A:B,2,FALSE) -> 2 | S88: 1 | T88: =VLOOKUP(B88,[3]二季度变更任务!A:B,2,FALSE) -> 4 | V88: =VLOOKUP(B88,[3]责任事件及缺陷!A:B,2,FALSE) -> 1 | W88: 适中 | X88: 网金集市、客服集市 | Y88: 网金集市、客服集市 | Z88: 1 | AE88: 基本适配 | AF88: 适中
A89: 87 | B89: 吴越 | C89: 数据开发部 | D89: 数仓开发组 | E89: 女 | F89: 0 | G89: 研究生 | H89: 华北电力大学 | I89: / | J89: =VLOOKUP(B89,[3]加班情况分析!D:G,4,FALSE) -> 1.1369759 | K89: =VLOOKUP(B89,[3]加班情况分析!D:H,5,FALSE) -> FALSE | L89: =VLOOKUP(B89,[3]加班情况分析!D:L,6,FALSE) -> 30 | M89: =VLOOKUP($B89,[3]加班情况分析!$D:$L,7,FALSE) -> 15 | N89: =VLOOKUP($B89,[3]加班情况分析!$D:$L,8,FALSE) -> 7 | O89: =VLOOKUP(B89,[3]加班情况分析!D:L,9,FALSE) -> 1 | S89: 1 | W89: 不饱和 | X89: 对公集市、票易贷项目 | Y89: 对公集市、票易贷项目 | Z89: 1 | AE89: 基本适配 | AF89: 适中
A90: 88 | B90: 张必歌 | C90: 数据开发部 | D90: 需求接入组 | E90: 女 | F90: 3 | G90: 研究生 | H90: 吉林大学 | I90: / | J90: =VLOOKUP(B90,[3]加班情况分析!D:G,4,FALSE) -> 0.34656481 | K90: =VLOOKUP(B90,[3]加班情况分析!D:H,5,FALSE) -> FALSE | L90: =VLOOKUP(B90,[3]加班情况分析!D:L,6,FALSE) -> 56 | M90: =VLOOKUP($B90,[3]加班情况分析!$D:$L,7,FALSE) -> 3 | N90: =VLOOKUP($B90,[3]加班情况分析!$D:$L,8,FALSE) -> 0 | O90: =VLOOKUP(B90,[3]加班情况分析!D:L,9,FALSE) -> 1 | Q90: =VLOOKUP(B90,'[3]牵头需求（当前进行中）'!A:B,2,FALSE) -> 3 | S90: 0 | T90: =VLOOKUP(B90,[3]二季度变更任务!A:B,2,FALSE) -> 29 | U90: =VLOOKUP(B90,[3]三季度变更任务!A:B,2,FALSE) -> 3 | W90: 不饱和 | X90: 已调出开发部 | Y90: 已调出开发部 | Z90: 1 | AE90: 基本适配 | AF90: 适中
A91: 89 | B91: 李凯文 | C91: 数据开发部 | D91: 需求接入组 | E91: 男 | F91: 2 | G91: 研究生 | H91: 中国科学技术大学 | I91: / | J91: =VLOOKUP(B91,[3]加班情况分析!D:G,4,FALSE) -> 3.790448 | K91: =VLOOKUP(B91,[3]加班情况分析!D:H,5,FALSE) -> TRUE | L91: =VLOOKUP(B91,[3]加班情况分析!D:L,6,FALSE) -> 2 | M91: =VLOOKUP($B91,[3]加班情况分析!$D:$L,7,FALSE) -> 11 | N91: =VLOOKUP($B91,[3]加班情况分析!$D:$L,8,FALSE) -> 11 | O91: =VLOOKUP(B91,[3]加班情况分析!D:L,9,FALSE) -> 38 | Q91: =VLOOKUP(B91,'[3]牵头需求（当前进行中）'!A:B,2,FALSE) -> 1 | R91: =VLOOKUP(B91,[3]主管应用系统数量!I:J,2,FALSE) -> 2 | S91: 1 | T91: =VLOOKUP(B91,[3]二季度变更任务!A:B,2,FALSE) -> 3 | U91: =VLOOKUP(B91,[3]三季度变更任务!A:B,2,FALSE) -> 6 | W91: 超负荷 | X91: 智芯工程数据接入 | Y91: 数据接入 | Z91: 1 | AE91: 基本适配 | AF91: 适中
A92: 90 | B92: 杜乐 | C92: 数据开发部 | D92: 需求接入组 | E92: 男 | F92: 1 | G92: 研究生 | H92: 华东理工大学 | I92: / | J92: =VLOOKUP(B92,[3]加班情况分析!D:G,4,FALSE) -> 3.1854049 | K92: =VLOOKUP(B92,[3]加班情况分析!D:H,5,FALSE) -> TRUE | L92: =VLOOKUP(B92,[3]加班情况分析!D:L,6,FALSE) -> 4 | M92: =VLOOKUP($B92,[3]加班情况分析!$D:$L,7,FALSE) -> 18 | N92: =VLOOKUP($B92,[3]加班情况分析!$D:$L,8,FALSE) -> 17 | O92: =VLOOKUP(B92,[3]加班情况分析!D:L,9,FALSE) -> 20 | Q92: =VLOOKUP(B92,'[3]牵头需求（当前进行中）'!A:B,2,FALSE) -> 2 | R92: =VLOOKUP(B92,[3]主管应用系统数量!I:J,2,FALSE) -> 1 | S92: 1 | T92: =VLOOKUP(B92,[3]二季度变更任务!A:B,2,FALSE) -> 11 | U92: =VLOOKUP(B92,[3]三季度变更任务!A:B,2,FALSE) -> 64 | W92: 超负荷 | X92: 智芯工程数据接入 | Y92: 数据接入 | Z92: 1 | AE92: 基本适配 | AF92: 适中
A93: 91 | B93: 连静 | C93: 数据开发部 | D93: 需求接入组 | E93: 女 | F93: 1 | G93: 研究生 | H93: 吉林大学 | I93: / | J93: =VLOOKUP(B93,[3]加班情况分析!D:G,4,FALSE) -> 2.9888172 | K93: =VLOOKUP(B93,[3]加班情况分析!D:H,5,FALSE) -> TRUE | L93: =VLOOKUP(B93,[3]加班情况分析!D:L,6,FALSE) -> 13 | M93: =VLOOKUP($B93,[3]加班情况分析!$D:$L,7,FALSE) -> 9 | N93: =VLOOKUP($B93,[3]加班情况分析!$D:$L,8,FALSE) -> 11 | O93: =VLOOKUP(B93,[3]加班情况分析!D:L,9,FALSE) -> 29 | Q93: =VLOOKUP(B93,'[3]牵头需求（当前进行中）'!A:B,2,FALSE) -> 3 | R93: =VLOOKUP(B93,[3]主管应用系统数量!I:J,2,FALSE) -> 1 | S93: 1 | T93: =VLOOKUP(B93,[3]二季度变更任务!A:B,2,FALSE) -> 8 | U93: =VLOOKUP(B93,[3]三季度变更任务!A:B,2,FALSE) -> 6 | W93: 适中 | X93: 实时数仓开发（微批） | Y93: 实时数仓开发（微批） | Z93: 1 | AE93: 基本适配 | AF93: 适中
A94: 92 | B94: 胡申民 | C94: 智能创新部 | D94: 负责人 | E94: 男 | F94: 9 | G94: 大学本科 | H94: 渤海大学 | I94: / | J94: =VLOOKUP(B94,[3]加班情况分析!D:G,4,FALSE) -> 2.6023493 | K94: =VLOOKUP(B94,[3]加班情况分析!D:H,5,FALSE) -> TRUE | L94: =VLOOKUP(B94,[3]加班情况分析!D:L,6,FALSE) -> 11 | M94: =VLOOKUP($B94,[3]加班情况分析!$D:$L,7,FALSE) -> 9 | N94: =VLOOKUP($B94,[3]加班情况分析!$D:$L,8,FALSE) -> 27 | O94: =VLOOKUP(B94,[3]加班情况分析!D:L,9,FALSE) -> 12 | S94: 0 | X94: 智能创新部全面管理工作 | Y94: 负责全行AI工作规划、推进AI场景应用落地与团队管理工作 | AF94: 超负荷
A95: 93 | B95: 陈超 | C95: 智能创新部 | D95: 待定 | E95: 女 | F95: 6 | G95: 研究生 | H95: 东南大学 | I95: / | S95: 0 | W95: 适中 | X95: 休假中
A96: 94 | B96: 祁鑫 | C96: 智能创新部 | D96: AI基础研发组 | E96: 男 | F96: 3 | G96: 研究生 | H96: 昆士兰大学 | I96: / | J96: =VLOOKUP(B96,[3]加班情况分析!D:G,4,FALSE) -> 2.0475463 | K96: =VLOOKUP(B96,[3]加班情况分析!D:H,5,FALSE) -> FALSE | L96: =VLOOKUP(B96,[3]加班情况分析!D:L,6,FALSE) -> 9 | M96: =VLOOKUP($B96,[3]加班情况分析!$D:$L,7,FALSE) -> 31 | N96: =VLOOKUP($B96,[3]加班情况分析!$D:$L,8,FALSE) -> 14 | O96: =VLOOKUP(B96,[3]加班情况分析!D:L,9,FALSE) -> 6 | Q96: =VLOOKUP(B96,'[3]牵头需求（当前进行中）'!A:B,2,FALSE) -> 1 | S96: 1 | U96: =VLOOKUP(B96,[3]三季度变更任务!A:B,2,FALSE) -> 1 | W96: 适中 | X96: 1、尽调助手场景建设 2、数字档案系统建设 | Y96: 尽调助手场景研发 | Z96: 0.5 | AA96: 数字档案系统建设 | AB96: 0.3 | AD96: 无 | AE96: 基本适配 | AF96: 适中
A97: 95 | B97: 黄亦豪 | C97: 智能创新部 | D97: AI基础研发组 | E97: 男 | F97: 1 | G97: 研究生 | H97: 同济大学 | I97: / | J97: =VLOOKUP(B97,[3]加班情况分析!D:G,4,FALSE) -> 4.5298704 | K97: =VLOOKUP(B97,[3]加班情况分析!D:H,5,FALSE) -> TRUE | L97: =VLOOKUP(B97,[3]加班情况分析!D:L,6,FALSE) -> 3 | M97: =VLOOKUP($B97,[3]加班情况分析!$D:$L,7,FALSE) -> 11 | N97: =VLOOKUP($B97,[3]加班情况分析!$D:$L,8,FALSE) -> 11 | O97: =VLOOKUP(B97,[3]加班情况分析!D:L,9,FALSE) -> 35 | R97: =VLOOKUP(B97,[3]主管应用系统数量!I:J,2,FALSE) -> 1 | S97: 2 | T97: =VLOOKUP(B97,[3]二季度变更任务!A:B,2,FALSE) -> 1 | U97: =VLOOKUP(B97,[3]三季度变更任务!A:B,2,FALSE) -> 10 | W97: 超负荷 | X97: AI手机银行 AI手机银行2.0 | Y97: AI手机银行 | Z97: 0.9 | AA97: 大模型智能体平台建设&运营 | AB97: 0.1 | AD97: 王友轩 | AE97: 任务难度略高/略低于个人能力 | AF97: 超负荷
A98: 96 | B98: 王友轩 | C98: 智能创新部 | D98: AI基础研发组 | E98: 男 | F98: 1 | G98: 研究生 | H98: 南京理工大学 | I98: / | J98: =VLOOKUP(B98,[3]加班情况分析!D:G,4,FALSE) -> 4.0354583 | K98: =VLOOKUP(B98,[3]加班情况分析!D:H,5,FALSE) -> TRUE | L98: =VLOOKUP(B98,[3]加班情况分析!D:L,6,FALSE) -> 6 | M98: =VLOOKUP($B98,[3]加班情况分析!$D:$L,7,FALSE) -> 4 | N98: =VLOOKUP($B98,[3]加班情况分析!$D:$L,8,FALSE) -> 16 | O98: =VLOOKUP(B98,[3]加班情况分析!D:L,9,FALSE) -> 34 | Q98: =VLOOKUP(B98,'[3]牵头需求（当前进行中）'!A:B,2,FALSE) -> 7 | S98: 1 | T98: =VLOOKUP(B98,[3]二季度变更任务!A:B,2,FALSE) -> 3 | U98: =VLOOKUP(B98,[3]三季度变更任务!A:B,2,FALSE) -> 7 | W98: 超负荷 | X98: AI手机银行 AI手机银行2.0 | Y98: AI手机银行 | Z98: 0.7 | AA98: 大模型安全防护 | AB98: 0.3 | AD98: 黄亦豪 | AE98: 任务难度略高/略低于个人能力 | AF98: 超负荷
A99: 97 | B99: 刘雅昕 | C99: 智能创新部 | D99: AI基础研发组 | E99: 女 | F99: 1 | G99: 研究生 | H99: 哥伦比亚大学 | I99: / | J99: =VLOOKUP(B99,[3]加班情况分析!D:G,4,FALSE) -> 0.91328625 | K99: =VLOOKUP(B99,[3]加班情况分析!D:H,5,FALSE) -> FALSE | L99: =VLOOKUP(B99,[3]加班情况分析!D:L,6,FALSE) -> 46 | M99: =VLOOKUP($B99,[3]加班情况分析!$D:$L,7,FALSE) -> 8 | N99: =VLOOKUP($B99,[3]加班情况分析!$D:$L,8,FALSE) -> 3 | O99: =VLOOKUP(B99,[3]加班情况分析!D:L,9,FALSE) -> 2 | S99: 0 | W99: 即将转岗，未安排重点工作 | X99: 向量知识库项目 | Y99: 向量知识库项目 | Z99: 0.1 | AA99: 极客大赛 | AB99: 0.5 | AD99: 无 | AE99: 基本适配 | AF99: 不饱和 | AG99: 即将转岗，不再继续安排重点工作
A100: 98 | B100: 杨沁怡 | C100: 智能创新部 | D100: 风险模型组 | E100: 女 | F100: 0 | G100: 研究生 | H100: 新加坡管理大学 | I100: / | J100: =VLOOKUP(B100,[3]加班情况分析!D:G,4,FALSE) -> 1.9652509 | K100: =VLOOKUP(B100,[3]加班情况分析!D:H,5,FALSE) -> FALSE | L100: =VLOOKUP(B100,[3]加班情况分析!D:L,6,FALSE) -> 6 | M100: =VLOOKUP($B100,[3]加班情况分析!$D:$L,7,FALSE) -> 33 | N100: =VLOOKUP($B100,[3]加班情况分析!$D:$L,8,FALSE) -> 20 | O100: =VLOOKUP(B100,[3]加班情况分析!D:L,9,FALSE) -> 3 | Q100: =VLOOKUP(B100,'[3]牵头需求（当前进行中）'!A:B,2,FALSE) -> 1 | S100: 1 | W100: 超负荷 | X100: AI手机银行 AI手机银行2.0 | Y100: AI手机银行 | Z100: 0.7 | AA100: 大模型安全防护 | AB100: 0.3 | AD100: 王友轩、黄亦豪 | AE100: 基本适配 | AF100: 超负荷
...

Sheet 3 人员画像-年
A1: 年度观测：人才梯队健康度/结构合理性、高潜力员工挖掘、专业水平提升、流动性分析、员工360环评等。
A2: 类别 | B2: 序号 | C2: 指标名称 | D2: 指标口径 | E2: 数据来源 | F2: 更新频率 | G2: 基础数据是否已获取 | H2: 配套动作
A3: 基本信息 （人才梯队健康度） | B3: =ROW()-2 -> 1 | C3: 年龄 | E3: EHR系统 | F3: - | G3: 是
B4: =ROW()-2 -> 2 | C4: 性别 | E4: EHR系统 | F4: - | G4: 是
B5: =ROW()-2 -> 3 | C5: 学历 | E5: EHR系统 | F5: - | G5: 是
B6: =ROW()-2 -> 4 | C6: 专业 | E6: EHR系统 | F6: - | G6: 是
B7: =ROW()-2 -> 5 | C7: 司龄 | E7: EHR系统 | F7: 年度 | G7: 是
B8: =ROW()-2 -> 6 | C8: 工龄 | E8: EHR系统 | F8: 年度 | G8: 是
B9: =ROW()-2 -> 7 | C9: 所在科室 | E9: EHR系统 | F9: 年度 | G9: 是
B10: =ROW()-2 -> 8 | C10: 所在组 | E10: EHR系统 | F10: 年度 | G10: 是
B11: =ROW()-2 -> 9 | C11: 校招/社招标识 | E11: EHR系统 | F11: 年度 | G11: 是
B12: =ROW()-2 -> 10 | C12: 任职岗位名称 | E12: EHR系统 | F12: 年度 | G12: 是
A13: 工作量化数据 （看负荷） | B13: =ROW()-2 -> 11 | C13: 近2年牵头项目个数 | E13: ADPM | F13: 年度 | G13: 是
B14: =ROW()-2 -> 12 | C14: 近2年参与项目个数 | E14: 手工数据 | F14: 年度 | G14: 是
B15: =ROW()-2 -> 13 | C15: 负责的系统个数 | E15: ADPM | F15: 年度 | G15: 是
B16: =ROW()-2 -> 14 | C16: 是否参与过重大工程 | E16: 手工数据 | F16: 年度 | G16: 是
B17: =ROW()-2 -> 15 | C17: 近1年是否在党、工、团等组织中任职 | E17: 手工数据 | F17: 年度 | G17: 是
B18: =ROW()-2 -> 16 | C18: 党、工、团等组织中的任职职务 | E18: 手工数据 | F18: 年度 | G18: 是
B19: =ROW()-2 -> 17 | C19: 岗位变更次数 | E19: EHR系统 | F19: 年度 | G19: 是
A20: 特殊岗位/职责标识 （看角色） | B20: =ROW()-2 -> 18 | C20: 组长/骨干标识 | E20: 手工数据 | F20: 年度 | G20: 是
B21: =ROW()-2 -> 19 | C21: 产品经理标识 | E21: 手工数据 | F21: 年度 | G21: 是
B22: =ROW()-2 -> 20 | C22: 架构师标识 | E22: 手工数据 | F22: 年度 | G22: 是
A23: 学习与培养 （看潜力） | B23: =ROW()-2 -> 21 | C23: 近2年行外发表的论文、杂志的数量 | E23: 手工数据 | F23: 年度 | G23: 是
B24: =ROW()-2 -> 22 | C24: 近2年获得的部门级以上奖励、荣誉数量 | E24: 手工数据 | F24: 年度 | G24: 是
B25: =ROW()-2 -> 23 | C25: 近2年获得的部门级以上的最高荣誉名称 | E25: 手工数据 | F25: 年度 | G25: 是
B26: =ROW()-2 -> 24 | C26: 年度部门内分享/培训次数（作为培训者） | E26: 培训系统数据 | F26: 年度 | G26: 是
B27: =ROW()-2 -> 25 | C27: 年度部门外培训次数（作为培训者） | E27: 培训系统数据 | F27: 年度 | G27: 是
B28: =ROW()-2 -> 26 | C28: 年度部门外培训次数（作为被培训者） | E28: 培训系统数据 | F28: 年度 | G28: 是
B29: =ROW()-2 -> 27 | C29: 年度部门内分享/培训次数（作为被培训者） | E29: 培训系统数据 | F29: 年度 | G29: 是
B30: =ROW()-2 -> 28 | C30: 近2年带教的实习生数量 | E30: 综合台账登记 | F30: 年度 | G30: 是
B31: =ROW()-2 -> 29 | C31: 近2年带教的校招新行员的数量 | E31: 综合台账登记 | F31: 年度 | G31: 是
B32: =ROW()-2 -> 30 | C32: 近2年带教的实习生转正数量 | E32: 综合台账登记 | F32: 年度 | G32: 是
B33: =ROW()-2 -> 31 | C33: 近2年带教的校招新行员转正成绩为A的数量 | E33: EHR系统 | F33: 年度 | G33: 是
B34: =ROW()-2 -> 32 | C34: 近3个月查看知识库会议纪要次数 | E34: 智能知识库系统 | F34: 年度 | G34: 是
B35: =ROW()-2 -> 33 | C35: 当年资质证书获取情况 | E35: 台账登记 | F35: 年度 | G35: 是
A36: 硬实力 （看技能） | B36: =ROW()-2 -> 34 | C36: 数据分析师-数据分析工具运用能力 | E36: 技能考试/证书获取 | F36: 年度 | G36: 否 | H36: 技能考试
B37: =ROW()-2 -> 35 | C37: 数据分析师-算法模型开发能力 | E37: 技能考试/证书获取 | F37: 年度 | G37: 否 | H37: 技能考试
B38: =ROW()-2 -> 36 | C38: 数据分析师-营销运营能力 | E38: 技能考试/证书获取 | F38: 年度 | G38: 否 | H38: 技能考试
B39: =ROW()-2 -> 37 | C39: 数据研发师-SQL开发 | E39: 技能考试/证书获取 | F39: 年度 | G39: 否 | H39: 技能考试
B40: =ROW()-2 -> 38 | C40: 数据研发师-数据模型设计 | E40: 技能考试/证书获取 | F40: 年度 | G40: 否 | H40: 技能考试
B41: =ROW()-2 -> 39 | C41: 数据研发师-业务理解 | E41: 技能考试/证书获取 | F41: 年度 | G41: 否 | H41: 技能考试
B42: =ROW()-2 -> 40 | C42: 应用研发-技术架构设计 | E42: 技能考试/证书获取 | F42: 年度 | G42: 否 | H42: 技能考试
B43: =ROW()-2 -> 41 | C43: 应用研发-应用开发能力 | E43: 技能考试/证书获取 | F43: 年度 | G43: 否 | H43: 技能考试
B44: =ROW()-2 -> 42 | C44: AI算法工程师-数学与建模理论基础 | E44: 技能考试/证书获取 | F44: 年度 | G44: 否 | H44: 技能考试
B45: =ROW()-2 -> 43 | C45: AI算法工程师-编程与工程实现 | E45: 技能考试/证书获取 | F45: 年度 | G45: 否 | H45: 技能考试
A46: 软实力 （看发展） | B46: =ROW()-2 -> 44 | C46: 学习能力 | E46: 专业测评问卷 | F46: 年度 | G46: 否 | H46: 专业测评问卷
B47: =ROW()-2 -> 45 | C47: 创新思维 | E47: 专业测评问卷 | F47: 年度 | G47: 否 | H47: 专业测评问卷
B48: =ROW()-2 -> 46 | C48: 任务拆解能力 | E48: 专业测评问卷 | F48: 年度 | G48: 否 | H48: 专业测评问卷
B49: =ROW()-2 -> 47 | C49: 领导力 | E49: 专业测评问卷 | F49: 年度 | G49: 否 | H49: 专业测评问卷
B50: =ROW()-2 -> 48 | C50: 团队合作 | E50: 专业测评问卷 | F50: 年度 | G50: 否 | H50: 专业测评问卷
A51: 360环评 （看协作） | B51: =ROW()-2 -> 49 | C51: 综合评价（A+、A、A-、B、B-）-直属上级 | E51: 组织力测评问卷 | F51: 年度 | G51: 否 | H51: 专业测评问卷
B52: =ROW()-2 -> 50 | C52: 综合评价（A+、A、A-、B、B-）-同级同事 | E52: 组织力测评问卷 | F52: 年度 | G52: 否 | H52: 专业测评问卷
B53: =ROW()-2 -> 51 | C53: 综合评价（A+、A、A-、B、B-）-下级（如有） | E53: 组织力测评问卷 | F53: 年度 | G53: 否 | H53: 专业测评问卷
A54: 兴趣爱好与特长 | B54: =ROW()-2 -> 52 | C54: 特长 | E54: 测评问卷 | F54: 年度 | G54: 否 | H54: 专业测评问卷
B55: =ROW()-2 -> 53 | C55: 兴趣爱好 | E55: 测评问卷 | F55: 年度 | G55: 否 | H55: 专业测评问卷
A57: 360评估，CPI测评结果

Sheet 4 人员画像-月 季
A1: 月度主要监测：人员饱和度，员工异常行为数据，特殊事件分析（好坏两面）， 为部门资源调配提供数据支撑，对异常员工行为提前预警、提前干预，潜力员工挖掘。
A2: 类别 | B2: 序号 | C2: 指标名称 | D2: 数据来源 | E2: 更新频率 | F2: 目前数据是否已获取 | G2: 备注
A3: 基本信息 （看结构） | B3: =ROW()-2 -> 1 | C3: 年龄 | D3: EHR系统 | E3: - | F3: 是
B4: =ROW()-2 -> 2 | C4: 性别 | D4: EHR系统 | E4: - | F4: 是
B5: =ROW()-2 -> 3 | C5: 学历 | D5: EHR系统 | E5: - | F5: 是
B6: =ROW()-2 -> 4 | C6: 专业 | D6: EHR系统 | E6: - | F6: 是
B7: =ROW()-2 -> 5 | C7: 司龄 | D7: EHR系统 | E7: 年度 | F7: 是
B8: =ROW()-2 -> 6 | C8: 工龄 | D8: EHR系统 | E8: 年度 | F8: 是
B9: =ROW()-2 -> 7 | C9: 所在科室 | D9: EHR系统 | E9: 年度 | F9: 是
B10: =ROW()-2 -> 8 | C10: 所在组 | D10: EHR系统 | E10: 年度 | F10: 是
B11: =ROW()-2 -> 9 | C11: 校招/社招标识 | D11: EHR系统 | E11: 年度 | F11: 是
B12: =ROW()-2 -> 10 | C12: 任职岗位名称 | D12: EHR系统 | E12: 年度 | F12: 是
A13: 特殊岗位/职责标识 （看角色） | B13: =ROW()-2 -> 11 | C13: 组长/骨干标识 | D13: 手工数据 | E13: 年度 | F13: 是
B14: =ROW()-2 -> 12 | C14: 产品经理标识 | D14: 手工数据 | E14: 年度 | F14: 是
B15: =ROW()-2 -> 13 | C15: 架构师标识 | D15: 手工数据 | E15: 年度 | F15: 是
A16: 日常行为数据 （看负荷） | B16: =ROW()-2 -> 14 | C16: 当前牵头项目个数 | D16: ADPM | E16: 月度 | F16: 否
B17: =ROW()-2 -> 15 | C17: 当前牵头需求个数 | D17: ADPM | E17: 月度 | F17: 否
B18: =ROW()-2 -> 16 | C18: 负责的系统个数 | D18: ADPM | E18: 月度 | F18: 否
B19: =ROW()-2 -> 17 | C19: 党、工、团等组织中的任职职务 | D19: 手工数据 | E19: 年度 | F19: 是
B20: =ROW()-2 -> 18 | C20: 考勤异常次数 | D20: 考勤系统 | E20: 月度
B21: =ROW()-2 -> 19 | C21: 加班平均时长/月 | D21: 考勤系统 | E21: 月度
B22: =ROW()-2 -> 20 | C22: 加班1h以下频次 | D22: 考勤系统 | E22: 月度
B23: =ROW()-2 -> 21 | C23: 加班1-2h频次 | D23: 考勤系统 | E23: 月度
B24: =ROW()-2 -> 22 | C24: 加班2-4h频次 | D24: 考勤系统 | E24: 月度
B25: =ROW()-2 -> 23 | C25: 加班4h以上频次 | D25: 考勤系统 | E25: 月度
B26: =ROW()-2 -> 24 | C26: 当前负责的系统个数 | D26: ADPM系统 | E26: 月度 | G26: 信管、信统有哪些数据可支撑？是否要管理那么精细？
B27: =ROW()-2 -> 25 | C27: 当月变更任务数 | D27: 管控中台 | E27: 月度
B28: =ROW()-2 -> 26 | C28: 当月部门活动参与度（频次） | D28: 手工数据 | E28: 季度
B29: =ROW()-2 -> 27 | C29: 当年部门活动参与度（频次） | D29: 手工数据 | E29: 季度
A30: 学习与培养 （看潜力） | B30: =ROW()-2 -> 28 | C30: 当月行外发表的论文、杂志的数量 | D30: 手工数据 | E30: 季度 | F30: 是
B31: =ROW()-2 -> 29 | C31: 当月获得的部门级以上奖励、荣誉数量 | D31: 手工数据 | E31: 季度 | F31: 是
B32: =ROW()-2 -> 30 | C32: 年累计部门内分享/培训次数（作为培训者） | D32: 培训系统数据 | E32: 季度 | F32: 是
B33: =ROW()-2 -> 31 | C33: 年累计部门外培训次数（作为培训者） | D33: 培训系统数据 | E33: 季度 | F33: 是
B34: =ROW()-2 -> 32 | C34: 年累计部门外培训次数（作为被培训者） | D34: 培训系统数据 | E34: 季度 | F34: 是
B35: =ROW()-2 -> 33 | C35: 年累计部门内分享/培训次数（作为被培训者） | D35: 培训系统数据 | E35: 季度 | F35: 是
B36: =ROW()-2 -> 34 | C36: 当前带教的实习生数量 | D36: 手工数据 | E36: 季度 | F36: 是
B37: =ROW()-2 -> 35 | C37: 当前带教的校招新行员的数量 | D37: 手工数据 | E37: 季度 | F37: 是
B38: =ROW()-2 -> 36 | C38: 近3个月查看知识库会议纪要次数 | D38: 智能知识库系统 | E38: 季度 | F38: 是
B39: =ROW()-2 -> 37 | C39: 当年资质证书获取情况 | D39: 手工数据 | E39: 季度 | F39: 否

Sheet 人员画像
A1: 画像分为以下三个维度：
A2: ​​业绩与经验维度：回答“他/她过去做了什么？做得怎么样？”——这是​​过去时​​的证明。
A3: ​​能力与行为维度：回答“他/她是如何完成工作的？具备什么能力？”——这是​​现在时​​的展现。
A4: ​​潜能与特质维度：回答“他/她未来还能做什么？成长潜力如何？”——这是​​未来时​​的预测。
A6: 评估维度 | B6: 具体指标 | C6: 数据来源
A7: ​​1. 业绩与经验​​ | B7: ​​基础背景​​ | C7: EHR系统
B8: 最高学历、院校背景
B9: 专业与岗位匹配度
B10: 工龄/司龄、本岗位年限
B11: 曾经的工作履历、任职岗位
B12: ​​项目历练​​ | C12: ADPM系统、年度述职报告
B13: 近3年​​主导​​的重大项目数及成效
B14: 近3年​​参与​​的跨部门项目数
B15: 成功的​​危机/突发事件​​处理案例
B16: ​​绩效与荣誉​​ | C16: EHR系统
B17: 近3年绩效评定结果（最好有曲线图）
B18: 获得部门级/全行级荣誉次数
B19: 科室OKR贡献 个人OKR/KPI平均达成率
B20: ​​组织贡献​​ | C20: 人事部门、党工团信息、知识贡献度
B21: 在党、工、团等组织中的任职情况
B22: 行外发表的论文、杂志的数量
B23: 担任内部讲师（年度主动分享培训次数）、实习生/新行员导师等情况
A24: ​​2. 能力与行为​​ | B24: ​​核心能力评价​​ | C24: 1、采取关键事件举例法，把好的行为和不好的行为进行描述，赋予分值。 2、360度环评：自评、上级、平级同事、下级（如有）。
B25: 专业胜任力​​（360度环评）
B26: 协作与影响力​​（360度环评）
B27: 沟通与执行力​​（360度环评）
A28: ​​3. 潜能与特质​​ | B28: ​​性格特质​​ | C28: 专业机构测评问卷：问卷1-职场压力测试，问卷2-PHP新质人才与新质团队调研，问卷分析。 EHR（培训记录）、访谈
B29: 责任感
B30: 情绪稳定性与抗压能力
B31: 内驱力（自我学习投入时间、技能认证）
B32: 价值观契合度（团队文化认可度）
B33: ​​发展潜质​​ | C33: 主动参加培训/考试情况、关键事件举例法。
B34: 学习敏锐度：快速学习并应用于新情境的能力
B35: 领导力潜质：展现出的带领、影响他人的潜力
B36: 战略思维：看问题的高度和长远度
B37: 态度和能力用关键事件举例法
B38: 1、把好的行为和不好的行为进行描述，赋予分值。
B39: 2、员工自评，自评等级高的时候需要举例说明；科长评分，和员工自评不一样的时候也要举事件说明。

Sheet 离职转出人员清单
A1: 序号 | B1: 姓名 | C1: 科室 | D1: 调出/离职日期 | E1: 性质 | F1: 原因 | G1: 去向 | H1: 备注
A2: =ROW()-1 -> 1 | B2: 王菲菲 | C2: 数据治理部 | D2: 45663 | E2: 调出 | F2: 主动申请调出 | G2: 风险管理部
A3: =ROW()-1 -> 2 | B3: 赵超起 | C3: 数据开发部 | D3: 45722 | E3: 调出 | F3: 履职回避原则 | G3: 网络金融部 | H3: 履职回避原则 金科段少楠
A4: =ROW()-1 -> 3 | B4: 陈锋 | C4: 信息统计部 | D4: 45757 | E4: 离职 | F4: 出国工作日本 | G4: 日本
A5: =ROW()-1 -> 4 | B5: 高梦瑶 | C5: 信息管理部 | D5: 45800 | E5: 调出 | F5: 主动申请调出 | G5: 零售业务部
A6: =ROW()-1 -> 5 | B6: 彭坤 | C6: 信息管理部 | D6: 45800 | E6: 调出 | F6: 主动申请调出 | G6: 零售业务部
A7: =ROW()-1 -> 6 | B7: 刘满 | C7: 风险模型团队 | D7: 45814 | E7: 离职 | F7: 感觉工作没什么收获，薪酬也变低了 | G7: 未鲲科技服务有限公司
A8: =ROW()-1 -> 7 | B8: 朱田成 | C8: 信息统计部 | D8: 45832 | E8: 离职 | F8: 向往发展空间更大的公司，对薪水期待更高 | G8: 携程
A9: =ROW()-1 -> 8 | B9: 余翠 | C9: 信息管理部 | D9: 45828 | E9: 离职 | F9: 回老家结婚 | G9: 湖北银行
A10: =ROW()-1 -> 9 | B10: 白旭 | C10: 数据治理部 | D10: 45828 | E10: 离职 | F10: 家庭原因 | G10: 与父母同行业
A11: =ROW()-1 -> 10 | B11: 蔡雪 | C11: 综合管理部 | D11: 45832 | E11: 离职 | F11: 智能问数工作压力大 | G11: 平安-陆金所
A12: =ROW()-1 -> 11 | B12: 谭学彤 | C12: 智能创新部 | D12: 45832 | E12: 离职 | F12: 感觉工作没什么收获，薪酬也变低了，工作分工上偏于综合（打杂/写材料），没有成就感。考核近两年也不好。 | G12: 证券公司
A13: =ROW()-1 -> 12 | B13: 陆怡晴 | C13: 智能创新部 | D13: 45889 | E13: 离职 | F13: 向往发展空间更大的公司 | G13: 深圳字节
A14: =ROW()-1 -> 13 | B14: 张琛玥 | C14: 数据平台部 | D14: 45863 | E14: 调出 | F14: 主动申请调出 | G14: 风险管理部
A15: =ROW()-1 -> 14 | B15: 黄澜 | C15: 信息统计部 | D15: 45968 | E15: 离职 | F15: 工作安排偏边缘化，成就感/获得感不足，感觉未受到上级重视。 | G15: 暂无找到
... A18: =ROW()-1 -> 17 | B18: 邱玥 | C18: 智能创新部 | D18: 45986 | E18: 调出 | F18: 主动申请调出 | G18: 零售业务部
A19: 1 | B19: 孙卫 | C19: 数据平台部 | D19: 45369 | E19: 离职 | F19: 互联网
A20: 2 | B20: 周纲林 | C20: 信息统计部 | D20: 45399 | E20: 离职 | F20: 回武汉，工作去向未定
A21: 3 | B21: 林焦奇 | C21: 信息管理部 | D21: 45432 | E21: 离职 | F21: 未知
A22: 4 | B22: 郑贻纹 | C22: 信息管理部 | D22: 45464 | E22: 离职 | F22: 杭州西湖财政局
A23: 5 | B23: 张弯 | C23: 数据治理部 | D23: 45485 | E23: 离职 | F23: 回老家休养
A24: 6 | B24: 许鹏健 | C24: 数据开发部 | D24: 45491 | E24: 离职 | F24: 中国大地财产保险股份有限公司
A25: 7 | B25: 宋欣瑞 | C25: 数据平台部 | D25: 45497 | E25: 离职 | F25: 回老家休养
A26: 8 | B26: 李嘉杰 | C26: 信息管理部 | D26: 45527 | E26: 离职 | F26: 互联网公司
A27: 9 | B27: 王轩儒 | C27: 数据开发部 | D27: 45580 | E27: 离职 | F27: 字节跳动
A28: 10 | B28: 徐亦浩 | C28: 信息管理部 | D28: 45602 | E28: 调动 | F28: 审计部
A29: 11 | B29: 王鹏洪 | C29: 数据治理部 | D29: 45626 | E29: 退休 | F29: 退休
B30: 陈超 | C30: 智能创新部 | G30: 数字化转型与客户体验部
B31: 郭庆睿 | C31: 信息统计部 | G31: 数字化转型与客户体验部

Sheet 组长骨干名单
A1: 工号 | B1: 姓名 | C1: 团队 | D1: 组名 | E1: 标识
A2: 319957 | B2: 罗仁杰 | C2: 数据开发部 | D2: 需求接入组 | E2: 组长
A3: 302570 | B3: 黄哲睿 | C3: 数据开发部 | D3: 模型设计组 | E3: 组长
A4: 305042 | B4: 邹小芳 | C4: 数据开发部 | D4: 应用开发组 | E4: 组长
A5: 304064 | B5: 兰昕蕾 | C5: 数据开发部 | D5: 数仓开发组 | E5: 组长
A6: 304795 | B6: 丁晨 | C6: 数据开发部 | D6: 数仓开发组 | E6: 组长
A7: 307234 | B7: 史朋飞 | C7: 数据平台部 | D7: 运维支持组 | E7: 组长
A8: 307351 | B8: 刘金良 | C8: 数据平台部 | D8: 架构安全组 | E8: 组长
A9: 302551 | B9: 鞠爱宁 | C9: 数据平台部 | D9: 数据服务组 | E9: 组长
A10: 306836 | B10: 魏佳翔 | C10: 数据平台部 | D10: 应用开发组 | E10: 组长
A11: 303401 | B11: 曹宁远 | C11: 数据平台部 | D11: 工具开发组 | E11: 组长
A12: 319909 | B12: 庄家宙 | C12: 数据治理部 | D12: 架构安全组 | E12: 组长
... A24: 306253 | B24: 杨萍 | C24: 综合管理部 | D24: 测试管理组 | E24: 组长
A25: 301732 | B25: 周龙 | C25: 数据开发部 | E25: 骨干
A26: 303060 | B26: 周影 | C26: 数据开发部 | E26: 骨干
A27: 303473 | B27: 康冉 | C27: 数据开发部 | E27: 骨干
A28: 306252 | B28: 陆慧 | C28: 数据开发部 | E28: 骨干
A29: 303494 | B29: 姚志环 | C29: 数据开发部 | E29: 骨干
A30: 304814 | B30: 林幸 | C30: 数据开发部 | E30: 骨干
A31: 305421 | B31: 骆静龙 | C31: 数据开发部 | E31: 骨干
A32: 304765 | B32: 王言哲 | C32: 数据开发部 | E32: 骨干
A33: 305026 | B33: 马富强 | C33: 数据开发部 | E33: 骨干
A34: 305131 | B34: 嵇雅娟 | C34: 数据平台部 | E34: 骨干
A35: 303450 | B35: 李天卓 | C35: 数据平台部 | E35: 骨干
A36: 303471 | B36: 王正超 | C36: 数据平台部 | E36: 骨干
... A60: 306537 | B60: 陈世辉 | C60: 综合管理部 | E60: 骨干

Sheet 产品经理架构师
A1: 领域 | B1: 应用性质 | C1: 应用标识 | D1: 应用 | E1: 架构师队伍 | H1: 产品经理 | M1: 姓名 | N1: 产品经理/架构师 | O1: 应用个数
E2: 架构组长 | F2: 架构组员 | G2: 架构师 | M2: 韩统优 | N2: 产品经理 | O2: 1
A3: 数据平台底座 | B3: 基础基建类 | C3: BDPHDP | D3: Hadoop集群 | E3: 史朋飞 | F3: 吴证、刘金良、李天卓、李响 | G3: 史朋飞 | H3: 同架构 | M3: 李然 | N3: 产品经理 | O3: 1
C4: BDPEDB | D4: Kafka消息集群 | G4: 刘金良 | M4: 范佳 | N4: 产品经理 | O4: 1
C5: BDPRTDP | D5: 实时数据集群 | G5: 刘金良 | M5: 同架构 | N5: 产品经理 | O5: 16
C6: BDPOSC | D6: 联机服务集群 | G6: 李天卓 | M6: 汪乐乐 | N6: 产品经理 | O6: 3
C7: BDPDWS | D7: DWS数据集群 | G7: 李天卓 | M7: 王璐珊 | N7: 产品经理 | O7: 1
A8: 数据研发运营一体化（dataops） | B8: 研发工具 | C8: DAT | D8: 数据采集工具 | E8: 刘金良 | F8: 曹宁远、鞠爱宁、魏佳翔、李响 | G8: 刘金良 | H8: 同架构 | M8: 王书祥 | N8: 产品经理 | O8: 1
C9: RTDP | D9: 实时开发平台 | G9: 刘金良 | M9: 王素雅 | N9: 产品经理 | O9: 4
C10: ODD | D10: 离线数据开发 | G10: 刘金良 | M10: 王新 | N10: 产品经理 | O10: 2
C11: DTP | D11: 数据测试平台 | G11: 刘金良 | M11: 杨婧 | N11: 产品经理 | O11: 1
C12: DOP | D12: 数据运维平台 | G12: 刘金良 | M12: 杨陆 | N12: 产品经理 | O12: 2
C13: USP | D13: 统一调度平台 | G13: 曹宁远 | M13: 于璐 | N13: 产品经理 | O13: 4
C14: CHS | D14: 冷热分离工具 | G14: 曹宁远 | M14: 张伟亮 | N14: 产品经理 | O14: 2
B15: 安全工具 | C15: DMM | D15: 数据脱敏工具 | G15: 曹宁远 | H15: 庄家宙 | M15: 周龙 | N15: 产品经理 | O15: 2
C16: DSDGS | D16: 数据安全脱敏网关系统 | G16: 曹宁远 | H16: 庄家宙 | M16: 庄家宙 | N16: 产品经理 | O16: 2
B17: 数据资产 | C17: DLA | D17: 智能数据血缘分析工具 | G17: 曹宁远 | H17: 于璐 | M17: 曹宁远 | N17: 架构师 | O17: 6
C18: DAMP | D18: 数据资产管理 | G18: 魏佳翔 | H18: 于璐 | M18: 胡帆 | N18: 架构师 | O18: 3
C19: DATP | D19: 数据资产门户 | G19: 魏佳翔 | H19: 于璐 | M19: 黄哲睿 | N19: 架构师 | O19: 2
C20: EDM | D20: 外部数据管理 | G20: 鞠爱宁 | H20: 于璐 | M20: 鞠爱宁 | N20: 架构师 | O20: 8
B21: 数据质量 | C21: DQMP | D21: 数据质量管理平台 | G21: 魏佳翔 | H21: 张伟亮 | M21: 李天卓 | N21: 架构师 | O21: 2
B22: 不适用 | C22: SFGW | D22: 大智慧舆情 | G22: 鞠爱宁 | H22: 不适用 | M22: 李响 | N22: 架构师 | O22: 5
B23: 基础基建类 | C23: BDEG | D23: 大数据外联网关 | G23: 鞠爱宁 | H23: 同架构 | M23: 刘金良 | N23: 架构师 | O23: 11
C24: DMC | D24: 数据服务中心 | G24: 鞠爱宁 | M24: 陆慧 | N24: 架构师 | O24: 5
B25: 策略运营服务 | C25: LBS | D25: 标签平台 | G25: 史朋飞 | H25: 杨陆 | M25: 罗仁杰 | N25: 架构师 | O25: 1
C26: ACCI | D26: 分析圈客一体化 | G26: 史朋飞 | H26: 杨陆 | M26: 史朋飞 | N26: 架构师 | O26: 3
B27: 经营管理服务 | C27: VRI | D27: 可视化报表助手 | G27: 刘金良 | H27: 王素雅 | M27: 魏佳翔 | N27: 架构师 | O27: 12
C28: DAM | D28: 数据分析挖掘（sas） | G28: 刘金良 | H28: 同架构 | M28: 于中宝 | N28: 架构师 | O28: 6
C29: UDAS | D29: 统一报表及指标平台 | G29: 魏佳翔 | H29: 王素雅 | M29: 周龙 | N29: 架构师 | O29: 12
C30: AMBI | D30: 掌上行 | G30: 魏佳翔 | H30: 王素雅
C31: DQAA | D31: 智能问数助手 | G31: 魏佳翔 | H31: 王素雅
B32: 分析工具 | C32: CDMM | D32: 神农数据开发平台 （stella sql查询工具） | G32: 曹宁远 | H32: 同架构
C33: BDM | D33: 开源算法平台 | G33: 刘金良
C34: RMM | D34: 模型实验室 | G34: 刘金良
A35: 客户经营 | B35: 客户关系管理 | C35: RCRM | D35: 零售客户关系管理 | E35: 魏佳翔 | F35: 刘金良 | G35: 魏佳翔 | H35: 陆雨欣、范佳
C36: ICRM | D36: 同业客户关系管理 | G36: 魏佳翔 | H36: 汪乐乐
C37: CCRM | D37: 公司客户关系管理 | G37: 魏佳翔 | H37: 汪乐乐
C38: PCCM | D38: 潜客发掘 | G38: 魏佳翔 | H38: 汪乐乐
A39: AI人工智能 | B39: 模型管理与应用 | C39: IALT | D39: 长文本智能分析 | E39: 李响 | F39: 刘金良、胡申民、于中宝 | G39: 于中宝 | H39: 同架构
C40: IRE | D40: 智能推荐引擎 | G40: 于中宝 | H40: 王璐珊
C41: RG | D41: 关联图谱 | G41: 于中宝 | H41: 同架构
C42: CBOS | D42: 百应大模型平台 | G42: 李响 | H42: 同架构
C43: CIA | D43: 代码智能助手 | G43: 李响 | H43: 杨婧
C44: LLMA | D44: 大模型智能体 | G44: 李响 | H44: 同架构
C45: DDRA | D45: 尽调报告助手 | G45: 李响 | H45: 韩统优
C46: CSIA | D46: 大模型客服助手 | G46: 李响 | H46: 同架构
C47: CAIS | D47: 会话式人工智能服务 | G47: 于中宝
C48: EIS | D48: E慧搜 | G48: 于中宝
C49: PCP | D49: 隐私计算建模 | G49: 于中宝
A50: 数据仓库及计算区 | B50: 数仓服务 | C50: EDWHDAP | D50: Hadoop数据仓库 | E50: 黄哲睿 | F50: 杨青、陆慧、罗仁杰、吴证、史朋飞 | G50: 黄哲睿 | H50: 同架构
C51: EDWDWS | D51: DWS数据仓库 | G51: 罗仁杰
C52: EDWRTDW | D52: 实时数据仓库 | G52: 黄哲睿
C53: CAFBDM | D53: 金融基础数据模型计算区 | G53: 陆慧
C54: CARSR | D54: 监管报送应用计算区 | G54: 陆慧
C55: CAML | D55: 模型实验室应用计算区 | G55: 陆慧
C56: CACRMM | D56: 信用风险管理监测应用计算区 | G56: 陆慧
C57: CACRS | D57: 征信管理应用计算区 | G57: 陆慧
A58: 风险计量与监测应用 | B58: 风险计量 | C58: RAD | D58: 信用风险监测预警 | E58: 白迪 | F58: 鞠爱宁、胡帆 | G58: 胡帆 | H58: 同架构
C59: RSD | D59: 风险底线排查 | G59: 胡帆
C60: MMM | D60: 魔镜智能风控 | G60: 胡帆
C61: IAFS | D61: 智能财报分析 | G61: 鞠爱宁
C62: CRPBC | D62: 人行证信 | G62: 鞠爱宁
C63: CFFIS | D63: 企业资金流信息共享 | G63: 鞠爱宁
C64: IAMS | D64: 审计综合管理系统 | G64: 鞠爱宁
A65: 监管报送 | B65: 监管报送 | C65: RCI | D65: 综合监管报送 | E65: 周龙 | F65: 吴证、魏佳翔 | G65: 周龙 | H65: 王新
C66: RBAC | D66: 银保监报送 | G66: 周龙 | H66: 张伟亮
C67: RBRP | D67: 村镇银行报送 | G67: 周龙 | H67: 王新
C68: RTZ | D68: 监管可信区 | G68: 周龙 | H68: 王书祥
C69: FIBDS | D69: 金融基础数据统计报送 | G69: 周龙 | H69: 李然
C70: PBGW | D70: 人行报送网关 | G70: 周龙 | H70: 同架构
C71: RTZCGW | D71: 监管可信区外联网关 | G71: 周龙 | H71: 同架构
C72: RPBC | D72: 央行监管报送 | G72: 周龙 | H72: 同架构
C73: PISA | D73: 支付信息报送 | G73: 周龙 | H73: 同架构
C74: ADCR | D74: 会计数据集中报送 | G74: 周龙
C75: CRSR | D75: 客户风险统计报送 | G75: 周龙
C76: FTTR | D76: 自贸区报送 | G76: 周龙
C77: AMLR | D77: 反洗钱报送 | G77: 魏佳翔 | H77: 周龙
C78: AMLIMS | D78: 反洗钱综合管理系统 | G78: 魏佳翔 | H78: 周龙

Sheet 累计工龄
A1: 姓名 | B1: 累计工龄
A2: 于浩瀚 | B2: 25 | P2: 3年以下89人，
A3: 宋晓迪 | B3: 18 | P3: 研究生150人，73.9%
A4: 卢易 | B4: 17 | P4: 校园招聘78%
A5: 杨晓彦 | B5: 7
A6: 乐洋 | B6: 19
A7: 刘召龙 | B7: 24
A8: 曾敏锐 | B8: 13
A9: 杨萍 | B9: 10
A10: 康冉 | B10: 5
A11: 陆雨欣 | B11: 5
A12: 黄佳佳 | B12: 6
A13: 许阿云 | B13: 5
A14: 宋子夜 | B14: 3
A15: 王枫 | B15: 9
A16: 胡超亭 | B16: 4
... A199: 沈子新 | B199: 4

Sheet 项目 需求个数
A1: 计数项:需求编号 | F1: 计数项:项目编号
A2: 需求负责人 | B2: 汇总 | F2: 项目经理 | G2: 汇总
B3: 7 | F3: 曹宁远 | G3: 1
A4: 安新宜 | B4: 1 | F4: 曹婉茹 | G4: 1
A5: 曹婕 | B5: 1 | F5: 曾敏锐 | G5: 1
A6: 曹婉茹 | B6: 7 | F6: 陈朗 | G6: 1
A7: 陈晨 | B7: 12 | F7: 崔建文 | G7: 1
A8: 陈笑轩 | B8: 1 | F8: 冯潇 | G8: 1
A9: 崔建文 | B9: 2 | F9: 龚毅磊 | G9: 1
A10: 丁晨 | B10: 2 | F10: 胡承萱 | G10: 2
A11: 杜乐 | B11: 2 | F11: 黄佳佳 | G11: 3
A12: 龚毅磊 | B12: 7 | F12: 贾世林 | G12: 1
A13: 胡楚 | B13: 2 | F13: 蒋捷 | G13: 1
A14: 胡庆 | B14: 1 | F14: 景丞 | G14: 1
A15: 胡雯 | B15: 25 | F15: 康冉 | G15: 3
... A42: 潘修滔 | B42: 2 | F42: 总计 | G42: 58
A43: 祁鑫 | B43: 1
A44: 钱磊 | B44: 7
A45: 邱玥 | B45: 1
A46: 任欣宇 | B46: 1
A47: 阮靖龙 | B47: 4
A48: 沈志贇 | B48: 2
A49: 施怡伶 | B49: 1
A50: 孙菡悦 | B50: 2
A51: 佟嘉欣 | B51: 11
A52: 万珊红 | B52: 1
A53: 王璐珊 | B53: 2
A54: 王萌萌 | B54: 4
... A88: 总计 | B88: 365

Sheet 新paso体系下参与应用数量
A1: 列A | B1: 计数
A2: 安新宜 | B2: 1
A3: 曹婕 | B3: 1
A4: 曹宁远 | B4: 5
A5: 陈晨 | B5: 2
A6: 陈佳宁 | B6: 1
A7: 陈科宇 | B7: 1
A8: 陈朗 | B8: 1
A9: 陈笑轩 | B9: 1
A10: 陈玉思 | B10: 2
A11: 崔建文 | B11: 1
A12: 丁晨 | B12: 3
A13: 杜乐 | B13: 1
... A99: 邹小芳 | B99: 2

Sheet Sheet1
C1: 序号 | D1: 姓名 | E1: 调出部门 | F1: 调入部门
C2: 1 | D2: 赵** | E2: 数据管理与应用部/数据开发部 | F2: 网络金融部
C3: 2 | D3: 高** | E3: 数据管理与应用部/信息管理部 | F3: 零售业务部
C4: 3 | D4: 彭** | E4: 数据管理与应用部/信息管理部 | F4: 零售业务部
C5: 4 | D5: 邱** | E5: 数据管理与应用部/智能创新部 | F5: 零售业务部
C6: 5 | D6: 杨** | E6: 数据管理与应用部/智能创新部 | F6: 金融市场部
C7: 6 | D7: 王** | E7: 数据管理与应用部/信息管理部 | F7: 杭州分行
C8: 7 | D8: 王** | E8: 数据管理与应用部/数据治理部 | F8: 风险管理部
C9: 8 | D9: 张** | E9: 数据管理与应用部/数据平台部 | F9: 风险管理部
C10: 9 | D10: 陈** | E10: 数据管理与应用部/智能创新部 | F10: 数字化转型与客户体验部
C11: 10 | D11: 郭** | E11: 数据管理与应用部/信息统计部 | F11: 数字化转型与客户体验部

Sheet Sheet2
B1: 月份 | C1: 议题一 | D1: 科室
B2: 3月 | C2: 数据部2026年度重点工作计划 | D2: 综合管理部
B3: 4月 | C3: 数据治理工作规划 | D3: 信息统计部
B4: 5月 | C4: 数据架构与数据安全工作汇报 | D4: 数据治理部
B5: 6月 | C5: AI场景应用工作汇报 | D5: 智能研发部
B6: 7月 | C6: 监管报送工作汇报 | D6: 信息统计部
B7: 8月 | C7: 数字化运营体系工作汇报 | D7: 信息管理部
B8: 9月 | C8: 业数融合工作成效总结 | D8: 信息管理部
B9: 10月 | C9: 数据治理工作阶段性成果总结 | D9: 信息统计部
B10: 11月 | C10: 数据安全年度工作总结 | D10: 数据治理部
B11: 12月 | C11: 数据部2026年度工作总结 | D11: 综合管理部
B13: 议题二
B14: 按季度，4月、7月、10月 | C14: 赋能分支行情况汇报 | D14: 机构服务团队
B15: 按季度，4月、7月、10月 | C15: 数据部重点工作回顾与分析 | D15: 综合管理部
B17: 议题3：分行数据工作汇报 3月 深圳分行；4月 成都分行；5月 总行营业部；6月 自贸区分行；7月 北京分行；8月 苏州分行；9月 宁波分行；10月 天津分行；11月 杭州分行；12月 浦东分行

Sheet 导出计数_组
A1: 组 | B1: 计数
A2: AI产品运营组 | B2: 2
A3: AI基础研发组 | B3: 2
A4: 标准质量组 | B4: 2
A5: 测试管理组 | B5: 2
A6: 非零BP | B6: 2
A7: 分行BP | B7: 2
A8: 风险模型团队 | B8: 2
A9: 工具开发组 | B9: 2
A10: 管理信息组 | B10: 2
A11: 架构安全组 | B11: 2
A12: 监管数据治理 | B12: 2
A13: 监管统计组 | B13: 1
... A21: 运维支持组 | B21: 2
